Workbook
Name Bahías_de_Linea: 'N Bahias'!$N$11
Name Bahías_Equipadas_13_8_kV: 'N Bahias'!$B$28
Name Bahías_Equipadas_34_5_kV: 'N Bahias'!$B$27
Name Metros_Caseta_a_Patio: 'N Bahias'!$B$26
Name Pase_de_Vía: 'N Bahias'!$B$29
Name Reconectador: 'N Bahias'!$N$5
Name Seccionador_Tripolar: 'N Bahias'!$N$6
Name Seccionador_Tripolar_CSPT: 'N Bahias'!$N$7
Name tubo2: '[1]N Bahias'!$B$30
Name Tubos_1_1_2: 'N Bahias'!$B$33
Name Tubos_2: 'N Bahias'!$B$32
Name Tubos_3: 'N Bahias'!$B$31
Name Tubos_4: 'N Bahias'!$B$30

Sheet Material
A1: Ref | B1: Descripción | C1: Tarifa | D1: Unidad | E1: Valor comercial + IVA | F1: Rentabilidad | G1: Fecha | H1: Link
A2: MA-01 | B2: GRAPA DE RETENCIÓN TIPO PISTOLA DE 6-4/0 DE 3 UES EN ALUMINIO | C2: =E2*F2 -> 104000 | D2: UN | E2: 80000 | F2: 1.3 | G2: 45693 | H2: https://interelectricas.com.co/grapa-retencion/2885-grapa-retencion-aluminio-tipo-pistola-1-0-266-awg-3-ues.html
A3: MA-02 | B3: AISLADOR TIPO DISCO DE HORQUILLA. DIAMETRO 254 MM 34.5 KV ANSI 52-4 | C3: =E3*F3 -> 107835 | D3: UN | E3: 82950 | F3: 1.3 | G3: 45693 | H3: https://interelectricas.com.co/aisladores/2970-aislador-suspension-10-ansi-52-4-ansi-52-4.html
A4: MA-03 | B4: AISLADOR TIPO PIN DE PORCELANA PARA 34.5 KV ANSI 56-3 | C4: =E4*F4 -> 99645 | D4: UN | E4: 76650 | F4: 1.3 | G4: 45693 | H4: https://interelectricas.com.co/aisladores/1825-aislador-tipo-pin-o-para-espigo-de-34-5-kv-ansi-56-3.html
A5: MA-04 | B5: COLLARIN DE DOS SALIDAS EN PLATINA DE HIERRO GALVANIZADO. DIAMETRO (6-8 IN) (17 - 22 CM) | C5: =E5*F5 -> 24505 | D5: UN | E5: 18850 | F5: 1.3 | G5: 45693 | H5: https://interelectricas.com.co/herrajes-electricos/13-abrazadera-o-collarin-de-2-dos-salidas-7-8-pl-1-4-idem-180-mm.html
A6: MA-05 | B6: COLLARIN DE DOS SALIDAS EN PLATINA DE HIERRO GALVANIZADO. DIAMETRO (7-10 IN) (20 - 25 CM) | C6: =E6*F6 -> 27755 | D6: UN | E6: 21350 | F6: 1.3 | G6: 45693 | H6: https://interelectricas.com.co/herrajes-electricos/2405-abrazadera-o-collarin-de-2-dos-salidas-10-11-pl-1-4-idem-240-mm.html
A7: MA-06 | B7: COLLARIN DE DOS SALIDAS EN PLATINA DE HIERRO GALVANIZADO. DIAMETRO (10-12 IN) (25 - 30 CM) | C7: =E7*F7 -> 33150 | D7: UN | E7: 25500 | F7: 1.3 | G7: 45693 | H7: https://interelectricas.com.co/collarines-dos-salidas/10375-abrazadera-o-collarin-de-2-dos-salidas-11-12-platina-1-4-pulgada-280-mm.html
A8: MA-07 | B8: COLLARIN DE UNA SALIDA EN PLATINA DE HIERRO GALVANIZADO. DIAMETRO (14-16 IN) (35 - 40 CM) | C8: =E8*F8 -> 39000 | D8: UN | E8: 30000 | F8: 1.3 | G8: 45693 | H8: Precio Aproximado
A9: MA-08 | B9: CRUCETA METÁLICA DE ANGULO GALVANIZADO DE 6 M DE LONGITUD. CALIBRE (76*76*6) MM | C9: =E9*F9 -> 763908.6 | D9: UN | E9: 587622 | F9: 1.3 | G9: 45693 | H9: https://edelco.co/producto/cruceta-metalica-de-6-00-mts-3-x-3-x-1-4/?srsltid=AfmBOoqz5z8FW7naYbdZ7ujXYt8ZocEtWebPM92yPcy0DlncWGxFd0kI
A10: MA-09 | B10: ESPARRAGO DE HIERRO GALVANIZADO ROSCADO EN TODA SU LONGITUD, 4 TUERCAS. DIAMETRO 16 MM LONGITUD 458 MM | C10: =E10*F10 -> 10920 | D10: UN | E10: 8400 | F10: 1.3 | G10: 45693 | H10: https://interelectricas.com.co/herrajes-electricos/50-esparrago-de-5-8-x-16-4-t.html
A11: MA-10 | B11: GRAPA DE OPERAR EN CALIENTE CONDUCTOR AWG-MCM 6 - 400 DIÁMETRO 4 - 13,5 MM | C11: =E11*F11 -> 37155.3 | D11: UN | E11: 28581 | F11: 1.3 | G11: 45693 | H11: https://edelco.co/producto/grapa-de-operar-en-caliente-aluminio/?srsltid=AfmBOor3_12iyoeksqg9zdDRVfZriRBzsXlzXIl4RnW5E_avlI5oIcbF
A12: MA-11 | B12: TUERCA DE OJO ALARGADO PARA PERNO 16 MM | C12: =E12*F12 -> 18200 | D12: UN | E12: 14000 | F12: 1.3 | G12: 45693 | H12: https://interelectricas.com.co/herrajes-electricos/1-tuerca-de-ojo-alargado-de-5-8.html
A13: MA-12 | B13: POSTE DE CONCRETO 14 m 1050 KG | C13: =E13*F13 -> 2782325 | D13: UN | E13: 2140250 | F13: 1.3 | G13: 45693 | H13: https://interelectricas.com.co/postes-de-concreto-y-metalicos/2402-poste-de-concreto-pretensado-de-14-metros-1050-kg.html
A14: MA-13 | B14: MALLA ELECTROSOLDADA 4 mm | C14: 8577 | D14: M2 | E14: 16379 | F14: 1.3 | G14: 45694 | H14: Base de datos Ing Santiago 20/02/2025
A15: MA-14 | B15: CONCRETO DE 3000 PSI | C15: =E15*F15 -> 620227.23 | D15: M3 | E15: 477097.87 | F15: 1.3 | G15: 45694 | H15: apus_caldas_2021_1
A16: MA-15 | B16: VARILLA DE REFUERZO | C16: =E16*F16 -> 46020 | D16: ML | E16: 35400 | F16: 1.3 | G16: 45694 | H16: https://www.homecenter.com.co/homecenter-co/product/73638/varilla-corrugada-g60-w-5-5-8-pulg-x-6m/73638/
A17: MA-16 | B17: FORMALETA EN MADERA CON TABLA DE 1/4" | C17: =E17*F17 -> 104000 | D17: M2 | E17: 80000 | F17: 1.3 | G17: 45694 | H17: Precio Aproximado
A18: MA-17 | B18: EXCAVACIÓN EN MATERIAL COMÚN BAJO AGUA DE 0 - 2 M MANUAL | C18: =E18*F18 -> 45663.8 | D18: M3 | E18: 35126 | F18: 1.3 | G18: 45694 | H18: file:///D:/04.%20DISE%C3%91O%203%20(L.G)/13.%20ID20200070%20-%20%20S.E.%20BARAYA/154/APUs%20Gobernaci%C3%B3n%20de%20Risaralda.pdf
A19: MA-18 | B19: CABLE ACSR 4/0 AWG PARA CONEXIÓN ENTRE EQUIPOS | C19: =E19*F19 -> 10400 | D19: ML | E19: 8000 | F19: 1.3 | G19: 45455 | H19: cotización ie cinco sas
A20: MA-19 | B20: CABLE AAAC 465.4Kcmil – CAIRO PARA BARRAJE | C20: =E20*F20 -> 63707.162 | D20: ML | E20: 49005.509 | F20: 1.3 | G20: 45694 | H20: https://www.comercialvoltex.com/cable-de-aluminio-desnudo-cairo-2358mm2-19h?srsltid=AfmBOorbpMtA8DvXmg-4_AwIQTWnE-S39PGXS-yc9vBb8xDCcfU0Ebna
A21: MA-20 | B21: TRANSFORMADOR DE POTENCIA DE 5/6.25 MVA, REFRIGERACIÓN ONAN/ONAF, 34.5/13.8 KV, CONEXIÓN DYN5, CON ACCESORIOS DE CONTROL Y PROTECCIÓN INCLUYENDO: TERMÓMETROS CON CONTACTOS, NIVEL DE ACEITE CON CONTACTOS, VÁLVULA QUALITROL, RELÉ DE BUCHHOLZ, TANQUE DE EXPANSIÓN, SECADORES DE AIRE, VENTILADORES, TABLERO DE CONEXIONES ACOPLADO, CAMBIADOR DE TAP`S DE OPERACIÓN SIN CARGA EN 34.5 KV. | C21: =E21*F21 -> 972000000 | D21: UN | E21: =180000*'Precio Monedas'!B2 -> 810000000 | F21: 1.2 | G21: 45694 | H21: Precio dado en cotización
A22: MA-21 | B22: RECONECTADOR TRIFÁSICO (R). UM:36KV, IN: 630A, ISC:12.5KA MIN, LIWV:170KV. INCLUYE CONTROL MICROPROCESADOR DE ÚLTIMA TECNOLOGÍA, CABLES DE 6M, PRENSACABLES Y TARJETA DE COMUNICACIÓN LAN DUAL ETHERNET RJ45 Y ÓPTICA MTRJ, 3 SENSORES DE TENSIÓN, 3 SENSORES DE CORRIENTE, UN GABINETE DE COMUNICACIÓN QUE INCLUYA RADIO Y ANTENA, BATERIA DE RESPALDO Y CARGADOR. | C22: =E22*F22 -> 156633750 | D22: UN | E22: =22500*'Precio Monedas'!B2*1.19 -> 120487500 | F22: 1.3 | G22: 45695 | H22: Cotización ABB del 25/06/2025
A23: MA-22 | B23: SECCIONADOR TRIPOLAR MOTORIZADO CON CUCHILLA DE PUESTA A TIERRA MOTORIZADA UM:38 KV, IN: 630A, ISC:12.5KA MIN, LIWV:95KV. INCLUYE: BRAZO DE MANDO MANUAL A LA ALTURA APROPIADA | C23: =E23*F23 -> 57857275 | D23: UN | E23: 48214395 | F23: 1.2 | G23: 45695 | H23: https://energiaputumayo.com/testimonial/solicitud-publica-de-oferta-no-002-2024/
A24: MA-23 | B24: SECCIONADOR TRIPOLAR MOTORIZADO SIN CUCHILLA DE PUESTA A TIERRA. UM:38 KV, IN: 630A, ISC:12.5KA MIN, LIWV:95KV. INCLUYE: BRAZO DE MANDO MANUAL A LA ALTURA APROPIADA | C24: =E24*F24 -> 38388149 | D24: UN | E24: 31990124 | F24: 1.2 | G24: 45695 | H24: https://energiaputumayo.com/testimonial/solicitud-publica-de-oferta-no-002-2024/
A25: MA-24 | B25: DPS VNOM: 38KV. ISC 12.5 KA | C25: =E25*F25 -> 394810 | D25: UN | E25: 303700 | F25: 1.3 | G25: 45692 | H25: https://interelectricas.com.co/pararrayos/2845-pararrayo-polimerico-36kv-10ka-sin-herraje.html
A26: MA-25 | B26: CERTIFICACIÓN RETIE PARA BAHIA EN SUBESTACIÓN 34.5 KV O 13.8 KV | C26: =E26*F26 -> 9282000 | D26: UN | E26: =6000000*1.19 -> 7140000 | F26: 1.3 | G26: 45692 | H26: Precio cotización cinco sas
A27: MA-26 | B27: TRANSFORMADOR DE CORRIENTE. USO EXTERIOR. TRIPLE NÚCLEO: ( N1:500-1000/5 CL: 0,5S, N2:500-1000/5 CL: 0,5S, N3:500-1000/5 CL: 5P20) UM:38KV, ISC:12.5KA MIN, RELACIÓN DE TRANSFORMACIÓN AJUSTADA SEGÚN DISEÑO. INCLUYE PROTOCOLOS DE PRUEBA DE PRECISIÓN DE FABRICANTE Y LABORATORIO ACREDITADO. | C27: =E27*F27 -> 25061400 | D27: UN | E27: =3900*'Precio Monedas'!B2*1.19 -> 20884500 | F27: 1.2 | G27: 45695 | H27: Cotización ABB 25/06/2025
A28: MA-27 | B28: TRANSFORMADOR DE CORRIENTE. USO EXTERIOR. TRIPLE NÚCLEO: ( N1:75-150/5 CL: 0,5S, N2:75-150/5 CL: 0,5S, N3:75-150/5 CL: 5P20) UM:38KV, ISC:12.5KA MIN, RELACIÓN DE TRANSFORMACIÓN AJUSTADA SEGÚN DISEÑO. INCLUYE PROTOCOLOS DE PRUEBA DE PRECISIÓN DE FABRICANTE Y LABORATORIO ACREDITADO. | C28: =E28*F28 -> 23776200 | D28: UN | E28: =3700*'Precio Monedas'!B2*1.19 -> 19813500 | F28: 1.2 | G28: 45695 | H28: Cotización ABB 25/06/2025
A29: MA-28 | B29: TRANSFORMADOR DE CORRIENTE. USO EXTERIOR. TRIPLE NÚCLEO: ( N1:150-300/5 CL: 0,5S, N2:150-300/5 CL: 0,5S, N3:150-300/5 CL: 5P20). UM:38KV, ISC:12.5KA MIN, RELACIÓN DE TRANSFORMACIÓN AJUSTADA SEGÚN DISEÑO. INCLUYE PROTOCOLOS DE PRUEBA DE PRECISIÓN DE FABRICANTE Y LABORATORIO ACREDITADO. | C29: =E29*F29 -> 23776200 | D29: UN | E29: =3700*'Precio Monedas'!B2*1.19 -> 19813500 | F29: 1.2 | G29: 45695 | H29: Cotización ABB 25/06/2025
A30: MA-29 | B30: TRANSFORMADOR DE TENSIÓN. USO EXTERIOR. NUCLEO SENCILLO. (N1: 34,5√3/115√3. CL 0.5, 1 VA). | C30: =E30*F30 -> 21205800 | D30: UN | E30: =3300*'Precio Monedas'!B2*1.19 -> 17671500 | F30: 1.2 | G30: 45695 | H30: Cotización ABB 25/06/2025
A31: MA-30 | B31: TRANSFORMADOR DE TENSIÓN. USO EXTERIOR. DOBLE NUCLEO. (N1: 34,5√3/115√3. CL 0,5, 10 VA; N2: 34,5√3/115√3.CL 3P) | C31: =E31*F31 -> 21205800 | D31: UN | E31: =3300*'Precio Monedas'!B2*1.19 -> 17671500 | F31: 1.2 | G31: 45695 | H31: Cotización ABB 25/06/2025
A32: MA-31 | B32: TABLERO AUTOSOPORTADO DE FABRICACIÓN ESPECIAL. DE USO INTERIOR. IP 65. LAMINA DE ACERO GALVANIZADA CALIBRE 18. PARA ALBERGAR HASTA 6 EQUIPOS DE MEDIDA SEMIDIRECTA | C32: =E32*F32 -> 9100000 | D32: UN | E32: 7000000 | F32: 1.3 | G32: 45695 | H32: https://energiaputumayo.com/testimonial/solicitud-publica-de-oferta-no-002-2024/
A33: MA-32 | B33: LÁMPARA LED | C33: =E33*F33 -> 307373.88 | D33: UN | E33: 236441.45 | F33: 1.3 | G33: 45323 | H33: https://www.proelectrico.com/wp-content/uploads/2024/10/Lista-de-Precios-2024.pdf
A34: MA-33 | B34: RESISTENCIA DE CALEFACCIÓN PARA CUADROS ELÉCTRICOS 30W. IP20 | C34: =E34*F34 -> 262031.84 | D34: UN | E34: 201562.95 | F34: 1.3 | G34: 45323 | H34: https://www.proelectrico.com/wp-content/uploads/2024/10/Lista-de-Precios-2024.pdf
A35: MA-34 | B35: BREAKER DE RIEL MONOPOLAR 1 X 20 AMP 6 KA | C35: =E35*F35 -> 23790 | D35: UN | E35: 18300 | F35: 1.3 | G35: 45698 | H35: https://interelectricas.com.co/breakers/1251-breaker-abb-riel-monopolar-1x-20-amp-6ka.html
A36: MA-35 | B36: BLOQUE DE BORNERAS CORTOCIRCUITABLES DE CORRIENTE Y TENSIÓN | C36: =E36*F36 -> 1075128.6 | D36: UN | E36: 827022 | F36: 1.3 | G36: 44602 | H36: https://indeq.mx/products/2007-8874_wago?srsltid=AfmBOoqMCX4DEwTRrdD6rjJ4kbnuJzcZ_7UTCwmRHF9Ur0cCQfLdsPG6
A37: MA-36 | B37: CANALETAS RANURADA 40X60 MM | C37: =E37*F37 -> 31908.5 | D37: ML | E37: 24545 | F37: 1.3 | G37: 45695 | H37: https://edelco.co/producto/canaleta-ranurada-40-x-60-mm-x-2-00-mts-gris/?srsltid=AfmBOoqvhTSUJXrQuW2aS11-DQhcCgHpNx5sw4G8xMtrYQQAcFT7RGlh
A38: MA-37 | B38: MEDIDOR DE ENERGÍA KWH-KVARH CL 0.5S, DE CONEXIÓN INDIRECTA, MULTIFUNCIONAL CON INSTRUMENTACIÓN Y CURVA DE CARGA, MÍNIMO 8 CANALES, PUERTO ETERNET Y DOS PUERTOS SERIALES, CALIBRADO EN KWH Y KVARH CUATRO CUADRANTES Y BORNERAS CORTOCIRCUITABLES (+Q01A, +Q03A). INCLUYE PRUEBAS DE CALIBRACIÓN POR LABORATORIO ACREDITADO. | C38: =E38*F38 -> 3445591.5 | D38: UN | E38: 2650455 | F38: 1.3 | G38: 45698 | H38: https://autosolar.co/accesorios/medidor-bidireccional-elster-a1800?srsltid=AfmBOooDyoZ8fuMQZLwNErLrcR0phKpWED1SeYthFv3BnYjQ0ZN-_SK3
A39: MA-38 | B39: RELÉ (FUNCIONES: 50, 51, 50N, 51N, 50BFE1/E2,25, 27,59, 74, 79, 67, 67N, 81). PUERTO DE COMUNICACIÓN PARA FIBRA ÓPTICA, PROTOCOLO DE COMUNICACIÓN 61850. PANTALLA TACTIL (IHM). PARA LA BAHÍA DE LÍNEA | C39: =E39*F39 -> 23390640 | D39: UN | E39: =3360*'Precio Monedas'!B2*1.19 -> 17992800 | F39: 1.3 | G39: 45692 | H39: https://selinc.com/es/products/351/
A40: MA-39 | B40: RELE (FUNCIONES: 50, 51, 50N, 51N,50BFE1,E2,27,59,26,49,63,71,96,33,63Q). PUERTO DE COMUNICACIÓN PARA FIBRA ÓPTICA, PROTOCOLO DE COMUNICACIÓN 61850. PANTALLA TACTIL (IHM). PARA LA BAHÍA DE TRANSFORMADOR | C40: =E40*F40 -> 49023954 | D40: UN | E40: =7629*'Precio Monedas'!B2*1.19 -> 40853295 | F40: 1.2 | G40: 45692 | H40: Cotización ABB 25/06/2025
A41: MA-40 | B41: CABLE DE FIBRA ÓPTICA MULTIMODO DE 24 HILOS. LOOSE TUBE - LSZH- UV - NORMA G652D. | C41: =E41*F41 -> 3445 | D41: ML | E41: 2650 | F41: 1.3 | G41: 45698 | H41: https://www.comdiel.cl/cable-fibra-optica-multimodo-exterior-24-fibras-om3-lszh?srsltid=AfmBOopOxT_YDy_JyXaH6EZHofJndYZUhiUW0RL_HanBHL9hkPOXK0_Z
A42: MA-41 | B42: CABLE DE CONTROL APANTALLADO 7x10 AWG Cu- TC-THHN/THWN - ER- 600 V | C42: =E42*F42 -> 52000 | D42: ML | E42: 40000 | F42: 1.3 | G42: 45692 | H42: https://interelectricas.com.co/cable-de-instrumentacion-control/10541-cable-instrumentacion-7x12-awg-gris-apantallado-con-foil-600v-90-grados-dw-12-awg-chaqfr-pvc-resistuv-8bbp107109-i2-241120.html
A43: MA-42 | B43: CABLE DE CONTROL APANTALLADO 7x14 AWG Cu- TC-THHN/THWN - 600 V | C43: =E43*F43 -> 32045 | D43: ML | E43: 24650 | F43: 1.3 | G43: 45692 | H43: https://interelectricas.com.co/cable-de-instrumentacion-control/10546-cable-instrumentacion-7x14-awg-gris-apantallado-con-foil-600v-90-grados-dw-18-awg-chaqfr-pvc-resistuv-8bcp107109-i2-241120.html
A44: MA-43 | B44: CABLE 3x10 AWG Cu- TC-THHN/THWN - 600 V | C44: =E44*F44 -> 26000 | D44: ML | E44: 20000 | F44: 1.3 | G44: 45692 | H44: https://ingecomsas.com/producto/cable-encauchetado-3x10-centelsa/
A45: MA-44 | B45: CABLE DE CONTROL APANTALLADO 19x14 Cu- TC-THHN/THWN- ER-600 V | C45: =E45*F45 -> 194877.74 | D45: ML | E45: 149905.96 | F45: 1.3 | G45: 45692 | H45: https://www.dartel.cl/cable-control-19x14-awg-apantallado-l-h-rz1oz1-r-06-1kv-ne-15364079-ascable/p
A46: MA-45 | B46: RECONECTADOR TRIFÁSICO (R). UM:15KV, IN: 630A, ISC:12.5KA MIN, LIWV:170KV. INCLUYE CONTROL MICROPROCESADOR DE ÚLTIMA TECNOLOGÍA, CABLES DE 6M, PRENSACABLES Y TARJETA DE COMUNICACIÓN LAN DUAL ETHERNET RJ45 Y ÓPTICA MTRJ, 3 SENSORES DE TENSIÓN, 3 SENSORES DE CORRIENTE, UN GABINETE DE COMUNICACIÓN QUE INCLUYA RADIO Y ANTENA, BATERIA DE RESPALDO Y CARGADOR. | C46: =E46*F46 -> 128787750 | D46: UN | E46: =18500*'Precio Monedas'!B2*1.19 -> 99067500 | F46: 1.3 | G46: 45698 | H46: Cotización ABB | I46: https://library.e.abb.com/public/2d5168643b254398924091c3c1a2bd6c/Lista%20de%20Precios%20EL%20ABB%20Chile%20Media%20Tension.pdf?x-sign=ZJKue/Z677X7jWkIvZMTxAEnbHiIE2kTsCwvxniKQViAircjFw29m/zuDKliB3Tz
A47: MA-46 | B47: SECCIONADOR TRIPOLAR MOTORIZADO CON CUCHILLA DE PUESTA A TIERRA MOTORIZADA (SC) UM:15KV, IN: 630A, ISC:12.5KA MIN, LIWV:95KV. INCLUYE: BRAZO DE MANDO MANUAL A LA ALTURA APROPIADA | C47: =E47*F47 -> 55063653 | D47: UN | E47: 45886378 | F47: 1.2 | G47: 45695 | H47: https://energiaputumayo.com/testimonial/solicitud-publica-de-oferta-no-002-2024/
A48: MA-47 | B48: SECCIONADOR TRIPOLAR MOTORIZADO SIN CUCHILLA DE PUESTA A TIERRA (SE). UM:15KV, IN: 630A, ISC:12.5KA MIN, LIWV:95KV. INCLUYE: BRAZO DE MANDO MANUAL A LA ALTURA APROPIADA | C48: =E48*F48 -> 37791537 | D48: UN | E48: 31492947 | F48: 1.2 | G48: 45695 | H48: https://energiaputumayo.com/testimonial/solicitud-publica-de-oferta-no-002-2024/
A49: MA-48 | B49: DPS VNOM: 15KV. ISC 12.5 KA | C49: =E49*F49 -> 154960 | D49: UN | E49: 119200 | F49: 1.3 | G49: 45692 | H49: https://interelectricas.com.co/cortacircuitos-y-proteccion-contra-rayos/2644-pararrayo-polimerico-15kv-10ka.html
A50: MA-49 | B50: TRANSFORMADOR DE CORRIENTE. USO EXTERIOR. TRIPLE NÚCLEO: ( N1:300-600/5 CL: 0,5S, N2:300-600/5 CL: 0,5S, N3:300-600/5 CL: 5P20) UM:15KV, ISC:12.5KA MIN. INCLUYE PROTOCOLOS DE PRUEBA DE PRECISIÓN DE FABRICANTE Y LABORATORIO ACREDITADO. | C50: =E50*F50 -> 20563200 | D50: UN | E50: =3200*'Precio Monedas'!B2*1.19 -> 17136000 | F50: 1.2 | G50: 45695 | H50: Cotización ABB 25/06/2025
A51: MA-50 | B51: TRANSFORMADOR DE CORRIENTE. USO EXTERIOR. TRIPLE NÚCLEO: ( N1:100-200/5 CL: 0,5S, N2:100-200/5 CL: 0,5S, N3:100-200/5 CL: 5P20) UM:15KV, ISC:12.5KA . INCLUYE PROTOCOLOS DE PRUEBA DE PRECISIÓN DE FABRICANTE Y LABORATORIO ACREDITADO. | C51: =E51*F51 -> 20563200 | D51: UN | E51: =3200*'Precio Monedas'!B2*1.19 -> 17136000 | F51: 1.2 | G51: 45695 | H51: Cotización ABB 25/06/2025
A52: MA-51 | B52: TRANSFORMADOR DE TENSIÓN. USO EXTERIOR. DOBLE NUCLEO. (N1: 13,8√3/115√3. CL 0,5, 10 VA; N2: 13,8√3/115√3. 3P) | C52: =E52*F52 -> 18635400 | D52: UN | E52: =2900*'Precio Monedas'!B2*1.19 -> 15529500 | F52: 1.2 | G52: 45695 | H52: Cotización ABB 25/06/2025
A53: MA-52 | B53: BANDEJA PORTACABLES EN ACERO GALVANIZADO RECTO ALTO: 15 CM, ANCHO: 40 CM | C53: =E53*F53 -> 157268.58 | D53: ML | E53: =290342/2.4 -> 120975.83 | F53: 1.3 | G53: 45170 | H53: https://interelectricas.com.co/lista/LISTA_PRECIOS_CL_INGENIERIA.pdf?__cf_chl_tk=zP6d1uC1CL3yA.cbhUVzZlb7FXa21VeeR_R5.JpYQ_4-1739292848-1.0.1.1-idh.FequtBahebQ5CvGqcSdKr.tgn87y7zLncKpo0AI
A54: MA-53 | B54: CURVA BANDEJA PORTACABLES EN ACERO GALVANIZADO A 90° ALTO: 15 CM, ANCHO: 40 CM | C54: =E54*F54 -> 68593.417 | D54: ML | E54: =126634/2.4 -> 52764.167 | F54: 1.3 | G54: 45170 | H54: https://interelectricas.com.co/lista/LISTA_PRECIOS_CL_INGENIERIA.pdf?__cf_chl_tk=zP6d1uC1CL3yA.cbhUVzZlb7FXa21VeeR_R5.JpYQ_4-1739292848-1.0.1.1-idh.FequtBahebQ5CvGqcSdKr.tgn87y7zLncKpo0AI
A55: MA-54 | B55: BANDEJA PORTACABLES EN ACERO GALVANIZADO RECTO ALTO: 15 CM, ANCHO: 20 CM | C55: =E55*F55 -> 137074.71 | D55: ML | E55: =253061/2.4 -> 105442.08 | F55: 1.3 | G55: 45170 | H55: https://interelectricas.com.co/lista/LISTA_PRECIOS_CL_INGENIERIA.pdf?__cf_chl_tk=zP6d1uC1CL3yA.cbhUVzZlb7FXa21VeeR_R5.JpYQ_4-1739292848-1.0.1.1-idh.FequtBahebQ5CvGqcSdKr.tgn87y7zLncKpo0AI
A56: MA-55 | B56: BANDEJA PORTACABLES EN ACERO GALVANIZADO RECTO ALTO: 15 CM, ANCHO: 10 CM | C56: =E56*F56 -> 126975.88 | D56: ML | E56: =234417/2.4 -> 97673.75 | F56: 1.3 | G56: 45170 | H56: https://interelectricas.com.co/lista/LISTA_PRECIOS_CL_INGENIERIA.pdf?__cf_chl_tk=zP6d1uC1CL3yA.cbhUVzZlb7FXa21VeeR_R5.JpYQ_4-1739292848-1.0.1.1-idh.FequtBahebQ5CvGqcSdKr.tgn87y7zLncKpo0AI
A57: MA-56 | B57: CURVA BANDEJA PORTACABLES EN ACERO GALVANIZADO A 90° ALTO: 15 CM, ANCHO: 10 CM. | C57: =E57*F57 -> 55381.083 | D57: ML | E57: =102242/2.4 -> 42600.833 | F57: 1.3 | G57: 45170 | H57: https://interelectricas.com.co/lista/LISTA_PRECIOS_CL_INGENIERIA.pdf?__cf_chl_tk=zP6d1uC1CL3yA.cbhUVzZlb7FXa21VeeR_R5.JpYQ_4-1739292848-1.0.1.1-idh.FequtBahebQ5CvGqcSdKr.tgn87y7zLncKpo0AI
A58: MA-57 | B58: CURVA BANDEJA PORTACABLES EN ACERO GALVANIZADO A 90° ALTO: 15 CM, ANCHO: 20 CM. | C58: =E58*F58 -> 59785.917 | D58: ML | E58: =110374/2.4 -> 45989.167 | F58: 1.3 | G58: 45170 | H58: https://interelectricas.com.co/lista/LISTA_PRECIOS_CL_INGENIERIA.pdf?__cf_chl_tk=zP6d1uC1CL3yA.cbhUVzZlb7FXa21VeeR_R5.JpYQ_4-1739292848-1.0.1.1-idh.FequtBahebQ5CvGqcSdKr.tgn87y7zLncKpo0AI
A59: MA-58 | B59: BANDEJA PORTACABLES EN ACERO GALVANIZADO RECTO ALTO: 15 CM, ANCHO: 20 CM. TIPO DUCTO CERRADO | C59: =E59*F59 -> 137074.71 | D59: ML | E59: =253061/2.4 -> 105442.08 | F59: 1.3 | G59: 45170 | H59: https://interelectricas.com.co/lista/LISTA_PRECIOS_CL_INGENIERIA.pdf?__cf_chl_tk=zP6d1uC1CL3yA.cbhUVzZlb7FXa21VeeR_R5.JpYQ_4-1739292848-1.0.1.1-idh.FequtBahebQ5CvGqcSdKr.tgn87y7zLncKpo0AI
A60: MA-59 | B60: CURVA BANDEJA PORTACABLES EN ACERO GALVANIZADO A 90° ALTO: 15 CM, ANCHO: 20 CM. TIPO DUCTO CERRADO | C60: =E60*F60 -> 59785.917 | D60: ML | E60: =110374/2.4 -> 45989.167 | F60: 1.3 | G60: 45170 | H60: https://interelectricas.com.co/lista/LISTA_PRECIOS_CL_INGENIERIA.pdf?__cf_chl_tk=zP6d1uC1CL3yA.cbhUVzZlb7FXa21VeeR_R5.JpYQ_4-1739292848-1.0.1.1-idh.FequtBahebQ5CvGqcSdKr.tgn87y7zLncKpo0AI
A61: MA-60 | B61: TUBO DUCTO PVC DB DE 4" | C61: =E61*F61 -> 22219.167 | D61: ML | E61: 17091.667 | F61: 1.3 | G61: 45699 | H61: https://interelectricas.com.co/tuberia-metalica-y-pvc/2352-tubo-ducto-pvc-db-de-4-x-6-mts.html
A62: MA-61 | B62: TUBO DUCTO PVC DB DE 3" | C62: =E62*F62 -> 13541.667 | D62: ML | E62: 10416.667 | F62: 1.3 | G62: 45699 | H62: https://interelectricas.com.co/tuberia-metalica-y-pvc/2348-tubo-ducto-pvc-db-de-3-x-3-mts.html
A63: MA-62 | B63: TUBO CONDUIT METÁLICO GALVANIZADO IMC DIAMETRO 1 1/4" | C63: =E63*F63 -> 45500 | D63: ML | E63: =105000/3 -> 35000 | F63: 1.3 | G63: 45699 | H63: https://interelectricas.com.co/tuberia-metalica-y-pvc/2322-tubo-metalico-imc-de-11-4-pulgadas-x-3-mts-con-union.html
A64: MA-63 | B64: CONDULETA TIPO LR DE 1 1/4" | C64: =E64*F64 -> 47646.3 | D64: UN | E64: 36651 | F64: 1.3 | G64: 45699 | H64: https://edelco.co/producto/conduleta-lr-1-1-4-rosca/?srsltid=AfmBOopqFThLk0zDiQ6GmppmAH2ChmkeVtxZxwzapDqhtM98tH4FLm6U
A65: MA-64 | B65: CORAZA METÁLICA LIQUID TIGHT DE 1 1/4" | C65: =E65*F65 -> 15275 | D65: ML | E65: 11750 | F65: 1.3 | G65: 45699 | H65: https://interelectricas.com.co/tuberia-metalica-y-pvc/2093-coraza-liquid-tight-tipo-americano-11-4-pulgadas-x-metro.html
A66: MA-65 | B66: CONECTOR RECTO LIQUID TIGHT DE 1 1/4" | C66: =E66*F66 -> 11505 | D66: UN | E66: 8850 | F66: 1.3 | G66: 45699 | H66: https://interelectricas.com.co/herrajes-electricos/1738-conector-coraza-liquid-recto-1-1-4-pulg-.html
A67: MA-66 | B67: TUBERÍA PVC 1 1/4" | C67: =E67*F67 -> 5200 | D67: ML | E67: =12000/3 -> 4000 | F67: 1.3 | G67: 45699 | H67: https://interelectricas.com.co/tuberia-metalica-y-pvc/2363-tubo-pvc-conduit-de-1-1-4-x-3mts.html
A68: MA-67 | B68: CURVA PVC 1 1/4" | C68: =E68*F68 -> 2600 | D68: UN | E68: 2000 | F68: 1.3 | G68: 45699 | H68: https://interelectricas.com.co/tuberia-metalica-y-pvc/972-curva-pvc-de-1-1-4.html
A69: MA-68 | B69: HEBILLA DE ACERO INOXIDABLE. DIMENSIONES 15.87 MM (REF. EH = 1292) | C69: =E69*F69 -> 780 | D69: UN | E69: 600 | F69: 1.3 | G69: 45699 | H69: https://interelectricas.com.co/cintas-o-zuncho-metalico-en-acero-inoxidable/1718-hebilla-en-acero-inoxidable-para-fleje-o-cinta-metalica-3-4.html
A70: MA-69 | B70: TUBO CONDUIT METÁLICO GALVANIZADO IMC DIAMETRO 3/4" | C70: =E70*F70 -> 29965 | D70: ML | E70: 23050 | F70: 1.3 | G70: 45699 | H70: https://interelectricas.com.co/tuberia-metalica-y-pvc/2326-tubo-metalico-imc-de-3-4-pulgadas-x-3-mts-con-union.html
A71: MA-70 | B71: CORAZA METÁLICA LIQUID TIGHT DE 3/4" | C71: =E71*F71 -> 8905 | D71: ML | E71: 6850 | F71: 1.3 | G71: 45699 | H71: https://interelectricas.com.co/tuberia-metalica-y-pvc/2087-coraza-liquid-tight-tipo-americano-3-4-pulgadas-x-metro.html
A72: MA-71 | B72: TUBERÍA PVC 3/4" | C72: =E72*F72 -> 2253.3333 | D72: ML | E72: 1733.3333 | F72: 1.3 | G72: 45699 | H72: https://interelectricas.com.co/tuberia-metalica-y-pvc/2368-tubo-pvc-conduit-de-3-4-x-3-mts.html
A73: MA-72 | B73: CURVA PVC 3/4" | C73: =E73*F73 -> 975 | D73: UN | E73: 750 | F73: 1.3 | G73: 45699 | H73: https://interelectricas.com.co/tuberia-metalica-y-pvc/967-curva-pvc-de-3-4.html
A74: MA-73 | B74: CONECTOR RECTO LIQUID TIGHT DE 3/4" | C74: =E74*F74 -> 19034.6 | D74: UN | E74: 14642 | F74: 1.3 | G74: 45699 | H74: https://interelectricas.com.co/conector-coraza/68-conector-coraza-liquid-tight-recto-3-4-pulg-hierro-a-prueba.html
A75: MA-74 | B75: CONDULETA TIPO LR DE 3/4" IMC | C75: =E75*F75 -> 8433.1 | D75: UN | E75: 6487 | F75: 1.3 | G75: 45699 | H75: https://electroservimos.co/sistemas-de-canalizacion/1859-c7lr11-conduleta-de-lr-imc-rosca-cooper-crouse-hinds.html
A76: MA-75 | B76: TUBO CONDUIT METÁLICO GALVANIZADO IMC DIAMETRO 2" | C76: =E76*F76 -> 69593.333 | D76: ML | E76: =160600/3 -> 53533.333 | F76: 1.3 | G76: 45699 | H76: https://interelectricas.com.co/tuberia-metalica-y-pvc/2324-tubo-metalico-imc-de-2-pulgadas-x-3-mts-con-union.html
A77: MA-76 | B77: CORAZA METÁLICA LIQUID TIGHT DE 2" | C77: =E77*F77 -> 25285 | D77: ML | E77: 19450 | F77: 1.3 | G77: 45700 | H77: https://interelectricas.com.co/tuberia-metalica-y-pvc/2089-coraza-liquid-tight-tipo-americano-2-pulgadas-x-metro-ref-2.html
A78: MA-77 | B78: TUBERÍA PVC 2" | C78: =E78*F78 -> 6261.6667 | D78: ML | E78: 4816.6667 | F78: 1.3 | G78: 45700 | H78: https://interelectricas.com.co/tuberia-metalica-y-pvc/2346-tubo-ducto-pvc-db-de-2-x-6-mts.html
A79: MA-78 | B79: CURVA PVC 2" | C79: =E79*F79 -> 4680 | D79: UN | E79: 3600 | F79: 1.3 | G79: 45700 | H79: https://interelectricas.com.co/tuberia-metalica-y-pvc/959-curva-pvc-de-2.html
A80: MA-79 | B80: CONECTOR RECTO LIQUID TIGHT DE 2" | C80: =E80*F80 -> 17095 | D80: UN | E80: 13150 | F80: 1.3 | G80: 45700 | H80: https://interelectricas.com.co/herrajes-electricos/1740-conector-coraza-liquid-tight-recto-2-pulg-.html
A81: MA-80 | B81: CONDULETA TIPO LR DE 2" IMC | C81: =E81*F81 -> 22662.9 | D81: UN | E81: 17433 | F81: 1.3 | G81: 45700 | H81: https://vitelenergia.com/es/condulet-aluminio-lr-2.html
A82: MA-81 | B82: GABINETE PISO PARA SERVIDOR 42RU 210 ALTO 60 ANCHO 90 PROFUNDO | C82: =E82*F82 -> 2275000 | D82: UN | E82: 1750000 | F82: 1.3 | G82: 45700 | H82: https://ferretodo.com.co/ferretienda/gabinete-piso-para-servidor-42ru-210-alto-60-ancho-90-profundo/?srsltid=AfmBOoqPIe88wtXl4DyTiL5gg279H2jOpLh2ArK0Dyj8b0628OVD6S3w
A83: MA-82 | B83: UPS 3000 VA | C83: =E83*F83 -> 2382590.6 | D83: UN | E83: 1832762 | F83: 1.3 | G83: 45700 | H83: https://sucomputo.com/producto/ups-interactiva-micronet-3000va/
A84: MA-83 | B84: CONCENTRADOR DE DATOS, GATEWAY | C84: =E84*F84 -> 20748000 | D84: UN | E84: 15960000 | F84: 1.3 | G84: 45700 | H84: https://selinc.com/es/products/3620/
A85: MA-84 | B85: SWITCH ETHERNET ADMINISTRABLE DE 24 PUERTOS | C85: =E85*F85 -> 17550000 | D85: UN | E85: =3000*'Precio Monedas'!B2 -> 13500000 | F85: 1.3 | G85: 45700 | H85: https://selinc.com/es/products/2730M/
A86: MA-85 | B86: COMPUTADOR DE ESCRITORIO. PANTALLA 32 PULGADAS, PROCESADOR QUAD-CORE A 1.6 GHZ O SUPERIOR, RAM: MÍNIMO 4 GB, ALMACENAMIENTO: 1 TB, 2 PUERTOS ETHERNET , COMPATIBILIDAD CON IEC 61850, MODBUS TCP/IP, DNP3, OPC UA/DA, Y PROTOCOLOS ESTÁNDAR SCADA. | C86: =E86*F86 -> 10400000 | D86: UN | E86: 8000000 | F86: 1.3 | G86: 45700 | H86: https://todotintasysuministros.com/computadores-de-escritorio/computador-de-escritorio-power-group-l23-21-5-ryzen7-ram16gb-ssd-1tb-t-vrtx-3050
A87: MA-86 | B87: RELOJ DE RED SINCRONIZADO VÍA SATÉLITE | C87: =E87*F87 -> 18181800 | D87: UN | E87: 13986000 | F87: 1.3 | G87: 45700 | H87: https://selinc.com/es/products/2488/
A88: MA-87 | B88: ROUTER. SOPORTE PARA IEC 61850 | C88: =E88*F88 -> 5951400 | D88: UN | E88: 4578000 | F88: 1.3 | G88: 45700 | H88: https://selinc.com/products/3622/
A89: MA-88 | B89: ODF DESLIZABLE TIPO RACK, CON ENFRENTADORES LC/LC EMBEBIDOS Y PIGTAILS MULTIMODO INCLUIDO CON CONECTORES LC/LC, TERMINACIÓN UPC. ANCHO DE 19” PARA COLOCAR 24 ACOPLADORES LC DUPLEX (48 HILOS). IP20 O SUPERIOR. | C89: =E89*F89 -> 280800 | D89: UN | E89: 216000 | F89: 1.3 | G89: 45700 | H89: https://www.macrotics.com/bandeja-de-fibra-optica-glc-con-adaptador-y-pigtail-sc-apc-x-24-puertos/p?srsltid=AfmBOoo_U4pRKfy26owDuHIX_gs84hN2jZObIj5eV9rVqCfR6eGacEz4
A90: MA-89 | B90: SERVICIO DE CANAL SATELITAL 128 KBPS UP/DOWN BANDA KU. 12 MESES DE SERVICIO | C90: =E90*F90 -> 11009570 | D90: UN | E90: 8468900 | F90: 1.3 | G90: 45695 | H90: https://energiaputumayo.com/testimonial/solicitud-publica-de-oferta-no-002-2024/
A91: MA-90 | B91: INTEGRACIÓN EQUIPOS DE MANIOBRA Y CORTE MEDIANTE EL SISTEMA SCADA AL CENTRO DE CONTROL DE ELECTROHUILA | C91: =E91*F91 -> 0 | D91: UN | E91: 0 | F91: 1.3 | G91: 45695 | H91: https://energiaputumayo.com/testimonial/solicitud-publica-de-oferta-no-002-2024/
A92: MA-91 | B92: PATCH CORD DE FIBRA ÓPTICA MULTIMODO OM3 LC - ST/UPC DE 2 METROS | C92: =E92*F92 -> 47582.6 | D92: UN | E92: 36602 | F92: 1.3 | G92: 45700 | H92: https://www.daga-store.com/patch-cords-duplex-multimodo-om3-lc-lc
A93: MA-92 | B93: TERMOENCOGIBLES 5 mm | C93: =E93*F93 -> 3900 | D93: UN | E93: 3000 | F93: 1.3 | G93: 45700 | H93: https://www.homecenter.com.co/homecenter-co/product/519772/tubo-termoencogible-6mm-x-10cm/519772/
A94: MA-93 | B94: CAJA DE DISTRIBUCIÓN DE FIBRA ÓPTICA PARA 24 EMPALMES CON 16 ACOPLADORES SC/APC | C94: =E94*F94 -> 202402.2 | D94: UN | E94: 155694 | F94: 1.3 | G94: 45700 | H94: https://lasus.com.co/es/caja-de-distribucion-de-fibra-optica-para-24-empalmes-con-16-acopladores-sc-apc?srsltid=AfmBOoqp_KIu98Ke6YlSHMRWWVUuNga1KIo8lBefui8lhTbN7MCmbnlx
A95: MA-94 | B95: ADAPTADORES DE FIBRA ÓPTICA LC, SC, ST | C95: =E95*F95 -> 37570 | D95: UN | E95: 28900 | F95: 1.3 | G95: 45700 | H95: https://ferretodo.com.co/ferretienda/conector-de-fibra-optica-sc-lightcrimp-plus/
A96: MA-95 | B96: TRANSFORMADOR TRIFASICO EN ACEITE DE 30 KVA - 34.500 V - 208 | C96: =E96*F96 -> 17280000 | D96: UN | E96: 14400000 | F96: 1.2 | G96: 45700 | H96: https://ineldec.com/producto/transformador-trifasico-convencional-30-kva/
A97: MA-96 | B97: TRANSFORMADOR TRIFASICO EN ACEITE DE 30 KVA - 13.200 V - 208 | C97: =E97*F97 -> 12621300 | D97: UN | E97: 10517750 | F97: 1.2 | G97: 45700 | H97: https://interelectricas.com.co/transformadores-en-aceite/2385-transformador-trifasico-en-aceite-de-30-kva-13200-v-208-120-v-plena.html
A98: MA-97 | B98: ARANDELA CUADRADA PLANA DE 51*17 MM DIAMETRO= 16 MM (2 PULG.X2 PULG.X5/8 PULG.) (REF. EH = 2412) | C98: =E98*F98 -> 1638 | D98: UN | E98: 1260 | F98: 1.3 | H98: APU cinco sas
A99: MA-98 | B99: ARANDELA DE PRESION DE DIAMETRO= 22 MM PARA PERNO DIAMETRO= 13 MM (1/2 PULG.) (REF. EH = 2433) | C99: =E99*F99 -> 507 | D99: UN | E99: 390 | F99: 1.3 | H99: APU cinco sas
A100: MA-99 | B100: ARANDELA DE PRESION DE DIAMETRO= 26 MM PARA PERNO DIAMETRO= 16 MM (5/8 PULG.) (REF. EH = 2434) | C100: =E100*F100 -> 509.6 | D100: UN | E100: 392 | F100: 1.3 | H100: APU cinco sas
...

Sheet APUs
A1: Codigo APU | B1: Nombre APU | D1: Unidad APU | E1: Rendimiento | F1: Fecha | G1: Valor APU
A2: =Presupuesto!B6 -> 001_OC | B2: =Presupuesto!C6 -> COMPLEMENTACIÓN Y/O AJUSTE A ESTUDIOS Y DISEÑOS (INCLUYE LEVANTAMIENTO TOPOGRÁFICO, ESTUDIO DE SUELO, DISEÑO HIDRÁULICO E HIDROSANITARIO, DISEÑO ELÉCTRICO, DISEÑO ESTRUCTURAL) | D2: UN | E2: 2 | G2: =G64 -> 26197600
A3: A. MATERIAL
A4: Referencia | B4: Descripción | D4: Unidad | E4: Cantidad | F4: Vr. Unitario ($) | G4: Vr. Total ($)
A5: =Material!A580 -> MA-579 | B5: =IFERROR(VLOOKUP(A5,Material!$A:$H,2,0),"-") -> COMPLEMENTACIÓN Y/O AJUSTE A ESTUDIOS Y DISEÑOS (INCLUYE LEVANTAMIENTO TOPOGRÁFICO, ESTUDIO DE SUELO, DISEÑO HIDRÁULICO E HIDROSANITARIO, DISEÑO ELÉCTRICO, DISEÑO ESTRUCTURAL) | D5: =IFERROR(VLOOKUP(A5,Material!$A:$H,4,0),"-") -> UN | E5: 1 | F5: =IFERROR(VLOOKUP(A5,Material!$A:$H,3,0),"-") -> 20800000 | G5: =IFERROR(ROUNDUP(F5*E5,0),"-") -> 20800000
A6: Subtotal A | G6: =SUM(G5:G5) -> 20800000
A8: B. MANO DE OBRA
A9: Referencia | B9: Descripción | C9: Cantidad | D9: Fac. Sal | E9: Jornal ($) | F9: Prestaciones ($) | G9: Vr. Total ($)
A10: MO-1 | B10: =VLOOKUP(A10,'Componentes APUs'!$H$1:$L$25,2,0) -> Ingeniero Residente de Obra | C10: 0 | D10: =VLOOKUP(A10,'Componentes APUs'!$H$1:$L$25,3,0) -> 4 | E10: =VLOOKUP(A10,'Componentes APUs'!$H$1:$L$25,4,0) -> 271142.86 | F10: =VLOOKUP(A10,'Componentes APUs'!$H$1:$L$25,5,0) -> 162685.71 | G10: =ROUNDUP((E10+F10)*C10/E2,0) -> 0
A11: MO-3 | B11: =VLOOKUP(A11,'Componentes APUs'!$H$1:$L$25,2,0) -> Tecnico Liniero | C11: 0 | D11: =VLOOKUP(A11,'Componentes APUs'!$H$1:$L$25,3,0) -> 2 | E11: =VLOOKUP(A11,'Componentes APUs'!$H$1:$L$25,4,0) -> 154619.05 | F11: =VLOOKUP(A11,'Componentes APUs'!$H$1:$L$25,5,0) -> 92771.429 | G11: =ROUNDUP((E11+F11)*C11/E2,0) -> 0
A12: MO-8 | B12: =VLOOKUP(A12,'Componentes APUs'!$H$1:$L$25,2,0) -> Maestro de obra civil | C12: 0 | D12: =VLOOKUP(A12,'Componentes APUs'!$H$1:$L$25,3,0) -> 2.5 | E12: =VLOOKUP(A12,'Componentes APUs'!$H$1:$L$25,4,0) -> 169464.29 | F12: =VLOOKUP(A12,'Componentes APUs'!$H$1:$L$25,5,0) -> 101678.57 | G12: =ROUNDUP((E12+F12)*C12/E2,0) -> 0
A13: MO-9 | B13: =VLOOKUP(A13,'Componentes APUs'!$H$1:$L$25,2,0) -> Oficial de Obra Civil | C13: 0 | D13: =VLOOKUP(A13,'Componentes APUs'!$H$1:$L$25,3,0) -> 1.5 | E13: =VLOOKUP(A13,'Componentes APUs'!$H$1:$L$25,4,0) -> 115964.29 | F13: =VLOOKUP(A13,'Componentes APUs'!$H$1:$L$25,5,0) -> 69578.571 | G13: =ROUNDUP((E13+F13)*C13/E2,0) -> 0
A14: MO-5 | B14: =VLOOKUP(A14,'Componentes APUs'!$H$1:$L$25,2,0) -> Profesional en SST | C14: 0 | D14: =VLOOKUP(A14,'Componentes APUs'!$H$1:$L$25,3,0) -> 2.5 | E14: =VLOOKUP(A14,'Componentes APUs'!$H$1:$L$25,4,0) -> 169464.29 | F14: =VLOOKUP(A14,'Componentes APUs'!$H$1:$L$25,5,0) -> 101678.57 | G14: =ROUNDUP((E14+F14)*C14/E2,0) -> 0
A15: MO-6 | B15: =VLOOKUP(A15,'Componentes APUs'!$H$1:$L$25,2,0) -> Ayudante No Calificado | C15: 0 | D15: =VLOOKUP(A15,'Componentes APUs'!$H$1:$L$25,3,0) -> 1 | E15: =VLOOKUP(A15,'Componentes APUs'!$H$1:$L$25,4,0) -> 77309.524 | F15: =VLOOKUP(A15,'Componentes APUs'!$H$1:$L$25,5,0) -> 46385.714 | G15: =ROUNDUP((E15+F15)*C15/E2,0) -> 0
A16: Subtotal B | G16: =SUM(G10:G15) -> 0
A18: C. EQUIPOS Y HERRAMIENTAS
A19: Referencia | B19: Descripción | D19: Unidad | E19: Cantidad | F19: Vr. Unitario ($) | G19: Vr. Total ($)
A20: EH-1 | B20: =VLOOKUP(A20,'Componentes APUs'!$S$1:$V$10,2,0) -> Juego Llaves | D20: U | E20: 0 | F20: =VLOOKUP(A20,'Componentes APUs'!$S$1:$V$10,4,0) -> 9167 | G20: =ROUNDUP(F20*((E20/21)/E2),0) -> 0
A21: EH-2 | B21: =VLOOKUP(A21,'Componentes APUs'!$S$1:$V$10,2,0) -> Manila de servicio | D21: U | E21: 0 | F21: =VLOOKUP(A21,'Componentes APUs'!$S$1:$V$10,4,0) -> 2333 | G21: =ROUNDUP(F21*((E21/21)/E2),0) -> 0
A22: EH-3 | B22: =VLOOKUP(A22,'Componentes APUs'!$S$1:$V$10,2,0) -> Tula portaherramientas | D22: U | E22: 0 | F22: =VLOOKUP(A22,'Componentes APUs'!$S$1:$V$10,4,0) -> 1250 | G22: =ROUNDUP(F22*((E22/21)/E2),0) -> 0
A23: EH-4 | B23: =VLOOKUP(A23,'Componentes APUs'!$S$1:$V$10,2,0) -> Agarradoras | D23: U | E23: 0 | F23: =VLOOKUP(A23,'Componentes APUs'!$S$1:$V$10,4,0) -> 125000 | G23: =ROUNDUP(F23*((E23/21)/E2),0) -> 0
A24: EH-5 | B24: =VLOOKUP(A24,'Componentes APUs'!$S$1:$V$10,2,0) -> Templadoras | D24: U | E24: 0 | F24: =VLOOKUP(A24,'Componentes APUs'!$S$1:$V$10,4,0) -> 250000 | G24: =ROUNDUP(F24*((E24/21)/E2),0) -> 0
A25: EH-6 | B25: =VLOOKUP(A25,'Componentes APUs'!$S$1:$V$10,2,0) -> Herramienta Menor | D25: U | E25: 0 | F25: =VLOOKUP(A25,'Componentes APUs'!$S$1:$V$10,4,0) -> 75758 | G25: =ROUNDUP(F25*((E25/21)/E2),0) -> 0
A26: Subtotal C | G26: =SUM(G20:G25) -> 0
A28: D. EPP Y DOTACION
A29: Referencia | B29: Descripción | D29: Unidad | E29: Cantidad | F29: Vr. Unitario ($) | G29: Vr. Total ($)
A30: ED-1 | B30: =VLOOKUP(A30,'Componentes APUs'!$A$1:$D$14,2,0) -> Camisa indigo sin partes metalicas | D30: =VLOOKUP(A30,'Componentes APUs'!$A$1:$D$14,3,0) -> U | E30: =SUM(C10:C15) -> 0 | F30: =VLOOKUP(A30,'Componentes APUs'!$A$1:$D$14,4,0) -> 8585.8586 | G30: =ROUNDUP(F30*(E30/21)/E2,0) -> 0
A31: ED-2 | B31: =VLOOKUP(A31,'Componentes APUs'!$A$1:$D$14,2,0) -> Bota de seguridad dielectrica | D31: =VLOOKUP(A31,'Componentes APUs'!$A$1:$D$14,3,0) -> Par | E31: =SUM(C10:C15) -> 0 | F31: =VLOOKUP(A31,'Componentes APUs'!$A$1:$D$14,4,0) -> 7500 | G31: =ROUNDUP(F31*(E31/21)/E2,0) -> 0
A32: ED-3 | B32: =VLOOKUP(A32,'Componentes APUs'!$A$1:$D$14,2,0) -> Casco dielectrico Tipo 1 Clase E con barbuquejo | D32: =VLOOKUP(A32,'Componentes APUs'!$A$1:$D$14,3,0) -> U | E32: =C10+C11+C13+C14+C15+IF(A12<>"MO-3",C12,0) -> 0 | F32: =VLOOKUP(A32,'Componentes APUs'!$A$1:$D$14,4,0) -> 10101.01 | G32: =ROUNDUP(F32*(E32/21)/E2,0) -> 0
A33: ED-4 | B33: =VLOOKUP(A33,'Componentes APUs'!$A$1:$D$14,2,0) -> Correa plastica y antiflama | D33: =VLOOKUP(A33,'Componentes APUs'!$A$1:$D$14,3,0) -> U | E33: =SUM(C10:C15) -> 0 | F33: =VLOOKUP(A33,'Componentes APUs'!$A$1:$D$14,4,0) -> 3787.8788 | G33: =ROUNDUP(F33*(E33/21)/E2,0) -> 0
A34: ED-5 | B34: =VLOOKUP(A34,'Componentes APUs'!$A$1:$D$14,2,0) -> Gafas protectoras filtro UV | D34: =VLOOKUP(A34,'Componentes APUs'!$A$1:$D$14,3,0) -> U | E34: =SUM(C10:C15) -> 0 | F34: =VLOOKUP(A34,'Componentes APUs'!$A$1:$D$14,4,0) -> 2777.7778 | G34: =ROUNDUP(F34*(E34/21)/E2,0) -> 0
A35: ED-6 | B35: =VLOOKUP(A35,'Componentes APUs'!$A$1:$D$14,2,0) -> Bota de seguridad PVC dielectrica | D35: =VLOOKUP(A35,'Componentes APUs'!$A$1:$D$14,3,0) -> Par | E35: =SUM(C10:C15) -> 0 | F35: =VLOOKUP(A35,'Componentes APUs'!$A$1:$D$14,4,0) -> 2916.6667 | G35: =ROUNDUP(F35*(E35/21)/E2,0) -> 0
A36: ED-7 | B36: =VLOOKUP(A36,'Componentes APUs'!$A$1:$D$14,2,0) -> Capuchon | D36: =VLOOKUP(A36,'Componentes APUs'!$A$1:$D$14,3,0) -> U | E36: =SUM(C10:C15) -> 0 | F36: =VLOOKUP(A36,'Componentes APUs'!$A$1:$D$14,4,0) -> 2525.2525 | G36: =ROUNDUP(F36*(E36/21)/E2,0) -> 0
A37: ED-8 | B37: =VLOOKUP(A37,'Componentes APUs'!$A$1:$D$14,2,0) -> Guantes Protectores - ingeniero reforzados | D37: =VLOOKUP(A37,'Componentes APUs'!$A$1:$D$14,3,0) -> Par | E37: =C12+C13+C15 -> 0 | F37: =VLOOKUP(A37,'Componentes APUs'!$A$1:$D$14,4,0) -> 2525.2525 | G37: =ROUNDUP(F37*(E37/21)/E2,0) -> 0
A38: ED-9 | B38: =VLOOKUP(A38,'Componentes APUs'!$A$1:$D$14,2,0) -> Impermeable (pantalon camisa) | D38: =VLOOKUP(A38,'Componentes APUs'!$A$1:$D$14,3,0) -> U | E38: =SUM(C10:C15) -> 0 | F38: =VLOOKUP(A38,'Componentes APUs'!$A$1:$D$14,4,0) -> 3750 | G38: =ROUNDUP(F38*(E38/21)/E2,0) -> 0
A39: ED-10 | B39: =VLOOKUP(A39,'Componentes APUs'!$A$1:$D$14,2,0) -> Jean Dielectrico | D39: =VLOOKUP(A39,'Componentes APUs'!$A$1:$D$14,3,0) -> U | E39: =SUM(C10:C15) -> 0 | F39: =VLOOKUP(A39,'Componentes APUs'!$A$1:$D$14,4,0) -> 7575.7576 | G39: =ROUNDUP(F39*(E39/21)/E2,0) -> 0
A40: ED-11 | B40: =VLOOKUP(A40,'Componentes APUs'!$A$1:$D$14,2,0) -> Casco dielectrico Tipo 2 Clase E con barboquejo | D40: =VLOOKUP(A40,'Componentes APUs'!$A$1:$D$14,3,0) -> U | E40: =IF(A12="MO-3",C12,0) -> 0 | F40: =VLOOKUP(A40,'Componentes APUs'!$A$1:$D$14,4,0) -> 7500 | G40: =ROUNDUP(F40*(E40/21)/E2,0) -> 0
A41: ED-12 | B41: =VLOOKUP(A41,'Componentes APUs'!$A$1:$D$14,2,0) -> Kit de rescate para trabajo en alturas | D41: =VLOOKUP(A41,'Componentes APUs'!$A$1:$D$14,3,0) -> U | E41: =IF(AND(A12="MO-3",C12=2),1,0) -> 0 | F41: =VLOOKUP(A41,'Componentes APUs'!$A$1:$D$14,4,0) -> 37500 | G41: =ROUNDUP(F41*(E41/21)/E2,0) -> 0
A42: ED-13 | B42: =VLOOKUP(A42,'Componentes APUs'!$A$1:$D$14,2,0) -> Equipo completo para trabajo en alturas con pretales (Arnes dielectrico, 1 mosqueton de seguridad, tie off dielectrico, eslinga de posicionamiento, juego de pretales) | D42: =VLOOKUP(A42,'Componentes APUs'!$A$1:$D$14,3,0) -> U | E42: =IF(A12="MO-3",C12,0) -> 0 | F42: =VLOOKUP(A42,'Componentes APUs'!$A$1:$D$14,4,0) -> 26041.667 | G42: =ROUNDUP(F42*(E42/21)/E2,0) -> 0
A43: Subtotal D | G43: =SUM(G30:G42) -> 0
A45: E. TRANSPORTE Y VIATICACION
A46: Referencia | B46: Descripción | D46: Unidad | E46: Cantidad | F46: Vr. Unitario ($) | G46: Vr. Total ($)
A47: TV-1 | B47: =VLOOKUP(A47,'Componentes APUs'!$N$1:$Q$30,2,0) -> Camioneta | D47: =VLOOKUP(A47,'Componentes APUs'!$N$1:$Q$30,3,0) -> U | E47: 0 | F47: =VLOOKUP(A47,'Componentes APUs'!$N$1:$Q$30,4,0) -> 5500000 | G47: =IFERROR(ROUNDUP(F47*(E47/21)/E2,0),"-") -> 0
A48: TV-10 | B48: =VLOOKUP(A48,'Componentes APUs'!$N$1:$Q$30,2,0) -> Rodillo Ligero | D48: =VLOOKUP(A48,'Componentes APUs'!$N$1:$Q$30,3,0) -> U | E48: 0 | F48: =VLOOKUP(A48,'Componentes APUs'!$N$1:$Q$30,4,0) -> 1675800 | G48: =IFERROR(ROUNDUP(F48*(E48/21)/E2,0),"-") -> 0
A49: TV-11 | B49: =VLOOKUP(A49,'Componentes APUs'!$N$1:$Q$30,2,0) -> Motocultor | D49: =VLOOKUP(A49,'Componentes APUs'!$N$1:$Q$30,3,0) -> U | E49: 0 | F49: =VLOOKUP(A49,'Componentes APUs'!$N$1:$Q$30,4,0) -> 1292760 | G49: =IFERROR(ROUNDUP(F49*(E49/21)/E2,0),"-") -> 0
A50: TV-4 | B50: =VLOOKUP(A50,'Componentes APUs'!$N$1:$Q$30,2,0) -> Volqueta | D50: =VLOOKUP(A50,'Componentes APUs'!$N$1:$Q$30,3,0) -> U | E50: 0 | F50: =VLOOKUP(A50,'Componentes APUs'!$N$1:$Q$30,4,0) -> 14828184 | G50: =IFERROR(ROUNDUP(F50*(E50/21)/E2,0),"-") -> 0
A51: TV-5 | B51: =VLOOKUP(A51,'Componentes APUs'!$N$1:$Q$30,2,0) -> Retroexcavadora | D51: =VLOOKUP(A51,'Componentes APUs'!$N$1:$Q$30,3,0) -> U | E51: 0 | F51: =VLOOKUP(A51,'Componentes APUs'!$N$1:$Q$30,4,0) -> 46030656 | G51: =IFERROR(ROUNDUP(F51*(E51/21)/E2,0),"-") -> 0
A52: Subtotal E | G52: =SUM(G47:G51) -> 0
A54: SUBTOTAL COSTOS DIRECTOS (A+B+C+D+E) | G54: =G52+G43+G26+G16+G6 -> 20800000
E56: ADMINISTRACIÓN | F56: 0.15 | G56: =G54*F56 -> 3120000
E57: IMPREVISTOS | F57: 0.05 | G57: =G54*F57 -> 1040000
E58: UTILIDAD | F58: 0.05 | G58: =G54*F58 -> 1040000
A60: SUBTOTAL COSTOS DIRECTOS (A+B+C+D+E) + COSTOS INDIRECTOS (C.I) | G60: =G54+G56+G57+G58 -> 26000000
E62: IVA (OBRA) | F62: 19% | G62: =G58*19% -> 197600
A64: TOTAL APU | G64: =G62+G60 -> 26197600
A66: Codigo APU | B66: Nombre APU | D66: Unidad APU | E66: Rendimiento | F66: Fecha | G66: Valor APU
A67: =Presupuesto!B7 -> 002_OC | B67: =Presupuesto!C7 -> LIMPIEZA DE LOTE, PARA QUITAR MALEZA Y PODAR CÉSPED | D67: M2 | E67: 300 | G67: =G135 -> 44151.772
A68: A. MATERIAL
A69: Referencia | B69: Descripción | D69: Unidad | E69: Cantidad | F69: Vr. Unitario ($) | G69: Vr. Total ($)
A70: =Material!A647 -> MA-646 | B70: =IFERROR(VLOOKUP(A70,Material!$A:$H,2,0),"-") -> DISOLVENTE ESMALTE | D70: =IFERROR(VLOOKUP(A70,Material!$A:$H,4,0),"-") -> LT | E70: 1 | F70: =IFERROR(VLOOKUP(A70,Material!$A:$H,3,0),"-") -> 33081.1 | G70: =IFERROR(ROUNDUP(F70*E70,0),"-") -> 33082
B71: =IFERROR(VLOOKUP(A71,Material!$A:$H,2,0),"-") -> - | D71: =IFERROR(VLOOKUP(A71,Material!$A:$H,4,0),"-") -> - | F71: =IFERROR(VLOOKUP(A71,Material!$A:$H,3,0),"-") -> - | G71: =IFERROR(ROUNDUP(F71*E71,0),"-") -> -
B72: =IFERROR(VLOOKUP(A72,Material!$A:$H,2,0),"-") -> - | D72: =IFERROR(VLOOKUP(A72,Material!$A:$H,4,0),"-") -> - | F72: =IFERROR(VLOOKUP(A72,Material!$A:$H,3,0),"-") -> - | G72: =IFERROR(ROUNDUP(F72*E72,0),"-") -> -
B73: =IFERROR(VLOOKUP(A73,Material!$A:$H,2,0),"-") -> - | D73: =IFERROR(VLOOKUP(A73,Material!$A:$H,4,0),"-") -> - | F73: =IFERROR(VLOOKUP(A73,Material!$A:$H,3,0),"-") -> - | G73: =IFERROR(ROUNDUP(F73*E73,0),"-") -> -
A77: Subtotal A | G77: =SUM(G70:G76) -> 33082
A79: B. MANO DE OBRA
A80: Referencia | B80: Descripción | C80: Cantidad | D80: Fac. Sal | E80: Jornal ($) | F80: Prestaciones ($) | G80: Vr. Total ($)
A81: MO-1 | B81: =VLOOKUP(A81,'Componentes APUs'!$H$1:$L$25,2,0) -> Ingeniero Residente de Obra | C81: 0 | D81: =VLOOKUP(A81,'Componentes APUs'!$H$1:$L$25,3,0) -> 4 | E81: =VLOOKUP(A81,'Componentes APUs'!$H$1:$L$25,4,0) -> 271142.86 | F81: =VLOOKUP(A81,'Componentes APUs'!$H$1:$L$25,5,0) -> 162685.71 | G81: =ROUNDUP((E81+F81)*C81/E67,0) -> 0
A82: MO-3 | B82: =VLOOKUP(A82,'Componentes APUs'!$H$1:$L$25,2,0) -> Tecnico Liniero | C82: 0 | D82: =VLOOKUP(A82,'Componentes APUs'!$H$1:$L$25,3,0) -> 2 | E82: =VLOOKUP(A82,'Componentes APUs'!$H$1:$L$25,4,0) -> 154619.05 | F82: =VLOOKUP(A82,'Componentes APUs'!$H$1:$L$25,5,0) -> 92771.429 | G82: =ROUNDUP((E82+F82)*C82/E67,0) -> 0
A83: MO-8 | B83: =VLOOKUP(A83,'Componentes APUs'!$H$1:$L$25,2,0) -> Maestro de obra civil | C83: 0 | D83: =VLOOKUP(A83,'Componentes APUs'!$H$1:$L$25,3,0) -> 2.5 | E83: =VLOOKUP(A83,'Componentes APUs'!$H$1:$L$25,4,0) -> 169464.29 | F83: =VLOOKUP(A83,'Componentes APUs'!$H$1:$L$25,5,0) -> 101678.57 | G83: =ROUNDUP((E83+F83)*C83/E67,0) -> 0
A84: MO-9 | B84: =VLOOKUP(A84,'Componentes APUs'!$H$1:$L$25,2,0) -> Oficial de Obra Civil | C84: 0 | D84: =VLOOKUP(A84,'Componentes APUs'!$H$1:$L$25,3,0) -> 1.5 | E84: =VLOOKUP(A84,'Componentes APUs'!$H$1:$L$25,4,0) -> 115964.29 | F84: =VLOOKUP(A84,'Componentes APUs'!$H$1:$L$25,5,0) -> 69578.571 | G84: =ROUNDUP((E84+F84)*C84/E67,0) -> 0
A85: MO-5 | B85: =VLOOKUP(A85,'Componentes APUs'!$H$1:$L$25,2,0) -> Profesional en SST | C85: 0.25 | D85: =VLOOKUP(A85,'Componentes APUs'!$H$1:$L$25,3,0) -> 2.5 | E85: =VLOOKUP(A85,'Componentes APUs'!$H$1:$L$25,4,0) -> 169464.29 | F85: =VLOOKUP(A85,'Componentes APUs'!$H$1:$L$25,5,0) -> 101678.57 | G85: =ROUNDUP((E85+F85)*C85/E67,0) -> 226
A86: MO-6 | B86: =VLOOKUP(A86,'Componentes APUs'!$H$1:$L$25,2,0) -> Ayudante No Calificado | C86: 2 | D86: =VLOOKUP(A86,'Componentes APUs'!$H$1:$L$25,3,0) -> 1 | E86: =VLOOKUP(A86,'Componentes APUs'!$H$1:$L$25,4,0) -> 77309.524 | F86: =VLOOKUP(A86,'Componentes APUs'!$H$1:$L$25,5,0) -> 46385.714 | G86: =ROUNDUP((E86+F86)*C86/E67,0) -> 825
A87: Subtotal B | G87: =SUM(G81:G86) -> 1051
A89: C. EQUIPOS Y HERRAMIENTAS
A90: Referencia | B90: Descripción | D90: Unidad | E90: Cantidad | F90: Vr. Unitario ($) | G90: Vr. Total ($)
A91: EH-1 | B91: =VLOOKUP(A91,'Componentes APUs'!$S$1:$V$10,2,0) -> Juego Llaves | D91: U | E91: 0 | F91: =VLOOKUP(A91,'Componentes APUs'!$S$1:$V$10,4,0) -> 9167 | G91: =ROUNDUP(F91*((E91/21)/E67),0) -> 0
A92: EH-2 | B92: =VLOOKUP(A92,'Componentes APUs'!$S$1:$V$10,2,0) -> Manila de servicio | D92: U | E92: 0 | F92: =VLOOKUP(A92,'Componentes APUs'!$S$1:$V$10,4,0) -> 2333 | G92: =ROUNDUP(F92*((E92/21)/E67),0) -> 0
A93: EH-3 | B93: =VLOOKUP(A93,'Componentes APUs'!$S$1:$V$10,2,0) -> Tula portaherramientas | D93: U | E93: 0 | F93: =VLOOKUP(A93,'Componentes APUs'!$S$1:$V$10,4,0) -> 1250 | G93: =ROUNDUP(F93*((E93/21)/E67),0) -> 0
A94: EH-4 | B94: =VLOOKUP(A94,'Componentes APUs'!$S$1:$V$10,2,0) -> Agarradoras | D94: U | E94: 0 | F94: =VLOOKUP(A94,'Componentes APUs'!$S$1:$V$10,4,0) -> 125000 | G94: =ROUNDUP(F94*((E94/21)/E67),0) -> 0
A95: EH-5 | B95: =VLOOKUP(A95,'Componentes APUs'!$S$1:$V$10,2,0) -> Templadoras | D95: U | E95: 0 | F95: =VLOOKUP(A95,'Componentes APUs'!$S$1:$V$10,4,0) -> 250000 | G95: =ROUNDUP(F95*((E95/21)/E67),0) -> 0
A96: EH-6 | B96: =VLOOKUP(A96,'Componentes APUs'!$S$1:$V$10,2,0) -> Herramienta Menor | D96: U | E96: 2 | F96: =VLOOKUP(A96,'Componentes APUs'!$S$1:$V$10,4,0) -> 75758 | G96: =ROUNDUP(F96*((E96/21)/E67),0) -> 25
A97: Subtotal C | G97: =SUM(G91:G96) -> 25
A99: D. EPP Y DOTACION
A100: Referencia | B100: Descripción | D100: Unidad | E100: Cantidad | F100: Vr. Unitario ($) | G100: Vr. Total ($)
A101: ED-1 | B101: =VLOOKUP(A101,'Componentes APUs'!$A$1:$D$14,2,0) -> Camisa indigo sin partes metalicas | D101: =VLOOKUP(A101,'Componentes APUs'!$A$1:$D$14,3,0) -> U | E101: =SUM(C81:C86) -> 2.25 | F101: =VLOOKUP(A101,'Componentes APUs'!$A$1:$D$14,4,0) -> 8585.8586 | G101: =ROUNDUP(F101*(E101/21)/E67,0) -> 4
A102: ED-2 | B102: =VLOOKUP(A102,'Componentes APUs'!$A$1:$D$14,2,0) -> Bota de seguridad dielectrica | D102: =VLOOKUP(A102,'Componentes APUs'!$A$1:$D$14,3,0) -> Par | E102: =SUM(C81:C86) -> 2.25 | F102: =VLOOKUP(A102,'Componentes APUs'!$A$1:$D$14,4,0) -> 7500 | G102: =ROUNDUP(F102*(E102/21)/E67,0) -> 3
A103: ED-3 | B103: =VLOOKUP(A103,'Componentes APUs'!$A$1:$D$14,2,0) -> Casco dielectrico Tipo 1 Clase E con barbuquejo | D103: =VLOOKUP(A103,'Componentes APUs'!$A$1:$D$14,3,0) -> U | E103: =C81+C82+C84+C85+C86+IF(A83<>"MO-3",C83,0) -> 2.25 | F103: =VLOOKUP(A103,'Componentes APUs'!$A$1:$D$14,4,0) -> 10101.01 | G103: =ROUNDUP(F103*(E103/21)/E67,0) -> 4
A104: ED-4 | B104: =VLOOKUP(A104,'Componentes APUs'!$A$1:$D$14,2,0) -> Correa plastica y antiflama | D104: =VLOOKUP(A104,'Componentes APUs'!$A$1:$D$14,3,0) -> U | E104: =SUM(C81:C86) -> 2.25 | F104: =VLOOKUP(A104,'Componentes APUs'!$A$1:$D$14,4,0) -> 3787.8788 | G104: =ROUNDUP(F104*(E104/21)/E67,0) -> 2
A105: ED-5 | B105: =VLOOKUP(A105,'Componentes APUs'!$A$1:$D$14,2,0) -> Gafas protectoras filtro UV | D105: =VLOOKUP(A105,'Componentes APUs'!$A$1:$D$14,3,0) -> U | E105: =SUM(C81:C86) -> 2.25 | F105: =VLOOKUP(A105,'Componentes APUs'!$A$1:$D$14,4,0) -> 2777.7778 | G105: =ROUNDUP(F105*(E105/21)/E67,0) -> 1
A106: ED-6 | B106: =VLOOKUP(A106,'Componentes APUs'!$A$1:$D$14,2,0) -> Bota de seguridad PVC dielectrica | D106: =VLOOKUP(A106,'Componentes APUs'!$A$1:$D$14,3,0) -> Par | E106: =SUM(C81:C86) -> 2.25 | F106: =VLOOKUP(A106,'Componentes APUs'!$A$1:$D$14,4,0) -> 2916.6667 | G106: =ROUNDUP(F106*(E106/21)/E67,0) -> 2
A107: ED-7 | B107: =VLOOKUP(A107,'Componentes APUs'!$A$1:$D$14,2,0) -> Capuchon | D107: =VLOOKUP(A107,'Componentes APUs'!$A$1:$D$14,3,0) -> U | E107: =SUM(C81:C86) -> 2.25 | F107: =VLOOKUP(A107,'Componentes APUs'!$A$1:$D$14,4,0) -> 2525.2525 | G107: =ROUNDUP(F107*(E107/21)/E67,0) -> 1
A108: ED-8 | B108: =VLOOKUP(A108,'Componentes APUs'!$A$1:$D$14,2,0) -> Guantes Protectores - ingeniero reforzados | D108: =VLOOKUP(A108,'Componentes APUs'!$A$1:$D$14,3,0) -> Par | E108: =C83+C84+C86 -> 2 | F108: =VLOOKUP(A108,'Componentes APUs'!$A$1:$D$14,4,0) -> 2525.2525 | G108: =ROUNDUP(F108*(E108/21)/E67,0) -> 1
A109: ED-9 | B109: =VLOOKUP(A109,'Componentes APUs'!$A$1:$D$14,2,0) -> Impermeable (pantalon camisa) | D109: =VLOOKUP(A109,'Componentes APUs'!$A$1:$D$14,3,0) -> U | E109: =SUM(C81:C86) -> 2.25 | F109: =VLOOKUP(A109,'Componentes APUs'!$A$1:$D$14,4,0) -> 3750 | G109: =ROUNDUP(F109*(E109/21)/E67,0) -> 2
A110: ED-10 | B110: =VLOOKUP(A110,'Componentes APUs'!$A$1:$D$14,2,0) -> Jean Dielectrico | D110: =VLOOKUP(A110,'Componentes APUs'!$A$1:$D$14,3,0) -> U | E110: =SUM(C81:C86) -> 2.25 | F110: =VLOOKUP(A110,'Componentes APUs'!$A$1:$D$14,4,0) -> 7575.7576 | G110: =ROUNDUP(F110*(E110/21)/E67,0) -> 3
A111: ED-11 | B111: =VLOOKUP(A111,'Componentes APUs'!$A$1:$D$14,2,0) -> Casco dielectrico Tipo 2 Clase E con barboquejo | D111: =VLOOKUP(A111,'Componentes APUs'!$A$1:$D$14,3,0) -> U | E111: =IF(A83="MO-3",C83,0) -> 0 | F111: =VLOOKUP(A111,'Componentes APUs'!$A$1:$D$14,4,0) -> 7500 | G111: =ROUNDUP(F111*(E111/21)/E67,0) -> 0
A112: ED-12 | B112: =VLOOKUP(A112,'Componentes APUs'!$A$1:$D$14,2,0) -> Kit de rescate para trabajo en alturas | D112: =VLOOKUP(A112,'Componentes APUs'!$A$1:$D$14,3,0) -> U | E112: =IF(AND(A83="MO-3",C83=2),1,0) -> 0 | F112: =VLOOKUP(A112,'Componentes APUs'!$A$1:$D$14,4,0) -> 37500 | G112: =ROUNDUP(F112*(E112/21)/E67,0) -> 0
A113: ED-13 | B113: =VLOOKUP(A113,'Componentes APUs'!$A$1:$D$14,2,0) -> Equipo completo para trabajo en alturas con pretales (Arnes dielectrico, 1 mosqueton de seguridad, tie off dielectrico, eslinga de posicionamiento, juego de pretales) | D113: =VLOOKUP(A113,'Componentes APUs'!$A$1:$D$14,3,0) -> U | E113: =IF(A83="MO-3",C83,0) -> 0 | F113: =VLOOKUP(A113,'Componentes APUs'!$A$1:$D$14,4,0) -> 26041.667 | G113: =ROUNDUP(F113*(E113/21)/E67,0) -> 0
A114: Subtotal D | G114: =SUM(G101:G113) -> 23
A116: E. TRANSPORTE Y VIATICACION
A117: Referencia | B117: Descripción | D117: Unidad | E117: Cantidad | F117: Vr. Unitario ($) | G117: Vr. Total ($)
...

Sheet Presupuesto
C1: ACTIVIDAD | D1: UNIDAD | G1: CANTIDAD | J1: COSTOS
J2: VALOR UNITARIO | K2: BARAYA | L2: TESALIA | M2: QUIRINAL | N2: TESORO | O2: URDANETA
E3: Baraya | F3: Tesalia | G3: Quirinal | H3: Tesoro | I3: Urdaneta
C4: OBRA CIVIL | K4: =K15+K5+K22+K45+K94+K144+K162 -> 1.7476531e+09 | L4: =L15+L5+L22+L45+L94+L144+L162 -> 1.4803857e+09 | M4: =M15+M5+M22+M45+M94+M144+M162 -> 2.6640022e+09 | N4: =N15+N5+N22+N45+N94+N144+N162 -> 2.7201052e+09 | O4: =O15+O5+O22+O45+O94+O144+O162 -> 2.172842e+09
C5: PRELIMINARES | K5: =SUM(K6:K14) -> 2.9648954e+08 | L5: =SUM(L6:L14) -> 2.5357069e+08 | M5: =SUM(M6:M14) -> 2.7126841e+08 | N5: =SUM(N6:N14) -> 3.1738699e+08 | O5: =SUM(O6:O14) -> 2.1852945e+08
A6: 001 | B6: =A6&"_OC" -> 001_OC | C6: COMPLEMENTACIÓN Y/O AJUSTE A ESTUDIOS Y DISEÑOS (INCLUYE LEVANTAMIENTO TOPOGRÁFICO, ESTUDIO DE SUELO, DISEÑO HIDRÁULICO E HIDROSANITARIO, DISEÑO ELÉCTRICO, DISEÑO ESTRUCTURAL) | D6: GB | E6: 1 | F6: 1 | G6: 1 | H6: 1 | I6: 1 | J6: =APUs!G54 -> 20800000 | K6: =$J6*E6 -> 20800000 | L6: =$J6*F6 -> 20800000 | M6: =$J6*G6 -> 20800000 | N6: =$J6*H6 -> 20800000 | O6: =$J6*I6 -> 20800000
A7: 002 | B7: =A7&"_OC" -> 002_OC | C7: LIMPIEZA DE LOTE, PARA QUITAR MALEZA Y PODAR CÉSPED | D7: M2 | E7: =E16 -> 3117 | F7: =F16 -> 2524 | G7: =G16 -> 2763.79 | H7: =H16 -> 3401 | I7: =I16 -> 2043 | J7: =APUs!G125 -> 35055 | K7: =$J7*E7 -> 109266435 | L7: =$J7*F7 -> 88478820 | M7: =$J7*G7 -> 96884658 | N7: =$J7*H7 -> 119222055 | O7: =$J7*I7 -> 71617365
A8: 003 | B8: =A8&"_OC" -> 003_OC | C8: VALLA DE INFORMACIÓN DE 2,00 X 4,00 M | D8: UN | E8: 1 | F8: 1 | G8: 1 | H8: 1 | I8: 1 | J8: =APUs!G194 -> 5491990 | K8: =$J8*E8 -> 5491990 | L8: =$J8*F8 -> 5491990 | M8: =$J8*G8 -> 5491990 | N8: =$J8*H8 -> 5491990 | O8: =$J8*I8 -> 5491990
A9: 004 | B9: =A9&"_OC" -> 004_OC | C9: DESCAPOTE Y LIMPIEZA DE TERRENO | D9: M2 | E9: =E7 -> 3117 | F9: =F7 -> 2524 | G9: =G7 -> 2763.79 | H9: =H7 -> 3401 | I9: =I7 -> 2043 | J9: =APUs!G263 -> 34153 | K9: =$J9*E9 -> 106454901 | L9: =$J9*F9 -> 86202172 | M9: =$J9*G9 -> 94391720 | N9: =$J9*H9 -> 116154353 | O9: =$J9*I9 -> 69774579
A10: 005 | B10: =A10&"_OC" -> 005_OC | C10: TALA Y CARGUE DE ARBOL CON ALTURA DE HASTA 10 METROS (DESDE LA PARTE RADICULAR) | D10: UN | E10: 2 | F10: 2 | G10: 5 | H10: 5 | I10: 0 | J10: =APUs!G332 -> 114241 | K10: =$J10*E10 -> 228482 | L10: =$J10*F10 -> 228482 | M10: =$J10*G10 -> 571205 | N10: =$J10*H10 -> 571205 | O10: =$J10*I10 -> 0
A11: 006 | B11: =A11&"_OC" -> 006_OC | C11: DISPOSICION FINAL DEL MATERIAL EN BOTADERO AUTORIZADO | D11: M3 | E11: =E16*0.2 -> 623.4 | F11: =F16*0.2 -> 504.8 | G11: =G16*0.2 -> 552.758 | H11: =H16*0.2 -> 680.2 | I11: =I16*0.2 -> 408.6 | J11: =APUs!G400 -> 15839 | K11: =$J11*E11 -> 9874032.6 | L11: =$J11*F11 -> 7995527.2 | M11: =$J11*G11 -> 8755134 | N11: =$J11*H11 -> 10773688 | O11: =$J11*I11 -> 6471815.4
A12: 007 | B12: =A12&"_OC" -> 007_OC | C12: CAMPAMENTO E INSTALACIONES PROVISIONALES, INCLUYE CERRAMIENTO EN MALLA VERDE | D12: M2 | E12: 50 | F12: 50 | G12: 50 | H12: 50 | I12: 50 | J12: =APUs!G475 -> 291240 | K12: =$J12*E12 -> 14562000 | L12: =$J12*F12 -> 14562000 | M12: =$J12*G12 -> 14562000 | N12: =$J12*H12 -> 14562000 | O12: =$J12*I12 -> 14562000
A13: 008 | B13: =A13&"_OC" -> 008_OC | C13: PROVISIONAL DE ENERGÍA | D13: UN | E13: 1 | F13: 1 | G13: 1 | H13: 1 | I13: 1 | J13: =APUs!G555 -> 27431501 | K13: =$J13*E13 -> 27431501 | L13: =$J13*F13 -> 27431501 | M13: =$J13*G13 -> 27431501 | N13: =$J13*H13 -> 27431501 | O13: =$J13*I13 -> 27431501
A14: 009 | B14: =A14&"_OC" -> 009_OC | C14: PROVISIONAL DE AGUA | D14: UN | E14: 1 | F14: 1 | G14: 1 | H14: 1 | I14: 1 | J14: =APUs!G627 -> 2380200 | K14: =$J14*E14 -> 2380200 | L14: =$J14*F14 -> 2380200 | M14: =$J14*G14 -> 2380200 | N14: =$J14*H14 -> 2380200 | O14: =$J14*I14 -> 2380200
C15: ADECUACIONES DE TERRENO | K15: =SUM(K16:K21) -> 471951301 | L15: =SUM(L16:L21) -> 229484629 | M15: =SUM(M16:M21) -> 4.7480222e+08 | N15: =SUM(N16:N21) -> 204436087 | O15: =SUM(O16:O21) -> 79919649
A16: 010 | B16: =A16&"_OC" -> 010_OC | C16: LOCALIZACIÓN Y REPLANTEO | D16: M2 | E16: =2194+424+499 -> 3117 | F16: 2524 | G16: =2763.79 -> 2763.79 | H16: 3401 | I16: 2043 | J16: =APUs!G692 -> 4226 | K16: =$J16*E16 -> 13172442 | L16: =$J16*F16 -> 10666424 | M16: =$J16*G16 -> 11679777 | N16: =$J16*H16 -> 14372626 | O16: =$J16*I16 -> 8633718
A17: 011 | B17: =A17&"_OC" -> 011_OC | C17: EXCAVACIÓN MECANICA EN MATERIAL COMUN (INCLUYE CORTE Y CARGUE) | D17: M3 | E17: 5629 | F17: 1660 | G17: 48 | H17: 1205 | I17: 958 | J17: =APUs!G760 -> 41291 | K17: =$J17*E17 -> 232427039 | L17: =$J17*F17 -> 68543060 | M17: =$J17*G17 -> 1981968 | N17: =$J17*H17 -> 49755655 | O17: =$J17*I17 -> 39556778
A18: 006 | B18: =A18&"_OC" -> 006_OC | C18: DISPOSICION FINAL DEL MATERIAL EN BOTADERO AUTORIZADO | D18: M3 | E18: =E17-49 -> 5580 | F18: =1660-474 -> 1186 | G18: 0 | H18: =1205-689 -> 516 | I18: =958-190 -> 768 | J18: =APUs!G400 -> 15839 | K18: =$J18*E18 -> 88381620 | L18: =$J18*F18 -> 18785054 | M18: =$J18*G18 -> 0 | N18: =$J18*H18 -> 8172924 | O18: =$J18*I18 -> 12164352
A19: 013 | B19: =A19&"_OC" -> 013_OC | C19: RELLENO EN MATERIAL SELECCIONADO, COMPACTADO | D19: M3 | E19: 0 | F19: 0 | G19: =3450-G17 -> 3402 | H19: 0 | I19: 0 | J19: =APUs!G829 -> 79977 | K19: =$J19*E19 -> 0 | L19: =$J19*F19 -> 0 | M19: =$J19*G19 -> 272081754 | N19: =$J19*H19 -> 0 | O19: =$J19*I19 -> 0
A20: 014 | B20: =A20&"_OC" -> 014_OC | C20: RELLENO CON GRAVILLA | D20: M3 | E20: =(700+500*2)*0.2 -> 340 | F20: 307 | G20: =(1108+322+850-440)*0.2 -> 368 | H20: =(2642-130-44-203-64-133-64-434)*0.2 -> 314 | I20: =(460+250+802-450)*0.2 -> 212.4 | J20: =APUs!G896 -> 92113 | K20: =$J20*E20 -> 31318420 | L20: =$J20*F20 -> 28278691 | M20: =$J20*G20 -> 33897584 | N20: =$J20*H20 -> 28923482 | O20: =$J20*I20 -> 19564801
A21: 015 | B21: =A21&"_OC" -> 015_OC | C21: REVEGETACIÓN Y EMPRADIZADO | D21: M2 | E21: 310 | F21: 300 | G21: =61+300+90 -> 451 | H21: 300 | I21: 0 | J21: =APUs!G965 -> 344038 | K21: =$J21*E21 -> 106651780 | L21: =$J21*F21 -> 103211400 | M21: =$J21*G21 -> 155161138 | N21: =$J21*H21 -> 103211400 | O21: =$J21*I21 -> 0
C22: DISEÑO ESTRUCTURAL (CIMENTACIÓN) | K22: =K23+K37 -> 292715309 | L22: =L23+L37 -> 292194955 | M22: =M23+M37 -> 523874980 | N22: =N23+N37 -> 543367941 | O22: =O23+O37 -> 498946163
C23: CÁRCAMOS | K23: =SUM(K24:K36) -> 93435491 | L23: =SUM(L24:L36) -> 92915137 | M23: =SUM(M24:M36) -> 285560110 | N23: =SUM(N24:N36) -> 331076439 | O23: =SUM(O24:O36) -> 280148819
A24: 016 | B24: =A24&"_OC" -> 016_OC | C24: CARCAMO DE 40X60 CM. SEGÚN ESPECIFICACIONES EN PLANO. INCLUYE EXCAVACIÓN | D24: ML | E24: =10*2+22*2+7+13+5 -> 89 | F24: =10*2+22*2+7+13+5 -> 89 | G24: =26+10+24+7+10 -> 77 | H24: =26+10+24+7+10 -> 77 | I24: =26+10+24+7+10 -> 77 | J24: =APUs!G1034 -> 528081 | K24: =$J24*E24 -> 46999209 | L24: =$J24*F24 -> 46999209 | M24: =$J24*G24 -> 40662237 | N24: =$J24*H24 -> 40662237 | O24: =$J24*I24 -> 40662237
A25: 017 | B25: =A25&"_OC" -> 017_OC | C25: CARCAMO DE 2,3 X 1,51 X 14,5 m. SEGÚN ESPECIFICACIONES EN PLANO. INCLUYE VIGAS DE SOPORTE DE CELDAS Y EXCAVACIÓN | D25: UN | E25: 0 | F25: 0 | G25: 1 | H25: 1 | I25: 1 | J25: =APUs!G1102 -> 40226556 | K25: =$J25*E25 -> 0 | L25: =$J25*F25 -> 0 | M25: =$J25*G25 -> 40226556 | N25: =$J25*H25 -> 40226556 | O25: =$J25*I25 -> 40226556
A26: 018 | B26: =A26&"_OC" -> 018_OC | C26: CARCAMO DE 2,7 X 1,4 X 9 m. SEGÚN ESPECIFICACIONES EN PLANO. INCLUYE VIGAS DE SOPORTE DE CELDAS Y EXCAVACIÓN | D26: UN | E26: 0 | F26: 0 | G26: 1 | H26: 1 | I26: 1 | J26: =APUs!G1170 -> 24818083 | K26: =$J26*E26 -> 0 | L26: =$J26*F26 -> 0 | M26: =$J26*G26 -> 24818083 | N26: =$J26*H26 -> 24818083 | O26: =$J26*I26 -> 24818083
A27: 019 | B27: =A27&"_OC" -> 019_OC | C27: TAPA EN ALFAJOR (1,10X 1 METROS) (CÁRCAMO 34,5 kV) | D27: ML | E27: 0 | F27: 0 | G27: 22 | H27: 22 | I27: 22 | J27: =APUs!G1239 -> 567987 | K27: =$J27*E27 -> 0 | L27: =$J27*F27 -> 0 | M27: =$J27*G27 -> 12495714 | N27: =$J27*H27 -> 12495714 | O27: =$J27*I27 -> 12495714
A28: 020 | B28: =A28&"_OC" -> 020_OC | C28: TAPA EN ALFAJOR (1 X1 METROS) (CÁRCAMO 13,8 kV) | D28: ML | E28: 0 | F28: 0 | G28: =13 -> 13 | H28: =13 -> 13 | I28: =13 -> 13 | J28: =APUs!G1310 -> 531632 | K28: =$J28*E28 -> 0 | L28: =$J28*F28 -> 0 | M28: =$J28*G28 -> 6911216 | N28: =$J28*H28 -> 6911216 | O28: =$J28*I28 -> 6911216
A29: 021 | B29: =A29&"_OC" -> 021_OC | C29: TAPA EN ALFAJOR (0,8X 1 METROS) (CÁRCAMO BAJA TENSIÓN) | D29: ML | E29: =7+13 -> 20 | F29: =7+13 -> 20 | G29: =G24 -> 77 | H29: =H24 -> 77 | I29: =I24 -> 77 | J29: =APUs!G1381 -> 458924 | K29: =$J29*E29 -> 9178480 | L29: =$J29*F29 -> 9178480 | M29: =$J29*G29 -> 35337148 | N29: =$J29*H29 -> 35337148 | O29: =$J29*I29 -> 35337148
A30: 022 | B30: =A30&"_OC" -> 022_OC | C30: TAPA TIPO A (1 X0.5 M) | D30: UN | E30: 118 | F30: 117 | G30: 0 | H30: 0 | I30: 0 | J30: =APUs!G1450 -> 100919 | K30: =$J30*E30 -> 11908442 | L30: =$J30*F30 -> 11807523 | M30: =$J30*G30 -> 0 | N30: =$J30*H30 -> 0 | O30: =$J30*I30 -> 0
A31: 023 | B31: =A31&"_OC" -> 023_OC | C31: TAPA TIPO B (DIMENSIÓN VARIABLE) | D31: UN | E31: 8 | F31: 8 | G31: 0 | H31: 0 | I31: 0 | J31: =APUs!G1519 -> 100919 | K31: =$J31*E31 -> 807352 | L31: =$J31*F31 -> 807352 | M31: =$J31*G31 -> 0 | N31: =$J31*H31 -> 0 | O31: =$J31*I31 -> 0
A32: 024 | B32: =A32&"_OC" -> 024_OC | C32: TAPA TIPO C (86 X 16 X 1018 X 1216) (ESQUINERA SEGÚN PLANOS) | D32: UN | E32: 4 | F32: 4 | G32: 0 | H32: 0 | I32: 0 | J32: =APUs!G1590 -> 105844 | K32: =$J32*E32 -> 423376 | L32: =$J32*F32 -> 423376 | M32: =$J32*G32 -> 0 | N32: =$J32*H32 -> 0 | O32: =$J32*I32 -> 0
A33: 025 | B33: =A33&"_OC" -> 025_OC | C33: CAJA DE INSPECCIÓN (NORMA EH RSS-033) BAJA TENSIÓN. INCLUYE EXCAVACIÓN | D33: UN | E33: 7 | F33: 7 | G33: 1 | H33: 1 | I33: 1 | J33: =APUs!G1659 -> 3014100 | K33: =$J33*E33 -> 21098700 | L33: =$J33*F33 -> 21098700 | M33: =$J33*G33 -> 3014100 | N33: =$J33*H33 -> 3014100 | O33: =$J33*I33 -> 3014100
A34: 026 | B34: =A34&"_OC" -> 026_OC | C34: CAJA DE INSPECCIÓN (NORMA EH RSS-041-2) - 13,8 Kv. INCLUYE EXCAVACIÓN | D34: UN | G34: 11 | H34: 15 | I34: 12 | J34: =APUs!G1728 -> 4714065 | K34: =$J34*E34 -> 0 | L34: =$J34*F34 -> 0 | M34: =$J34*G34 -> 51854715 | N34: =$J34*H34 -> 70710975 | O34: =$J34*I34 -> 56568780
A35: 027 | B35: =A35&"_OC" -> 027_OC | C35: CAJA DE INSPECCIÓN (NORMA EH RSS-152-2) - 34,5 kV. INCLUYE EXCAVACIÓN | D35: UN | G35: 9 | H35: 13 | I35: 8 | J35: =APUs!G1797 -> 7357085 | K35: =$J35*E35 -> 0 | L35: =$J35*F35 -> 0 | M35: =$J35*G35 -> 66213765 | N35: =$J35*H35 -> 95642105 | O35: =$J35*I35 -> 58856680
A36: 028 | B36: =A36&"_OC" -> 028_OC | C36: REFUERZO PARA BANCO DE DUCTO DE 0,8X0,1 m 3000 PSI PARA CRUCE DE VIAS (NORMA ENEL CS-221) | D36: ML | E36: =12+14+10 -> 36 | F36: =6+5+5+15 -> 31 | G36: =6*8 -> 48 | H36: =6+9 -> 15 | I36: =6+9 -> 15 | J36: =APUs!G1863 -> 83887 | K36: =$J36*E36 -> 3019932 | L36: =$J36*F36 -> 2600497 | M36: =$J36*G36 -> 4026576 | N36: =$J36*H36 -> 1258305 | O36: =$J36*I36 -> 1258305
C37: TRANSFORMADOR | K37: =SUM(K38:K43) -> 199279818 | L37: =SUM(L38:L43) -> 199279818 | M37: =SUM(M38:M43) -> 238314870 | N37: =SUM(N38:N43) -> 212291502 | O37: =SUM(O38:O43) -> 218797344
A38: 029 | B38: =A38&"_OC" -> 029_OC | C38: EXCAVACION MANUAL EN MATERIAL COMÚN | D38: M3 | E38: =25*2+0.5*E40+27*4 -> 170 | F38: =25*2+0.5*F40+27*4 -> 170 | G38: =25*2+0.5*G40+27*4 -> 182 | H38: =25*2+0.5*H40+27*4 -> 174 | I38: =25*2+0.5*I40+27*4 -> 176 | J38: =APUs!G1928 -> 38345 | K38: =$J38*E38 -> 6518650 | L38: =$J38*F38 -> 6518650 | M38: =$J38*G38 -> 6978790 | N38: =$J38*H38 -> 6672030 | O38: =$J38*I38 -> 6748720
A39: 030 | B39: =A39&"_OC" -> 030_OC | C39: FOSO DE TRANSFORMADOR Y CARRILERAS SEGÚN DISEÑO. INCLUYE RIEL DE DESPLAZAMIENTO. | D39: UN | E39: 2 | F39: 2 | G39: 2 | H39: 2 | I39: 2 | J39: =APUs!G1997 -> 42138921 | K39: =$J39*E39 -> 84277842 | L39: =$J39*F39 -> 84277842 | M39: =$J39*G39 -> 84277842 | N39: =$J39*H39 -> 84277842 | O39: =$J39*I39 -> 84277842
A40: 031 | B40: =A40&"_OC" -> 031_OC | C40: CARRILERA DE 1,2*0,4 M, PARA TRANSFORMADOR SEGÚN DISEÑO. INCLUYE RIEL DE DESPLAZAMIENTO. | D40: ML | E40: =6*4 -> 24 | F40: =6*4 -> 24 | G40: =12*4 -> 48 | H40: =8*4 -> 32 | I40: =9*4 -> 36 | J40: =APUs!G2065 -> 1607288 | K40: =$J40*E40 -> 38574912 | L40: =$J40*F40 -> 38574912 | M40: =$J40*G40 -> 77149824 | N40: =$J40*H40 -> 51433216 | O40: =$J40*I40 -> 57862368
A41: 032 | B41: =A41&"_OC" -> 032_OC | C41: TRAMPA DE ACEITE PARA TRANSFORMADOR DE 6,5 M3 ( DETALLE SEGÚN PLANOS). INCLUYE CAMARA PARA LA VÁLVULA. IMPERMEABILIZACIÓN INTEGRAL, TAPAS Y ACCESORIOS. | D41: UN | E41: 2 | F41: 2 | G41: 2 | H41: 2 | I41: 2 | J41: =APUs!G2135 -> 27777038 | K41: =$J41*E41 -> 55554076 | L41: =$J41*F41 -> 55554076 | M41: =$J41*G41 -> 55554076 | N41: =$J41*H41 -> 55554076 | O41: =$J41*I41 -> 55554076
A42: 033 | B42: =A42&"_OC" -> 033_OC | C42: MURO CORTAFUEGO DE (5 METROS DE ALTO X 5,6 METROS LARGO Y 15CM ESPESOR) | D42: UN | E42: 1 | F42: 1 | G42: 1 | H42: 1 | I42: 1 | J42: =APUs!G2203 -> 10437316 | K42: =$J42*E42 -> 10437316 | L42: =$J42*F42 -> 10437316 | M42: =$J42*G42 -> 10437316 | N42: =$J42*H42 -> 10437316 | O42: =$J42*I42 -> 10437316
A43: 034 | B43: =A43&"_OC" -> 034_OC | C43: =UPPER("Solado en concreto premezclado de 2000 psi incluye suministro y colocacion") -> SOLADO EN CONCRETO PREMEZCLADO DE 2000 PSI INCLUYE SUMINISTRO Y COLOCACION | D43: M3 | E43: =E41*2+4*0.5 -> 6 | F43: =F41*2+4*0.5 -> 6 | G43: =G41*2+4*0.5 -> 6 | H43: =H41*2+4*0.5 -> 6 | I43: =I41*2+4*0.5 -> 6 | J43: =APUs!G2271 -> 652837 | K43: =$J43*E43 -> 3917022 | L43: =$J43*F43 -> 3917022 | M43: =$J43*G43 -> 3917022 | N43: =$J43*H43 -> 3917022 | O43: =$J43*I43 -> 3917022
C45: RED HIDROSANITARIA | K45: =K46+K57+K67+K79 -> 2.1191912e+08 | L45: =L46+L57+L67+L79 -> 1.9901149e+08 | M45: =M46+M57+M67+M79 -> 2.3837735e+08 | N45: =N46+N57+N67+N79 -> 3.279918e+08 | O45: =O46+O57+O67+O79 -> 2.4831756e+08
C46: FILTROS | K46: =SUM(K47:K56) -> 109177437 | L46: =SUM(L47:L56) -> 92524929 | M46: =SUM(M47:M56) -> 1.1542338e+08 | N46: =SUM(N47:N56) -> 1.7128489e+08 | O46: =SUM(O47:O56) -> 93661172
A47: 029 | B47: =A47&"_OC" -> 029_OC | C47: EXCAVACION MANUAL EN MATERIAL COMÚN | D47: M3 | E47: =180*0.5*1.5 -> 135 | F47: =145*0.5*1.5 -> 108.75 | G47: =(46+130)*0.5*1.5 -> 132 | H47: =(32+120+44+88+11+14)*0.5*1.5 -> 231.75 | I47: =(120+32)*0.5*1.5 -> 114 | J47: =APUs!G1928 -> 38345 | K47: =$J47*E47 -> 5176575 | L47: =$J47*F47 -> 4170018.8 | M47: =$J47*G47 -> 5061540 | N47: =$J47*H47 -> 8886453.8 | O47: =$J47*I47 -> 4371330
A48: 036 | B48: =A48&"_OC" -> 036_OC | C48: SISTEMA DE FILTRO TIPO DREN FRANCES (50X60 CM) CON TUBERÍA PVC Ø6" PERFORADA Y CORRUGADA, GRAVA Y GEOTEXTIL NT 1600. | D48: ML | E48: 180 | F48: 145 | G48: =46+130 -> 176 | H48: =32+120+44+88+11+14 -> 309 | I48: =120+32 -> 152 | J48: =APUs!G2405 -> 200006 | K48: =$J48*E48 -> 36001080 | L48: =$J48*F48 -> 29000870 | M48: =$J48*G48 -> 35201056 | N48: =$J48*H48 -> 61801854 | O48: =$J48*I48 -> 30400912
A49: 037 | B49: =A49&"_OC" -> 037_OC | C49: RELLENO Y COMPACTACIÓN 50CM DE ANCHO HASTA 1.5M PROFUNDIDAD. PARA INSTALACIÓN DE TUBERÍA Ø6". | D49: M3 | E49: =180*0.5*0.9 -> 81 | F49: =145*0.5*0.9 -> 65.25 | G49: =(46+130)*0.5*0.9 -> 79.2 | H49: =(32+120+44+88+11+14)*0.5*0.9 -> 139.05 | I49: =(120+32)*0.5*0.9 -> 68.4 | J49: =APUs!G2472 -> 106938 | K49: =$J49*E49 -> 8661978 | L49: =$J49*F49 -> 6977704.5 | M49: =$J49*G49 -> 8469489.6 | N49: =$J49*H49 -> 14869729 | O49: =$J49*I49 -> 7314559.2
A50: 038 | B50: =A50&"_OC" -> 038_OC | C50: CAJA DE INSPECCIÓN DE 80X80 CM INTERNOS EN CONCRETO REFORZADO E INCLUYE TAPA EN CONCRETO REFORZADO CON MANIJA, HASTA 1.5 METROS DE PROFUNDIDAD | D50: UN | E50: 12 | F50: 11 | G50: 17 | H50: 24 | I50: 14 | J50: =APUs!G2544 -> 1126658 | K50: =$J50*E50 -> 13519896 | L50: =$J50*F50 -> 12393238 | M50: =$J50*G50 -> 19153186 | N50: =$J50*H50 -> 27039792 | O50: =$J50*I50 -> 15773212
A51: 039 | B51: =A51&"_OC" -> 039_OC | C51: CAJA DE INSPECCIÓN DE 100X100 CM INTERNOS EN CONCRETO REFORZADO E INCLUYE TAPA EN CONCRETO REFORZADO CON MANIJA, HASTA 1.5 METROS DE PROFUNDIDAD | D51: UN | E51: 0 | F51: 0 | G51: 0 | H51: 3 | I51: 0 | J51: =APUs!G2616 -> 1349870 | K51: =$J51*E51 -> 0 | L51: =$J51*F51 -> 0 | M51: =$J51*G51 -> 0 | N51: =$J51*H51 -> 4049610 | O51: =$J51*I51 -> 0
A52: 040 | B52: =A52&"_OC" -> 040_OC | C52: CONO CÁM INSP C20.7MPA D=1.2 T24" | D52: UN | E52: 4 | F52: 2 | G52: 3 | H52: 5 | I52: 1 | J52: =APUs!G2682 -> 677631 | K52: =$J52*E52 -> 2710524 | L52: =$J52*F52 -> 1355262 | M52: =$J52*G52 -> 2032893 | N52: =$J52*H52 -> 3388155 | O52: =$J52*I52 -> 677631
A53: 041 | B53: =A53&"_OC" -> 041_OC | C53: CUERPO CÁMARA DE INSPECCIÓN C20.7MPA | D53: M3 | E53: 4 | F53: 2 | G53: 3 | H53: 5 | I53: 1 | J53: =APUs!G2748 -> 1147838 | K53: =$J53*E53 -> 4591352 | L53: =$J53*F53 -> 2295676 | M53: =$J53*G53 -> 3443514 | N53: =$J53*H53 -> 5739190 | O53: =$J53*I53 -> 1147838
A54: 042 | B54: =A54&"_OC" -> 042_OC | C54: TAPA CÁM ALC C20.7MPA+ARO LÁMINA (UN) | D54: UN | E54: 4 | F54: 2 | G54: 3 | H54: 5 | I54: 1 | J54: =APUs!G2814 -> 1091936 | K54: =$J54*E54 -> 4367744 | L54: =$J54*F54 -> 2183872 | M54: =$J54*G54 -> 3275808 | N54: =$J54*H54 -> 5459680 | O54: =$J54*I54 -> 1091936
A55: 043 | B55: =A55&"_OC" -> 043_OC | C55: REJILLA TRAGATORMENTAS | D55: UN | E55: 1 | F55: 1 | G55: 2 | H55: 1 | I55: 2 | J55: =APUs!G2882 -> 10539740 | K55: =$J55*E55 -> 10539740 | L55: =$J55*F55 -> 10539740 | M55: =$J55*G55 -> 21079480 | N55: =$J55*H55 -> 10539740 | O55: =$J55*I55 -> 21079480
A56: 044 | B56: =A56&"_OC" -> 044_OC | C56: SUMIDERO VERTICAL SEGÚN (NORMA EPM, NC-AS-IL02-17/NEGC 818-01) | D56: UN | E56: 4 | F56: 4 | G56: 3 | H56: 5 | I56: 2 | J56: =APUs!G2952 -> 5902137 | K56: =$J56*E56 -> 23608548 | L56: =$J56*F56 -> 23608548 | M56: =$J56*G56 -> 17706411 | N56: =$J56*H56 -> 29510685 | O56: =$J56*I56 -> 11804274
C57: AGUAS LLUVIAS | K57: =SUM(K58:K65) -> 72581562 | L57: =SUM(L58:L65) -> 71049284 | M57: =SUM(M58:M65) -> 82319631 | N57: =SUM(N58:N65) -> 1.130794e+08 | O57: =SUM(O58:O65) -> 1.1347924e+08
A58: 029 | B58: =A58&"_OC" -> 029_OC | C58: EXCAVACION MANUAL EN MATERIAL COMUN | D58: M3 | E58: =SUM(E60:E64)*0.5*1.5 -> 135 | F58: =SUM(F60:F64)*0.5*1.5 -> 135 | G58: =SUM(G60:G64)*0.5*1.5 -> 207 | H58: =SUM(H60:H64)*0.5*1.5 -> 280.5 | I58: =SUM(I60:I64)*0.5*1.5 -> 315.75 | J58: =APUs!G1928 -> 38345 | K58: =$J58*E58 -> 5176575 | L58: =$J58*F58 -> 5176575 | M58: =$J58*G58 -> 7937415 | N58: =$J58*H58 -> 10755772 | O58: =$J58*I58 -> 12107434
A59: 046 | B59: =A59&"_OC" -> 046_OC | C59: RELLENO CON MATERIAL DE SITIO, ARENA Y CINTA DE SEÑALIZACIÓN | D59: ML | E59: =SUM(E60:E64) -> 180 | F59: =SUM(F60:F64) -> 180 | G59: =SUM(G60:G64) -> 276 | H59: =SUM(H60:H64) -> 374 | I59: =SUM(I60:I64) -> 421 | J59: =APUs!G3022 -> 118227 | K59: =$J59*E59 -> 21280860 | L59: =$J59*F59 -> 21280860 | M59: =$J59*G59 -> 32630652 | N59: =$J59*H59 -> 44216898 | O59: =$J59*I59 -> 49773567
A60: 047 | B60: =A60&"_OC" -> 047_OC | C60: TUBO PVC DE Ø2". INCLUYE CODOS, UNIONES, SOLDADURA Y LIMPIADOR | D60: ML | E60: 15 | F60: 15 | G60: 5 | H60: =10 -> 10 | I60: =10 -> 10 | J60: =APUs!G3094 -> 133163 | K60: =$J60*E60 -> 1997445 | L60: =$J60*F60 -> 1997445 | M60: =$J60*G60 -> 665815 | N60: =$J60*H60 -> 1331630 | O60: =$J60*I60 -> 1331630
A61: 048 | B61: =A61&"_OC" -> 048_OC | C61: TUBO PVC DE Ø4". INCLUYE CODOS, UNIONES, SOLDADURA Y LIMPIADOR | D61: ML | E61: 0 | F61: 0 | G61: =60+8*7 -> 116 | H61: =70+8*7 -> 126 | I61: =210+8*7 -> 266 | J61: =APUs!G3166 -> 54757 | K61: =$J61*E61 -> 0 | L61: =$J61*F61 -> 0 | M61: =$J61*G61 -> 6351812 | N61: =$J61*H61 -> 6899382 | O61: =$J61*I61 -> 14565362
A62: 049 | B62: =A62&"_OC" -> 049_OC | C62: TUBO PVC DE Ø6". INCLUYE CODOS, UNIONES, SOLDADURA Y LIMPIADOR | D62: ML | E62: 0 | F62: 0 | G62: 60 | H62: =90+5+30 -> 125 | I62: =50+10 -> 60 | J62: =APUs!G3238 -> 175804 | K62: =$J62*E62 -> 0 | L62: =$J62*F62 -> 0 | M62: =$J62*G62 -> 10548240 | N62: =$J62*H62 -> 21975500 | O62: =$J62*I62 -> 10548240
A63: 050 | B63: =A63&"_OC" -> 050_OC | C63: TUBO PVC DE Ø8". INCLUYE CODOS, UNIONES, SOLDADURA Y LIMPIADOR | D63: ML | E63: =115+35 -> 150 | F63: 150 | G63: =40+15 -> 55 | H63: 98 | I63: 50 | J63: =APUs!G3310 -> 247756 | K63: =$J63*E63 -> 37163400 | L63: =$J63*F63 -> 37163400 | M63: =$J63*G63 -> 13626580 | N63: =$J63*H63 -> 24280088 | O63: =$J63*I63 -> 12387800
A64: 051 | B64: =A64&"_OC" -> 051_OC | C64: TUBO PVC DE Ø10". INCLUYE CODOS, UNIONES, SOLDADURA Y LIMPIADOR | D64: ML | E64: 15 | F64: 15 | G64: 40 | H64: 15 | I64: 35 | J64: =APUs!G3382 -> 241342 | K64: =$J64*E64 -> 3620130 | L64: =$J64*F64 -> 3620130 | M64: =$J64*G64 -> 9653680 | N64: =$J64*H64 -> 3620130 | O64: =$J64*I64 -> 8446970
A65: 052 | B65: =A65&"_OC" -> 052_OC | C65: SUMINISTRO E INSTALACIÓN DE PROTECCIÓN EN CONCRETO DE 2500 PSI DE 100 X 5 CM PARA CRUCES DE CANALIZACIONES EN VIA | D65: ML | E65: =10+6+6+10+16 -> 48 | F65: =10+10+6 -> 26 | G65: 13 | H65: 0 | I65: =10+12+8+8+8+8+8 -> 62 | J65: =APUs!G3448 -> 69649 | K65: =$J65*E65 -> 3343152 | L65: =$J65*F65 -> 1810874 | M65: =$J65*G65 -> 905437 | N65: =$J65*H65 -> 0 | O65: =$J65*I65 -> 4318238
C67: SANITARIO | K67: =SUM(K68:K78) -> 14063098 | L67: =SUM(L68:L78) -> 15878782 | M67: =SUM(M68:M78) -> 22371838 | N67: =SUM(N68:N78) -> 22371838 | O67: =SUM(O68:O78) -> 21418052
A68: 029 | B68: =A68&"_OC" -> 029_OC | C68: EXCAVACION MANUAL EN MATERIAL COMUN | D68: M3 | E68: =E76*0.5*1.5 -> 9.75 | F68: =F76*0.5*1.5 -> 16.5 | G68: =G76*0.5*1.5 -> 37.5 | H68: =H76*0.5*1.5 -> 37.5 | I68: =I76*0.5*1.5 -> 37.5 | J68: =APUs!G1928 -> 38345 | K68: =$J68*E68 -> 373863.75 | L68: =$J68*F68 -> 632692.5 | M68: =$J68*G68 -> 1437937.5 | N68: =$J68*H68 -> 1437937.5 | O68: =$J68*I68 -> 1437937.5
A69: 046 | B69: =A69&"_OC" -> 046_OC | C69: RELLENO CON MATERIAL DE SITIO, ARENA Y CINTA DE SEÑALIZACIÓN | D69: ML | E69: =E76 -> 13 | F69: =F76 -> 22 | G69: =G76 -> 50 | H69: =H76 -> 50 | I69: =I76 -> 50 | J69: =APUs!G3022 -> 118227 | K69: =$J69*E69 -> 1536951 | L69: =$J69*F69 -> 2600994 | M69: =$J69*G69 -> 5911350 | N69: =$J69*H69 -> 5911350 | O69: =$J69*I69 -> 5911350
A70: 055 | B70: =A70&"_OC" -> 055_OC | C70: PUNTO SANITARIO DE EN PVC Ø4". LONGITUD PROMEDIO 3 METROS | D70: UN | E70: 1 | F70: 1 | G70: 1 | H70: 1 | I70: 1 | J70: =APUs!G3520 -> 243999 | K70: =$J70*E70 -> 243999 | L70: =$J70*F70 -> 243999 | M70: =$J70*G70 -> 243999 | N70: =$J70*H70 -> 243999 | O70: =$J70*I70 -> 243999
A71: 056 | B71: =A71&"_OC" -> 056_OC | C71: PUNTO SANITARIO DE EN PVC Ø2". LONGITUD PROMEDIO 3 METROS | D71: UN | E71: 1 | F71: 1 | G71: 2 | H71: 2 | I71: 2 | J71: =APUs!G3592 -> 193431 | K71: =$J71*E71 -> 193431 | L71: =$J71*F71 -> 193431 | M71: =$J71*G71 -> 386862 | N71: =$J71*H71 -> 386862 | O71: =$J71*I71 -> 386862
A72: 057 | B72: =A72&"_OC" -> 057_OC | C72: SUMINISTRO E INSTALACIÓN DE SANITARIO TIPO INSTITUCIONAL, AHORRADOR DE AGUA Y ACCESORIOS | D72: UN | E72: 1 | F72: 1 | G72: 1 | H72: 1 | I72: 1 | J72: =APUs!G3664 -> 906527 | K72: =$J72*E72 -> 906527 | L72: =$J72*F72 -> 906527 | M72: =$J72*G72 -> 906527 | N72: =$J72*H72 -> 906527 | O72: =$J72*I72 -> 906527
A73: 058 | B73: =A73&"_OC" -> 058_OC | C73: CAJA SANITARIA DE 80X80x80 CM | D73: UN | E73: 2 | F73: 2 | G73: 4 | H73: 4 | I73: 3 | J73: =APUs!G3736 -> 953786 | K73: =$J73*E73 -> 1907572 | L73: =$J73*F73 -> 1907572 | M73: =$J73*G73 -> 3815144 | N73: =$J73*H73 -> 3815144 | O73: =$J73*I73 -> 2861358
A74: 059 | B74: =A74&"_OC" -> 059_OC | C74: SUMINISTRO E INSTALACIÓN DE POZO SÉPTICO PLÁSTICO PREFABRICADO DE 1.650 LITROS. INCLUYE EXCAVACIÓN Y ACCESORIOS | D74: UN | E74: 1 | F74: 1 | G74: 0 | H74: 0 | I74: 0 | J74: =APUs!G3805 -> 7178909 | K74: =$J74*E74 -> 7178909 | L74: =$J74*F74 -> 7178909 | M74: =$J74*G74 -> 0 | N74: =$J74*H74 -> 0 | O74: =$J74*I74 -> 0
A75: 047 | B75: 047_OC | C75: TUBO PVC DE Ø2". INCLUYE CODOS, UNIONES, SOLDADURA Y LIMPIADOR | D75: ML | E75: 3 | F75: 3 | G75: 40 | H75: 40 | I75: 40 | J75: =APUs!G3094 -> 133163 | K75: =$J75*E75 -> 399489 | L75: =$J75*F75 -> 399489 | M75: =$J75*G75 -> 5326520 | N75: =$J75*H75 -> 5326520 | O75: =$J75*I75 -> 5326520
A76: 048 | B76: 048_OC | C76: TUBO PVC DE Ø4". INCLUYE CODOS, UNIONES, SOLDADURA Y LIMPIADOR | D76: ML | E76: =10+3 -> 13 | F76: =10+3+9 -> 22 | G76: 50 | H76: 50 | I76: 50 | J76: =APUs!G3166 -> 54757 | K76: =$J76*E76 -> 711841 | L76: =$J76*F76 -> 1204654 | M76: =$J76*G76 -> 2737850 | N76: =$J76*H76 -> 2737850 | O76: =$J76*I76 -> 2737850
A77: 062 | B77: =A77&"_OC" -> 062_OC | C77: SIFON PARA DESAGÜE DE Ø2"(CÁRCAMOS Y PISO) | D77: UN | E77: 5 | F77: 5 | G77: 11 | H77: 11 | I77: 11 | J77: =APUs!G3878 -> 122103 | K77: =$J77*E77 -> 610515 | L77: =$J77*F77 -> 610515 | M77: =$J77*G77 -> 1343133 | N77: =$J77*H77 -> 1343133 | O77: =$J77*I77 -> 1343133
A78: 063 | B78: =A78&"_OC" -> 063_OC | C78: FILTROS EN GRAVILLA PARA CARCAMOS DE 40 CM (ANCHO) X40 CM (LARGO) X 100CM (PROFUNDIDAD) | D78: UN | E78: 0 | F78: 0 | G78: 5 | H78: 5 | I78: 5 | J78: =APUs!G3945 -> 52503 | K78: =$J78*E78 -> 0 | L78: =$J78*F78 -> 0 | M78: =$J78*G78 -> 262515 | N78: =$J78*H78 -> 262515 | O78: =$J78*I78 -> 262515
C79: HIDRÁULICO | K79: =SUM(K80:K92) -> 16097020 | L79: =SUM(L80:L92) -> 19558490 | M79: =SUM(M80:M92) -> 18262507 | N79: =SUM(N80:N92) -> 21255677 | O79: =SUM(O80:O92) -> 19759092
A80: 029 | B80: 029_OC | C80: EXCAVACION MANUAL EN MATERIAL COMUN | D80: M3 | E80: =(E85+E84)*0.5*1 -> 30 | F80: =(F85+F84)*0.5*1 -> 40 | G80: =(G85+G84)*0.5*1 -> 25 | H80: =(H85+H84)*0.5*1 -> 35 | I80: =(I85+I84)*0.5*1 -> 30 | J80: =APUs!G1928 -> 38345 | K80: =$J80*E80 -> 1150350 | L80: =$J80*F80 -> 1533800 | M80: =$J80*G80 -> 958625 | N80: =$J80*H80 -> 1342075 | O80: =$J80*I80 -> 1150350
A81: 046 | B81: 046_OC | C81: RELLENO CON MATERIAL DE SITIO, ARENA Y CINTA DE SEÑALIZACIÓN | D81: ML | E81: =E85+E84 -> 60 | F81: =F85+F84 -> 80 | G81: =G85+G84 -> 50 | H81: =H85+H84 -> 70 | I81: =I85+I84 -> 60 | J81: =APUs!G3022 -> 118227 | K81: =$J81*E81 -> 7093620 | L81: =$J81*F81 -> 9458160 | M81: =$J81*G81 -> 5911350 | N81: =$J81*H81 -> 8275890 | O81: =$J81*I81 -> 7093620
A82: 066 | B82: =A82&"_OC" -> 066_OC | C82: TANQUE DE ALMACENAMIENTO 500 LITROS | D82: UN | E82: 1 | F82: 1 | G82: 1 | H82: 1 | I82: 1 | J82: =APUs!G4020 -> 1401163 | K82: =$J82*E82 -> 1401163 | L82: =$J82*F82 -> 1401163 | M82: =$J82*G82 -> 1401163 | N82: =$J82*H82 -> 1401163 | O82: =$J82*I82 -> 1401163
A83: 067 | B83: =A83&"_OC" -> 067_OC | C83: PUNTOS HIDRAULICOS DE Ø1/2". LONGITUD PROMEDIO DE 10 METROS. INCLUYE ACCESORIOS. | D83: UN | E83: 3 | F83: 3 | G83: 6 | H83: 6 | I83: 6 | J83: =APUs!G4092 -> 186434 | K83: =$J83*E83 -> 559302 | L83: =$J83*F83 -> 559302 | M83: =$J83*G83 -> 1118604 | N83: =$J83*H83 -> 1118604 | O83: =$J83*I83 -> 1118604
A84: 068 | B84: =A84&"_OC" -> 068_OC | C84: TUBO PVC DE Ø1" Y ACCESORIOS | D84: ML | E84: 0 | F84: 0 | G84: 50 | H84: 70 | I84: 60 | J84: =APUs!G4162 -> 12259 | K84: =$J84*E84 -> 0 | L84: =$J84*F84 -> 0 | M84: =$J84*G84 -> 612950 | N84: =$J84*H84 -> 858130 | O84: =$J84*I84 -> 735540
A85: 069 | B85: =A85&"_OC" -> 069_OC | C85: TUBO PVC DE Ø 1 1/2" Y ACCESORIOS | D85: ML | E85: 60 | F85: 80 | G85: 0 | H85: 0 | I85: 0 | J85: =APUs!G4232 -> 35674 | K85: =$J85*E85 -> 2140440 | L85: =$J85*F85 -> 2853920 | M85: =$J85*G85 -> 0 | N85: =$J85*H85 -> 0 | O85: =$J85*I85 -> 0
A86: 070 | B86: =A86&"_OC" -> 070_OC | C86: LAVAMANOS INSTITUCIONAL TIPO CORONA O EQUIVALENTE + ACCESORIOS | D86: UN | E86: 1 | F86: 1 | G86: 1 | H86: 1 | I86: 1 | J86: =APUs!G4300 -> 990662 | K86: =$J86*E86 -> 990662 | L86: =$J86*F86 -> 990662 | M86: =$J86*G86 -> 990662 | N86: =$J86*H86 -> 990662 | O86: =$J86*I86 -> 990662
A87: 071 | B87: =A87&"_OC" -> 071_OC | C87: DUCHA. INCLUYE DIVISIÓN EN VIDRIO OPALIZADO Y ACCESORIOS PARA SU CORRECTA INSTALACIÓN. | D87: UN | E87: 0 | F87: 0 | G87: 1 | H87: 1 | I87: 1 | J87: =APUs!G4368 -> 2548979 | K87: =$J87*E87 -> 0 | L87: =$J87*F87 -> 0 | M87: =$J87*G87 -> 2548979 | N87: =$J87*H87 -> 2548979 | O87: =$J87*I87 -> 2548979
A88: 072 | B88: =A88&"_OC" -> 072_OC | C88: POCETA PREFABRICADA DE 40X40X25 cm | D88: UN | E88: 0 | F88: 0 | G88: 1 | H88: 1 | I88: 1 | J88: =APUs!G4435 -> 341341 | K88: =$J88*E88 -> 0 | L88: =$J88*F88 -> 0 | M88: =$J88*G88 -> 341341 | N88: =$J88*H88 -> 341341 | O88: =$J88*I88 -> 341341
A89: 073 | B89: =A89&"_OC" -> 073_OC | C89: LAVAOJOS | D89: UN | E89: 0 | F89: 0 | G89: 1 | H89: 1 | I89: 1 | J89: =APUs!G4503 -> 1617350 | K89: =$J89*E89 -> 0 | L89: =$J89*F89 -> 0 | M89: =$J89*G89 -> 1617350 | N89: =$J89*H89 -> 1617350 | O89: =$J89*I89 -> 1617350
A90: 074 | B90: =A90&"_OC" -> 074_OC | C90: VÁLVULA DE BAY-PASS MARIPOSA 1/2" PARA TANQUE DE ALMACENAMIENTO. INCLUYE CAJA DE REGISTRO | D90: UN | E90: 4 | F90: 4 | G90: 4 | H90: 4 | I90: 4 | J90: =APUs!G4571 -> 150829 | K90: =$J90*E90 -> 603316 | L90: =$J90*F90 -> 603316 | M90: =$J90*G90 -> 603316 | N90: =$J90*H90 -> 603316 | O90: =$J90*I90 -> 603316
A91: 075 | B91: =A91&"_OC" -> 075_OC | C91: PUNTO DE CONEXIÓN MEDIDOR. INCLUYE (VÁLVULA DE PASO DE MEDIDOR PRINCIPAL, CHEQUE) | D91: UN | E91: 1 | F91: 1 | G91: 1 | H91: 1 | I91: 1 | J91: =APUs!G4644 -> 1758495 | K91: =$J91*E91 -> 1758495 | L91: =$J91*F91 -> 1758495 | M91: =$J91*G91 -> 1758495 | N91: =$J91*H91 -> 1758495 | O91: =$J91*I91 -> 1758495
A92: 076 | B92: =A92&"_OC" -> 076_OC | C92: CAJA EN CONCRETO PARA MEDIDOR. TAPA EN HIERRO FUNDIDO | D92: UN | E92: 1 | F92: 1 | G92: 1 | H92: 1 | I92: 1 | J92: =APUs!G4712 -> 399672 | K92: =$J92*E92 -> 399672 | L92: =$J92*F92 -> 399672 | M92: =$J92*G92 -> 399672 | N92: =$J92*H92 -> 399672 | O92: =$J92*I92 -> 399672
C94: EDIFICIO DE FUERZA Y CONTROL | K94: =K95+K117+K126 -> 1.4234433e+08 | L94: =L95+L117+L126 -> 1.4234433e+08 | M94: =M95+M117+M126 -> 8.1822664e+08 | N94: =N95+N117+N126 -> 8.1822664e+08 | O94: =O95+O117+O126 -> 8.1822664e+08
C95: CIMENTACIÓN ESTRUCTURAL | K95: =SUM(K96:K116) -> 55647331 | L95: =SUM(L96:L116) -> 55647331 | M95: =SUM(M96:M116) -> 5.3774862e+08 | N95: =SUM(N96:N116) -> 5.3774862e+08 | O95: =SUM(O96:O116) -> 5.3774862e+08
A96: 077 | B96: =A96&"_OC" -> 077_OC | C96: MANPOSTERIA EN LADRILLO PRENSADO LIVIANO | D96: M2 | E96: =5*4+1.3*4+1.2*4+1.85*4+5.3+3.1 -> 45.8 | F96: =5*4+1.3*4+1.2*4+1.85*4+5.3+3.1 -> 45.8 | G96: 0 | H96: 0 | I96: 0 | J96: =APUs!G4785 -> 195467.5 | K96: =$J96*E96 -> 8952411.5 | L96: =$J96*F96 -> 8952411.5 | M96: =$J96*G96 -> 0 | N96: =$J96*H96 -> 0 | O96: =$J96*I96 -> 0
A97: 078 | B97: =A97&"_OC" -> 078_OC | C97: MURO BLOQUE ESTRUCTURAL14X19X39+ AS + GRAFIL (M2) | D97: M2 | E97: 0 | F97: 0 | G97: =74*(6.1-0.4-0.4-0.12)-0.6*20-3*6-6.2*2-9.3*1+12+12+15.3+12+9.7*5+15.3+4.2*5*3+2.5*5*1 -> 522.22 | H97: =74*(6.1-0.4-0.4-0.12)-0.6*20-3*6-6.2*2-9.3*1+12+12+15.3+12+9.7*5+15.3+4.2*5*3+2.5*5*1 -> 522.22 | I97: =74*(6.1-0.4-0.4-0.12)-0.6*20-3*6-6.2*2-9.3*1+12+12+15.3+12+9.7*5+15.3+4.2*5*3+2.5*5*1 -> 522.22 | J97: =APUs!G4848 -> 325670 | K97: =$J97*E97 -> 0 | L97: =$J97*F97 -> 0 | M97: =$J97*G97 -> 1.7007139e+08 | N97: =$J97*H97 -> 1.7007139e+08 | O97: =$J97*I97 -> 1.7007139e+08
A98: 079 | B98: =A98&"_OC" -> 079_OC | C98: CONTRAPISO EN CONCRETO DE 3000 PSI E=0,15 M, INCLUYE REFUERZO | D98: M2 | E98: =12+2.4+2.5+2.5+2.4+8.4+0.93 -> 31.13 | F98: =12+2.4+2.5+2.5+2.4+8.4+0.93 -> 31.13 | G98: =434-0.4*0.4*18-38-20-28-6-5.5-4 -> 329.62 | H98: =434-0.4*0.4*18-38-20-28-6-5.5-4 -> 329.62 | I98: =434-0.4*0.4*18-38-20-28-6-5.5-4 -> 329.62 | J98: =APUs!G4917 -> 167115 | K98: =$J98*E98 -> 5202289.9 | L98: =$J98*F98 -> 5202289.9 | M98: =$J98*G98 -> 55084446 | N98: =$J98*H98 -> 55084446 | O98: =$J98*I98 -> 55084446
A99: 080 | B99: =A99&"_OC" -> 080_OC | C99: PLACA EN CONCRETO DE 3000 PSI E: 0,10 MTS INCLUYE MALLA ELECTROSOLDADA. | D99: M2 | E99: 4 | F99: 4 | G99: 349 | H99: 349 | I99: 349 | J99: =APUs!G4986 -> 135532 | K99: =$J99*E99 -> 542128 | L99: =$J99*F99 -> 542128 | M99: =$J99*G99 -> 47300668 | N99: =$J99*H99 -> 47300668 | O99: =$J99*I99 -> 47300668
A100: 081 | B100: =A100&"_OC" -> 081_OC | C100: ZAPATA DE CIMENTACIÓN DE CONCRETO SIMPLE | D100: M3 | E100: =(0.8*0.8*0.3)*6 -> 1.152 | F100: =(0.8*0.8*0.3)*6 -> 1.152 | G100: =(1.4*1.4*0.4)*12+(1.5*1.5*0.4)*6 -> 14.808 | H100: =(1.4*1.4*0.4)*12+(1.5*1.5*0.4)*6 -> 14.808 | I100: =(1.4*1.4*0.4)*12+(1.5*1.5*0.4)*6 -> 14.808 | J100: =APUs!G5052 -> 786070 | K100: =$J100*E100 -> 905552.64 | L100: =$J100*F100 -> 905552.64 | M100: =$J100*G100 -> 11640125 | N100: =$J100*H100 -> 11640125 | O100: =$J100*I100 -> 11640125
A101: 029 | B101: 029_OC | C101: EXCAVACION MANUAL EN MATERIAL COMÚN | D101: M3 | E101: =(10+8.6+5*3+2.7+1.6)*0.3*0.7+(0.8*0.8*1)*6 -> 11.799 | F101: =(10+8.6+5*3+2.7+1.6)*0.3*0.7+(0.8*0.8*1)*6 -> 11.799 | G101: =0.5*1.3*G103+0.5*0.5*G104 -> 106 | H101: =0.5*1.3*H103+0.5*0.5*H104 -> 106 | I101: =0.5*1.3*I103+0.5*0.5*I104 -> 106 | J101: =APUs!G1928 -> 38345 | K101: =$J101*E101 -> 452432.66 | L101: =$J101*F101 -> 452432.66 | M101: =$J101*G101 -> 4064570 | N101: =$J101*H101 -> 4064570 | O101: =$J101*I101 -> 4064570
A102: 083 | B102: =A102&"_OC" -> 083_OC | C102: VIGA DE CIMENTACIÓN 30X30 CM | D102: ML | E102: =10+8.6+5*3+2.7+1.6+8.6*3+5*3 -> 78.7 | F102: =10+8.6+5*3+2.7+1.6+8.6*3+5*3 -> 78.7 | G102: 0 | H102: 0 | I102: 0 | J102: =APUs!G5120 -> 232826 | K102: =$J102*E102 -> 18323406 | L102: =$J102*F102 -> 18323406 | M102: =$J102*G102 -> 0 | N102: =$J102*H102 -> 0 | O102: =$J102*I102 -> 0
A103: 084 | B103: =A103&"_OC" -> 084_OC | C103: VIGA DE CIMENTACIÓN 30X40 CM | D103: ML | E103: 0 | F103: 0 | G103: 160 | H103: 160 | I103: 160 | J103: =APUs!G5188 -> 304033 | K103: =$J103*E103 -> 0 | L103: =$J103*F103 -> 0 | M103: =$J103*G103 -> 48645280 | N103: =$J103*H103 -> 48645280 | O103: =$J103*I103 -> 48645280
...

Sheet IPP
A1: Fecha | B1: Índice de Precios del Productor (IPP)
A2: yyyy/mm/dd | B2: Índice
A3: 1999/06/30 | B3: 43.87
A4: 1999/07/31 | B4: 44.59
A5: 1999/08/31 | B5: 45.24
A6: 1999/09/30 | B6: 45.71
A7: 1999/10/31 | B7: 46.27
A8: 1999/11/30 | B8: 46.89
A9: 1999/12/31 | B9: 47.41
A10: 2000/01/31 | B10: 48.07
A11: 2000/02/29 | B11: 49.19
A12: 2000/03/31 | B12: 49.87
A13: 2000/04/30 | B13: 50.36
A14: 2000/05/31 | B14: 50.83
... A220: 2017/07/31 | B220: 107.1
A221: 2017/08/31 | B221: 107.7 | C221: =$B$310/B220 -> 1.75845
A222: 2017/09/30 | B222: 108.17 | C222: =$B$310/B221 -> 1.7486537
A223: 2017/10/31 | B223: 109.04 | C223: =$B$310/B222 -> 1.7410557
A224: 2017/11/30 | B224: 110.76 | C224: =$B$310/B223 -> 1.7271643
A225: 2017/12/31 | B225: 111.29 | C225: =$B$310/B224 -> 1.7003431
A226: 2018/01/31 | B226: 111.5 | C226: =$B$310/B225 -> 1.6922455
A227: 2018/02/28 | B227: 111.35 | C227: =$B$310/B226 -> 1.6890583
A228: 2018/03/31 | B228: 111.14 | C228: =$B$310/B227 -> 1.6913336
A229: 2018/04/30 | B229: 111.41 | C229: =$B$310/B228 -> 1.6945294
A230: 2018/05/31 | B230: 113.86 | C230: =$B$310/B229 -> 1.6904228
A231: 2018/06/30 | B231: 113.72 | C231: =$B$310/B230 -> 1.6540488
A232: 2018/07/31 | B232: 113.45 | C232: =$B$310/B231 -> 1.6560851
... A310: 2025/01/31 | B310: 188.33 | C310: =$B$310/B309 -> 1.0102457
A313: Descargado de sistema del Banco de la República viernes, 7 de febrero de 2025 1:51:54 p. m.

Sheet N Bahias
A1: BAHÍAS ACTIVAS | F1: ELEMENTOS POR BAHÍA | J1: TOTAL EQUIPOS EN 34,5 kV | P1: TOTAL EQUIPOS EN 13,8 kV
A2: Tensión | B2: DDP | C2: Activa | D2: Bahía de Línea | F2: Equipo | G2: Bahía de Línea | H2: Bahía de Trafo | J2: Cod | K2: Equipo | L2: Bahía de Línea | M2: Bahía de Trafo | N2: Total | P2: Cod | Q2: Elementos por S/E | R2: Bahía de Línea | S2: Bahía de Trafo | T2: Total
A3: 34.5 | B3: FORTALECILLAS | C3: SI | D3: L | F3: DPS | G3: 3 | H3: 3 | J3: 1.1 | K3: Transformador de Potencia | M3: 1 | N3: =SUM(L3:M3) -> 1
A4: 34.5 | B4: COLOMBIA | C4: SI | D4: L | F4: Reconectador/Interruptor | G4: 1 | H4: 1 | J4: 2.1 | K4: DPS | L4: =G3*B$21 -> 12 | M4: =H3*C$21 -> 3 | N4: =SUM(L4:M4) -> 15 | P4: 1.2 | Q4: DPS | R4: =G3*B$22 -> 9 | S4: =H3*C$22 -> 3 | T4: =SUM(R4:S4) -> 12
A5: 34.5 | B5: AIPE | C5: SI | D5: L | F5: Seccionador Tripolar | G5: 1 | H5: 1 | J5: 3.1 | K5: Reconectador/Interruptor | L5: =G4*B$21 -> 4 | M5: =H4*C$21 -> 1 | N5: =SUM(L5:M5) -> 5 | P5: 2.2 | Q5: Reconectador/Interruptor | R5: =G4*B$22 -> 3 | S5: =H4*C$22 -> 1 | T5: =SUM(R5:S5) -> 4
A6: 34.5 | B6: TRAFO 1 | C6: SI | D6: T | F6: Seccionador con cuchilla PT | G6: 1 | H6: 0 | J6: 4.1 | K6: Seccionador Tripolar | L6: =G5*B$21 -> 4 | M6: =H5*C$21 -> 1 | N6: =SUM(L6:M6) -> 5 | P6: 3.2 | Q6: Seccionador Tripolar | R6: =G5*B$22 -> 3 | S6: =H5*C$22 -> 1 | T6: =SUM(R6:S6) -> 4
A7: 34.5 | B7: SERV AUX | C7: SI | D7: Aux | F7: TC | G7: 3 | H7: 3 | J7: 5.1 | K7: Seccionador con cuchilla PT | L7: =G6*B$21 -> 4 | M7: =H6*C$21 -> 0 | N7: =SUM(L7:M7) -> 4 | P7: 4.2 | Q7: Seccionador con cuchilla PT | R7: =G6*B$22 -> 3 | S7: =H6*C$22 -> 0 | T7: =SUM(R7:S7) -> 3
A8: 34.5 | B8: TRAFO 2 - RESER | C8: NO | D8: T | F8: Medidor | G8: 1 | H8: 1 | J8: 6.1 | K8: TC General | L8: =G7*B$21 -> 12 | M8: =H7*C$21 -> 3 | N8: =SUM(L8:M8) -> 15 | P8: 5.2 | Q8: TC General | R8: =G7*B$22 -> 9 | S8: =H7*C$22 -> 3 | T8: =SUM(R8:S8) -> 12
A9: 34.5 | B9: RESERVA LÍNEA 1 | C9: NO | D9: L | J9: 7.1 | K9: TP General | L9: 3 | M9: 0 | N9: =SUM(L9:M9) -> 3 | P9: 6.2 | Q9: TP General | R9: 3 | S9: 0 | T9: =SUM(R9:S9) -> 3
A10: 34.5 | B10: RESERVA LÍNEA 2 | C10: NO | D10: L | J10: 8.1 | K10: TP Particular | L10: 1 | M10: 0 | N10: =SUM(L10:M10) -> 1 | P10: 7.2 | Q10: =H18 -> 0 | R10: =H19 -> 0 | S10: 0 | T10: =SUM(R10:S10) -> 0
A11: 13.8 | B11: LAURELES-PATIA | C11: SI | D11: L | J11: 9.1 | K11: =B20 -> Bahías de Línea | L11: =B21 -> 4 | M11: 0 | N11: =SUM(L11:M11) -> 4 | P11: 8.2 | Q11: =I18 -> 0 | R11: 0 | S11: =I19 -> 0 | T11: =SUM(R11:S11) -> 0
A12: 13.8 | B12: SAN ANDRÉS | C12: SI | D12: L | J12: 10.1 | K12: =C20 -> Bahías de Trafo | L12: 0 | M12: =C21 -> 1 | N12: =SUM(L12:M12) -> 1 | P12: 9.2 | Q12: Medidor | R12: =M6*H$21 -> 0 | S12: =N6*I$21 -> 0 | T12: =SUM(R12:S12) -> 0
A13: 13.8 | B13: URBANO | C13: SI | D13: L | J13: 11.1 | K13: Medidor | L13: =G8*B$21 -> 4 | M13: =H8*C$21 -> 1 | N13: =SUM(L13:M13) -> 5
A14: 13.8 | B14: SERV AUX | C14: SI | D14: Aux
A15: 13.8 | B15: TRAFO 1 | C15: SI | D15: T
A16: 13.8 | B16: TRAFO 2 - RESER | C16: NO | D16: T
A17: 13.8 | B17: RESERVA LÍNEA 2 | C17: NO | D17: L
A18: 13.8 | B18: RESERVA LÍNEA 2 | C18: NO | D18: L
A20: Tensión | B20: Bahías de Línea | C20: Bahías de Trafo | D20: Bahías Aux
A21: 34.5 | B21: 4 | C21: =COUNTIFS($D$3:$D$18,"T",$C$3:$C$18,"SI",$A$3:$A$18,$A21) -> 1 | D21: =COUNTIFS($D$3:$D$18,"Aux",$C$3:$C$18,"SI",$A$3:$A$18,$A$21) -> 1
A22: 13.8 | B22: =COUNTIFS($D$3:$D$18,"L",$C$3:$C$18,"SI",$A$3:$A$18,$A$21) -> 3 | C22: =COUNTIFS($D$3:$D$18,"T",$C$3:$C$18,"SI",$A$3:$A$18,$A22) -> 1 | D22: =COUNTIFS($D$3:$D$18,"Aux",$C$3:$C$18,"SI",$A$3:$A$18,$A$21) -> 1
A23: Total | B23: =SUM(B21:B22) -> 7 | C23: =SUM(C21:C22) -> 2 | D23: =SUM(D21:D22) -> 2
A25: Descripción | B25: Metros
A26: Metros Caseta a Patio | B26: 15
A27: Bahías Equipadas 34,5 kV | B27: 5
A28: Bahías Equipadas 13,8 kV | B28: 4
A29: Pase de Vía | B29: 21
A30: Tubos 4" | B30: 8
A31: Tubos 3" | B31: 4
A32: Tubos 2" | B32: 3
A33: Tubos 1 1/2" | B33: 4

Sheet Componentes APUs
A1: Referencia | B1: Descripción | C1: Unidad | D1: Vr. Unitario ($) | E1: Vida Util (Años) | F1: Valor ED | H1: Referencia | I1: Descripción | J1: Fac. Sal | K1: Jornal ($) | L1: Prestaciones ($) | N1: Referencia | O1: Descripción | P1: Unidad | Q1: Vr. Unitario ($) | S1: Referencia | T1: Descripción | U1: Unidad | V1: Vr. Unitario ($)
A2: ED-1 | B2: Camisa indigo sin partes metalicas | C2: U | D2: =F2/(E2*12) -> 8585.8586 | E2: 0.33 | F2: 34000 | H2: MO-1 | I2: Ingeniero Residente de Obra | J2: 4 | K2: =J2*IF(J2>2,1423500,(1423500+200000))/21 -> 271142.86 | L2: =0.6*K2 -> 162685.71 | N2: TV-1 | O2: Camioneta | P2: U | Q2: 5500000 | S2: EH-1 | T2: Juego Llaves | U2: U | V2: 9167
A3: ED-2 | B3: Bota de seguridad dielectrica | C3: Par | D3: =F3/(E3*12) -> 7500 | E3: 1 | F3: 90000 | H3: MO-2 | I3: Tecnico Supervisor | J3: 2.3 | K3: =J3*IF(J3>2,1423500,(1423500+200000))/21 -> 155907.14 | L3: =0.6*K3 -> 93544.286 | N3: TV-2 | O3: Grúa Hidráulica | P3: U | Q3: 21000000 | S3: EH-2 | T3: Manila de servicio | U3: U | V3: 2333
A4: ED-3 | B4: Casco dielectrico Tipo 1 Clase E con barbuquejo | C4: U | D4: =F4/(E4*12) -> 10101.01 | E4: 0.33 | F4: 40000 | H4: MO-3 | I4: Tecnico Liniero | J4: 2 | K4: =J4*IF(J4>2,1423500,(1423500+200000))/21 -> 154619.05 | L4: =0.6*K4 -> 92771.429 | N4: TV-3 | O4: Camabaja | P4: TON/KM | Q4: 611 | S4: EH-3 | T4: Tula portaherramientas | U4: U | V4: 1250
A5: ED-4 | B5: Correa plastica y antiflama | C5: U | D5: =F5/(E5*12) -> 3787.8788 | E5: 0.33 | F5: 15000 | H5: MO-4 | I5: Ayudante Calificado | J5: 1.5 | K5: =J5*IF(J5>2,1423500,(1423500+200000))/21 -> 115964.29 | L5: =0.6*K5 -> 69578.571 | N5: TV-4 | O5: Volqueta | P5: U | Q5: =88263*21*8 -> 14828184 | S5: EH-4 | T5: Agarradoras | U5: U | V5: 125000
A6: ED-5 | B6: Gafas protectoras filtro UV | C6: U | D6: =F6/(E6*12) -> 2777.7778 | E6: 0.33 | F6: 11000 | H6: MO-5 | I6: Profesional en SST | J6: 2.5 | K6: =J6*IF(J6>2,1423500,(1423500+200000))/21 -> 169464.29 | L6: =0.6*K6 -> 101678.57 | N6: TV-5 | O6: Retroexcavadora | P6: U | Q6: =273992*21*8 -> 46030656 | S6: EH-5 | T6: Templadoras | U6: U | V6: 250000
A7: ED-6 | B7: Bota de seguridad PVC dielectrica | C7: Par | D7: =F7/(E7*12) -> 2916.6667 | E7: 2 | F7: 70000 | H7: MO-6 | I7: Ayudante No Calificado | J7: 1 | K7: =J7*IF(J7>2,1423500,(1423500+200000))/21 -> 77309.524 | L7: =0.6*K7 -> 46385.714 | N7: TV-6 | O7: Montacarga | P7: U | Q7: pendiente | S7: EH-6 | T7: Herramienta Menor | U7: U | V7: 75758
A8: ED-7 | B8: Capuchon | C8: U | D8: =F8/(E8*12) -> 2525.2525 | E8: 0.33 | F8: 10000 | H8: MO-7 | I8: Ayudante de Obra Civil | J8: 1 | K8: =J8*IF(J8>2,1423500,(1423500+200000))/21 -> 77309.524 | L8: =0.6*K8 -> 46385.714 | N8: TV-7 | O8: Vibrador de concreto | P8: U | Q8: =63070*21 -> 1324470 | S8: EH-7 | T8: =PROPER("MOLDE GRAFITO SOLDADURA EXOTÉRMICA EN X") -> Molde Grafito Soldadura Exotérmica En X | U8: U | V8: 239000
A9: ED-8 | B9: Guantes Protectores - ingeniero reforzados | C9: Par | D9: =F9/(E9*12) -> 2525.2525 | E9: 0.33 | F9: 10000 | H9: MO-8 | I9: Maestro de obra civil | J9: 2.5 | K9: =J9*IF(J9>2,1423500,(1423500+200000))/21 -> 169464.29 | L9: =0.6*K9 -> 101678.57 | N9: TV-8 | O9: Miniretroexcavadora | P9: M3 | Q9: 70000 | S9: EH-8 | T9: Equipo para trabajo con fibra óptica | U9: U | V9: =899*1.19*'Precio Monedas'!B2 -> 4814145
A10: ED-9 | B10: Impermeable (pantalon camisa) | C10: U | D10: =F10/(E10*12) -> 3750 | E10: 1 | F10: 45000 | H10: MO-9 | I10: Oficial de Obra Civil | J10: 1.5 | K10: =J10*IF(J10>2,1423500,(1423500+200000))/21 -> 115964.29 | L10: =0.6*K10 -> 69578.571 | N10: TV-9 | O10: Dumper de descarga Frontal 2T | P10: U | Q10: =26420.93*8*21 -> 4438716.2 | S10: EH-9 | T10: Diferencial 2 Toneladas | U10: U | V10: 474905
A11: ED-10 | B11: Jean Dielectrico | C11: U | D11: =F11/(E11*12) -> 7575.7576 | E11: 0.33 | F11: 30000 | H11: MO-10 | I11: Ingeniero Civil Residente de Obra | J11: 3 | K11: =J11*IF(J11>2,1423500,(1423500+200000))/21 -> 203357.14 | L11: =0.6*K11 -> 122014.29 | N11: TV-10 | O11: Rodillo Ligero | P11: U | Q11: =9975*8*21 -> 1675800
A12: ED-11 | B12: Casco dielectrico Tipo 2 Clase E con barboquejo | C12: U | D12: =F12/(E12*12) -> 7500 | E12: 1 | F12: 90000 | H12: MO-11 | I12: Ingeniero Especialista de Control y Protección Subestación | J12: 14 | K12: =J12*IF(J12>2,1423500,(1423500+200000))/21 -> 949000 | L12: =0.6*K12 -> 569400 | N12: TV-11 | O12: Motocultor | P12: U | Q12: =7695*8*21 -> 1292760
A13: ED-12 | B13: Kit de rescate para trabajo en alturas | C13: U | D13: =F13/(E13*12) -> 37500 | E13: 4 | F13: 1800000 | H13: MO-12 | I13: Técnico calificado para Comunicaciones | J13: 3 | K13: =J13*IF(J13>2,1423500,(1423500+200000))/21 -> 203357.14 | L13: =0.6*K13 -> 122014.29 | N13: TV-12 | O13: Concretera | P13: U | Q13: =3278*8*21 -> 550704
A14: ED-13 | B14: Equipo completo para trabajo en alturas con pretales (Arnes dielectrico, 1 mosqueton de seguridad, tie off dielectrico, eslinga de posicionamiento, juego de pretales) | C14: U | D14: =F14/(E14*12) -> 26041.667 | E14: 4 | F14: 1250000 | H14: MO-13 | I14: Oficial Eléctrico | J14: 2 | K14: =J14*IF(J14>2,1423500,(1423500+200000))/21 -> 154619.05 | L14: =0.6*K14 -> 92771.429 | N14: TV-13 | O14: Extendedora Asfáltica De Cadenas 110 Cv | P14: U | Q14: =141307*8*21 -> 23739576
H15: MO-14 | I15: Topografo | J15: 2 | K15: =J15*IF(J15>2,1423500,(1423500+200000))/21 -> 154619.05 | L15: =0.6*K15 -> 92771.429 | N15: TV-14 | O15: Rodillo Vibrante Tándem Autopropulsado, De 2300 Kg, Anchura De Trabajo 105 Cm | P15: U | Q15: =29162*8*21 -> 4899216
N16: TV-15 | O16: Compactador De Neumáticos Autopropulsado, De 12/22 T | P16: U | Q16: =102366*8*21 -> 17197488
N17: TV-16 | O17: Planta de asfalto en caliente continua de 120 toneladas de capacidad | P17: U | Q17: =675749.029432224*8*21 -> 1.1352584e+08
N18: TV-17 | O18: Cargador: potencia en el volante 125 hp, clasificación de rpm del motor 2300 | P18: U | Q18: =256739.231927711*8*21 -> 43132191
N19: TV-18 | O19: Compactador de rodillo potencia: 99 hp, peso: 8 toneladas | P19: U | Q19: =248057.228915663*21*8 -> 41673614
N20: TV-19 | O20: Terminadora de asfalto (Finisher), potencia en el volante 174 HP, R=20M3/H, velocidad de desplazamiento 114 m/min | P20: U | Q20: =197412.809400494*21*8 -> 33165352
N21: TV-20 | O21: Carrotanque de agua (1000 Galones) | P21: U | Q21: =124028.614457831*8*21 -> 20836807
N22: TV-21 | O22: Motoniveladora potencia 215 HP, ancho de cuchilla 4,27 m, peso 18 ton | P22: U | Q22: =221341.634782372*8*21 -> 37185395
N23: TV-22 | O23: Vibrocompactador, potencia 153 HP, peso 10 ton | P23: U | Q23: =232553.652108434*8*21 -> 39069014
N24: TV-23 | O24: Compresor (barrido y soplado) | P24: U | Q24: =53839.8571092257*21*8 -> 9045096
N25: TV-24 | O25: Vehículo delineador para aplicación de pintura con mínimo 2 boquillas (NTC 4744-2) | P25: U | Q25: 214489.08
N26: TV-25 | O26: CILINDRO COMPACTADOR BENITÍN DE 300 Kg | P26: U | Q26: =103154*21*8 -> 17329872
N27: TV-26 | O27: CARRETA BUGGIE, PALA, ZAPAPICO | P27: U | Q27: =429030*21*8 -> 72077040
N28: TV-27 | O28: MINICARGADOR CON OPERARIO | P28: U | Q28: =117332*21*8 -> 19711776
N29: TV-28 | O29: Cilindro compactador vibrador dynapac | P29: U | Q29: =141751.68*8*21 -> 23814282
N30: TV-29 | O30: Carrotanque agua | P30: U | Q30: =76057.8*8*21 -> 12777710
N31: TV-30 | O31: Compactador asfalto | P31: U | Q31: =117530.196*8*21 -> 19745073
N32: TV-31 | O32: Terminador de asfalto | P32: U | Q32: =154259.427*8*21 -> 25915584

Sheet Precio Monedas
A1: Moneda | B1: Valor
A2: Dólar Americano | B2: 4500
A3: Peso chileno | B3: 4.3
A4: Euro | B4: 4300
A5: Peso Mexicano | B5: 220
