Workbook

Sheet Presupuesto
A2: PRESUPUESTO PALERMO JUNCAL
A4: No. | B4: DESCRIPCIÓN | C4: UNIDAD | D4: CANTIDAD | E4: A. MATERIAL | F4: B. MANO DE OBRA | G4: C. SERVICIO, EQUIPO, HERRAMIENTAS Y HSE | H4: D. TRANSPORTE | I4: E. VIATICOS | J4: PRECIO UNITARIO | K4: PRECIO TOTAL
A5: 1 | B5: MANO DE OBRA | K5: =SUM(K6:K39) -> 101655558
A6: 1.2 | B6: ='1.2'!B6:G6 -> APERTURA DE EXCAVACION POSTE DE 14 MTS M.T. RURAL | C6: UND | D6: =APU_P!N4 -> 2 | E6: ='1.2'!$H$17 -> 0 | F6: ='1.2'!$H$34 -> 184872.77 | G6: ='1.2'!$H$51 -> 23233.722 | H6: ='1.2'!$H$58 -> 0 | I6: ='1.2'!$H$65 -> 0 | J6: ='1.2'!F4 -> 208106.49 | K6: =ROUNDUP(Tabla1[[#This Row],[CANTIDAD]]*Tabla1[[#This Row],[PRECIO UNITARIO]],0) -> 416213
A7: 1.3 | B7: ='1.3'!B6:G6 -> APERTURA DE EXCAVACION PARA VIGUETA EN RETENIDA RURAL | C7: UND | D7: =APU_P!N5 -> 12 | E7: ='1.3'!$H$17 -> 0 | F7: ='1.3'!$H$34 -> 83520.324 | G7: ='1.3'!$H$51 -> 8712.6456 | H7: ='1.3'!$H$58 -> 0 | I7: ='1.3'!$H$65 -> 0 | J7: ='1.3'!F4 -> 92232.969 | K7: =ROUNDUP(Tabla1[[#This Row],[CANTIDAD]]*Tabla1[[#This Row],[PRECIO UNITARIO]],0) -> 1106796
A8: 1.6 | B8: ='1.6'!$B$6:$G$6 -> HINCADA, PLOMADA Y ORIENTACIÓN DE POSTE DE 14, 16 Y 18 MTS CON GRUA | C8: UND | D8: =APU_P!N6 -> 5 | E8: ='1.6'!$H$17 -> 0 | F8: ='1.6'!$H$34 -> 109533.17 | G8: ='1.6'!$H$51 -> 308712.65 | H8: ='1.6'!$H$58 -> 0 | I8: ='1.6'!$H$65 -> 0 | J8: ='1.6'!F4 -> 418245.81 | K8: =ROUNDUP(Tabla1[[#This Row],[CANTIDAD]]*Tabla1[[#This Row],[PRECIO UNITARIO]],0) -> 2091230
A9: 1.7 | B9: ='1.7'!$B$6:$G$6 -> INSTALACION LINE A TIERRA MEDIA TENSION | C9: UND | D9: =APU_P!N7 -> 4 | E9: ='1.7'!$H$17 -> 0 | F9: ='1.7'!$H$34 -> 136919.2 | G9: ='1.7'!$H$51 -> 6970.1165 | H9: ='1.7'!$H$58 -> 0 | I9: ='1.7'!$H$65 -> 0 | J9: ='1.7'!F4 -> 143889.32 | K9: =ROUNDUP(Tabla1[[#This Row],[CANTIDAD]]*Tabla1[[#This Row],[PRECIO UNITARIO]],0) -> 575558
A10: 1.8 | B10: ='1.8'!$B$6:$G$6 -> INSTALACIÓN DE TEMPLETE CUERDA GUITARRA CON TODOS SUS ACCESORIOS M.T. RURAL | C10: UND | D10: =APU_P!N8 -> 5 | E10: ='1.8'!$H$17 -> 0 | F10: ='1.8'!$H$34 -> 95832.542 | G10: ='1.8'!$H$51 -> 4646.7443 | H10: ='1.8'!$H$58 -> 0 | I10: ='1.8'!$H$65 -> 0 | J10: ='1.8'!F4 -> 100479.29 | K10: =ROUNDUP(Tabla1[[#This Row],[CANTIDAD]]*Tabla1[[#This Row],[PRECIO UNITARIO]],0) -> 502397
A11: 1.9 | B11: ='1.9'!B6:G6 -> RIEGA, TENDIDO Y TENSIONADO DE UN CABLE DE GUARDA | C11: KM | D11: =APU_P!N9 -> 0.716 | E11: ='1.9'!$H$17 -> 0 | F11: ='1.9'!$H$34 -> 648058.43 | G11: ='1.9'!$H$51 -> 511041.06 | H11: ='1.9'!$H$58 -> 210000 | I11: ='1.9'!$H$65 -> 0 | J11: ='1.9'!F4 -> 1369099.5 | K11: =ROUNDUP(Tabla1[[#This Row],[CANTIDAD]]*Tabla1[[#This Row],[PRECIO UNITARIO]],0) -> 980276
A12: 1.11 | B12: ='1.11'!B6:G6 -> TENDIDO Y TENSIONADO DE CABLE ECOLOGICO PARA RED MT TRIFASICA 36 KV DISPOSICION HORIZONTAL | C12: KM | D12: =APU_P!N11 -> 2.149 | E12: ='1.11'!$H$17 -> 0 | F12: ='1.11'!$H$34 -> 2466647.4 | G12: ='1.11'!$H$51 -> 1430245.4 | H12: ='1.11'!$H$58 -> 420000 | I12: ='1.11'!$H$65 -> 0 | J12: ='1.11'!F4 -> 4316892.8 | K12: =ROUNDUP(Tabla1[[#This Row],[CANTIDAD]]*Tabla1[[#This Row],[PRECIO UNITARIO]],0) -> 9277003
A13: 1.12 | B13: ='1.12'!$B$6:$G$6 -> TRANSPORTE DE POSTE 14 MTS M.T. RURAL DE BODEGA A SITIO CERCANO | C13: UND | D13: =APU_P!N12 -> 5 | E13: ='1.12'!$H$17 -> 0 | F13: ='1.12'!$H$34 -> 77975.29 | G13: ='1.12'!$H$51 -> 294701.17 | H13: ='1.12'!$H$58 -> 0 | I13: ='1.12'!$H$65 -> 0 | J13: ='1.12'!F4 -> 372676.45 | K13: =ROUNDUP(Tabla1[[#This Row],[CANTIDAD]]*Tabla1[[#This Row],[PRECIO UNITARIO]],0) -> 1863383
A14: 1.15 | B14: ='1.15'!$B$6:$G$6 -> VESTIDA DE ESTRUCTURA TRIFASICA DE PASO UN POSTE 13,8kV | C14: UND | D14: =APU_P!N15 -> 3 | E14: ='1.15'!$H$17 -> 0 | F14: ='1.15'!$H$34 -> 67418.622 | G14: ='1.15'!$H$51 -> 8712.6456 | H14: ='1.15'!$H$58 -> 26250 | I14: ='1.15'!$H$65 -> 0 | J14: ='1.15'!F4 -> 102381.27 | K14: =ROUNDUP(Tabla1[[#This Row],[CANTIDAD]]*Tabla1[[#This Row],[PRECIO UNITARIO]],0) -> 307144
A15: 1.16 | B15: ='1.16'!$B$6:$G$6 -> VESTIDA DE ESTRUCTURA TRIFASICA DE RETENCION UN POSTE 13,8 Kv | C15: UND | D15: =APU_P!N16 -> 2 | E15: ='1.16'!$H$17 -> 0 | F15: ='1.16'!$H$34 -> 89880.129 | G15: ='1.16'!$H$51 -> 11616.861 | H15: ='1.16'!$H$58 -> 35000 | I15: ='1.16'!$H$65 -> 0 | J15: ='1.16'!F4 -> 136496.99 | K15: =ROUNDUP(Tabla1[[#This Row],[CANTIDAD]]*Tabla1[[#This Row],[PRECIO UNITARIO]],0) -> 272994
A16: 1.17 | B16: ='1.17'!$B$6:$G$6 -> VESTIDA DE ESTRUCTURA TRIFASICA DE UN POSTE TIPO PASO 34.5 KV | C16: UND | D16: =APU_P!N17 -> 3 | E16: ='1.17'!$H$17 -> 0 | F16: ='1.17'!$H$34 -> 184702.7 | G16: ='1.17'!$H$51 -> 17425.291 | H16: ='1.17'!$H$58 -> 52500 | I16: ='1.17'!$H$65 -> 0 | J16: ='1.17'!F4 -> 254628 | K16: =ROUNDUP(Tabla1[[#This Row],[CANTIDAD]]*Tabla1[[#This Row],[PRECIO UNITARIO]],0) -> 763884
A17: 1.18 | B17: ='1.18'!$B$6:$G$6 -> VESTIDA DE ESTRUCTURA TRIFASICA DE UN POSTE TIPO RETENCIÓN - 34.5 KV | C17: UND | D17: =APU_P!N18 -> 5 | E17: ='1.18'!$H$17 -> 0 | F17: ='1.18'!$H$34 -> 246270.27 | G17: ='1.18'!$H$51 -> 23233.722 | H17: ='1.18'!$H$58 -> 70000 | I17: ='1.18'!$H$65 -> 0 | J17: ='1.18'!F4 -> 339503.99 | K17: =ROUNDUP(Tabla1[[#This Row],[CANTIDAD]]*Tabla1[[#This Row],[PRECIO UNITARIO]],0) -> 1697520
A18: 1.19 | B18: ='1.19'!B6:G6 -> VESTIDA ESTRUCTURA CABLE DE GUARDA - RETENCION | C18: UND | D18: =APU_P!N19 -> 3 | E18: ='1.19'!$H$17 -> 0 | F18: ='1.19'!$H$34 -> 65455.762 | G18: ='1.19'!$H$51 -> 9957.3093 | H18: ='1.19'!$H$58 -> 30000 | I18: ='1.19'!$H$65 -> 0 | J18: ='1.19'!F4 -> 105413.07 | K18: =ROUNDUP(Tabla1[[#This Row],[CANTIDAD]]*Tabla1[[#This Row],[PRECIO UNITARIO]],0) -> 316240
A19: 1.20 | B19: ='1.20'!B6:G6 -> VESTIDA ESTRUCTURA CABLE DE GUARDA DE PASO | C19: UND | D19: =APU_P!N20 -> 3 | E19: ='1.20'!$H$17 -> 0 | F19: ='1.20'!$H$34 -> 57273.791 | G19: ='1.20'!$H$51 -> 8712.6456 | H19: ='1.20'!$H$58 -> 26250 | I19: ='1.20'!$H$65 -> 0 | J19: ='1.20'!F4 -> 92236.437 | K19: =ROUNDUP(Tabla1[[#This Row],[CANTIDAD]]*Tabla1[[#This Row],[PRECIO UNITARIO]],0) -> 276710
A20: 1.21 | B20: ='1.21'!A1 -> DESVESTIDA ESTRUCTURA DE RETENCION MT RURAL | C20: UND | D20: =APU_P!N21 -> 3 | E20: ='1.21'!$H$17 -> 0 | F20: ='1.21'!$H$34 -> 136919.2 | G20: ='1.21'!$H$51 -> 6970.1165 | H20: ='1.21'!$H$58 -> 0 | I20: ='1.21'!$H$65 -> 0 | J20: ='1.21'!F4 -> 143889.32 | K20: =ROUNDUP(Tabla1[[#This Row],[CANTIDAD]]*Tabla1[[#This Row],[PRECIO UNITARIO]],0) -> 431668
A21: 1.22 | B21: ='1.22'!A1 -> DESVESTIDA ESTRUCTURA DE SUSPENSION MT RURAL | C21: UND | D21: =APU_P!N22 -> 1 | E21: ='1.22'!$H$17 -> 0 | F21: ='1.22'!$H$34 -> 95832.542 | G21: ='1.22'!$H$51 -> 4646.7443 | H21: ='1.22'!$H$58 -> 0 | I21: ='1.22'!$H$65 -> 0 | J21: ='1.22'!F4 -> 100479.29 | K21: =ROUNDUP(Tabla1[[#This Row],[CANTIDAD]]*Tabla1[[#This Row],[PRECIO UNITARIO]],0) -> 100480
A22: 1.23 | B22: ='1.23'!B6:G6 -> DESHINCADA DE POSTES 10, 12 Y 14 mts MT | C22: UND | D22: =APU_P!N23 -> 4 | E22: ='1.23'!$H$17 -> 0 | F22: ='1.23'!$H$34 -> 188203.38 | G22: ='1.23'!$H$51 -> 339701.17 | H22: ='1.23'!$H$58 -> 0 | I22: ='1.23'!$H$65 -> 0 | J22: ='1.23'!F4 -> 527904.55 | K22: =ROUNDUP(Tabla1[[#This Row],[CANTIDAD]]*Tabla1[[#This Row],[PRECIO UNITARIO]],0) -> 2111619
A23: 1.24 | B23: ='1.24'!B6:G6 -> INSTALACIÓN DE TEMPLETE SENCILLO CON TODOS SUS ACCESORIOS M.T. RURAL | C23: UND | D23: =APU_P!N24 -> 7 | E23: ='1.24'!$H$17 -> 0 | F23: ='1.24'!$H$34 -> 82136.989 | G23: ='1.24'!$H$51 -> 3872.2869 | H23: ='1.24'!$H$58 -> 0 | I23: ='1.24'!$H$65 -> 0 | J23: ='1.24'!F4 -> 86009.275 | K23: =ROUNDUP(Tabla1[[#This Row],[CANTIDAD]]*Tabla1[[#This Row],[PRECIO UNITARIO]],0) -> 602065
A24: 1.26 | B24: ='1.26'!B6:G6 -> TRANSPORTE DE POSTE RURAL DE SITIO CERCANO A BODEGA EH | C24: UND | D24: =APU_P!N26 -> 4 | E24: ='1.26'!$H$17 -> 0 | F24: ='1.26'!$H$34 -> 46034.989 | G24: ='1.26'!$H$51 -> 162923.6 | H24: ='1.26'!$H$58 -> 0 | I24: ='1.26'!$H$65 -> 0 | J24: ='1.26'!F4 -> 208958.59 | K24: =ROUNDUP(Tabla1[[#This Row],[CANTIDAD]]*Tabla1[[#This Row],[PRECIO UNITARIO]],0) -> 835835
A25: 1.27 | B25: ='1.27'!B6 -> DESMONTE DE TRANSFORMADOR MONOFASICO | C25: UND | D25: =APU_P!N27 -> 1 | E25: ='1.27'!$H$17 -> 0 | F25: ='1.27'!$H$34 -> 290740.35 | G25: ='1.27'!$H$51 -> 116168.61 | H25: ='1.27'!$H$58 -> 0 | I25: ='1.27'!$H$65 -> 0 | J25: ='1.27'!F4 -> 406908.96 | K25: =ROUNDUP(Tabla1[[#This Row],[CANTIDAD]]*Tabla1[[#This Row],[PRECIO UNITARIO]],0) -> 406909
A26: 1.28 | B26: ='1.28'!B6 -> MONTAJE DE TRANSFORMADOR MONOFASICO CON TODAS SUS PROTECCIONES RURAL | C26: UND | D26: =APU_P!N28 -> 1 | E26: ='1.28'!$H$17 -> 0 | F26: ='1.28'!$H$34 -> 391577.84 | G26: ='1.28'!$H$51 -> 348505.83 | H26: ='1.28'!$H$58 -> 0 | I26: ='1.28'!$H$65 -> 0 | J26: ='1.28'!F4 -> 740083.67 | K26: =ROUNDUP(Tabla1[[#This Row],[CANTIDAD]]*Tabla1[[#This Row],[PRECIO UNITARIO]],0) -> 740084
A27: 1.29 | B27: ='1.29'!B6:G6 -> DESVESTIDA DE ESTRUCTURA BT EXISTENTE | C27: UND | D27: =APU_P!N29 -> 2 | E27: ='1.29'!$H$17 -> 0 | F27: ='1.29'!$H$34 -> 45332.476 | G27: ='1.29'!$H$51 -> 20190 | H27: ='1.29'!$H$58 -> 0 | I27: ='1.29'!$H$65 -> 0 | J27: ='1.29'!F4 -> 65522.476 | K27: =ROUNDUP(Tabla1[[#This Row],[CANTIDAD]]*Tabla1[[#This Row],[PRECIO UNITARIO]],0) -> 131045
A28: 1.30 | B28: ='1.30'!B6:G6 -> VESTIDA DE ESTRUCTURA BT | C28: UND | D28: =APU_P!N30 -> 2 | E28: ='1.30'!$H$17 -> 0 | F28: ='1.30'!$H$34 -> 77259.417 | G28: ='1.30'!$H$51 -> 38250 | H28: ='1.30'!$H$58 -> 0 | I28: ='1.30'!$H$65 -> 0 | J28: ='1.30'!F4 -> 115509.42 | K28: =ROUNDUP(Tabla1[[#This Row],[CANTIDAD]]*Tabla1[[#This Row],[PRECIO UNITARIO]],0) -> 231019
A29: 1.31 | B29: ='1.31'!A1 -> DESMONTE, RECOGIDA Y ENROLLADO CABLE MT URBANO TRIFASICO | C29: Km | D29: =APU_P!N31 -> 1.47 | E29: ='1.31'!$H$17 -> 0 | F29: ='1.31'!$H$34 -> 33299.249 | G29: ='1.31'!$H$51 -> 477584.5 | H29: ='1.31'!$H$58 -> 0 | I29: ='1.31'!$H$65 -> 0 | J29: ='1.31'!F4 -> 510883.75 | K29: =ROUNDUP(Tabla1[[#This Row],[CANTIDAD]]*Tabla1[[#This Row],[PRECIO UNITARIO]],0) -> 751000
A30: 1.32 | B30: ='1.32'!B6 -> TENDIDO Y TENSIONADO DE CABLE ECOLOGICO PARA RED MT TRIFASICA 15 KV DISPOSICION HORIZONTAL | C30: Km | D30: =APU_P!N32 -> 1.47 | E30: ='1.32'!$H$17 -> 0 | F30: ='1.32'!$H$34 -> 2216152.2 | G30: ='1.32'!$H$51 -> 260177.36 | H30: ='1.32'!$H$58 -> 0 | I30: ='1.32'!$H$65 -> 0 | J30: ='1.32'!F4 -> 2476329.5 | K30: =ROUNDUP(Tabla1[[#This Row],[CANTIDAD]]*Tabla1[[#This Row],[PRECIO UNITARIO]],0) -> 3640205
A31: 1.33 | B31: ='1.33'!A1 -> INSTALACIÓN DE DEFENSA METALICA - ABATIMIENTO N2 | C31: M | D31: =APU_P!N33 -> 307 | E31: ='1.33'!$H$17 -> 0 | F31: ='1.33'!$H$34 -> 28788.144 | G31: ='1.33'!$H$51 -> 8712.775 | H31: ='1.33'!$H$58 -> 0 | I31: ='1.33'!$H$65 -> 0 | J31: ='1.33'!F4 -> 37500.919 | K31: =ROUNDUP(Tabla1[[#This Row],[CANTIDAD]]*Tabla1[[#This Row],[PRECIO UNITARIO]],0) -> 11512783
A32: 2.1 | B32: ='2.1'!$B$6:$G$6 -> INSTALACIÓN DE PLACAS DE IDENTIFICACIÓN DE PELIGRO RED ENERGIZADA (INCLUYE PLACA EN ACRILICO Y CONECTORES A RED) | C32: UND | D32: =APU_P!N34 -> 5 | E32: ='2.1'!$H$17 -> 35000 | F32: ='2.1'!$H$34 -> 5882.2661 | G32: ='2.1'!$H$51 -> 3485.0583 | H32: ='2.1'!$H$58 -> 0 | I32: ='2.1'!$H$65 -> 0 | J32: ='2.1'!F4 -> 44367.324 | K32: =ROUNDUP(Tabla1[[#This Row],[CANTIDAD]]*Tabla1[[#This Row],[PRECIO UNITARIO]],0) -> 221837
A33: 2.2 | B33: ='2.2'!$B$6:$G$6 -> INSTALACIÓN DE PLACAS DE IDENTIFICACIÓN DE POSTE, (INCLUYE PLACA DE ALUMINIO, CINTA BAND IT Y HEBILLA) | C33: UND | D33: =APU_P!N35 -> 5 | E33: ='2.2'!$H$17 -> 19590 | F33: ='2.2'!$H$34 -> 14760.758 | G33: ='2.2'!$H$51 -> 3485.0583 | H33: ='2.2'!$H$58 -> 0 | I33: ='2.2'!$H$65 -> 0 | J33: ='2.2'!F4 -> 37835.817 | K33: =ROUNDUP(Tabla1[[#This Row],[CANTIDAD]]*Tabla1[[#This Row],[PRECIO UNITARIO]],0) -> 189180
A34: 2.3 | B34: ='2.3'!$B$6:$G$6 -> LEVANTAMIENTO DE PLANO AS-BUILT DE OBRA CONSTRUIDA, GEOREFERENCIADA, MEDIA TENSIÓN Y BAJA TENSIÓN, INCLUYE REGISTRO FOTOGRÁFICO, COPIA FÍSICA Y ARCHIVOS EN CD | C34: UND | D34: =APU_P!N36 -> 1 | E34: ='2.3'!$H$17 -> 0 | F34: ='2.3'!$H$34 -> 2324579.3 | G34: ='2.3'!$H$51 -> 69701.165 | H34: ='2.3'!$H$58 -> 0 | I34: ='2.3'!$H$65 -> 0 | J34: ='2.3'!F4 -> 2394280.4 | K34: =ROUNDUP(Tabla1[[#This Row],[CANTIDAD]]*Tabla1[[#This Row],[PRECIO UNITARIO]],0) -> 2394281
A35: 2.4 | B35: ='2.4'!$B$6:$G$6 -> PREPARACION DISEÑO, MEMORIA DE CALCULO Y DEMAS DOCUMENTOS PARA CERTIFICACION RETIE (ART 10.1 DE RETIE-2013) | C35: UND | D35: =APU_P!N37 -> 1 | E35: ='2.4'!$H$17 -> 0 | F35: ='2.4'!$H$34 -> 10039483 | G35: ='2.4'!$H$51 -> 69701.165 | H35: ='2.4'!$H$58 -> 210000 | I35: ='2.4'!$H$65 -> 0 | J35: ='2.4'!F4 -> 10319185 | K35: =ROUNDUP(Tabla1[[#This Row],[CANTIDAD]]*Tabla1[[#This Row],[PRECIO UNITARIO]],0) -> 10319185
A36: 2.5 | B36: ='2.5'!$B$6:$G$6 -> REUNIR, DILIGENCIAR Y HACER ENTREGA DE LA INFORMACIÓN GENERAL DEL PROYECTO INCLUYENDO FORMATOS SPARD, INFORMES Y DOCUMENTOS REQUERIDOS POR EH SEGÚN FORMATO FT-DEX-03-004. ENTREGA FÍSICA Y MAGNÉTICA DE LA INFORMACIÓN | C36: UND | D36: =APU_P!N38 -> 1 | E36: ='2.5'!$H$17 -> 0 | F36: ='2.5'!$H$34 -> 603249.11 | G36: ='2.5'!$H$51 -> 0 | H36: ='2.5'!$H$58 -> 0 | I36: ='2.5'!$H$65 -> 0 | J36: ='2.5'!F4 -> 603249.11 | K36: =ROUNDUP(Tabla1[[#This Row],[CANTIDAD]]*Tabla1[[#This Row],[PRECIO UNITARIO]],0) -> 603250
A37: 2.6 | B37: ='2.6'!$B$6:$G$6 -> INSPECCION RETIE | C37: UND | D37: =APU_P!N39 -> 1 | E37: ='2.6'!$H$17 -> 12000000 | F37: ='2.6'!$H$34 -> 3327831.3 | G37: ='2.6'!$H$51 -> 69701.165 | H37: ='2.6'!$H$58 -> 630000 | I37: ='2.6'!$H$65 -> 0 | J37: ='2.6'!F4 -> 16027532 | K37: =ROUNDUP(Tabla1[[#This Row],[CANTIDAD]]*Tabla1[[#This Row],[PRECIO UNITARIO]],0) -> 16027533
A38: 3.1 | B38: ='3.1'!$B$6:$G$6 -> REDISEÑO DE RED NIVEL DE TENSIÓN DE 34,5KV/13,8KV | C38: UND | D38: =APU_P!N40 -> 1 | E38: ='3.1'!$H$17 -> 0 | F38: ='3.1'!$H$34 -> 13186233 | G38: ='3.1'!$H$51 -> 6069701.2 | H38: ='3.1'!$H$58 -> 840000 | I38: ='3.1'!$H$65 -> 0 | J38: ='3.1'!F4 -> 20095934 | K38: =ROUNDUP(Tabla1[[#This Row],[CANTIDAD]]*Tabla1[[#This Row],[PRECIO UNITARIO]],0) -> 20095935
A39: 3.2 | B39: ='3.2'!$B$6:$G$6 -> ELABORACIÓN DE DOSSIER Y MANUALES DE OPERACIÓN Y MANTENIMIENTO | C39: UND | D39: =APU_P!N41 -> 1 | E39: ='3.2'!$H$17 -> 0 | F39: ='3.2'!$H$34 -> 8952595.8 | G39: ='3.2'!$H$51 -> 69701.165 | H39: ='3.2'!$H$58 -> 840000 | I39: ='3.2'!$H$65 -> 0 | J39: ='3.2'!F4 -> 9862297 | K39: =ROUNDUP(Tabla1[[#This Row],[CANTIDAD]]*Tabla1[[#This Row],[PRECIO UNITARIO]],0) -> 9862297
A40: 4 | B40: SUMINISTRO MATERIALES | K40: =SUM(K41:K59) -> 281164761
A41: 4.1 | B41: ='4.1'!B6:G6 -> SUMINISTRO DE MATERIALES PARA ESTRUCTURA P103 N2 | C41: UND | D41: =APU_P!N42 -> 2 | E41: ='4.1'!$H$22 -> 387643.28 | F41: ='4.1'!$H$39 -> 0 | G41: ='4.1'!$H$56 -> 0 | H41: ='4.1'!$H$63 -> 42000 | I41: ='4.1'!$H$70 -> 0 | J41: ='4.1'!$F$4 -> 429643.28 | K41: =ROUNDUP(D41*J41,0) -> 859287
A42: 4.2 | B42: ='4.2'!B6:G6 -> SUMINISTRO DE MATERIALES PARA ESTRUCTURA P103 N3 | C42: UND | D42: =APU_P!N43 -> 3 | E42: ='4.2'!$H$22 -> 425060.34 | F42: ='4.2'!$H$39 -> 0 | G42: ='4.2'!$H$56 -> 0 | H42: ='4.2'!$H$63 -> 42000 | I42: ='4.2'!$H$70 -> 0 | J42: ='4.2'!$F$4 -> 467060.34 | K42: =ROUNDUP(D42*J42,0) -> 1401182
A43: 4.3 | B43: ='4.3'!B6:G6 -> SUMINISTRO DE MATERIALES PARA ESTRUCTURA 560 N2 | C43: UND | D43: =APU_P!N44 -> 2 | E43: ='4.3'!$H$23 -> 1743713.9 | F43: ='4.3'!$H$40 -> 0 | G43: ='4.3'!$H$57 -> 0 | H43: ='4.3'!$H$64 -> 42000 | I43: ='4.3'!$H$71 -> 0 | J43: ='4.3'!$F$4 -> 1785713.9 | K43: =ROUNDUP(D43*J43,0) -> 3571428
A44: 4.4 | B44: ='4.4'!B6:G6 -> SUMINISTRO DE MATERIALES PARA ESTRUCTURA 562 N3 | C44: UND | D44: =APU_P!N45 -> 1 | E44: ='4.4'!$H$26 -> 2300879.1 | F44: ='4.4'!$H$43 -> 0 | G44: ='4.4'!$H$60 -> 0 | H44: ='4.4'!$H$67 -> 42000 | I44: ='4.4'!$H$74 -> 0 | J44: ='4.4'!$F$4 -> 2342879.1 | K44: =ROUNDUP(D44*J44,0) -> 2342880
A45: 4.5 | B45: ='4.5'!B6:G6 -> SUMINISTRO DE MATERIALES PARA ESTRUCTURA 580 N2 | C45: UND | D45: =APU_P!N46 -> 1 | E45: ='4.5'!$H$26 -> 2190316.8 | F45: ='4.5'!$H$43 -> 0 | G45: ='4.5'!$H$60 -> 0 | H45: ='4.5'!$H$67 -> 42000 | I45: ='4.5'!$H$74 -> 0 | J45: ='4.5'!$F$4 -> 2232316.8 | K45: =ROUNDUP(D45*J45,0) -> 2232317
A46: 4.6 | B46: ='4.6'!B6:G6 -> SUMINISTRO DE MATERIALES PARA ESTRUCTURA DE HILO GUARDA DE PASO HG-P | C46: UND | D46: =APU_P!N47 -> 4 | E46: ='4.6'!$H$16 -> 107297.16 | F46: ='4.6'!$H$33 -> 0 | G46: ='4.6'!$H$50 -> 0 | H46: ='4.6'!$H$57 -> 42000 | I46: ='4.6'!$H$64 -> 0 | J46: ='4.6'!$F$4 -> 149297.16 | K46: =ROUNDUP(D46*J46,0) -> 597189
A47: 4.7 | B47: ='4.7'!B6:G6 -> SUMINISTRO DE MATERIALES PARA ESTRUCTURA DE HILO GUARDA DE RETENCIÓN HG-R | C47: UND | D47: =APU_P!N48 -> 2 | E47: ='4.7'!$H$17 -> 77338.997 | F47: ='4.7'!$H$34 -> 0 | G47: ='4.7'!$H$51 -> 0 | H47: ='4.7'!$H$58 -> 42000 | I47: ='4.7'!$H$65 -> 0 | J47: ='4.7'!$F$4 -> 119339 | K47: =ROUNDUP(D47*J47,0) -> 238678
A48: 4.8 | B48: ='4.8'!B6:G6 -> SUMINISTRO DE MATERIALES PARA ESTRUCTURA 555 N3 | C48: UND | D48: =APU_P!N49 -> 6 | E48: ='4.8'!$H$22 -> 1227542.3 | F48: ='4.8'!$H$39 -> 0 | G48: ='4.8'!$H$56 -> 0 | H48: ='4.8'!$H$63 -> 42000 | I48: ='4.8'!$H$70 -> 0 | J48: ='4.8'!$F$4 -> 1269542.3 | K48: =ROUNDUP(D48*J48,0) -> 7617254
A49: 4.9 | B49: ='4.9'!B6:G6 -> SUMINISTRO DE MATERIALES PARA ESTRUCTURA 619 N1 | C49: UND | D49: =APU_P!N50 -> 1 | E49: ='4.9'!$H$17 -> 57742.293 | F49: ='4.9'!$H$34 -> 0 | G49: ='4.9'!$H$51 -> 0 | H49: ='4.9'!$H$58 -> 42000 | I49: ='4.9'!$H$65 -> 0 | J49: ='4.9'!$F$4 -> 99742.293 | K49: =ROUNDUP(D49*J49,0) -> 99743
A50: 4.10 | B50: ='4.10'!B6:G6 -> SUMINISTRO DE MATERIALES PARA TMEPLETE TIPO CUERDA GUITARRA N3 | C50: UND | D50: =APU_P!N51 -> 5 | E50: ='4.10'!$H$19 -> 416854.66 | F50: ='4.10'!$H$36 -> 0 | G50: ='4.10'!$H$53 -> 0 | H50: ='4.10'!$H$60 -> 42000 | I50: ='4.10'!$H$67 -> 0 | J50: ='4.10'!$F$4 -> 458854.66 | K50: =ROUNDUP(D50*J50,0) -> 2294274
A51: 4.11 | B51: ='4.11'!B6:G6 -> SUMINISTRO DE MATERIALES PARA TEMPLETE TIPO DIRECTO N3 | C51: UND | D51: =APU_P!N52 -> 7 | E51: ='4.11'!$H$19 -> 334404.16 | F51: ='4.11'!$H$36 -> 0 | G51: ='4.11'!$H$53 -> 0 | H51: ='4.11'!$H$60 -> 42000 | I51: ='4.11'!$H$67 -> 0 | J51: ='4.11'!$F$4 -> 376404.16 | K51: =ROUNDUP(D51*J51,0) -> 2634830
A52: 4.12 | B52: ='4.12'!B6:G6 -> SUMINISTRO DE MATERIALES PARA SISTEMA DE PUESTA A TIERRA PARA POSTE SENCILLO N3 | C52: UND | D52: =APU_P!N53 -> 4 | E52: ='4.12'!$H$19 -> 117930.21 | F52: ='4.12'!$H$36 -> 0 | G52: ='4.12'!$H$53 -> 0 | H52: ='4.12'!$H$60 -> 42000 | I52: ='4.12'!$H$67 -> 0 | J52: ='4.12'!$F$4 -> 159930.21 | K52: =ROUNDUP(D52*J52,0) -> 639721
A53: 4.13 | B53: ='4.13'!B6:G6 -> SUMINISTRO DE MATERIALES PARA INSTALACIÓN DE BARRERAS METÁLICAS CON ABATIMIENTO "N2" | C53: UND | D53: =APU_P!N54 -> 1 | E53: ='4.13'!$H$19 -> 1.2001802e+08 | F53: ='4.13'!$H$36 -> 0 | G53: ='4.13'!$H$53 -> 0 | H53: ='4.13'!$H$60 -> 2100000 | I53: ='4.13'!$H$67 -> 0 | J53: ='4.13'!$F$4 -> 1.2211802e+08 | K53: =ROUNDUP(D53*J53,0) -> 122118017
A54: 4.14 | B54: ='4.14'!B6:G6 -> SUMINISTRO DE CABLE ECOLÓGICO TRICAPA XLPE-TK de 4/0 | C54: M | D54: =APU_P!N55 -> 2149 | E54: ='4.14'!H19 -> 34512.431 | F54: ='4.14'!H36 -> 0 | G54: ='4.14'!H53 -> 0 | H54: ='4.14'!H60 -> 97.71987 | I54: ='4.14'!H67 -> 0 | J54: ='4.14'!$F$4 -> 34610.151 | K54: =ROUNDUP(D54*J54,0) -> 74377216
A55: 4.15 | B55: ='4.15'!B6:G6 -> SUMINISTRO DE CABLE DE ACERO GALVANIZADO EXTRARRESISTENTE DE 1/4 GX-3000 KG PARA HILO GUARDA | C55: M | D55: =APU_P!N56 -> 716.4 | E55: ='4.15'!$H$19 -> 2502.385 | F55: ='4.15'!$H$36 -> 0 | G55: ='4.15'!$H$53 -> 0 | H55: ='4.15'!$H$60 -> 77.777778 | I55: ='4.15'!$H$67 -> 0 | J55: ='4.15'!$F$4 -> 2580.1628 | K55: =ROUNDUP(D55*J55,0) -> 1848429
A56: 4.16 | B56: ='4.16'!B6:G6 -> SUMINISTRO DE POSTE DE CONCRETO DE 14 M X 750 KGF VIBRADO Y REFORZADO | C56: UND | D56: =APU_P!N57 -> 2 | E56: ='4.16'!$H$19 -> 2073445 | F56: ='4.16'!$H$36 -> 0 | G56: ='4.16'!$H$53 -> 0 | H56: ='4.16'!$H$60 -> 105000 | I56: ='4.16'!$H$67 -> 0 | J56: ='4.16'!$F$4 -> 2178445 | K56: =ROUNDUP(D56*J56,0) -> 4356890
A57: 4.17 | B57: ='4.17'!B6:G6 -> SUMINISTRO DE POSTE DE CONCRETO DE 14 M X 1050 KGF VIBRADO Y REFORZADO | C57: UND | D57: =APU_P!N58 -> 1 | E57: ='4.17'!$H$19 -> 3046689 | F57: ='4.17'!$H$36 -> 0 | G57: ='4.17'!$H$53 -> 0 | H57: ='4.17'!$H$60 -> 105000 | I57: ='4.17'!$H$67 -> 0 | J57: ='4.17'!$F$4 -> 3151689 | K57: =ROUNDUP(D57*J57,0) -> 3151689
A58: 4.18 | B58: ='4.18'!B6:G6 -> SUMINISTRO DE POSTE DE CONCRETO DE 16 M X 1350 KGF VIBRADO Y REFORZADO | C58: UND | D58: =APU_P!N59 -> 2 | E58: ='4.18'!$H$19 -> 4696050.4 | F58: ='4.18'!$H$36 -> 0 | G58: ='4.18'!$H$53 -> 0 | H58: ='4.18'!$H$60 -> 105000 | I58: ='4.18'!$H$67 -> 0 | J58: ='4.18'!$F$4 -> 4801050.4 | K58: =ROUNDUP(D58*J58,0) -> 9602101
A59: 4.19 | B59: ='4.19'!B6:G6 -> SUMINISTRO DE CABLE ECOLÓGICO TRICAPA XLPE-TK 2/0 | C59: M | D59: =APU_P!N60 -> 1470 | E59: ='4.19'!H19 -> 27930.718 | F59: ='4.19'!H36 -> 0 | G59: ='4.19'!H53 -> 0 | H59: ='4.19'!H60 -> 84 | I59: ='4.19'!H67 -> 0 | J59: ='4.19'!F4 -> 28014.718 | K59: =ROUNDUP(D59*J59,0) -> 41181636
B61: COSTO MANO DE OBRA | C61: =K5 -> 101655558
B62: COSTO MATERIALES | C62: =K40 -> 281164761
B63: COSTO MANO DE OBRA, MATERIALES Y TRANSPORTE | C63: =SUM(C61:C62) -> 382820319
B64: ADMINISTRACION | C64: =$C$63*D64 -> 57423048 | D64: 0.15
B65: IMPREVISTOS | C65: =$C$63*D65 -> 19141016 | D65: 0.05
B66: UTILIDAD | C66: =$C$63*D66 -> 19141016 | D66: 0.05
B67: I.V.A. ( 19 % SOBRE UTILIDAD ) | C67: =C66*D67 -> 3636793 | D67: 0.19
B68: VALOR TOTAL PRESENTE OBRA | C68: =SUM(C63:C67) -> 4.8216219e+08

Sheet Actividades
A1: APOYO | C1: DESCRIPCIÓN | D1: Unidad | E1: Cantidad | F1: A. MATERIAL | G1: B. MANO DE OBRA | H1: C. SERVICIO, EQUIPO, HERRAMIENTAS Y HSE | I1: D. TRANSPORTE | J1: E. VIATICOS | K1: PRECIO UNITARIO | L1: PRECIO TOTAL
A2: E100 | B2: ACTIVIDAD | C2: Se instalará una estructura terminal 555 N3 con el fin de acoplar la linea 34,5kV proyectada con la existente | D2: GLB | E2: 1 | F2: =SUM(F3:F4) -> 1227542.3 | G2: =SUM(G3:G4) -> 246270.27 | H2: =SUM(H3:H4) -> 23233.722 | I2: =SUM(I3:I4) -> 112000 | J2: =SUM(J3:J4) -> 0 | K2: =SUM(K3:K4) -> 1609046.3 | L2: =SUM(L3:L4) -> 1609046.3
B3: 1.18 | C3: =VLOOKUP(B3,APU_P!$A$3:$M$59,2,FALSE) -> VESTIDA DE ESTRUCTURA TRIFASICA DE UN POSTE TIPO RETENCIÓN - 34.5 KV | D3: =VLOOKUP(B3,Presupuesto!$A$6:$K$58,3,FALSE) -> UND | E3: =VLOOKUP(B3,APU_P!$A$3:$M$56,3,FALSE) -> 1 | F3: =VLOOKUP($B$3,Presupuesto!$A$6:$K$58,5,FALSE) -> 0 | G3: =VLOOKUP(B3,Presupuesto!$A$6:$K$58,6,FALSE) -> 246270.27 | H3: =VLOOKUP(B3,Presupuesto!$A$6:$K$58,7,FALSE) -> 23233.722 | I3: =VLOOKUP(B3,Presupuesto!$A$6:$K$58,8,FALSE) -> 70000 | J3: =VLOOKUP(B3,Presupuesto!$A$6:$K$58,9,FALSE) -> 0 | K3: =VLOOKUP(B3,Presupuesto!$A$6:$K$58,10,FALSE) -> 339503.99 | L3: =E3*K3 -> 339503.99
B4: 4.8 | C4: =VLOOKUP(B4,APU_P!$A$3:$M$59,2,FALSE) -> SUMINISTRO DE MATERIALES PARA LA ESTRUCTURA 555 N3 | D4: =VLOOKUP(B4,Presupuesto!$A$6:$K$58,3,FALSE) -> UND | E4: 1 | F4: =VLOOKUP(B4,Presupuesto!$A$6:$K$58,5,FALSE) -> 1227542.3 | G4: =VLOOKUP(B4,Presupuesto!$A$6:$K$58,6,FALSE) -> 0 | H4: =VLOOKUP(B4,Presupuesto!$A$6:$K$58,7,FALSE) -> 0 | I4: =VLOOKUP(B4,Presupuesto!$A$6:$K$58,8,FALSE) -> 42000 | J4: =VLOOKUP(B4,Presupuesto!$A$6:$K$58,9,FALSE) -> 0 | K4: =VLOOKUP(B4,Presupuesto!$A$6:$K$58,10,FALSE) -> 1269542.3 | L4: =E4*K4 -> 1269542.3
A5: E97 | B5: ACTIVIDAD | C5: Se reemplazará el poste de concreto de 14m 1050 kg, se debe desvestir las estructuras instaladas, y retirar el poste. Posteriormente se hincará y vestira con las estructuras 619, 560 y 562 de retención para N1, N2 y N3 respectivamente. Además se harán excavaciones de viguetas para instalación de templetes, junto con la instalación del sistema de puesta a tierra. Al poste se instalará placas de peligro de red energizada y de identificación. | D5: GLB | E5: 1 | F5: =SUM(F6:F29) -> 8180100.6 | G5: =SUM(G6:G29) -> 1501916.2 | H5: =SUM(H6:H29) -> 1247428.5 | I5: =SUM(I6:I29) -> 534000 | J5: =SUM(J6:J29) -> 0 | K5: =SUM(K6:K29) -> 11463445 | L5: =SUM(L6:L29) -> 12110325
B6: ='Listado actividades'!A16 -> 1.3 | C6: =VLOOKUP(B6,APU_P!$A$3:$M$59,2,FALSE) -> APERTURA DE EXCAVACION PARA VIGUETA EN RETENIDA RURAL | D6: =VLOOKUP(B6,Presupuesto!$A$6:$K$58,3,FALSE) -> UND | E6: =VLOOKUP(B6,'Listado actividades'!$A$16:$C$40,3,FALSE) -> 3 | F6: =VLOOKUP(B6,Presupuesto!$A$6:$K$58,5,FALSE) -> 0 | G6: =VLOOKUP(B6,Presupuesto!$A$6:$K$58,6,FALSE) -> 83520.324 | H6: =VLOOKUP(B6,Presupuesto!$A$6:$K$58,7,FALSE) -> 8712.6456 | I6: =VLOOKUP(B6,Presupuesto!$A$6:$K$58,8,FALSE) -> 0 | J6: =VLOOKUP(B6,Presupuesto!$A$6:$K$58,9,FALSE) -> 0 | K6: =VLOOKUP(B6,Presupuesto!$A$6:$K$58,10,FALSE) -> 92232.969 | L6: =K6*E6 -> 276698.91
B7: ='Listado actividades'!A17 -> 1.6 | C7: =VLOOKUP(B7,APU_P!$A$3:$M$59,2,FALSE) -> HINCADA, PLOMADA Y ORIENTACIÓN DE POSTE DE 14, 16 Y 18 MTS CON GRUA | D7: =VLOOKUP(B7,Presupuesto!$A$6:$K$58,3,FALSE) -> UND | E7: =VLOOKUP(B7,'Listado actividades'!$A$16:$C$40,3,FALSE) -> 1 | F7: =VLOOKUP(B7,Presupuesto!$A$6:$K$58,5,FALSE) -> 0 | G7: =VLOOKUP(B7,Presupuesto!$A$6:$K$58,6,FALSE) -> 109533.17 | H7: =VLOOKUP(B7,Presupuesto!$A$6:$K$58,7,FALSE) -> 308712.65 | I7: =VLOOKUP(B7,Presupuesto!$A$6:$K$58,8,FALSE) -> 0 | J7: =VLOOKUP(B7,Presupuesto!$A$6:$K$58,9,FALSE) -> 0 | K7: =VLOOKUP(B7,Presupuesto!$A$6:$K$58,10,FALSE) -> 418245.81 | L7: =K7*E7 -> 418245.81
B8: ='Listado actividades'!A18 -> 1.7 | C8: =VLOOKUP(B8,APU_P!$A$3:$M$59,2,FALSE) -> INSTALACION LINE A TIERRA MEDIA TENSION | D8: =VLOOKUP(B8,Presupuesto!$A$6:$K$58,3,FALSE) -> UND | E8: =VLOOKUP(B8,'Listado actividades'!$A$16:$C$40,3,FALSE) -> 1 | F8: =VLOOKUP(B8,Presupuesto!$A$6:$K$58,5,FALSE) -> 0 | G8: =VLOOKUP(B8,Presupuesto!$A$6:$K$58,6,FALSE) -> 136919.2 | H8: =VLOOKUP(B8,Presupuesto!$A$6:$K$58,7,FALSE) -> 6970.1165 | I8: =VLOOKUP(B8,Presupuesto!$A$6:$K$58,8,FALSE) -> 0 | J8: =VLOOKUP(B8,Presupuesto!$A$6:$K$58,9,FALSE) -> 0 | K8: =VLOOKUP(B8,Presupuesto!$A$6:$K$58,10,FALSE) -> 143889.32 | L8: =K8*E8 -> 143889.32
B9: ='Listado actividades'!A19 -> 1.8 | C9: =VLOOKUP(B9,APU_P!$A$3:$M$59,2,FALSE) -> INSTALACIÓN DE TEMPLETE CUERDA GUITARRA CON TODOS SUS ACCESORIOS M.T. RURAL | D9: =VLOOKUP(B9,Presupuesto!$A$6:$K$58,3,FALSE) -> UND | E9: =VLOOKUP(B9,'Listado actividades'!$A$16:$C$40,3,FALSE) -> 1 | F9: =VLOOKUP(B9,Presupuesto!$A$6:$K$58,5,FALSE) -> 0 | G9: =VLOOKUP(B9,Presupuesto!$A$6:$K$58,6,FALSE) -> 95832.542 | H9: =VLOOKUP(B9,Presupuesto!$A$6:$K$58,7,FALSE) -> 4646.7443 | I9: =VLOOKUP(B9,Presupuesto!$A$6:$K$58,8,FALSE) -> 0 | J9: =VLOOKUP(B9,Presupuesto!$A$6:$K$58,9,FALSE) -> 0 | K9: =VLOOKUP(B9,Presupuesto!$A$6:$K$58,10,FALSE) -> 100479.29 | L9: =K9*E9 -> 100479.29
B10: ='Listado actividades'!A20 -> 1.12 | C10: =VLOOKUP(B10,APU_P!$A$3:$M$59,2,FALSE) -> TRANSPORTE DE POSTE 14 MTS M.T. RURAL DE BODEGA A SITIO CERCANO | D10: =VLOOKUP(B10,Presupuesto!$A$6:$K$58,3,FALSE) -> UND | E10: =VLOOKUP(B10,'Listado actividades'!$A$16:$C$40,3,FALSE) -> 1 | F10: =VLOOKUP(B10,Presupuesto!$A$6:$K$58,5,FALSE) -> 0 | G10: =VLOOKUP(B10,Presupuesto!$A$6:$K$58,6,FALSE) -> 77975.29 | H10: =VLOOKUP(B10,Presupuesto!$A$6:$K$58,7,FALSE) -> 294701.17 | I10: =VLOOKUP(B10,Presupuesto!$A$6:$K$58,8,FALSE) -> 0 | J10: =VLOOKUP(B10,Presupuesto!$A$6:$K$58,9,FALSE) -> 0 | K10: =VLOOKUP(B10,Presupuesto!$A$6:$K$58,10,FALSE) -> 372676.45 | L10: =K10*E10 -> 372676.45
B11: ='Listado actividades'!A21 -> 1.16 | C11: =VLOOKUP(B11,APU_P!$A$3:$M$59,2,FALSE) -> VESTIDA DE ESTRUCTURA TRIFASICA DE RETENCION UN POSTE 13,8 Kv | D11: =VLOOKUP(B11,Presupuesto!$A$6:$K$58,3,FALSE) -> UND | E11: =VLOOKUP(B11,'Listado actividades'!$A$16:$C$40,3,FALSE) -> 1 | F11: =VLOOKUP(B11,Presupuesto!$A$6:$K$58,5,FALSE) -> 0 | G11: =VLOOKUP(B11,Presupuesto!$A$6:$K$58,6,FALSE) -> 89880.129 | H11: =VLOOKUP(B11,Presupuesto!$A$6:$K$58,7,FALSE) -> 11616.861 | I11: =VLOOKUP(B11,Presupuesto!$A$6:$K$58,8,FALSE) -> 35000 | J11: =VLOOKUP(B11,Presupuesto!$A$6:$K$58,9,FALSE) -> 0 | K11: =VLOOKUP(B11,Presupuesto!$A$6:$K$58,10,FALSE) -> 136496.99 | L11: =K11*E11 -> 136496.99
B12: ='Listado actividades'!A22 -> 1.18 | C12: =VLOOKUP(B12,APU_P!$A$3:$M$59,2,FALSE) -> VESTIDA DE ESTRUCTURA TRIFASICA DE UN POSTE TIPO RETENCIÓN - 34.5 KV | D12: =VLOOKUP(B12,Presupuesto!$A$6:$K$58,3,FALSE) -> UND | E12: =VLOOKUP(B12,'Listado actividades'!$A$16:$C$40,3,FALSE) -> 1 | F12: =VLOOKUP(B12,Presupuesto!$A$6:$K$58,5,FALSE) -> 0 | G12: =VLOOKUP(B12,Presupuesto!$A$6:$K$58,6,FALSE) -> 246270.27 | H12: =VLOOKUP(B12,Presupuesto!$A$6:$K$58,7,FALSE) -> 23233.722 | I12: =VLOOKUP(B12,Presupuesto!$A$6:$K$58,8,FALSE) -> 70000 | J12: =VLOOKUP(B12,Presupuesto!$A$6:$K$58,9,FALSE) -> 0 | K12: =VLOOKUP(B12,Presupuesto!$A$6:$K$58,10,FALSE) -> 339503.99 | L12: =K12*E12 -> 339503.99
B13: ='Listado actividades'!A23 -> 1.19 | C13: =VLOOKUP(B13,APU_P!$A$3:$M$59,2,FALSE) -> VESTIDA ESTRUCTURA CABLE DE GUARDA - RETENCION | D13: =VLOOKUP(B13,Presupuesto!$A$6:$K$58,3,FALSE) -> UND | E13: =VLOOKUP(B13,'Listado actividades'!$A$16:$C$40,3,FALSE) -> 1 | F13: =VLOOKUP(B13,Presupuesto!$A$6:$K$58,5,FALSE) -> 0 | G13: =VLOOKUP(B13,Presupuesto!$A$6:$K$58,6,FALSE) -> 65455.762 | H13: =VLOOKUP(B13,Presupuesto!$A$6:$K$58,7,FALSE) -> 9957.3093 | I13: =VLOOKUP(B13,Presupuesto!$A$6:$K$58,8,FALSE) -> 30000 | J13: =VLOOKUP(B13,Presupuesto!$A$6:$K$58,9,FALSE) -> 0 | K13: =VLOOKUP(B13,Presupuesto!$A$6:$K$58,10,FALSE) -> 105413.07 | L13: =K13*E13 -> 105413.07
B14: ='Listado actividades'!A24 -> 1.21 | C14: =VLOOKUP(B14,APU_P!$A$3:$M$59,2,FALSE) -> DESVESTIDA ESTRUCTURA DE RETENCION MT RURAL | D14: =VLOOKUP(B14,Presupuesto!$A$6:$K$58,3,FALSE) -> UND | E14: =VLOOKUP(B14,'Listado actividades'!$A$16:$C$40,3,FALSE) -> 1 | F14: =VLOOKUP(B14,Presupuesto!$A$6:$K$58,5,FALSE) -> 0 | G14: =VLOOKUP(B14,Presupuesto!$A$6:$K$58,6,FALSE) -> 136919.2 | H14: =VLOOKUP(B14,Presupuesto!$A$6:$K$58,7,FALSE) -> 6970.1165 | I14: =VLOOKUP(B14,Presupuesto!$A$6:$K$58,8,FALSE) -> 0 | J14: =VLOOKUP(B14,Presupuesto!$A$6:$K$58,9,FALSE) -> 0 | K14: =VLOOKUP(B14,Presupuesto!$A$6:$K$58,10,FALSE) -> 143889.32 | L14: =K14*E14 -> 143889.32
B15: ='Listado actividades'!A25 -> 1.23 | C15: =VLOOKUP(B15,APU_P!$A$3:$M$59,2,FALSE) -> DESHINCADA DE POSTES 10, 12 Y 14 mts MT | D15: =VLOOKUP(B15,Presupuesto!$A$6:$K$58,3,FALSE) -> UND | E15: =VLOOKUP(B15,'Listado actividades'!$A$16:$C$40,3,FALSE) -> 1 | F15: =VLOOKUP(B15,Presupuesto!$A$6:$K$58,5,FALSE) -> 0 | G15: =VLOOKUP(B15,Presupuesto!$A$6:$K$58,6,FALSE) -> 188203.38 | H15: =VLOOKUP(B15,Presupuesto!$A$6:$K$58,7,FALSE) -> 339701.17 | I15: =VLOOKUP(B15,Presupuesto!$A$6:$K$58,8,FALSE) -> 0 | J15: =VLOOKUP(B15,Presupuesto!$A$6:$K$58,9,FALSE) -> 0 | K15: =VLOOKUP(B15,Presupuesto!$A$6:$K$58,10,FALSE) -> 527904.55 | L15: =K15*E15 -> 527904.55
B16: ='Listado actividades'!A26 -> 1.24 | C16: =VLOOKUP(B16,APU_P!$A$3:$M$59,2,FALSE) -> INSTALACIÓN DE TEMPLETE SENCILLO CON TODOS SUS ACCESORIOS M.T. RURAL | D16: =VLOOKUP(B16,Presupuesto!$A$6:$K$58,3,FALSE) -> UND | E16: =VLOOKUP(B16,'Listado actividades'!$A$16:$C$40,3,FALSE) -> 2 | F16: =VLOOKUP(B16,Presupuesto!$A$6:$K$58,5,FALSE) -> 0 | G16: =VLOOKUP(B16,Presupuesto!$A$6:$K$58,6,FALSE) -> 82136.989 | H16: =VLOOKUP(B16,Presupuesto!$A$6:$K$58,7,FALSE) -> 3872.2869 | I16: =VLOOKUP(B16,Presupuesto!$A$6:$K$58,8,FALSE) -> 0 | J16: =VLOOKUP(B16,Presupuesto!$A$6:$K$58,9,FALSE) -> 0 | K16: =VLOOKUP(B16,Presupuesto!$A$6:$K$58,10,FALSE) -> 86009.275 | L16: =K16*E16 -> 172018.55
B17: ='Listado actividades'!A28 -> 1.26 | C17: =VLOOKUP(B17,APU_P!$A$3:$M$59,2,FALSE) -> TRANSPORTE DE POSTE RURAL DE SITIO CERCANO A BODEGA EH | D17: =VLOOKUP(B17,Presupuesto!$A$6:$K$58,3,FALSE) -> UND | E17: =VLOOKUP(B17,'Listado actividades'!$A$16:$C$40,3,FALSE) -> 1 | F17: =VLOOKUP(B17,Presupuesto!$A$6:$K$58,5,FALSE) -> 0 | G17: =VLOOKUP(B17,Presupuesto!$A$6:$K$58,6,FALSE) -> 46034.989 | H17: =VLOOKUP(B17,Presupuesto!$A$6:$K$58,7,FALSE) -> 162923.6 | I17: =VLOOKUP(B17,Presupuesto!$A$6:$K$58,8,FALSE) -> 0 | J17: =VLOOKUP(B17,Presupuesto!$A$6:$K$58,9,FALSE) -> 0 | K17: =VLOOKUP(B17,Presupuesto!$A$6:$K$58,10,FALSE) -> 208958.59 | L17: =K17*E17 -> 208958.59
B18: ='Listado actividades'!A29 -> 1.29 | C18: =VLOOKUP(B18,APU_P!$A$3:$M$59,2,FALSE) -> DESVESTIDA DE ESTRUCTURA BT EXISTENTE | D18: =VLOOKUP(B18,Presupuesto!$A$6:$K$58,3,FALSE) -> UND | E18: =VLOOKUP(B18,'Listado actividades'!$A$16:$C$40,3,FALSE) -> 1 | F18: =VLOOKUP(B18,Presupuesto!$A$6:$K$58,5,FALSE) -> 0 | G18: =VLOOKUP(B18,Presupuesto!$A$6:$K$58,6,FALSE) -> 45332.476 | H18: =VLOOKUP(B18,Presupuesto!$A$6:$K$58,7,FALSE) -> 20190 | I18: =VLOOKUP(B18,Presupuesto!$A$6:$K$58,8,FALSE) -> 0 | J18: =VLOOKUP(B18,Presupuesto!$A$6:$K$58,9,FALSE) -> 0 | K18: =VLOOKUP(B18,Presupuesto!$A$6:$K$58,10,FALSE) -> 65522.476 | L18: =K18*E18 -> 65522.476
B19: ='Listado actividades'!A30 -> 1.30 | C19: =VLOOKUP(B19,APU_P!$A$3:$M$59,2,FALSE) -> VESTIDA DE ESTRUCTURA BT | D19: =VLOOKUP(B19,Presupuesto!$A$6:$K$58,3,FALSE) -> UND | E19: =VLOOKUP(B19,'Listado actividades'!$A$16:$C$40,3,FALSE) -> 1 | F19: =VLOOKUP(B19,Presupuesto!$A$6:$K$58,5,FALSE) -> 0 | G19: =VLOOKUP(B19,Presupuesto!$A$6:$K$58,6,FALSE) -> 77259.417 | H19: =VLOOKUP(B19,Presupuesto!$A$6:$K$58,7,FALSE) -> 38250 | I19: =VLOOKUP(B19,Presupuesto!$A$6:$K$58,8,FALSE) -> 0 | J19: =VLOOKUP(B19,Presupuesto!$A$6:$K$58,9,FALSE) -> 0 | K19: =VLOOKUP(B19,Presupuesto!$A$6:$K$58,10,FALSE) -> 115509.42 | L19: =K19*E19 -> 115509.42
B20: ='Listado actividades'!A31 -> 2.1 | C20: =VLOOKUP(B20,APU_P!$A$3:$M$59,2,FALSE) -> INSTALACIÓN DE PLACAS DE IDENTIFICACIÓN DE PELIGRO RED ENERGIZADA (INCLUYE PLACA EN ACRILICO Y CONECTORES A RED) | D20: =VLOOKUP(B20,Presupuesto!$A$6:$K$58,3,FALSE) -> UND | E20: =VLOOKUP(B20,'Listado actividades'!$A$16:$C$40,3,FALSE) -> 1 | F20: =VLOOKUP(B20,Presupuesto!$A$6:$K$58,5,FALSE) -> 35000 | G20: =VLOOKUP(B20,Presupuesto!$A$6:$K$58,6,FALSE) -> 5882.2661 | H20: =VLOOKUP(B20,Presupuesto!$A$6:$K$58,7,FALSE) -> 3485.0583 | I20: =VLOOKUP(B20,Presupuesto!$A$6:$K$58,8,FALSE) -> 0 | J20: =VLOOKUP(B20,Presupuesto!$A$6:$K$58,9,FALSE) -> 0 | K20: =VLOOKUP(B20,Presupuesto!$A$6:$K$58,10,FALSE) -> 44367.324 | L20: =K20*E20 -> 44367.324
B21: ='Listado actividades'!A32 -> 2.2 | C21: =VLOOKUP(B21,APU_P!$A$3:$M$59,2,FALSE) -> INSTALACIÓN DE PLACAS DE IDENTIFICACIÓN DE POSTE, (INCLUYE PLACA DE ALUMINIO, CINTA BAND IT Y HEBILLA) | D21: =VLOOKUP(B21,Presupuesto!$A$6:$K$58,3,FALSE) -> UND | E21: =VLOOKUP(B21,'Listado actividades'!$A$16:$C$40,3,FALSE) -> 1 | F21: =VLOOKUP(B21,Presupuesto!$A$6:$K$58,5,FALSE) -> 19590 | G21: =VLOOKUP(B21,Presupuesto!$A$6:$K$58,6,FALSE) -> 14760.758 | H21: =VLOOKUP(B21,Presupuesto!$A$6:$K$58,7,FALSE) -> 3485.0583 | I21: =VLOOKUP(B21,Presupuesto!$A$6:$K$58,8,FALSE) -> 0 | J21: =VLOOKUP(B21,Presupuesto!$A$6:$K$58,9,FALSE) -> 0 | K21: =VLOOKUP(B21,Presupuesto!$A$6:$K$58,10,FALSE) -> 37835.817 | L21: =K21*E21 -> 37835.817
B22: ='Listado actividades'!A33 -> 4.3 | C22: =VLOOKUP(B22,APU_P!$A$3:$M$59,2,FALSE) -> SUMINISTRO DE MATERIALES PARA LA ESTRUCTURA 560 N2 | D22: =VLOOKUP(B22,Presupuesto!$A$6:$K$58,3,FALSE) -> UND | E22: =VLOOKUP(B22,'Listado actividades'!$A$16:$C$40,3,FALSE) -> 1 | F22: =VLOOKUP(B22,Presupuesto!$A$6:$K$58,5,FALSE) -> 1743713.9 | G22: =VLOOKUP(B22,Presupuesto!$A$6:$K$58,6,FALSE) -> 0 | H22: =VLOOKUP(B22,Presupuesto!$A$6:$K$58,7,FALSE) -> 0 | I22: =VLOOKUP(B22,Presupuesto!$A$6:$K$58,8,FALSE) -> 42000 | J22: =VLOOKUP(B22,Presupuesto!$A$6:$K$58,9,FALSE) -> 0 | K22: =VLOOKUP(B22,Presupuesto!$A$6:$K$58,10,FALSE) -> 1785713.9 | L22: =K22*E22 -> 1785713.9
B23: ='Listado actividades'!A34 -> 4.4 | C23: =VLOOKUP(B23,APU_P!$A$3:$M$59,2,FALSE) -> SUMINISTRO DE MATERIALES PARA LA ESTRUCTURA 562 N2 | D23: =VLOOKUP(B23,Presupuesto!$A$6:$K$58,3,FALSE) -> UND | E23: =VLOOKUP(B23,'Listado actividades'!$A$16:$C$40,3,FALSE) -> 1 | F23: =VLOOKUP(B23,Presupuesto!$A$6:$K$58,5,FALSE) -> 2300879.1 | G23: =VLOOKUP(B23,Presupuesto!$A$6:$K$58,6,FALSE) -> 0 | H23: =VLOOKUP(B23,Presupuesto!$A$6:$K$58,7,FALSE) -> 0 | I23: =VLOOKUP(B23,Presupuesto!$A$6:$K$58,8,FALSE) -> 42000 | J23: =VLOOKUP(B23,Presupuesto!$A$6:$K$58,9,FALSE) -> 0 | K23: =VLOOKUP(B23,Presupuesto!$A$6:$K$58,10,FALSE) -> 2342879.1 | L23: =K23*E23 -> 2342879.1
B24: ='Listado actividades'!A35 -> 4.6 | C24: =VLOOKUP(B24,APU_P!$A$3:$M$59,2,FALSE) -> SUMINISTRO DE MATERIALES PARA LA ESTRUCTURA DE HILO DE GUARDA INDEPENDIENTE PARA ESTRUCTURA TIPO PASO HG-P | D24: =VLOOKUP(B24,Presupuesto!$A$6:$K$58,3,FALSE) -> UND | E24: =VLOOKUP(B24,'Listado actividades'!$A$16:$C$40,3,FALSE) -> 1 | F24: =VLOOKUP(B24,Presupuesto!$A$6:$K$58,5,FALSE) -> 107297.16 | G24: =VLOOKUP(B24,Presupuesto!$A$6:$K$58,6,FALSE) -> 0 | H24: =VLOOKUP(B24,Presupuesto!$A$6:$K$58,7,FALSE) -> 0 | I24: =VLOOKUP(B24,Presupuesto!$A$6:$K$58,8,FALSE) -> 42000 | J24: =VLOOKUP(B24,Presupuesto!$A$6:$K$58,9,FALSE) -> 0 | K24: =VLOOKUP(B24,Presupuesto!$A$6:$K$58,10,FALSE) -> 149297.16 | L24: =K24*E24 -> 149297.16
B25: ='Listado actividades'!A36 -> 4.9 | C25: =VLOOKUP(B25,APU_P!$A$3:$M$59,2,FALSE) -> SUMINISTRO DE MATERIALES PARA LA ESTRUCTURA 619 N1 | D25: =VLOOKUP(B25,Presupuesto!$A$6:$K$58,3,FALSE) -> UND | E25: =VLOOKUP(B25,'Listado actividades'!$A$16:$C$40,3,FALSE) -> 1 | F25: =VLOOKUP(B25,Presupuesto!$A$6:$K$58,5,FALSE) -> 57742.293 | G25: =VLOOKUP(B25,Presupuesto!$A$6:$K$58,6,FALSE) -> 0 | H25: =VLOOKUP(B25,Presupuesto!$A$6:$K$58,7,FALSE) -> 0 | I25: =VLOOKUP(B25,Presupuesto!$A$6:$K$58,8,FALSE) -> 42000 | J25: =VLOOKUP(B25,Presupuesto!$A$6:$K$58,9,FALSE) -> 0 | K25: =VLOOKUP(B25,Presupuesto!$A$6:$K$58,10,FALSE) -> 99742.293 | L25: =K25*E25 -> 99742.293
B26: ='Listado actividades'!A37 -> 4.10 | C26: =VLOOKUP(B26,APU_P!$A$3:$M$59,2,FALSE) -> SUMINISTRO DE TEMPLETE CUAERDA DE GUITARRA 34.5 KV | D26: =VLOOKUP(B26,Presupuesto!$A$6:$K$58,3,FALSE) -> UND | E26: =VLOOKUP(B26,'Listado actividades'!$A$16:$C$40,3,FALSE) -> 1 | F26: =VLOOKUP(B26,Presupuesto!$A$6:$K$58,5,FALSE) -> 416854.66 | G26: =VLOOKUP(B26,Presupuesto!$A$6:$K$58,6,FALSE) -> 0 | H26: =VLOOKUP(B26,Presupuesto!$A$6:$K$58,7,FALSE) -> 0 | I26: =VLOOKUP(B26,Presupuesto!$A$6:$K$58,8,FALSE) -> 42000 | J26: =VLOOKUP(B26,Presupuesto!$A$6:$K$58,9,FALSE) -> 0 | K26: =VLOOKUP(B26,Presupuesto!$A$6:$K$58,10,FALSE) -> 458854.66 | L26: =K26*E26 -> 458854.66
B27: ='Listado actividades'!A38 -> 4.11 | C27: =VLOOKUP(B27,APU_P!$A$3:$M$59,2,FALSE) -> SUMINISTRO DE TEMPLETE DIRECTO A VARILLA DE ANCLAJE 34.5 KV | D27: =VLOOKUP(B27,Presupuesto!$A$6:$K$58,3,FALSE) -> UND | E27: =VLOOKUP(B27,'Listado actividades'!$A$16:$C$40,3,FALSE) -> 2 | F27: =VLOOKUP(B27,Presupuesto!$A$6:$K$58,5,FALSE) -> 334404.16 | G27: =VLOOKUP(B27,Presupuesto!$A$6:$K$58,6,FALSE) -> 0 | H27: =VLOOKUP(B27,Presupuesto!$A$6:$K$58,7,FALSE) -> 0 | I27: =VLOOKUP(B27,Presupuesto!$A$6:$K$58,8,FALSE) -> 42000 | J27: =VLOOKUP(B27,Presupuesto!$A$6:$K$58,9,FALSE) -> 0 | K27: =VLOOKUP(B27,Presupuesto!$A$6:$K$58,10,FALSE) -> 376404.16 | L27: =K27*E27 -> 752808.32
B28: ='Listado actividades'!A39 -> 4.12 | C28: =VLOOKUP(B28,APU_P!$A$3:$M$59,2,FALSE) -> SUMINISTRO DE SISTEMA DE PUESTA A TIERRA REDES TRIFASICAS CON CABLE DE GUARDA POSTE SENCILLO | D28: =VLOOKUP(B28,Presupuesto!$A$6:$K$58,3,FALSE) -> UND | E28: =VLOOKUP(B28,'Listado actividades'!$A$16:$C$40,3,FALSE) -> 1 | F28: =VLOOKUP(B28,Presupuesto!$A$6:$K$58,5,FALSE) -> 117930.21 | G28: =VLOOKUP(B28,Presupuesto!$A$6:$K$58,6,FALSE) -> 0 | H28: =VLOOKUP(B28,Presupuesto!$A$6:$K$58,7,FALSE) -> 0 | I28: =VLOOKUP(B28,Presupuesto!$A$6:$K$58,8,FALSE) -> 42000 | J28: =VLOOKUP(B28,Presupuesto!$A$6:$K$58,9,FALSE) -> 0 | K28: =VLOOKUP(B28,Presupuesto!$A$6:$K$58,10,FALSE) -> 159930.21 | L28: =K28*E28 -> 159930.21
B29: ='Listado actividades'!A40 -> 4.17 | C29: =VLOOKUP(B29,APU_P!$A$3:$M$59,2,FALSE) -> SUMINISTRO DE POSTE DE CONCRETO DE 14 M X 1050 KGF VIBRADO Y REFORZADO | D29: =VLOOKUP(B29,Presupuesto!$A$6:$K$58,3,FALSE) -> UND | E29: =VLOOKUP(B29,'Listado actividades'!$A$16:$C$40,3,FALSE) -> 1 | F29: =VLOOKUP(B29,Presupuesto!$A$6:$K$58,5,FALSE) -> 3046689 | G29: =VLOOKUP(B29,Presupuesto!$A$6:$K$58,6,FALSE) -> 0 | H29: =VLOOKUP(B29,Presupuesto!$A$6:$K$58,7,FALSE) -> 0 | I29: =VLOOKUP(B29,Presupuesto!$A$6:$K$58,8,FALSE) -> 105000 | J29: =VLOOKUP(B29,Presupuesto!$A$6:$K$58,9,FALSE) -> 0 | K29: =VLOOKUP(B29,Presupuesto!$A$6:$K$58,10,FALSE) -> 3151689 | L29: =K29*E29 -> 3151689
A30: E96 | B30: ACTIVIDAD | C30: Se instalará una estructura trifásica tipo paso 103N3 y una estructura de hilo guarda tipo paso. | D30: GLB | E30: 1 | F30: =SUM(F31:F34) -> 532357.5 | G30: =SUM(G31:G34) -> 241976.5 | H30: =SUM(H31:H34) -> 26137.937 | I30: =SUM(I31:I34) -> 162750 | J30: =SUM(J31:J34) -> 0 | K30: =SUM(K31:K34) -> 963221.93 | L30: =SUM(L31:L34) -> 963221.93
B31: ='Listado actividades'!A44 -> 1.17 | C31: =VLOOKUP(B31,APU_P!$A$3:$M$59,2,FALSE) -> VESTIDA DE ESTRUCTURA TRIFASICA DE UN POSTE TIPO PASO 34.5 KV | D31: =VLOOKUP(B31,Presupuesto!$A$6:$K$58,3,FALSE) -> UND | E31: =VLOOKUP(B31,'Listado actividades'!$A$44:$C$47,3,FALSE) -> 1 | F31: =VLOOKUP(B31,Presupuesto!$A$6:$K$58,5,FALSE) -> 0 | G31: =VLOOKUP(B31,Presupuesto!$A$6:$K$58,6,FALSE) -> 184702.7 | H31: =VLOOKUP(B31,Presupuesto!$A$6:$K$58,7,FALSE) -> 17425.291 | I31: =VLOOKUP(B31,Presupuesto!$A$6:$K$58,8,FALSE) -> 52500 | J31: =VLOOKUP(B31,Presupuesto!$A$6:$K$58,9,FALSE) -> 0 | K31: =VLOOKUP(B31,Presupuesto!$A$6:$K$58,10,FALSE) -> 254628 | L31: =K31*E31 -> 254628
B32: ='Listado actividades'!A45 -> 1.20 | C32: =VLOOKUP(B32,APU_P!$A$3:$M$59,2,FALSE) -> VESTIDA ESTRUCTURA CABLE DE GUARDA DE PASO | D32: =VLOOKUP(B32,Presupuesto!$A$6:$K$58,3,FALSE) -> UND | E32: =VLOOKUP(B32,'Listado actividades'!$A$44:$C$47,3,FALSE) -> 1 | F32: =VLOOKUP(B32,Presupuesto!$A$6:$K$58,5,FALSE) -> 0 | G32: =VLOOKUP(B32,Presupuesto!$A$6:$K$58,6,FALSE) -> 57273.791 | H32: =VLOOKUP(B32,Presupuesto!$A$6:$K$58,7,FALSE) -> 8712.6456 | I32: =VLOOKUP(B32,Presupuesto!$A$6:$K$58,8,FALSE) -> 26250 | J32: =VLOOKUP(B32,Presupuesto!$A$6:$K$58,9,FALSE) -> 0 | K32: =VLOOKUP(B32,Presupuesto!$A$6:$K$58,10,FALSE) -> 92236.437 | L32: =K32*E32 -> 92236.437
B33: ='Listado actividades'!A46 -> 4.2 | C33: =VLOOKUP(B33,APU_P!$A$3:$M$59,2,FALSE) -> SUMINISTRO DE MATERIALES PARA LA ESTRUCTURA P103 N3 | D33: =VLOOKUP(B33,Presupuesto!$A$6:$K$58,3,FALSE) -> UND | E33: =VLOOKUP(B33,'Listado actividades'!$A$44:$C$47,3,FALSE) -> 1 | F33: =VLOOKUP(B33,Presupuesto!$A$6:$K$58,5,FALSE) -> 425060.34 | G33: =VLOOKUP(B33,Presupuesto!$A$6:$K$58,6,FALSE) -> 0 | H33: =VLOOKUP(B33,Presupuesto!$A$6:$K$58,7,FALSE) -> 0 | I33: =VLOOKUP(B33,Presupuesto!$A$6:$K$58,8,FALSE) -> 42000 | J33: =VLOOKUP(B33,Presupuesto!$A$6:$K$58,9,FALSE) -> 0 | K33: =VLOOKUP(B33,Presupuesto!$A$6:$K$58,10,FALSE) -> 467060.34 | L33: =K33*E33 -> 467060.34
B34: ='Listado actividades'!A47 -> 4.6 | C34: =VLOOKUP(B34,APU_P!$A$3:$M$59,2,FALSE) -> SUMINISTRO DE MATERIALES PARA LA ESTRUCTURA DE HILO DE GUARDA INDEPENDIENTE PARA ESTRUCTURA TIPO PASO HG-P | D34: =VLOOKUP(B34,Presupuesto!$A$6:$K$58,3,FALSE) -> UND | E34: =VLOOKUP(B34,'Listado actividades'!$A$44:$C$47,3,FALSE) -> 1 | F34: =VLOOKUP(B34,Presupuesto!$A$6:$K$58,5,FALSE) -> 107297.16 | G34: =VLOOKUP(B34,Presupuesto!$A$6:$K$58,6,FALSE) -> 0 | H34: =VLOOKUP(B34,Presupuesto!$A$6:$K$58,7,FALSE) -> 0 | I34: =VLOOKUP(B34,Presupuesto!$A$6:$K$58,8,FALSE) -> 42000 | J34: =VLOOKUP(B34,Presupuesto!$A$6:$K$58,9,FALSE) -> 0 | K34: =VLOOKUP(B34,Presupuesto!$A$6:$K$58,10,FALSE) -> 149297.16 | L34: =K34*E34 -> 149297.16
A35: E95D | B35: ACTIVIDAD | C35: Se reemplazará el poste de concreto de 14m por uno de 16m 1350 kg, se debe desvestir las estructuras instaladas, desmontar un transformador monofásico y retirar el poste. Posteriormente se hincará y vestirá el nuevo poste con las estructuras trifásicas 580 N2 y dos 555 N3. Se realizará el montaje del transformador monofásico. Además se harán excavaciones de viguetas para instalación de templetes, junto con la instalación del sistema de puesta a tierra. Al poste se le instalarán placas de peligro de red energizada y de identificación. | D35: GLB | E35: 1 | F35: =SUM(F36:F58) -> 8780623.3 | G35: =SUM(G36:G58) -> 2102097.4 | H35: =SUM(H36:H58) -> 1708230.6 | I35: =SUM(I36:I58) -> 450000 | J35: =SUM(J36:J58) -> 0 | K35: =SUM(K36:K58) -> 13040951 | L35: =SUM(L36:L58) -> 14962061
B36: ='Listado actividades'!A51 -> 1.3 | C36: =VLOOKUP(B36,APU_P!$A$3:$M$59,2,FALSE) -> APERTURA DE EXCAVACION PARA VIGUETA EN RETENIDA RURAL | D36: =VLOOKUP(B36,Presupuesto!$A$6:$K$58,3,FALSE) -> UND | E36: =VLOOKUP(B36,'Listado actividades'!$A$51:$C$74,3,FALSE) -> 2 | F36: =VLOOKUP(B36,Presupuesto!$A$6:$K$58,5,FALSE) -> 0 | G36: =VLOOKUP(B36,Presupuesto!$A$6:$K$58,6,FALSE) -> 83520.324 | H36: =VLOOKUP(B36,Presupuesto!$A$6:$K$58,7,FALSE) -> 8712.6456 | I36: =VLOOKUP(B36,Presupuesto!$A$6:$K$58,8,FALSE) -> 0 | J36: =VLOOKUP(B36,Presupuesto!$A$6:$K$58,9,FALSE) -> 0 | K36: =VLOOKUP(B36,Presupuesto!$A$6:$K$58,10,FALSE) -> 92232.969 | L36: =K36*E36 -> 184465.94
B37: ='Listado actividades'!A52 -> 1.6 | C37: =VLOOKUP(B37,APU_P!$A$3:$M$59,2,FALSE) -> HINCADA, PLOMADA Y ORIENTACIÓN DE POSTE DE 14, 16 Y 18 MTS CON GRUA | D37: =VLOOKUP(B37,Presupuesto!$A$6:$K$58,3,FALSE) -> UND | E37: =VLOOKUP(B37,'Listado actividades'!$A$51:$C$74,3,FALSE) -> 1 | F37: =VLOOKUP(B37,Presupuesto!$A$6:$K$58,5,FALSE) -> 0 | G37: =VLOOKUP(B37,Presupuesto!$A$6:$K$58,6,FALSE) -> 109533.17 | H37: =VLOOKUP(B37,Presupuesto!$A$6:$K$58,7,FALSE) -> 308712.65 | I37: =VLOOKUP(B37,Presupuesto!$A$6:$K$58,8,FALSE) -> 0 | J37: =VLOOKUP(B37,Presupuesto!$A$6:$K$58,9,FALSE) -> 0 | K37: =VLOOKUP(B37,Presupuesto!$A$6:$K$58,10,FALSE) -> 418245.81 | L37: =K37*E37 -> 418245.81
B38: ='Listado actividades'!A53 -> 1.7 | C38: =VLOOKUP(B38,APU_P!$A$3:$M$59,2,FALSE) -> INSTALACION LINE A TIERRA MEDIA TENSION | D38: =VLOOKUP(B38,Presupuesto!$A$6:$K$58,3,FALSE) -> UND | E38: =VLOOKUP(B38,'Listado actividades'!$A$51:$C$74,3,FALSE) -> 1 | F38: =VLOOKUP(B38,Presupuesto!$A$6:$K$58,5,FALSE) -> 0 | G38: =VLOOKUP(B38,Presupuesto!$A$6:$K$58,6,FALSE) -> 136919.2 | H38: =VLOOKUP(B38,Presupuesto!$A$6:$K$58,7,FALSE) -> 6970.1165 | I38: =VLOOKUP(B38,Presupuesto!$A$6:$K$58,8,FALSE) -> 0 | J38: =VLOOKUP(B38,Presupuesto!$A$6:$K$58,9,FALSE) -> 0 | K38: =VLOOKUP(B38,Presupuesto!$A$6:$K$58,10,FALSE) -> 143889.32 | L38: =K38*E38 -> 143889.32
B39: ='Listado actividades'!A54 -> 1.8 | C39: =VLOOKUP(B39,APU_P!$A$3:$M$59,2,FALSE) -> INSTALACIÓN DE TEMPLETE CUERDA GUITARRA CON TODOS SUS ACCESORIOS M.T. RURAL | D39: =VLOOKUP(B39,Presupuesto!$A$6:$K$58,3,FALSE) -> UND | E39: =VLOOKUP(B39,'Listado actividades'!$A$51:$C$74,3,FALSE) -> 2 | F39: =VLOOKUP(B39,Presupuesto!$A$6:$K$58,5,FALSE) -> 0 | G39: =VLOOKUP(B39,Presupuesto!$A$6:$K$58,6,FALSE) -> 95832.542 | H39: =VLOOKUP(B39,Presupuesto!$A$6:$K$58,7,FALSE) -> 4646.7443 | I39: =VLOOKUP(B39,Presupuesto!$A$6:$K$58,8,FALSE) -> 0 | J39: =VLOOKUP(B39,Presupuesto!$A$6:$K$58,9,FALSE) -> 0 | K39: =VLOOKUP(B39,Presupuesto!$A$6:$K$58,10,FALSE) -> 100479.29 | L39: =K39*E39 -> 200958.57
B40: ='Listado actividades'!A55 -> 1.12 | C40: =VLOOKUP(B40,APU_P!$A$3:$M$59,2,FALSE) -> TRANSPORTE DE POSTE 14 MTS M.T. RURAL DE BODEGA A SITIO CERCANO | D40: =VLOOKUP(B40,Presupuesto!$A$6:$K$58,3,FALSE) -> UND | E40: =VLOOKUP(B40,'Listado actividades'!$A$51:$C$74,3,FALSE) -> 1 | F40: =VLOOKUP(B40,Presupuesto!$A$6:$K$58,5,FALSE) -> 0 | G40: =VLOOKUP(B40,Presupuesto!$A$6:$K$58,6,FALSE) -> 77975.29 | H40: =VLOOKUP(B40,Presupuesto!$A$6:$K$58,7,FALSE) -> 294701.17 | I40: =VLOOKUP(B40,Presupuesto!$A$6:$K$58,8,FALSE) -> 0 | J40: =VLOOKUP(B40,Presupuesto!$A$6:$K$58,9,FALSE) -> 0 | K40: =VLOOKUP(B40,Presupuesto!$A$6:$K$58,10,FALSE) -> 372676.45 | L40: =K40*E40 -> 372676.45
B41: ='Listado actividades'!A56 -> 1.16 | C41: =VLOOKUP(B41,APU_P!$A$3:$M$59,2,FALSE) -> VESTIDA DE ESTRUCTURA TRIFASICA DE RETENCION UN POSTE 13,8 Kv | D41: =VLOOKUP(B41,Presupuesto!$A$6:$K$58,3,FALSE) -> UND | E41: =VLOOKUP(B41,'Listado actividades'!$A$51:$C$74,3,FALSE) -> 1 | F41: =VLOOKUP(B41,Presupuesto!$A$6:$K$58,5,FALSE) -> 0 | G41: =VLOOKUP(B41,Presupuesto!$A$6:$K$58,6,FALSE) -> 89880.129 | H41: =VLOOKUP(B41,Presupuesto!$A$6:$K$58,7,FALSE) -> 11616.861 | I41: =VLOOKUP(B41,Presupuesto!$A$6:$K$58,8,FALSE) -> 35000 | J41: =VLOOKUP(B41,Presupuesto!$A$6:$K$58,9,FALSE) -> 0 | K41: =VLOOKUP(B41,Presupuesto!$A$6:$K$58,10,FALSE) -> 136496.99 | L41: =K41*E41 -> 136496.99
B42: ='Listado actividades'!A57 -> 1.18 | C42: =VLOOKUP(B42,APU_P!$A$3:$M$59,2,FALSE) -> VESTIDA DE ESTRUCTURA TRIFASICA DE UN POSTE TIPO RETENCIÓN - 34.5 KV | D42: =VLOOKUP(B42,Presupuesto!$A$6:$K$58,3,FALSE) -> UND | E42: =VLOOKUP(B42,'Listado actividades'!$A$51:$C$74,3,FALSE) -> 1 | F42: =VLOOKUP(B42,Presupuesto!$A$6:$K$58,5,FALSE) -> 0 | G42: =VLOOKUP(B42,Presupuesto!$A$6:$K$58,6,FALSE) -> 246270.27 | H42: =VLOOKUP(B42,Presupuesto!$A$6:$K$58,7,FALSE) -> 23233.722 | I42: =VLOOKUP(B42,Presupuesto!$A$6:$K$58,8,FALSE) -> 70000 | J42: =VLOOKUP(B42,Presupuesto!$A$6:$K$58,9,FALSE) -> 0 | K42: =VLOOKUP(B42,Presupuesto!$A$6:$K$58,10,FALSE) -> 339503.99 | L42: =K42*E42 -> 339503.99
B43: ='Listado actividades'!A58 -> 1.19 | C43: =VLOOKUP(B43,APU_P!$A$3:$M$59,2,FALSE) -> VESTIDA ESTRUCTURA CABLE DE GUARDA - RETENCION | D43: =VLOOKUP(B43,Presupuesto!$A$6:$K$58,3,FALSE) -> UND | E43: =VLOOKUP(B43,'Listado actividades'!$A$51:$C$74,3,FALSE) -> 1 | F43: =VLOOKUP(B43,Presupuesto!$A$6:$K$58,5,FALSE) -> 0 | G43: =VLOOKUP(B43,Presupuesto!$A$6:$K$58,6,FALSE) -> 65455.762 | H43: =VLOOKUP(B43,Presupuesto!$A$6:$K$58,7,FALSE) -> 9957.3093 | I43: =VLOOKUP(B43,Presupuesto!$A$6:$K$58,8,FALSE) -> 30000 | J43: =VLOOKUP(B43,Presupuesto!$A$6:$K$58,9,FALSE) -> 0 | K43: =VLOOKUP(B43,Presupuesto!$A$6:$K$58,10,FALSE) -> 105413.07 | L43: =K43*E43 -> 105413.07
B44: ='Listado actividades'!A59 -> 1.21 | C44: =VLOOKUP(B44,APU_P!$A$3:$M$59,2,FALSE) -> DESVESTIDA ESTRUCTURA DE RETENCION MT RURAL | D44: =VLOOKUP(B44,Presupuesto!$A$6:$K$58,3,FALSE) -> UND | E44: =VLOOKUP(B44,'Listado actividades'!$A$51:$C$74,3,FALSE) -> 1 | F44: =VLOOKUP(B44,Presupuesto!$A$6:$K$58,5,FALSE) -> 0 | G44: =VLOOKUP(B44,Presupuesto!$A$6:$K$58,6,FALSE) -> 136919.2 | H44: =VLOOKUP(B44,Presupuesto!$A$6:$K$58,7,FALSE) -> 6970.1165 | I44: =VLOOKUP(B44,Presupuesto!$A$6:$K$58,8,FALSE) -> 0 | J44: =VLOOKUP(B44,Presupuesto!$A$6:$K$58,9,FALSE) -> 0 | K44: =VLOOKUP(B44,Presupuesto!$A$6:$K$58,10,FALSE) -> 143889.32 | L44: =K44*E44 -> 143889.32
B45: ='Listado actividades'!A60 -> 1.23 | C45: =VLOOKUP(B45,APU_P!$A$3:$M$59,2,FALSE) -> DESHINCADA DE POSTES 10, 12 Y 14 mts MT | D45: =VLOOKUP(B45,Presupuesto!$A$6:$K$58,3,FALSE) -> UND | E45: =VLOOKUP(B45,'Listado actividades'!$A$51:$C$74,3,FALSE) -> 1 | F45: =VLOOKUP(B45,Presupuesto!$A$6:$K$58,5,FALSE) -> 0 | G45: =VLOOKUP(B45,Presupuesto!$A$6:$K$58,6,FALSE) -> 188203.38 | H45: =VLOOKUP(B45,Presupuesto!$A$6:$K$58,7,FALSE) -> 339701.17 | I45: =VLOOKUP(B45,Presupuesto!$A$6:$K$58,8,FALSE) -> 0 | J45: =VLOOKUP(B45,Presupuesto!$A$6:$K$58,9,FALSE) -> 0 | K45: =VLOOKUP(B45,Presupuesto!$A$6:$K$58,10,FALSE) -> 527904.55 | L45: =K45*E45 -> 527904.55
B46: ='Listado actividades'!A62 -> 1.26 | C46: =VLOOKUP(B46,APU_P!$A$3:$M$59,2,FALSE) -> TRANSPORTE DE POSTE RURAL DE SITIO CERCANO A BODEGA EH | D46: =VLOOKUP(B46,Presupuesto!$A$6:$K$58,3,FALSE) -> UND | E46: =VLOOKUP(B46,'Listado actividades'!$A$51:$C$74,3,FALSE) -> 1 | F46: =VLOOKUP(B46,Presupuesto!$A$6:$K$58,5,FALSE) -> 0 | G46: =VLOOKUP(B46,Presupuesto!$A$6:$K$58,6,FALSE) -> 46034.989 | H46: =VLOOKUP(B46,Presupuesto!$A$6:$K$58,7,FALSE) -> 162923.6 | I46: =VLOOKUP(B46,Presupuesto!$A$6:$K$58,8,FALSE) -> 0 | J46: =VLOOKUP(B46,Presupuesto!$A$6:$K$58,9,FALSE) -> 0 | K46: =VLOOKUP(B46,Presupuesto!$A$6:$K$58,10,FALSE) -> 208958.59 | L46: =K46*E46 -> 208958.59
B47: ='Listado actividades'!A63 -> 1.27 | C47: =VLOOKUP(B47,APU_P!$A$3:$M$59,2,FALSE) -> DESMONTE DE TRANSFORMADOR MONOFASICO | D47: =VLOOKUP(B47,Presupuesto!$A$6:$K$58,3,FALSE) -> UND | E47: =VLOOKUP(B47,'Listado actividades'!$A$51:$C$74,3,FALSE) -> 1 | F47: =VLOOKUP(B47,Presupuesto!$A$6:$K$58,5,FALSE) -> 0 | G47: =VLOOKUP(B47,Presupuesto!$A$6:$K$58,6,FALSE) -> 290740.35 | H47: =VLOOKUP(B47,Presupuesto!$A$6:$K$58,7,FALSE) -> 116168.61 | I47: =VLOOKUP(B47,Presupuesto!$A$6:$K$58,8,FALSE) -> 0 | J47: =VLOOKUP(B47,Presupuesto!$A$6:$K$58,9,FALSE) -> 0 | K47: =VLOOKUP(B47,Presupuesto!$A$6:$K$58,10,FALSE) -> 406908.96 | L47: =K47*E47 -> 406908.96
B48: ='Listado actividades'!A64 -> 1.28 | C48: =VLOOKUP(B48,APU_P!$A$3:$M$59,2,FALSE) -> MONTAJE DE TRANSFORMADOR MONOFASICO CON TODAS SUS PROTECCIONES RURAL | D48: =VLOOKUP(B48,Presupuesto!$A$6:$K$58,3,FALSE) -> UND | E48: =VLOOKUP(B48,'Listado actividades'!$A$51:$C$74,3,FALSE) -> 1 | F48: =VLOOKUP(B48,Presupuesto!$A$6:$K$58,5,FALSE) -> 0 | G48: =VLOOKUP(B48,Presupuesto!$A$6:$K$58,6,FALSE) -> 391577.84 | H48: =VLOOKUP(B48,Presupuesto!$A$6:$K$58,7,FALSE) -> 348505.83 | I48: =VLOOKUP(B48,Presupuesto!$A$6:$K$58,8,FALSE) -> 0 | J48: =VLOOKUP(B48,Presupuesto!$A$6:$K$58,9,FALSE) -> 0 | K48: =VLOOKUP(B48,Presupuesto!$A$6:$K$58,10,FALSE) -> 740083.67 | L48: =K48*E48 -> 740083.67
B49: ='Listado actividades'!A65 -> 1.29 | C49: =VLOOKUP(B49,APU_P!$A$3:$M$59,2,FALSE) -> DESVESTIDA DE ESTRUCTURA BT EXISTENTE | D49: =VLOOKUP(B49,Presupuesto!$A$6:$K$58,3,FALSE) -> UND | E49: =VLOOKUP(B49,'Listado actividades'!$A$51:$C$74,3,FALSE) -> 1 | F49: =VLOOKUP(B49,Presupuesto!$A$6:$K$58,5,FALSE) -> 0 | G49: =VLOOKUP(B49,Presupuesto!$A$6:$K$58,6,FALSE) -> 45332.476 | H49: =VLOOKUP(B49,Presupuesto!$A$6:$K$58,7,FALSE) -> 20190 | I49: =VLOOKUP(B49,Presupuesto!$A$6:$K$58,8,FALSE) -> 0 | J49: =VLOOKUP(B49,Presupuesto!$A$6:$K$58,9,FALSE) -> 0 | K49: =VLOOKUP(B49,Presupuesto!$A$6:$K$58,10,FALSE) -> 65522.476 | L49: =K49*E49 -> 65522.476
B50: ='Listado actividades'!A66 -> 1.30 | C50: =VLOOKUP(B50,APU_P!$A$3:$M$59,2,FALSE) -> VESTIDA DE ESTRUCTURA BT | D50: =VLOOKUP(B50,Presupuesto!$A$6:$K$58,3,FALSE) -> UND | E50: =VLOOKUP(B50,'Listado actividades'!$A$51:$C$74,3,FALSE) -> 1 | F50: =VLOOKUP(B50,Presupuesto!$A$6:$K$58,5,FALSE) -> 0 | G50: =VLOOKUP(B50,Presupuesto!$A$6:$K$58,6,FALSE) -> 77259.417 | H50: =VLOOKUP(B50,Presupuesto!$A$6:$K$58,7,FALSE) -> 38250 | I50: =VLOOKUP(B50,Presupuesto!$A$6:$K$58,8,FALSE) -> 0 | J50: =VLOOKUP(B50,Presupuesto!$A$6:$K$58,9,FALSE) -> 0 | K50: =VLOOKUP(B50,Presupuesto!$A$6:$K$58,10,FALSE) -> 115509.42 | L50: =K50*E50 -> 115509.42
B51: ='Listado actividades'!A67 -> 2.1 | C51: =VLOOKUP(B51,APU_P!$A$3:$M$59,2,FALSE) -> INSTALACIÓN DE PLACAS DE IDENTIFICACIÓN DE PELIGRO RED ENERGIZADA (INCLUYE PLACA EN ACRILICO Y CONECTORES A RED) | D51: =VLOOKUP(B51,Presupuesto!$A$6:$K$58,3,FALSE) -> UND | E51: =VLOOKUP(B51,'Listado actividades'!$A$51:$C$74,3,FALSE) -> 1 | F51: =VLOOKUP(B51,Presupuesto!$A$6:$K$58,5,FALSE) -> 35000 | G51: =VLOOKUP(B51,Presupuesto!$A$6:$K$58,6,FALSE) -> 5882.2661 | H51: =VLOOKUP(B51,Presupuesto!$A$6:$K$58,7,FALSE) -> 3485.0583 | I51: =VLOOKUP(B51,Presupuesto!$A$6:$K$58,8,FALSE) -> 0 | J51: =VLOOKUP(B51,Presupuesto!$A$6:$K$58,9,FALSE) -> 0 | K51: =VLOOKUP(B51,Presupuesto!$A$6:$K$58,10,FALSE) -> 44367.324 | L51: =K51*E51 -> 44367.324
B52: ='Listado actividades'!A68 -> 2.2 | C52: =VLOOKUP(B52,APU_P!$A$3:$M$59,2,FALSE) -> INSTALACIÓN DE PLACAS DE IDENTIFICACIÓN DE POSTE, (INCLUYE PLACA DE ALUMINIO, CINTA BAND IT Y HEBILLA) | D52: =VLOOKUP(B52,Presupuesto!$A$6:$K$58,3,FALSE) -> UND | E52: =VLOOKUP(B52,'Listado actividades'!$A$51:$C$74,3,FALSE) -> 1 | F52: =VLOOKUP(B52,Presupuesto!$A$6:$K$58,5,FALSE) -> 19590 | G52: =VLOOKUP(B52,Presupuesto!$A$6:$K$58,6,FALSE) -> 14760.758 | H52: =VLOOKUP(B52,Presupuesto!$A$6:$K$58,7,FALSE) -> 3485.0583 | I52: =VLOOKUP(B52,Presupuesto!$A$6:$K$58,8,FALSE) -> 0 | J52: =VLOOKUP(B52,Presupuesto!$A$6:$K$58,9,FALSE) -> 0 | K52: =VLOOKUP(B52,Presupuesto!$A$6:$K$58,10,FALSE) -> 37835.817 | L52: =K52*E52 -> 37835.817
B53: ='Listado actividades'!A69 -> 4.5 | C53: =VLOOKUP(B53,APU_P!$A$3:$M$59,2,FALSE) -> SUMINISTRO DE MATERIALES PARA LA ESTRUCTURA 580 N2 | D53: =VLOOKUP(B53,Presupuesto!$A$6:$K$58,3,FALSE) -> UND | E53: =VLOOKUP(B53,'Listado actividades'!$A$51:$C$74,3,FALSE) -> 1 | F53: =VLOOKUP(B53,Presupuesto!$A$6:$K$58,5,FALSE) -> 2190316.8 | G53: =VLOOKUP(B53,Presupuesto!$A$6:$K$58,6,FALSE) -> 0 | H53: =VLOOKUP(B53,Presupuesto!$A$6:$K$58,7,FALSE) -> 0 | I53: =VLOOKUP(B53,Presupuesto!$A$6:$K$58,8,FALSE) -> 42000 | J53: =VLOOKUP(B53,Presupuesto!$A$6:$K$58,9,FALSE) -> 0 | K53: =VLOOKUP(B53,Presupuesto!$A$6:$K$58,10,FALSE) -> 2232316.8 | L53: =K53*E53 -> 2232316.8
B54: ='Listado actividades'!A70 -> 4.7 | C54: =VLOOKUP(B54,APU_P!$A$3:$M$59,2,FALSE) -> SUMINISTRO DE MATERIALES PARA LA ESTRUCTURA DE HILO DE GUARDA INDEPENDIENTE PARA ESTRUCTURA TIPO RETENCIÓN HG-R | D54: =VLOOKUP(B54,Presupuesto!$A$6:$K$58,3,FALSE) -> UND | E54: =VLOOKUP(B54,'Listado actividades'!$A$51:$C$74,3,FALSE) -> 1 | F54: =VLOOKUP(B54,Presupuesto!$A$6:$K$58,5,FALSE) -> 77338.997 | G54: =VLOOKUP(B54,Presupuesto!$A$6:$K$58,6,FALSE) -> 0 | H54: =VLOOKUP(B54,Presupuesto!$A$6:$K$58,7,FALSE) -> 0 | I54: =VLOOKUP(B54,Presupuesto!$A$6:$K$58,8,FALSE) -> 42000 | J54: =VLOOKUP(B54,Presupuesto!$A$6:$K$58,9,FALSE) -> 0 | K54: =VLOOKUP(B54,Presupuesto!$A$6:$K$58,10,FALSE) -> 119339 | L54: =K54*E54 -> 119339
B55: ='Listado actividades'!A71 -> 4.8 | C55: =VLOOKUP(B55,APU_P!$A$3:$M$59,2,FALSE) -> SUMINISTRO DE MATERIALES PARA LA ESTRUCTURA 555 N3 | D55: =VLOOKUP(B55,Presupuesto!$A$6:$K$58,3,FALSE) -> UND | E55: =VLOOKUP(B55,'Listado actividades'!$A$51:$C$74,3,FALSE) -> 2 | F55: =VLOOKUP(B55,Presupuesto!$A$6:$K$58,5,FALSE) -> 1227542.3 | G55: =VLOOKUP(B55,Presupuesto!$A$6:$K$58,6,FALSE) -> 0 | H55: =VLOOKUP(B55,Presupuesto!$A$6:$K$58,7,FALSE) -> 0 | I55: =VLOOKUP(B55,Presupuesto!$A$6:$K$58,8,FALSE) -> 42000 | J55: =VLOOKUP(B55,Presupuesto!$A$6:$K$58,9,FALSE) -> 0 | K55: =VLOOKUP(B55,Presupuesto!$A$6:$K$58,10,FALSE) -> 1269542.3 | L55: =K55*E55 -> 2539084.5
B56: ='Listado actividades'!A72 -> 4.10 | C56: =VLOOKUP(B56,APU_P!$A$3:$M$59,2,FALSE) -> SUMINISTRO DE TEMPLETE CUAERDA DE GUITARRA 34.5 KV | D56: =VLOOKUP(B56,Presupuesto!$A$6:$K$58,3,FALSE) -> UND | E56: =VLOOKUP(B56,'Listado actividades'!$A$51:$C$74,3,FALSE) -> 2 | F56: =VLOOKUP(B56,Presupuesto!$A$6:$K$58,5,FALSE) -> 416854.66 | G56: =VLOOKUP(B56,Presupuesto!$A$6:$K$58,6,FALSE) -> 0 | H56: =VLOOKUP(B56,Presupuesto!$A$6:$K$58,7,FALSE) -> 0 | I56: =VLOOKUP(B56,Presupuesto!$A$6:$K$58,8,FALSE) -> 42000 | J56: =VLOOKUP(B56,Presupuesto!$A$6:$K$58,9,FALSE) -> 0 | K56: =VLOOKUP(B56,Presupuesto!$A$6:$K$58,10,FALSE) -> 458854.66 | L56: =K56*E56 -> 917709.32
B57: ='Listado actividades'!A73 -> 4.12 | C57: =VLOOKUP(B57,APU_P!$A$3:$M$59,2,FALSE) -> SUMINISTRO DE SISTEMA DE PUESTA A TIERRA REDES TRIFASICAS CON CABLE DE GUARDA POSTE SENCILLO | D57: =VLOOKUP(B57,Presupuesto!$A$6:$K$58,3,FALSE) -> UND | E57: =VLOOKUP(B57,'Listado actividades'!$A$51:$C$74,3,FALSE) -> 1 | F57: =VLOOKUP(B57,Presupuesto!$A$6:$K$58,5,FALSE) -> 117930.21 | G57: =VLOOKUP(B57,Presupuesto!$A$6:$K$58,6,FALSE) -> 0 | H57: =VLOOKUP(B57,Presupuesto!$A$6:$K$58,7,FALSE) -> 0 | I57: =VLOOKUP(B57,Presupuesto!$A$6:$K$58,8,FALSE) -> 42000 | J57: =VLOOKUP(B57,Presupuesto!$A$6:$K$58,9,FALSE) -> 0 | K57: =VLOOKUP(B57,Presupuesto!$A$6:$K$58,10,FALSE) -> 159930.21 | L57: =K57*E57 -> 159930.21
B58: ='Listado actividades'!A74 -> 4.18 | C58: =VLOOKUP(B58,APU_P!$A$3:$M$59,2,FALSE) -> SUMINISTRO DE POSTE DE CONCRETO DE 16 M X 1350 KGF VIBRADO Y REFORZADO | D58: =VLOOKUP(B58,Presupuesto!$A$6:$K$58,3,FALSE) -> UND | E58: =VLOOKUP(B58,'Listado actividades'!$A$51:$C$74,3,FALSE) -> 1 | F58: =VLOOKUP(B58,Presupuesto!$A$6:$K$58,5,FALSE) -> 4696050.4 | G58: =VLOOKUP(B58,Presupuesto!$A$6:$K$58,6,FALSE) -> 0 | H58: =VLOOKUP(B58,Presupuesto!$A$6:$K$58,7,FALSE) -> 0 | I58: =VLOOKUP(B58,Presupuesto!$A$6:$K$58,8,FALSE) -> 105000 | J58: =VLOOKUP(B58,Presupuesto!$A$6:$K$58,9,FALSE) -> 0 | K58: =VLOOKUP(B58,Presupuesto!$A$6:$K$58,10,FALSE) -> 4801050.4 | L58: =K58*E58 -> 4801050.4
A59: E95C | B59: ACTIVIDAD | C59: Se realizará la excavación e hincada de un poste de 14m 750kg. Se instalarán estructuras trifásicas de tipo paso P102N2 y P103N3. Además se harán excavaciones de viguetas para instalación de templetes, junto con la instalación del sistema de puesta a tierra. Al poste se le instalarán placas de peligro de red energizada y de identificación. | D59: GLB | E59: 1 | F59: =SUM(F60:F76) -> 3500370.1 | G59: =SUM(G60:G76) -> 1004995.9 | H59: =SUM(H60:H76) -> 688023.28 | I59: =SUM(I60:I76) -> 420000 | J59: =SUM(J60:J76) -> 0 | K59: =SUM(K60:K76) -> 5613389.3 | L59: =SUM(L60:L76) -> 6168035.7
B60: ='Listado actividades'!A78 -> 1.2 | C60: =VLOOKUP(B60,APU_P!$A$3:$M$59,2,FALSE) -> APERTURA DE EXCAVACION POSTE DE 14 MTS M.T. RURAL | D60: =VLOOKUP(B60,Presupuesto!$A$6:$K$58,3,FALSE) -> UND | E60: =VLOOKUP(B60,'Listado actividades'!$A$78:$C$94,3,FALSE) -> 1 | F60: =VLOOKUP(B60,Presupuesto!$A$6:$K$58,5,FALSE) -> 0 | G60: =VLOOKUP(B60,Presupuesto!$A$6:$K$58,6,FALSE) -> 184872.77 | H60: =VLOOKUP(B60,Presupuesto!$A$6:$K$58,7,FALSE) -> 23233.722 | I60: =VLOOKUP(B60,Presupuesto!$A$6:$K$58,8,FALSE) -> 0 | J60: =VLOOKUP(B60,Presupuesto!$A$6:$K$58,9,FALSE) -> 0 | K60: =VLOOKUP(B60,Presupuesto!$A$6:$K$58,10,FALSE) -> 208106.49 | L60: =E60*K60 -> 208106.49
B61: ='Listado actividades'!A79 -> 1.3 | C61: =VLOOKUP(B61,APU_P!$A$3:$M$59,2,FALSE) -> APERTURA DE EXCAVACION PARA VIGUETA EN RETENIDA RURAL | D61: =VLOOKUP(B61,Presupuesto!$A$6:$K$58,3,FALSE) -> UND | E61: =VLOOKUP(B61,'Listado actividades'!$A$78:$C$94,3,FALSE) -> 2 | F61: =VLOOKUP(B61,Presupuesto!$A$6:$K$58,5,FALSE) -> 0 | G61: =VLOOKUP(B61,Presupuesto!$A$6:$K$58,6,FALSE) -> 83520.324 | H61: =VLOOKUP(B61,Presupuesto!$A$6:$K$58,7,FALSE) -> 8712.6456 | I61: =VLOOKUP(B61,Presupuesto!$A$6:$K$58,8,FALSE) -> 0 | J61: =VLOOKUP(B61,Presupuesto!$A$6:$K$58,9,FALSE) -> 0 | K61: =VLOOKUP(B61,Presupuesto!$A$6:$K$58,10,FALSE) -> 92232.969 | L61: =E61*K61 -> 184465.94
B62: ='Listado actividades'!A80 -> 1.6 | C62: =VLOOKUP(B62,APU_P!$A$3:$M$59,2,FALSE) -> HINCADA, PLOMADA Y ORIENTACIÓN DE POSTE DE 14, 16 Y 18 MTS CON GRUA | D62: =VLOOKUP(B62,Presupuesto!$A$6:$K$58,3,FALSE) -> UND | E62: =VLOOKUP(B62,'Listado actividades'!$A$78:$C$94,3,FALSE) -> 1 | F62: =VLOOKUP(B62,Presupuesto!$A$6:$K$58,5,FALSE) -> 0 | G62: =VLOOKUP(B62,Presupuesto!$A$6:$K$58,6,FALSE) -> 109533.17 | H62: =VLOOKUP(B62,Presupuesto!$A$6:$K$58,7,FALSE) -> 308712.65 | I62: =VLOOKUP(B62,Presupuesto!$A$6:$K$58,8,FALSE) -> 0 | J62: =VLOOKUP(B62,Presupuesto!$A$6:$K$58,9,FALSE) -> 0 | K62: =VLOOKUP(B62,Presupuesto!$A$6:$K$58,10,FALSE) -> 418245.81 | L62: =E62*K62 -> 418245.81
B63: ='Listado actividades'!A81 -> 1.7 | C63: =VLOOKUP(B63,APU_P!$A$3:$M$59,2,FALSE) -> INSTALACION LINE A TIERRA MEDIA TENSION | D63: =VLOOKUP(B63,Presupuesto!$A$6:$K$58,3,FALSE) -> UND | E63: =VLOOKUP(B63,'Listado actividades'!$A$78:$C$94,3,FALSE) -> 1 | F63: =VLOOKUP(B63,Presupuesto!$A$6:$K$58,5,FALSE) -> 0 | G63: =VLOOKUP(B63,Presupuesto!$A$6:$K$58,6,FALSE) -> 136919.2 | H63: =VLOOKUP(B63,Presupuesto!$A$6:$K$58,7,FALSE) -> 6970.1165 | I63: =VLOOKUP(B63,Presupuesto!$A$6:$K$58,8,FALSE) -> 0 | J63: =VLOOKUP(B63,Presupuesto!$A$6:$K$58,9,FALSE) -> 0 | K63: =VLOOKUP(B63,Presupuesto!$A$6:$K$58,10,FALSE) -> 143889.32 | L63: =E63*K63 -> 143889.32
B64: ='Listado actividades'!A82 -> 1.12 | C64: =VLOOKUP(B64,APU_P!$A$3:$M$59,2,FALSE) -> TRANSPORTE DE POSTE 14 MTS M.T. RURAL DE BODEGA A SITIO CERCANO | D64: =VLOOKUP(B64,Presupuesto!$A$6:$K$58,3,FALSE) -> UND | E64: =VLOOKUP(B64,'Listado actividades'!$A$78:$C$94,3,FALSE) -> 1 | F64: =VLOOKUP(B64,Presupuesto!$A$6:$K$58,5,FALSE) -> 0 | G64: =VLOOKUP(B64,Presupuesto!$A$6:$K$58,6,FALSE) -> 77975.29 | H64: =VLOOKUP(B64,Presupuesto!$A$6:$K$58,7,FALSE) -> 294701.17 | I64: =VLOOKUP(B64,Presupuesto!$A$6:$K$58,8,FALSE) -> 0 | J64: =VLOOKUP(B64,Presupuesto!$A$6:$K$58,9,FALSE) -> 0 | K64: =VLOOKUP(B64,Presupuesto!$A$6:$K$58,10,FALSE) -> 372676.45 | L64: =E64*K64 -> 372676.45
B65: ='Listado actividades'!A83 -> 1.15 | C65: =VLOOKUP(B65,APU_P!$A$3:$M$59,2,FALSE) -> VESTIDA DE ESTRUCTURA TRIFASICA DE PASO UN POSTE 13,8kV | D65: =VLOOKUP(B65,Presupuesto!$A$6:$K$58,3,FALSE) -> UND | E65: =VLOOKUP(B65,'Listado actividades'!$A$78:$C$94,3,FALSE) -> 1 | F65: =VLOOKUP(B65,Presupuesto!$A$6:$K$58,5,FALSE) -> 0 | G65: =VLOOKUP(B65,Presupuesto!$A$6:$K$58,6,FALSE) -> 67418.622 | H65: =VLOOKUP(B65,Presupuesto!$A$6:$K$58,7,FALSE) -> 8712.6456 | I65: =VLOOKUP(B65,Presupuesto!$A$6:$K$58,8,FALSE) -> 26250 | J65: =VLOOKUP(B65,Presupuesto!$A$6:$K$58,9,FALSE) -> 0 | K65: =VLOOKUP(B65,Presupuesto!$A$6:$K$58,10,FALSE) -> 102381.27 | L65: =E65*K65 -> 102381.27
B66: ='Listado actividades'!A84 -> 1.17 | C66: =VLOOKUP(B66,APU_P!$A$3:$M$59,2,FALSE) -> VESTIDA DE ESTRUCTURA TRIFASICA DE UN POSTE TIPO PASO 34.5 KV | D66: =VLOOKUP(B66,Presupuesto!$A$6:$K$58,3,FALSE) -> UND | E66: =VLOOKUP(B66,'Listado actividades'!$A$78:$C$94,3,FALSE) -> 1 | F66: =VLOOKUP(B66,Presupuesto!$A$6:$K$58,5,FALSE) -> 0 | G66: =VLOOKUP(B66,Presupuesto!$A$6:$K$58,6,FALSE) -> 184702.7 | H66: =VLOOKUP(B66,Presupuesto!$A$6:$K$58,7,FALSE) -> 17425.291 | I66: =VLOOKUP(B66,Presupuesto!$A$6:$K$58,8,FALSE) -> 52500 | J66: =VLOOKUP(B66,Presupuesto!$A$6:$K$58,9,FALSE) -> 0 | K66: =VLOOKUP(B66,Presupuesto!$A$6:$K$58,10,FALSE) -> 254628 | L66: =E66*K66 -> 254628
B67: ='Listado actividades'!A85 -> 1.20 | C67: =VLOOKUP(B67,APU_P!$A$3:$M$59,2,FALSE) -> VESTIDA ESTRUCTURA CABLE DE GUARDA DE PASO | D67: =VLOOKUP(B67,Presupuesto!$A$6:$K$58,3,FALSE) -> UND | E67: =VLOOKUP(B67,'Listado actividades'!$A$78:$C$94,3,FALSE) -> 1 | F67: =VLOOKUP(B67,Presupuesto!$A$6:$K$58,5,FALSE) -> 0 | G67: =VLOOKUP(B67,Presupuesto!$A$6:$K$58,6,FALSE) -> 57273.791 | H67: =VLOOKUP(B67,Presupuesto!$A$6:$K$58,7,FALSE) -> 8712.6456 | I67: =VLOOKUP(B67,Presupuesto!$A$6:$K$58,8,FALSE) -> 26250 | J67: =VLOOKUP(B67,Presupuesto!$A$6:$K$58,9,FALSE) -> 0 | K67: =VLOOKUP(B67,Presupuesto!$A$6:$K$58,10,FALSE) -> 92236.437 | L67: =E67*K67 -> 92236.437
B68: ='Listado actividades'!A86 -> 1.24 | C68: =VLOOKUP(B68,APU_P!$A$3:$M$59,2,FALSE) -> INSTALACIÓN DE TEMPLETE SENCILLO CON TODOS SUS ACCESORIOS M.T. RURAL | D68: =VLOOKUP(B68,Presupuesto!$A$6:$K$58,3,FALSE) -> UND | E68: =VLOOKUP(B68,'Listado actividades'!$A$78:$C$94,3,FALSE) -> 2 | F68: =VLOOKUP(B68,Presupuesto!$A$6:$K$58,5,FALSE) -> 0 | G68: =VLOOKUP(B68,Presupuesto!$A$6:$K$58,6,FALSE) -> 82136.989 | H68: =VLOOKUP(B68,Presupuesto!$A$6:$K$58,7,FALSE) -> 3872.2869 | I68: =VLOOKUP(B68,Presupuesto!$A$6:$K$58,8,FALSE) -> 0 | J68: =VLOOKUP(B68,Presupuesto!$A$6:$K$58,9,FALSE) -> 0 | K68: =VLOOKUP(B68,Presupuesto!$A$6:$K$58,10,FALSE) -> 86009.275 | L68: =E68*K68 -> 172018.55
B69: ='Listado actividades'!A87 -> 2.1 | C69: =VLOOKUP(B69,APU_P!$A$3:$M$59,2,FALSE) -> INSTALACIÓN DE PLACAS DE IDENTIFICACIÓN DE PELIGRO RED ENERGIZADA (INCLUYE PLACA EN ACRILICO Y CONECTORES A RED) | D69: =VLOOKUP(B69,Presupuesto!$A$6:$K$58,3,FALSE) -> UND | E69: =VLOOKUP(B69,'Listado actividades'!$A$78:$C$94,3,FALSE) -> 1 | F69: =VLOOKUP(B69,Presupuesto!$A$6:$K$58,5,FALSE) -> 35000 | G69: =VLOOKUP(B69,Presupuesto!$A$6:$K$58,6,FALSE) -> 5882.2661 | H69: =VLOOKUP(B69,Presupuesto!$A$6:$K$58,7,FALSE) -> 3485.0583 | I69: =VLOOKUP(B69,Presupuesto!$A$6:$K$58,8,FALSE) -> 0 | J69: =VLOOKUP(B69,Presupuesto!$A$6:$K$58,9,FALSE) -> 0 | K69: =VLOOKUP(B69,Presupuesto!$A$6:$K$58,10,FALSE) -> 44367.324 | L69: =E69*K69 -> 44367.324
B70: ='Listado actividades'!A88 -> 2.2 | C70: =VLOOKUP(B70,APU_P!$A$3:$M$59,2,FALSE) -> INSTALACIÓN DE PLACAS DE IDENTIFICACIÓN DE POSTE, (INCLUYE PLACA DE ALUMINIO, CINTA BAND IT Y HEBILLA) | D70: =VLOOKUP(B70,Presupuesto!$A$6:$K$58,3,FALSE) -> UND | E70: =VLOOKUP(B70,'Listado actividades'!$A$78:$C$94,3,FALSE) -> 1 | F70: =VLOOKUP(B70,Presupuesto!$A$6:$K$58,5,FALSE) -> 19590 | G70: =VLOOKUP(B70,Presupuesto!$A$6:$K$58,6,FALSE) -> 14760.758 | H70: =VLOOKUP(B70,Presupuesto!$A$6:$K$58,7,FALSE) -> 3485.0583 | I70: =VLOOKUP(B70,Presupuesto!$A$6:$K$58,8,FALSE) -> 0 | J70: =VLOOKUP(B70,Presupuesto!$A$6:$K$58,9,FALSE) -> 0 | K70: =VLOOKUP(B70,Presupuesto!$A$6:$K$58,10,FALSE) -> 37835.817 | L70: =E70*K70 -> 37835.817
B71: ='Listado actividades'!A89 -> 4.1 | C71: =VLOOKUP(B71,APU_P!$A$3:$M$59,2,FALSE) -> SUMINISTRO DE MATERIALES PARA LA ESTRUCTURA P103 N2 | D71: =VLOOKUP(B71,Presupuesto!$A$6:$K$58,3,FALSE) -> UND | E71: =VLOOKUP(B71,'Listado actividades'!$A$78:$C$94,3,FALSE) -> 1 | F71: =VLOOKUP(B71,Presupuesto!$A$6:$K$58,5,FALSE) -> 387643.28 | G71: =VLOOKUP(B71,Presupuesto!$A$6:$K$58,6,FALSE) -> 0 | H71: =VLOOKUP(B71,Presupuesto!$A$6:$K$58,7,FALSE) -> 0 | I71: =VLOOKUP(B71,Presupuesto!$A$6:$K$58,8,FALSE) -> 42000 | J71: =VLOOKUP(B71,Presupuesto!$A$6:$K$58,9,FALSE) -> 0 | K71: =VLOOKUP(B71,Presupuesto!$A$6:$K$58,10,FALSE) -> 429643.28 | L71: =E71*K71 -> 429643.28
... B76: ='Listado actividades'!A94 -> 4.16 | C76: =VLOOKUP(B76,APU_P!$A$3:$M$59,2,FALSE) -> SUMINISTRO DE POSTE DE CONCRETO DE 14 M X 750 KGF VIBRADO Y REFORZADO | D76: =VLOOKUP(B76,Presupuesto!$A$6:$K$58,3,FALSE) -> UND | E76: =VLOOKUP(B76,'Listado actividades'!$A$78:$C$94,3,FALSE) -> 1 | F76: =VLOOKUP(B76,Presupuesto!$A$6:$K$58,5,FALSE) -> 2073445 | G76: =VLOOKUP(B76,Presupuesto!$A$6:$K$58,6,FALSE) -> 0 | H76: =VLOOKUP(B76,Presupuesto!$A$6:$K$58,7,FALSE) -> 0 | I76: =VLOOKUP(B76,Presupuesto!$A$6:$K$58,8,FALSE) -> 105000 | J76: =VLOOKUP(B76,Presupuesto!$A$6:$K$58,9,FALSE) -> 0 | K76: =VLOOKUP(B76,Presupuesto!$A$6:$K$58,10,FALSE) -> 2178445 | L76: =E76*K76 -> 2178445
A77: E95B | B77: ACTIVIDAD | C77: Se realizará la desvestida y deshincada de poste de 14m. Se realizará la excavación e hincada de un poste de 14m 750kg en las coordenadas especificadas en el plano. Se instalarán estructuras trifásicas de tipo paso P102N2 y P103N3. Además se harán excavaciones de viguetas para instalación de templetes, junto con la instalación del sistema de puesta a tierra. Al poste se le instalarán placas de peligro de red energizada y de identificación. | D77: GLB | E77: 1 | F77: =SUM(F78:F97) -> 3500370.1 | G77: =SUM(G78:G97) -> 1335066.8 | H77: =SUM(H78:H97) -> 1195294.8 | I77: =SUM(I78:I97) -> 420000 | J77: =SUM(J78:J97) -> 0 | K77: =SUM(K78:K97) -> 6450731.7 | L77: =SUM(L78:L97) -> 7005378.1
B78: ='Listado actividades'!A98 -> 1.2 | C78: =VLOOKUP(B78,APU_P!$A$3:$M$59,2,FALSE) -> APERTURA DE EXCAVACION POSTE DE 14 MTS M.T. RURAL | D78: =VLOOKUP(B78,Presupuesto!$A$6:$K$58,3,FALSE) -> UND | E78: =VLOOKUP(B78,'Listado actividades'!$A$98:$C$118,3,FALSE) -> 1 | F78: =VLOOKUP(B78,Presupuesto!$A$6:$K$58,5,FALSE) -> 0 | G78: =VLOOKUP(B78,Presupuesto!$A$6:$K$58,6,FALSE) -> 184872.77 | H78: =VLOOKUP(B78,Presupuesto!$A$6:$K$58,7,FALSE) -> 23233.722 | I78: =VLOOKUP(B78,Presupuesto!$A$6:$K$58,8,FALSE) -> 0 | J78: =VLOOKUP(B78,Presupuesto!$A$6:$K$58,9,FALSE) -> 0 | K78: =VLOOKUP(B78,Presupuesto!$A$6:$K$58,10,FALSE) -> 208106.49 | L78: =K78*E78 -> 208106.49
B79: ='Listado actividades'!A99 -> 1.3 | C79: =VLOOKUP(B79,APU_P!$A$3:$M$59,2,FALSE) -> APERTURA DE EXCAVACION PARA VIGUETA EN RETENIDA RURAL | D79: =VLOOKUP(B79,Presupuesto!$A$6:$K$58,3,FALSE) -> UND | E79: =VLOOKUP(B79,'Listado actividades'!$A$98:$C$118,3,FALSE) -> 2 | F79: =VLOOKUP(B79,Presupuesto!$A$6:$K$58,5,FALSE) -> 0 | G79: =VLOOKUP(B79,Presupuesto!$A$6:$K$58,6,FALSE) -> 83520.324 | H79: =VLOOKUP(B79,Presupuesto!$A$6:$K$58,7,FALSE) -> 8712.6456 | I79: =VLOOKUP(B79,Presupuesto!$A$6:$K$58,8,FALSE) -> 0 | J79: =VLOOKUP(B79,Presupuesto!$A$6:$K$58,9,FALSE) -> 0 | K79: =VLOOKUP(B79,Presupuesto!$A$6:$K$58,10,FALSE) -> 92232.969 | L79: =K79*E79 -> 184465.94
B80: ='Listado actividades'!A100 -> 1.6 | C80: =VLOOKUP(B80,APU_P!$A$3:$M$59,2,FALSE) -> HINCADA, PLOMADA Y ORIENTACIÓN DE POSTE DE 14, 16 Y 18 MTS CON GRUA | D80: =VLOOKUP(B80,Presupuesto!$A$6:$K$58,3,FALSE) -> UND | E80: =VLOOKUP(B80,'Listado actividades'!$A$98:$C$118,3,FALSE) -> 1 | F80: =VLOOKUP(B80,Presupuesto!$A$6:$K$58,5,FALSE) -> 0 | G80: =VLOOKUP(B80,Presupuesto!$A$6:$K$58,6,FALSE) -> 109533.17 | H80: =VLOOKUP(B80,Presupuesto!$A$6:$K$58,7,FALSE) -> 308712.65 | I80: =VLOOKUP(B80,Presupuesto!$A$6:$K$58,8,FALSE) -> 0 | J80: =VLOOKUP(B80,Presupuesto!$A$6:$K$58,9,FALSE) -> 0 | K80: =VLOOKUP(B80,Presupuesto!$A$6:$K$58,10,FALSE) -> 418245.81 | L80: =K80*E80 -> 418245.81
B81: ='Listado actividades'!A101 -> 1.7 | C81: =VLOOKUP(B81,APU_P!$A$3:$M$59,2,FALSE) -> INSTALACION LINE A TIERRA MEDIA TENSION | D81: =VLOOKUP(B81,Presupuesto!$A$6:$K$58,3,FALSE) -> UND | E81: =VLOOKUP(B81,'Listado actividades'!$A$98:$C$118,3,FALSE) -> 1 | F81: =VLOOKUP(B81,Presupuesto!$A$6:$K$58,5,FALSE) -> 0 | G81: =VLOOKUP(B81,Presupuesto!$A$6:$K$58,6,FALSE) -> 136919.2 | H81: =VLOOKUP(B81,Presupuesto!$A$6:$K$58,7,FALSE) -> 6970.1165 | I81: =VLOOKUP(B81,Presupuesto!$A$6:$K$58,8,FALSE) -> 0 | J81: =VLOOKUP(B81,Presupuesto!$A$6:$K$58,9,FALSE) -> 0 | K81: =VLOOKUP(B81,Presupuesto!$A$6:$K$58,10,FALSE) -> 143889.32 | L81: =K81*E81 -> 143889.32
B82: ='Listado actividades'!A102 -> 1.12 | C82: =VLOOKUP(B82,APU_P!$A$3:$M$59,2,FALSE) -> TRANSPORTE DE POSTE 14 MTS M.T. RURAL DE BODEGA A SITIO CERCANO | D82: =VLOOKUP(B82,Presupuesto!$A$6:$K$58,3,FALSE) -> UND | E82: =VLOOKUP(B82,'Listado actividades'!$A$98:$C$118,3,FALSE) -> 1 | F82: =VLOOKUP(B82,Presupuesto!$A$6:$K$58,5,FALSE) -> 0 | G82: =VLOOKUP(B82,Presupuesto!$A$6:$K$58,6,FALSE) -> 77975.29 | H82: =VLOOKUP(B82,Presupuesto!$A$6:$K$58,7,FALSE) -> 294701.17 | I82: =VLOOKUP(B82,Presupuesto!$A$6:$K$58,8,FALSE) -> 0 | J82: =VLOOKUP(B82,Presupuesto!$A$6:$K$58,9,FALSE) -> 0 | K82: =VLOOKUP(B82,Presupuesto!$A$6:$K$58,10,FALSE) -> 372676.45 | L82: =K82*E82 -> 372676.45
B83: ='Listado actividades'!A103 -> 1.15 | C83: =VLOOKUP(B83,APU_P!$A$3:$M$59,2,FALSE) -> VESTIDA DE ESTRUCTURA TRIFASICA DE PASO UN POSTE 13,8kV | D83: =VLOOKUP(B83,Presupuesto!$A$6:$K$58,3,FALSE) -> UND | E83: =VLOOKUP(B83,'Listado actividades'!$A$98:$C$118,3,FALSE) -> 1 | F83: =VLOOKUP(B83,Presupuesto!$A$6:$K$58,5,FALSE) -> 0 | G83: =VLOOKUP(B83,Presupuesto!$A$6:$K$58,6,FALSE) -> 67418.622 | H83: =VLOOKUP(B83,Presupuesto!$A$6:$K$58,7,FALSE) -> 8712.6456 | I83: =VLOOKUP(B83,Presupuesto!$A$6:$K$58,8,FALSE) -> 26250 | J83: =VLOOKUP(B83,Presupuesto!$A$6:$K$58,9,FALSE) -> 0 | K83: =VLOOKUP(B83,Presupuesto!$A$6:$K$58,10,FALSE) -> 102381.27 | L83: =K83*E83 -> 102381.27
B84: ='Listado actividades'!A104 -> 1.17 | C84: =VLOOKUP(B84,APU_P!$A$3:$M$59,2,FALSE) -> VESTIDA DE ESTRUCTURA TRIFASICA DE UN POSTE TIPO PASO 34.5 KV | D84: =VLOOKUP(B84,Presupuesto!$A$6:$K$58,3,FALSE) -> UND | E84: =VLOOKUP(B84,'Listado actividades'!$A$98:$C$118,3,FALSE) -> 1 | F84: =VLOOKUP(B84,Presupuesto!$A$6:$K$58,5,FALSE) -> 0 | G84: =VLOOKUP(B84,Presupuesto!$A$6:$K$58,6,FALSE) -> 184702.7 | H84: =VLOOKUP(B84,Presupuesto!$A$6:$K$58,7,FALSE) -> 17425.291 | I84: =VLOOKUP(B84,Presupuesto!$A$6:$K$58,8,FALSE) -> 52500 | J84: =VLOOKUP(B84,Presupuesto!$A$6:$K$58,9,FALSE) -> 0 | K84: =VLOOKUP(B84,Presupuesto!$A$6:$K$58,10,FALSE) -> 254628 | L84: =K84*E84 -> 254628
B85: ='Listado actividades'!A105 -> 1.20 | C85: =VLOOKUP(B85,APU_P!$A$3:$M$59,2,FALSE) -> VESTIDA ESTRUCTURA CABLE DE GUARDA DE PASO | D85: =VLOOKUP(B85,Presupuesto!$A$6:$K$58,3,FALSE) -> UND | E85: =VLOOKUP(B85,'Listado actividades'!$A$98:$C$118,3,FALSE) -> 1 | F85: =VLOOKUP(B85,Presupuesto!$A$6:$K$58,5,FALSE) -> 0 | G85: =VLOOKUP(B85,Presupuesto!$A$6:$K$58,6,FALSE) -> 57273.791 | H85: =VLOOKUP(B85,Presupuesto!$A$6:$K$58,7,FALSE) -> 8712.6456 | I85: =VLOOKUP(B85,Presupuesto!$A$6:$K$58,8,FALSE) -> 26250 | J85: =VLOOKUP(B85,Presupuesto!$A$6:$K$58,9,FALSE) -> 0 | K85: =VLOOKUP(B85,Presupuesto!$A$6:$K$58,10,FALSE) -> 92236.437 | L85: =K85*E85 -> 92236.437
B86: ='Listado actividades'!A106 -> 1.22 | C86: =VLOOKUP(B86,APU_P!$A$3:$M$59,2,FALSE) -> DESVESTIDA ESTRUCTURA DE SUSPENSION MT RURAL | D86: =VLOOKUP(B86,Presupuesto!$A$6:$K$58,3,FALSE) -> UND | E86: =VLOOKUP(B86,'Listado actividades'!$A$98:$C$118,3,FALSE) -> 1 | F86: =VLOOKUP(B86,Presupuesto!$A$6:$K$58,5,FALSE) -> 0 | G86: =VLOOKUP(B86,Presupuesto!$A$6:$K$58,6,FALSE) -> 95832.542 | H86: =VLOOKUP(B86,Presupuesto!$A$6:$K$58,7,FALSE) -> 4646.7443 | I86: =VLOOKUP(B86,Presupuesto!$A$6:$K$58,8,FALSE) -> 0 | J86: =VLOOKUP(B86,Presupuesto!$A$6:$K$58,9,FALSE) -> 0 | K86: =VLOOKUP(B86,Presupuesto!$A$6:$K$58,10,FALSE) -> 100479.29 | L86: =K86*E86 -> 100479.29
B87: ='Listado actividades'!A107 -> 1.23 | C87: =VLOOKUP(B87,APU_P!$A$3:$M$59,2,FALSE) -> DESHINCADA DE POSTES 10, 12 Y 14 mts MT | D87: =VLOOKUP(B87,Presupuesto!$A$6:$K$58,3,FALSE) -> UND | E87: =VLOOKUP(B87,'Listado actividades'!$A$98:$C$118,3,FALSE) -> 1 | F87: =VLOOKUP(B87,Presupuesto!$A$6:$K$58,5,FALSE) -> 0 | G87: =VLOOKUP(B87,Presupuesto!$A$6:$K$58,6,FALSE) -> 188203.38 | H87: =VLOOKUP(B87,Presupuesto!$A$6:$K$58,7,FALSE) -> 339701.17 | I87: =VLOOKUP(B87,Presupuesto!$A$6:$K$58,8,FALSE) -> 0 | J87: =VLOOKUP(B87,Presupuesto!$A$6:$K$58,9,FALSE) -> 0 | K87: =VLOOKUP(B87,Presupuesto!$A$6:$K$58,10,FALSE) -> 527904.55 | L87: =K87*E87 -> 527904.55
B88: ='Listado actividades'!A108 -> 1.24 | C88: =VLOOKUP(B88,APU_P!$A$3:$M$59,2,FALSE) -> INSTALACIÓN DE TEMPLETE SENCILLO CON TODOS SUS ACCESORIOS M.T. RURAL | D88: =VLOOKUP(B88,Presupuesto!$A$6:$K$58,3,FALSE) -> UND | E88: =VLOOKUP(B88,'Listado actividades'!$A$98:$C$118,3,FALSE) -> 2 | F88: =VLOOKUP(B88,Presupuesto!$A$6:$K$58,5,FALSE) -> 0 | G88: =VLOOKUP(B88,Presupuesto!$A$6:$K$58,6,FALSE) -> 82136.989 | H88: =VLOOKUP(B88,Presupuesto!$A$6:$K$58,7,FALSE) -> 3872.2869 | I88: =VLOOKUP(B88,Presupuesto!$A$6:$K$58,8,FALSE) -> 0 | J88: =VLOOKUP(B88,Presupuesto!$A$6:$K$58,9,FALSE) -> 0 | K88: =VLOOKUP(B88,Presupuesto!$A$6:$K$58,10,FALSE) -> 86009.275 | L88: =K88*E88 -> 172018.55
B89: ='Listado actividades'!A110 -> 1.26 | C89: =VLOOKUP(B89,APU_P!$A$3:$M$59,2,FALSE) -> TRANSPORTE DE POSTE RURAL DE SITIO CERCANO A BODEGA EH | D89: =VLOOKUP(B89,Presupuesto!$A$6:$K$58,3,FALSE) -> UND | E89: =VLOOKUP(B89,'Listado actividades'!$A$98:$C$118,3,FALSE) -> 1 | F89: =VLOOKUP(B89,Presupuesto!$A$6:$K$58,5,FALSE) -> 0 | G89: =VLOOKUP(B89,Presupuesto!$A$6:$K$58,6,FALSE) -> 46034.989 | H89: =VLOOKUP(B89,Presupuesto!$A$6:$K$58,7,FALSE) -> 162923.6 | I89: =VLOOKUP(B89,Presupuesto!$A$6:$K$58,8,FALSE) -> 0 | J89: =VLOOKUP(B89,Presupuesto!$A$6:$K$58,9,FALSE) -> 0 | K89: =VLOOKUP(B89,Presupuesto!$A$6:$K$58,10,FALSE) -> 208958.59 | L89: =K89*E89 -> 208958.59
B90: ='Listado actividades'!A111 -> 2.1 | C90: =VLOOKUP(B90,APU_P!$A$3:$M$59,2,FALSE) -> INSTALACIÓN DE PLACAS DE IDENTIFICACIÓN DE PELIGRO RED ENERGIZADA (INCLUYE PLACA EN ACRILICO Y CONECTORES A RED) | D90: =VLOOKUP(B90,Presupuesto!$A$6:$K$58,3,FALSE) -> UND | E90: =VLOOKUP(B90,'Listado actividades'!$A$98:$C$118,3,FALSE) -> 1 | F90: =VLOOKUP(B90,Presupuesto!$A$6:$K$58,5,FALSE) -> 35000 | G90: =VLOOKUP(B90,Presupuesto!$A$6:$K$58,6,FALSE) -> 5882.2661 | H90: =VLOOKUP(B90,Presupuesto!$A$6:$K$58,7,FALSE) -> 3485.0583 | I90: =VLOOKUP(B90,Presupuesto!$A$6:$K$58,8,FALSE) -> 0 | J90: =VLOOKUP(B90,Presupuesto!$A$6:$K$58,9,FALSE) -> 0 | K90: =VLOOKUP(B90,Presupuesto!$A$6:$K$58,10,FALSE) -> 44367.324 | L90: =K90*E90 -> 44367.324
B91: ='Listado actividades'!A112 -> 2.2 | C91: =VLOOKUP(B91,APU_P!$A$3:$M$59,2,FALSE) -> INSTALACIÓN DE PLACAS DE IDENTIFICACIÓN DE POSTE, (INCLUYE PLACA DE ALUMINIO, CINTA BAND IT Y HEBILLA) | D91: =VLOOKUP(B91,Presupuesto!$A$6:$K$58,3,FALSE) -> UND | E91: =VLOOKUP(B91,'Listado actividades'!$A$98:$C$118,3,FALSE) -> 1 | F91: =VLOOKUP(B91,Presupuesto!$A$6:$K$58,5,FALSE) -> 19590 | G91: =VLOOKUP(B91,Presupuesto!$A$6:$K$58,6,FALSE) -> 14760.758 | H91: =VLOOKUP(B91,Presupuesto!$A$6:$K$58,7,FALSE) -> 3485.0583 | I91: =VLOOKUP(B91,Presupuesto!$A$6:$K$58,8,FALSE) -> 0 | J91: =VLOOKUP(B91,Presupuesto!$A$6:$K$58,9,FALSE) -> 0 | K91: =VLOOKUP(B91,Presupuesto!$A$6:$K$58,10,FALSE) -> 37835.817 | L91: =K91*E91 -> 37835.817
B92: ='Listado actividades'!A113 -> 4.1 | C92: =VLOOKUP(B92,APU_P!$A$3:$M$59,2,FALSE) -> SUMINISTRO DE MATERIALES PARA LA ESTRUCTURA P103 N2 | D92: =VLOOKUP(B92,Presupuesto!$A$6:$K$58,3,FALSE) -> UND | E92: =VLOOKUP(B92,'Listado actividades'!$A$98:$C$118,3,FALSE) -> 1 | F92: =VLOOKUP(B92,Presupuesto!$A$6:$K$58,5,FALSE) -> 387643.28 | G92: =VLOOKUP(B92,Presupuesto!$A$6:$K$58,6,FALSE) -> 0 | H92: =VLOOKUP(B92,Presupuesto!$A$6:$K$58,7,FALSE) -> 0 | I92: =VLOOKUP(B92,Presupuesto!$A$6:$K$58,8,FALSE) -> 42000 | J92: =VLOOKUP(B92,Presupuesto!$A$6:$K$58,9,FALSE) -> 0 | K92: =VLOOKUP(B92,Presupuesto!$A$6:$K$58,10,FALSE) -> 429643.28 | L92: =K92*E92 -> 429643.28
B93: ='Listado actividades'!A114 -> 4.2 | C93: =VLOOKUP(B93,APU_P!$A$3:$M$59,2,FALSE) -> SUMINISTRO DE MATERIALES PARA LA ESTRUCTURA P103 N3 | D93: =VLOOKUP(B93,Presupuesto!$A$6:$K$58,3,FALSE) -> UND | E93: =VLOOKUP(B93,'Listado actividades'!$A$98:$C$118,3,FALSE) -> 1 | F93: =VLOOKUP(B93,Presupuesto!$A$6:$K$58,5,FALSE) -> 425060.34 | G93: =VLOOKUP(B93,Presupuesto!$A$6:$K$58,6,FALSE) -> 0 | H93: =VLOOKUP(B93,Presupuesto!$A$6:$K$58,7,FALSE) -> 0 | I93: =VLOOKUP(B93,Presupuesto!$A$6:$K$58,8,FALSE) -> 42000 | J93: =VLOOKUP(B93,Presupuesto!$A$6:$K$58,9,FALSE) -> 0 | K93: =VLOOKUP(B93,Presupuesto!$A$6:$K$58,10,FALSE) -> 467060.34 | L93: =K93*E93 -> 467060.34
B94: ='Listado actividades'!A115 -> 4.6 | C94: =VLOOKUP(B94,APU_P!$A$3:$M$59,2,FALSE) -> SUMINISTRO DE MATERIALES PARA LA ESTRUCTURA DE HILO DE GUARDA INDEPENDIENTE PARA ESTRUCTURA TIPO PASO HG-P | D94: =VLOOKUP(B94,Presupuesto!$A$6:$K$58,3,FALSE) -> UND | E94: =VLOOKUP(B94,'Listado actividades'!$A$98:$C$118,3,FALSE) -> 1 | F94: =VLOOKUP(B94,Presupuesto!$A$6:$K$58,5,FALSE) -> 107297.16 | G94: =VLOOKUP(B94,Presupuesto!$A$6:$K$58,6,FALSE) -> 0 | H94: =VLOOKUP(B94,Presupuesto!$A$6:$K$58,7,FALSE) -> 0 | I94: =VLOOKUP(B94,Presupuesto!$A$6:$K$58,8,FALSE) -> 42000 | J94: =VLOOKUP(B94,Presupuesto!$A$6:$K$58,9,FALSE) -> 0 | K94: =VLOOKUP(B94,Presupuesto!$A$6:$K$58,10,FALSE) -> 149297.16 | L94: =K94*E94 -> 149297.16
B95: ='Listado actividades'!A116 -> 4.11 | C95: =VLOOKUP(B95,APU_P!$A$3:$M$59,2,FALSE) -> SUMINISTRO DE TEMPLETE DIRECTO A VARILLA DE ANCLAJE 34.5 KV | D95: =VLOOKUP(B95,Presupuesto!$A$6:$K$58,3,FALSE) -> UND | E95: =VLOOKUP(B95,'Listado actividades'!$A$98:$C$118,3,FALSE) -> 2 | F95: =VLOOKUP(B95,Presupuesto!$A$6:$K$58,5,FALSE) -> 334404.16 | G95: =VLOOKUP(B95,Presupuesto!$A$6:$K$58,6,FALSE) -> 0 | H95: =VLOOKUP(B95,Presupuesto!$A$6:$K$58,7,FALSE) -> 0 | I95: =VLOOKUP(B95,Presupuesto!$A$6:$K$58,8,FALSE) -> 42000 | J95: =VLOOKUP(B95,Presupuesto!$A$6:$K$58,9,FALSE) -> 0 | K95: =VLOOKUP(B95,Presupuesto!$A$6:$K$58,10,FALSE) -> 376404.16 | L95: =K95*E95 -> 752808.32
B96: ='Listado actividades'!A117 -> 4.12 | C96: =VLOOKUP(B96,APU_P!$A$3:$M$59,2,FALSE) -> SUMINISTRO DE SISTEMA DE PUESTA A TIERRA REDES TRIFASICAS CON CABLE DE GUARDA POSTE SENCILLO | D96: =VLOOKUP(B96,Presupuesto!$A$6:$K$58,3,FALSE) -> UND | E96: =VLOOKUP(B96,'Listado actividades'!$A$98:$C$118,3,FALSE) -> 1 | F96: =VLOOKUP(B96,Presupuesto!$A$6:$K$58,5,FALSE) -> 117930.21 | G96: =VLOOKUP(B96,Presupuesto!$A$6:$K$58,6,FALSE) -> 0 | H96: =VLOOKUP(B96,Presupuesto!$A$6:$K$58,7,FALSE) -> 0 | I96: =VLOOKUP(B96,Presupuesto!$A$6:$K$58,8,FALSE) -> 42000 | J96: =VLOOKUP(B96,Presupuesto!$A$6:$K$58,9,FALSE) -> 0 | K96: =VLOOKUP(B96,Presupuesto!$A$6:$K$58,10,FALSE) -> 159930.21 | L96: =K96*E96 -> 159930.21
B97: ='Listado actividades'!A118 -> 4.16 | C97: =VLOOKUP(B97,APU_P!$A$3:$M$59,2,FALSE) -> SUMINISTRO DE POSTE DE CONCRETO DE 14 M X 750 KGF VIBRADO Y REFORZADO | D97: =VLOOKUP(B97,Presupuesto!$A$6:$K$58,3,FALSE) -> UND | E97: =VLOOKUP(B97,'Listado actividades'!$A$98:$C$118,3,FALSE) -> 1 | F97: =VLOOKUP(B97,Presupuesto!$A$6:$K$58,5,FALSE) -> 2073445 | G97: =VLOOKUP(B97,Presupuesto!$A$6:$K$58,6,FALSE) -> 0 | H97: =VLOOKUP(B97,Presupuesto!$A$6:$K$58,7,FALSE) -> 0 | I97: =VLOOKUP(B97,Presupuesto!$A$6:$K$58,8,FALSE) -> 105000 | J97: =VLOOKUP(B97,Presupuesto!$A$6:$K$58,9,FALSE) -> 0 | K97: =VLOOKUP(B97,Presupuesto!$A$6:$K$58,10,FALSE) -> 2178445 | L97: =K97*E97 -> 2178445
A98: E95A | B98: ACTIVIDAD | C98: Se reemplazará el poste de concreto de 14m por uno de 16m 1350 kg, se debe desvestir las estructuras instaladas y retirar el poste. Posteriormente se hincará y vestirá el nuevo poste con las estructuras trifásicas 560 N2 (tipo paso) y dos 555 N3. Además se harán excavaciones de viguetas para instalación de templetes. Al poste se le instalarán placas de peligro de red energizada y de identificación. | D98: GLB | E98: 1 | F98: =SUM(F99:F117) -> 8550494.4 | G98: =SUM(G99:G117) -> 1219943.6 | H98: =SUM(H99:H117) -> 1179114.2 | I98: =SUM(I99:I117) -> 441250 | J98: =SUM(J99:J117) -> 0 | K98: =SUM(K99:K117) -> 11390802 | L98: =SUM(L99:L117) -> 13404144
B99: ='Listado actividades'!A122 -> 1.3 | C99: =VLOOKUP(B99,APU_P!$A$3:$M$59,2,FALSE) -> APERTURA DE EXCAVACION PARA VIGUETA EN RETENIDA RURAL | D99: =VLOOKUP(B99,Presupuesto!$A$6:$K$58,3,FALSE) -> UND | E99: =VLOOKUP(B99,'Listado actividades'!$A$122:$C$141,3,FALSE) -> 3 | F99: =VLOOKUP(B99,Presupuesto!$A$6:$K$58,5,FALSE) -> 0 | G99: =VLOOKUP(B99,Presupuesto!$A$6:$K$58,6,FALSE) -> 83520.324 | H99: =VLOOKUP(B99,Presupuesto!$A$6:$K$58,7,FALSE) -> 8712.6456 | I99: =VLOOKUP(B99,Presupuesto!$A$6:$K$58,8,FALSE) -> 0 | J99: =VLOOKUP(B99,Presupuesto!$A$6:$K$58,9,FALSE) -> 0 | K99: =VLOOKUP(B99,Presupuesto!$A$6:$K$58,10,FALSE) -> 92232.969 | L99: =K99*E99 -> 276698.91
B100: ='Listado actividades'!A123 -> 1.6 | C100: =VLOOKUP(B100,APU_P!$A$3:$M$59,2,FALSE) -> HINCADA, PLOMADA Y ORIENTACIÓN DE POSTE DE 14, 16 Y 18 MTS CON GRUA | D100: =VLOOKUP(B100,Presupuesto!$A$6:$K$58,3,FALSE) -> UND | E100: =VLOOKUP(B100,'Listado actividades'!$A$122:$C$141,3,FALSE) -> 1 | F100: =VLOOKUP(B100,Presupuesto!$A$6:$K$58,5,FALSE) -> 0 | G100: =VLOOKUP(B100,Presupuesto!$A$6:$K$58,6,FALSE) -> 109533.17 | H100: =VLOOKUP(B100,Presupuesto!$A$6:$K$58,7,FALSE) -> 308712.65 | I100: =VLOOKUP(B100,Presupuesto!$A$6:$K$58,8,FALSE) -> 0 | J100: =VLOOKUP(B100,Presupuesto!$A$6:$K$58,9,FALSE) -> 0 | K100: =VLOOKUP(B100,Presupuesto!$A$6:$K$58,10,FALSE) -> 418245.81 | L100: =K100*E100 -> 418245.81
B101: ='Listado actividades'!A124 -> 1.8 | C101: =VLOOKUP(B101,APU_P!$A$3:$M$59,2,FALSE) -> INSTALACIÓN DE TEMPLETE CUERDA GUITARRA CON TODOS SUS ACCESORIOS M.T. RURAL | D101: =VLOOKUP(B101,Presupuesto!$A$6:$K$58,3,FALSE) -> UND | E101: =VLOOKUP(B101,'Listado actividades'!$A$122:$C$141,3,FALSE) -> 2 | F101: =VLOOKUP(B101,Presupuesto!$A$6:$K$58,5,FALSE) -> 0 | G101: =VLOOKUP(B101,Presupuesto!$A$6:$K$58,6,FALSE) -> 95832.542 | H101: =VLOOKUP(B101,Presupuesto!$A$6:$K$58,7,FALSE) -> 4646.7443 | I101: =VLOOKUP(B101,Presupuesto!$A$6:$K$58,8,FALSE) -> 0 | J101: =VLOOKUP(B101,Presupuesto!$A$6:$K$58,9,FALSE) -> 0 | K101: =VLOOKUP(B101,Presupuesto!$A$6:$K$58,10,FALSE) -> 100479.29 | L101: =K101*E101 -> 200958.57
B102: ='Listado actividades'!A125 -> 1.12 | C102: =VLOOKUP(B102,APU_P!$A$3:$M$59,2,FALSE) -> TRANSPORTE DE POSTE 14 MTS M.T. RURAL DE BODEGA A SITIO CERCANO | D102: =VLOOKUP(B102,Presupuesto!$A$6:$K$58,3,FALSE) -> UND | E102: =VLOOKUP(B102,'Listado actividades'!$A$122:$C$141,3,FALSE) -> 1 | F102: =VLOOKUP(B102,Presupuesto!$A$6:$K$58,5,FALSE) -> 0 | G102: =VLOOKUP(B102,Presupuesto!$A$6:$K$58,6,FALSE) -> 77975.29 | H102: =VLOOKUP(B102,Presupuesto!$A$6:$K$58,7,FALSE) -> 294701.17 | I102: =VLOOKUP(B102,Presupuesto!$A$6:$K$58,8,FALSE) -> 0 | J102: =VLOOKUP(B102,Presupuesto!$A$6:$K$58,9,FALSE) -> 0 | K102: =VLOOKUP(B102,Presupuesto!$A$6:$K$58,10,FALSE) -> 372676.45 | L102: =K102*E102 -> 372676.45
B103: ='Listado actividades'!A126 -> 1.15 | C103: =VLOOKUP(B103,APU_P!$A$3:$M$59,2,FALSE) -> VESTIDA DE ESTRUCTURA TRIFASICA DE PASO UN POSTE 13,8kV | D103: =VLOOKUP(B103,Presupuesto!$A$6:$K$58,3,FALSE) -> UND | E103: =VLOOKUP(B103,'Listado actividades'!$A$122:$C$141,3,FALSE) -> 1 | F103: =VLOOKUP(B103,Presupuesto!$A$6:$K$58,5,FALSE) -> 0 | G103: =VLOOKUP(B103,Presupuesto!$A$6:$K$58,6,FALSE) -> 67418.622 | H103: =VLOOKUP(B103,Presupuesto!$A$6:$K$58,7,FALSE) -> 8712.6456 | I103: =VLOOKUP(B103,Presupuesto!$A$6:$K$58,8,FALSE) -> 26250 | J103: =VLOOKUP(B103,Presupuesto!$A$6:$K$58,9,FALSE) -> 0 | K103: =VLOOKUP(B103,Presupuesto!$A$6:$K$58,10,FALSE) -> 102381.27 | L103: =K103*E103 -> 102381.27
B104: ='Listado actividades'!A127 -> 1.18 | C104: =VLOOKUP(B104,APU_P!$A$3:$M$59,2,FALSE) -> VESTIDA DE ESTRUCTURA TRIFASICA DE UN POSTE TIPO RETENCIÓN - 34.5 KV | D104: =VLOOKUP(B104,Presupuesto!$A$6:$K$58,3,FALSE) -> UND | E104: =VLOOKUP(B104,'Listado actividades'!$A$122:$C$141,3,FALSE) -> 1 | F104: =VLOOKUP(B104,Presupuesto!$A$6:$K$58,5,FALSE) -> 0 | G104: =VLOOKUP(B104,Presupuesto!$A$6:$K$58,6,FALSE) -> 246270.27 | H104: =VLOOKUP(B104,Presupuesto!$A$6:$K$58,7,FALSE) -> 23233.722 | I104: =VLOOKUP(B104,Presupuesto!$A$6:$K$58,8,FALSE) -> 70000 | J104: =VLOOKUP(B104,Presupuesto!$A$6:$K$58,9,FALSE) -> 0 | K104: =VLOOKUP(B104,Presupuesto!$A$6:$K$58,10,FALSE) -> 339503.99 | L104: =K104*E104 -> 339503.99
...

Sheet Cotización materiales
A1: STOCK (bodega neiva) | C1: Código | D1: Material | E1: Unidad | F1: Cantidad | G1: Precios Unitario (COP) | K1: Precio Unitario | L1: TOTAL
A2: Código | B2: Cantidad | G2: ERI | H2: Distrieléctricos | I2: Internacional de eléctricos | J2: Otros
A3: 1- 04- 05- 1756 | B3: 1 | C3: 3301 | D3: ACCESORIOS PARA TEMPLETE CUERDA GUITARRA | E3: UND | F3: =VLOOKUP(C3,$C$185:$E$229,3,FALSE) -> 5 | G3: 0 | H3: 81137 | I3: 83764 | K3: =AVERAGEIF(G3:J3,">0") -> 82450.5 | L3: =K3*F3 -> 412252.5
A4: 1- 04- 05- 0016 | B4: 459 | C4: 621 | D4: AISLADOR TIPO CARRETE. ALTURA 76,2 MM ANSI 53-3 | E4: UND | F4: =VLOOKUP(C4,$C$185:$E$229,3,FALSE) -> 3 | J4: 4200 | K4: =AVERAGEIF(G4:J4,">0") -> 4200 | L4: =K4*F4 -> 12600
A5: 1- 04- 19- 0237 | B5: 56 | C5: 601 | D5: AISLADOR TIPO DISCO DE HORQUILLA. DIAMETRO 152 MM 13,2 KV ANSI 52-1 | E5: UND | F5: =VLOOKUP(C5,$C$185:$E$228,3,FALSE) -> 36 | G5: 113243.7 | H5: 45438 | I5: 90223 | K5: =AVERAGEIF(G5:J5,">0") -> 82968.233 | L5: =K5*F5 -> 2986856.4
A6: 1- 04- 05- 1579 | B6: 60 | C6: 603 | D6: AISLADOR TIPO DISCO DE HORQUILLA. DIAMETRO 254 MM 34.5 KV ANSI 52-4 | E6: UND | F6: =VLOOKUP(C6,$C$185:$E$228,3,FALSE) -> 72 | J6: 82950 | K6: =AVERAGEIF(G6:J6,">0") -> 82950 | L6: =K6*F6 -> 5972400
A7: 1- 04- 05- 0019 | B7: 194 | C7: 611 | D7: AISLADOR TIPO ESPIGO ROSCA 25,4MM 15kV ANSI 55-5 | E7: UND | F7: =VLOOKUP(C7,$C$185:$E$228,3,FALSE) -> 10 | G7: 77352.94 | H7: 43788 | I7: 60286 | K7: =AVERAGEIF(G7:J7,">0") -> 60475.647 | L7: =K7*F7 -> 604756.47
A8: 1- 04- 05- 0018 | B8: 184 | C8: 613 | D8: AISLADOR TIPO ESPIGO ROSCA 35MM 15kV ANSI 56-3 | E8: UND | F8: =VLOOKUP(C8,$C$185:$E$228,3,FALSE) -> 10 | J8: 73900 | K8: =AVERAGEIF(G8:J8,">0") -> 73900 | L8: =K8*F8 -> 739000
A9: 1- 04- 05- 0015 | B9: 366 | C9: 634 | D9: AISLADOR TIPO TENSOR ANSI 54-4 DE 6 3/4" PARA 34.5 KV | E9: UND | F9: =VLOOKUP(C9,$C$185:$E$228,3,FALSE) -> 9 | G9: 0 | H9: 5313 | I9: 0 | K9: =AVERAGEIF(G9:J9,">0") -> 5313 | L9: =K9*F9 -> 47817
A10: 1- 04- 19- 0242 | B10: 125 | C10: 2412 | D10: ARANDELA CUADRADA PLANA DE 51*17 MM Ø= 16 MM (2"X2"X5/8") | E10: UND | F10: =VLOOKUP(C10,$C$185:$E$228,3,FALSE) -> 19 | G10: 802.52 | H10: 726 | I10: 779 | K10: =AVERAGEIF(G10:J10,">0") -> 769.17333 | L10: =K10*F10 -> 14614.293
A11: 1- 04- 05- 0023 | B11: 550 | C11: 2433 | D11: ARANDELA DE PRESIÓN DE Ø= 26 MM PARA PERNO Ø= 13 MM (1/2") | E11: UND | F11: =VLOOKUP(C11,$C$185:$E$228,3,FALSE) -> 35 | G11: 168 | H11: 121 | I11: 121 | K11: =AVERAGEIF(G11:J11,">0") -> 136.66667 | L11: =K11*F11 -> 4783.3333
A12: 1- 04- 05- 0030 | B12: 1137 | C12: 2434 | D12: ARANDELA DE PRESIÓN DE Ø= 26 MM PARA PERNO Ø= 16 MM (5/8") | E12: UND | F12: =VLOOKUP(C12,$C$185:$E$228,3,FALSE) -> 167 | G12: 310.92 | H12: 260 | I12: 164 | K12: =AVERAGEIF(G12:J12,">0") -> 244.97333 | L12: =K12*F12 -> 40910.547
C13: 5 | D13: ABATIMIENTO N2 (PARALES 1500) 12m | E13: UND | F13: 2 | J13: 3416445 | K13: =AVERAGEIF(G13:J13,">0") -> 3416445 | L13: =K13*F13 -> 6832890
C14: 6 | D14: BARRERA METÁLICA DOBLE ONDA | E14: ML | F14: 307 | J14: 329300 | K14: =AVERAGEIF(G14:J14,">0") -> 329300 | L14: =K14*F14 -> 101095100
A15: 1- 04- 05- 1589 | B15: 10 | C15: 1903 | D15: BAYONETA SENCILLA, ESTRUCTURA EN ALINEAMIETO, 2 PERFORACIONES 11/16" DE 1,5 M | E15: UND | F15: =VLOOKUP(C15,$C$185:$E$228,3,FALSE) -> 4 | G15: 96470.59 | H15: 68750 | I15: 96637 | K15: =AVERAGEIF(G15:J15,">0") -> 87285.863 | L15: =K15*F15 -> 349143.45
A16: 1- 04- 01- 0011 | B16: 7529 | C16: 2815 | D16: CABLE DE ACERO GALVANIZADO TIPO SUPERRRESISTENTE PARA TEMPLETE DE 9,5 MM CON CARGA DE ROTURA 6980 KGF | E16: M | F16: =VLOOKUP(C16,$C$185:$E$228,3,FALSE) -> 180 | G16: 5567 | H16: 5000 | I16: 0 | K16: =AVERAGEIF(G16:J16,">0") -> 5283.5 | L16: =K16*F16 -> 951030
A17: 1- 04- 01- 0020 | B17: 1450 | C17: 803 | D17: CABLE DE COBRE DESNUDO CALIBRE 4 AWG | E17: M | F17: 56 | G17: 14226.89 | H17: 13324 | I17: 16881 | K17: =AVERAGEIF(G17:J17,">0") -> 14810.63 | L17: =K17*F17 -> 829395.28
C18: 7 | D18: CABLE DE ACERO GALVANIZADO EXTRARRESISTENTE DE 1/4 SUPER GX-3000 KGF (CABLE DE GUARDA) | E18: MTS | F18: 716 | G18: 2432.77 | H18: 2572 | K18: =AVERAGEIF(G18:J18,">0") -> 2502.385 | L18: =K18*F18 -> 1791707.7
A19: 1- 04- 01- 0143 | B19: 3783 | C19: 8 | D19: CABLE ECOLÓGICO TRICAPA NO 4/0 XLPE-TK 35KV CONDUCTOR ACSR | E19: MTS | F19: 2149 | G19: 35077.863 | H19: 33947 | K19: =AVERAGEIF(G19:J19,">0") -> 34512.431 | L19: =K19*F19 -> 74167215
A20: 1- 04- 01- 0173 | B20: 8964 | C20: 9 | D20: CABLE ECOLÓGICO TRICAPA NO 2/0 XLPE-TK 35KV CONDUCTOR ACSR | E20: MTS | F20: 1470 | G20: 28388.436 | H20: 27473 | K20: =AVERAGEIF(G20:J20,">0") -> 27930.718 | L20: =K20*F20 -> 41058156
C21: 10 | D21: CAPTAFARO B/B GALVANIZADO | E21: UND | F21: 76 | J21: 6535 | K21: =AVERAGEIF(G21:J21,">0") -> 6535 | L21: =K21*F21 -> 496660
A22: 1- 04- 05- 0054 | B22: 54 | C22: 1222 | D22: COLLARÍN DE DOS SALIDAS EN PLATINA DE HIERRO GALVANIZADO. DIAMETRO DEL POSTE 15 - 20 CM | E22: UND | F22: =VLOOKUP(C22,$C$185:$E$229,3,FALSE) -> 1 | G22: 20966.39 | H22: 15193 | I22: 19759 | K22: =AVERAGEIF(G22:J22,">0") -> 18639.463 | L22: =K22*F22 -> 18639.463
C23: 1214 | D23: COLLARÍN DE UNA SALIDA EN PLATINA DE HIERRO GALVANIZADO. DIAMETRO DEL POSTE 20 - 25 CM | E23: UND | F23: =VLOOKUP(C23,$C$185:$E$228,3,FALSE) -> 7 | G23: 25630.25 | H23: 23400 | I23: 20069.7 | K23: =AVERAGEIF(G23:J23,">0") -> 23033.317 | L23: =K23*F23 -> 161233.22
C24: 1202 | D24: COLLARÍN SIN SALIDA EN PLATINA DE HIERRO GALVANIZADO. DIAMETRO DEL POSTE 15 - 20 CM | E24: UND | F24: =VLOOKUP(C24,$C$185:$E$228,3,FALSE) -> 9 | G24: 0 | H24: 17272 | I24: 0 | K24: =AVERAGEIF(G24:J24,">0") -> 17272 | L24: =K24*F24 -> 155448
A25: 1- 04- 05- 1142 | B25: 50 | C25: 1 | D25: CONECTOR DE COMPRESIÓN TIPO C EN COBRE | E25: UND | F25: =VLOOKUP(C25,$C$185:$E$228,3,FALSE) -> 8 | J25: 8400 | K25: =AVERAGEIF(G25:J25,">0") -> 8400 | L25: =K25*F25 -> 67200
A26: 1- 04- 05- 1891 | B26: 50 | C26: 2 | D26: CONECTOR DE COMPRESIÓN TIPO PALA 4 AWG DE 1 HUECO | E26: UND | F26: =VLOOKUP(C26,$C$185:$E$228,3,FALSE) -> 8 | G26: 1681.51 | H26: 1820 | I26: 1573.29 | K26: =AVERAGEIF(G26:J26,">0") -> 1691.6 | L26: =K26*F26 -> 13532.8
A27: 1- 04- 05- 1297 | B27: 38 | C27: 1021 | D27: CONECTOR DE RANURAS PARALELAS DE UN PERNO. DIMENSIONES 35*45*45 MM | E27: UND | F27: =VLOOKUP(C27,$C$185:$E$228,3,FALSE) -> 42 | G27: 3521.01 | H27: 2210 | I27: 6099 | K27: =AVERAGEIF(G27:J27,">0") -> 3943.3367 | L27: =K27*F27 -> 165620.14
A28: 1- 04- 05- 0087 | B28: 448 | C28: 41062 | D28: CONECTOR TIPO TORNILLO PARA PUESTA A TIERRA | E28: UND | F28: =VLOOKUP(C28,$C$185:$E$228,3,FALSE) -> 4 | G28: 6243.7 | H28: 0 | I28: 0 | K28: =AVERAGEIF(G28:J28,">0") -> 6243.7 | L28: =K28*F28 -> 24974.8
A29: 1- 04- 05- 0838 | B29: 275 | C29: 3 | D29: CONECTOS COMPRESIÓN TIPO H | E29: UND | F29: =VLOOKUP(C29,$C$185:$E$228,3,FALSE) -> 4 | G29: 20336.13 | H29: 23887 | I29: 17726 | K29: =AVERAGEIF(G29:J29,">0") -> 20649.71 | L29: =K29*F29 -> 82598.84
A30: 1- 04- 05- 1401 | B30: 8 | C30: 268 | D30: CRUCETA METÁLICA DE ÁNGULO GALVANIZADO DE 2 M DE LONGITUD. CALIBRE (64*64*5) MM | E30: UND | F30: =VLOOKUP(C30,$C$185:$E$228,3,FALSE) -> 27 | G30: 123075.63 | H30: 130584 | I30: 108307 | K30: =AVERAGEIF(G30:J30,">0") -> 120655.54 | L30: =K30*F30 -> 3257699.7
A31: 1- 04- 05- 0111 | B31: 177 | C31: 332 | D31: DIAGONAL RECTA EN ÁNGULO PARA CRUCETA METÁLICA DE (38*38*5)MM - LONGITUD 1100MM | E31: UND | F31: =VLOOKUP(C31,$C$185:$E$228,3,FALSE) -> 19 | G31: 0 | H31: 16635 | I31: 0 | K31: =AVERAGEIF(G31:J31,">0") -> 16635 | L31: =K31*F31 -> 316065
A32: 1- 04- 05- 0110 | B32: 283 | C32: 333 | D32: DIAGONAL RECTA EN ÁNGULO PARA CRUCETA METÁLICA DE (38*38*5)MM - LONGITUD 680MM | E32: UND | F32: =VLOOKUP(C32,$C$185:$E$228,3,FALSE) -> 16 | G32: 20697.48 | H32: 16635 | I32: 18317 | K32: =AVERAGEIF(G32:J32,">0") -> 18549.827 | L32: =K32*F32 -> 296797.23
C33: 1601 | D33: ESLABÓN EN U CON PASADOR. DIMENSIONES 51 MM 8000 KGF | E33: UND | F33: =VLOOKUP(C33,$C$185:$E$228,3,FALSE) -> 10 | J33: 12750 | K33: =AVERAGEIF(G33:J33,">0") -> 12750 | L33: =K33*F33 -> 127500
A34: 1- 04- 05- 0116 | B34: 199 | C34: 2102 | D34: ESPÁRRAGO DE HIERRO GALVANIZADO ROSCADO EN TODA SU LONGITUD, 4 TUERCAS. DIAMETRO 16 MM LONGITUD 305 MM | E34: UND | F34: =VLOOKUP(C34,$C$185:$E$228,3,FALSE) -> 12 | G34: 11445.38 | H34: 5337 | I34: 7760 | K34: =AVERAGEIF(G34:J34,">0") -> 8180.7933 | L34: =K34*F34 -> 98169.52
A35: 1- 04- 05- 0413 | B35: 23 | C35: 2103 | D35: ESPÁRRAGO DE HIERRO GALVANIZADO ROSCADO EN TODA SU LONGITUD, 4 TUERCAS. DIAMETRO 16 MM LONGITUD 356 MM | E35: UND | F35: =VLOOKUP(C35,$C$185:$E$228,3,FALSE) -> 18 | J35: 8500 | K35: =AVERAGEIF(G35:J35,">0") -> 8500 | L35: =K35*F35 -> 153000
C36: 2105 | D36: ESPÁRRAGO DE HIERRO GALVANIZADO ROSCADO EN TODA SU LONGITUD, 4 TUERCAS. DIAMETRO 16 MM LONGITUD 458 MM | E36: UND | F36: =VLOOKUP(C36,$C$185:$E$228,3,FALSE) -> 3 | J36: 9200 | K36: =AVERAGEIF(G36:J36,">0") -> 9200 | L36: =K36*F36 -> 27600
A37: 1- 04- 05- 0122 | B37: 73 | C37: 511 | D37: ESPIGO DE ACERO GALVANIZADO ALTURA 150 MM DIAMETRO 19 MM PARA CRUCETA METÁLICA | E37: UND | F37: =VLOOKUP(C37,$C$185:$E$228,3,FALSE) -> 10 | G37: 16504 | H37: 8500 | I37: 0 | J37: 0 | K37: =AVERAGEIF(G37:J37,">0") -> 12502 | L37: =K37*F37 -> 125020
A38: 1- 04- 05- 0123 | B38: 40 | C38: 512 | D38: ESPIGO DE ACERO GALVANIZADO ALTURA 330 MM DIÁMETRO 35 MM PARA CRUCETA METÁLICA | E38: UND | F38: =VLOOKUP(C38,$C$185:$E$228,3,FALSE) -> 10 | J38: 11550 | K38: =AVERAGEIF(G38:J38,">0") -> 11550 | L38: =K38*F38 -> 115500
A39: 1- 04- 05- 0656 | B39: 754 | C39: 771 | D39: GRAPA PRENSADORA. DIÁMETRO DEL CONDUCTOR 6,35MM - 9,18MM DIMENSIONES 150*15MM | E39: UND | F39: =VLOOKUP(C39,$C$185:$E$228,3,FALSE) -> 36 | G39: 31684.87 | H39: 30355 | I39: 45571 | K39: =AVERAGEIF(G39:J39,">0") -> 35870.29 | L39: =K39*F39 -> 1291330.4
C40: 711 | D40: GRAPA TERMINAL O DE RETENCIÓN EN ACERO GALVANIZADO. CONDUCTORES AWG-MCM 6 - 2/0. 6000 KGF. | E40: UND | F40: =VLOOKUP(C40,$C$185:$E$228,3,FALSE) -> 42 | G40: 31684.87 | H40: 30355 | I40: 45571 | K40: =AVERAGEIF(G40:J40,">0") -> 35870.29 | L40: =K40*F40 -> 1506552.2
A41: 1- 04- 05- 0160 | B41: 72 | C41: 701 | D41: GRAPA TERMINAL O DE RETENCIÓN EN ALEACIÓN DE ALUMINIO DE 2 PERNOS. CONDUCTORES AWG-MCM 5 - 2/0. 3000 KGF. | E41: UND | F41: =VLOOKUP(C41,$C$185:$E$228,3,FALSE) -> 4 | J41: 5000 | K41: =AVERAGEIF(G41:J41,">0") -> 5000 | L41: =K41*F41 -> 20000
C42: 1101 | D42: GUARDACABO DE ACERO GALVANIZADO PARA CABLE DE 15,87MM | E42: UND | F42: =VLOOKUP(C42,$C$185:$E$228,3,FALSE) -> 9 | G42: 0 | H42: 1788 | I42: 0 | J42: 0 | K42: =AVERAGEIF(G42:J42,">0") -> 1788 | L42: =K42*F42 -> 16092
C43: 11 | D43: MURO SEPARADOR DE CONCRETO TIPO NEW JERSEY | E43: UND | F43: 20 | J43: 458379 | K43: =AVERAGEIF(G43:J43,">0") -> 458379 | L43: =K43*F43 -> 9167580
A44: 1- 04- 05- 0202 | B44: 45 | C44: 1803 | D44: PERCHA DE HIERRO FORJADAS Y GALVANIZADAS EN CALIENTE, TRES PUESTOS | E44: UND | F44: =VLOOKUP(C44,$C$185:$E$228,3,FALSE) -> 1 | J44: 31450 | K44: =AVERAGEIF(G44:J44,">0") -> 31450 | L44: =K44*F44 -> 31450
A45: 1- 04- 05- 0210 | B45: 59 | C45: 2014 | D45: PERNO DE MÁQUINA DE HIERRO GALVANIZADO CON CABEZA Y TUERCA CUADRADA. DIAMETRO 13 MM. LARGO 51 MM. | E45: UND | F45: =VLOOKUP(C45,$C$185:$E$228,3,FALSE) -> 35 | G45: 1571 | H45: 1254 | I45: 1386 | K45: =AVERAGEIF(G45:J45,">0") -> 1403.6667 | L45: =K45*F45 -> 49128.333
A46: 1- 04- 05- 0212 | B46: 168 | C46: 2034 | D46: PERNO DE MÁQUINA DE HIERRO GALVANIZADO CON CABEZA Y TUERCA CUADRADA. DIAMETRO 16 MM. LARGO 254 MM. | E46: UND | F46: =VLOOKUP(C46,$C$185:$E$228,3,FALSE) -> 30 | G46: 6462 | H46: 5395 | I46: 5639 | K46: =AVERAGEIF(G46:J46,">0") -> 5832 | L46: =K46*F46 -> 174960 | N46: =IF(G46,0,D107) -> 0 | O46: =IF(H46,0,D107) -> 0 | P46: =IF(I46,0,D107) -> 0
A47: 1- 04- 05- 0215 | B47: 808 | C47: 2201 | D47: PERNO DE OJO – DOS TUERCAS – DIÁMETRO 16 MM – LONGITUD 102 MM | E47: UND | F47: =VLOOKUP(C47,$C$185:$E$228,3,FALSE) -> 2 | J47: 6450 | K47: =AVERAGEIF(G47:J47,">0") -> 6450 | L47: =K47*F47 -> 12900 | N47: =IF(G47,0,D108) -> GRAPA TERMINAL O DE RETENCIÓN EN ACERO GALVANIZADO. CONDUCTORES AWG-MCM 6 - 2/0. 6000 KGF. | O47: =IF(H47,0,D108) -> GRAPA TERMINAL O DE RETENCIÓN EN ACERO GALVANIZADO. CONDUCTORES AWG-MCM 6 - 2/0. 6000 KGF. | P47: =IF(I47,0,D108) -> GRAPA TERMINAL O DE RETENCIÓN EN ACERO GALVANIZADO. CONDUCTORES AWG-MCM 6 - 2/0. 6000 KGF.
C48: 2204 | D48: PERNO DE OJO – DOS TUERCAS – DIÁMETRO 16 MM – LONGITUD 254 MM | E48: UND | F48: =VLOOKUP(C48,$C$185:$E$228,3,FALSE) -> 2 | G48: 10655 | H48: 9353 | I48: 12444 | K48: =AVERAGEIF(G48:J48,">0") -> 10817.333 | L48: =K48*F48 -> 21634.667
C49: 1661 | D49: PERNO EN U PARA ESTRUCTURA EN SUSPENSIÓN 5.400KGF. 51*32*38 mm 12000 LBF | E49: UND | F49: =VLOOKUP(C49,$C$185:$E$228,3,FALSE) -> 4 | G49: 4000 | H49: 0 | I49: 8638 | K49: =AVERAGEIF(G49:J49,">0") -> 6319 | L49: =K49*F49 -> 25276 | N49: =IF(G49,0,D110) -> 0 | O49: =IF(H49,0,D110) -> ESLABÓN EN U CON PASADOR. DIMENSIONES 51 MM 8000 KGF | P49: =IF(I49,0,D110) -> 0
A50: 1- 08- 04- 0018 | B50: 2 | C50: 12 | D50: POSTE DE CONCRETO DE 14 MTS X 750 REFORZADO Y VIBRADO | E50: UND | F50: 2 | H50: 2073445 | K50: =AVERAGEIF(G50:J50,">0") -> 2073445 | L50: =K50*F50 -> 4146890
A51: 1- 08- 04- 0079 | B51: 5 | C51: 13 | D51: POSTE DE CONCRETO DE 14 MTS X 1050 REFORZADO Y VIBRADO | E51: UND | F51: 1 | G51: 2941176 | H51: 2859400 | I51: 3339491 | K51: =AVERAGEIF(G51:J51,">0") -> 3046689 | L51: =K51*F51 -> 3046689
C52: 14 | D52: POSTE DE CONCRETO DE 16 MTS X 1350 REFORZADO Y VIBRADO | E52: UND | F52: 2 | G52: 5181848.7 | H52: 4210252 | K52: =AVERAGEIF(G52:J52,">0") -> 4696050.4 | L52: =K52*F52 -> 9392100.7
C53: 4 | D53: TORNILLO EN ACERO GALVANIZADO DE CABEZA Y TUERCA HEXAGONAL 3/8" X 1" CON ARNDELA REDONDA DE 3/8" | E53: UND | F53: =VLOOKUP(C53,$C$185:$E$228,3,FALSE) -> 8 | J53: 600 | K53: =AVERAGEIF(G53:J53,">0") -> 600 | L53: =K53*F53 -> 4800 | N53: =IF(G53,0,D111) -> PERNO DE MÁQUINA DE HIERRO GALVANIZADO CON CABEZA Y TUERCA CUADRADA. DIAMETRO 13 MM. LARGO 51 MM. | O53: =IF(H53,0,D111) -> PERNO DE MÁQUINA DE HIERRO GALVANIZADO CON CABEZA Y TUERCA CUADRADA. DIAMETRO 13 MM. LARGO 51 MM. | P53: =IF(I53,0,D111) -> PERNO DE MÁQUINA DE HIERRO GALVANIZADO CON CABEZA Y TUERCA CUADRADA. DIAMETRO 13 MM. LARGO 51 MM.
A54: 1- 04- 05- 0245 | B54: 248 | C54: 2512 | D54: TUERCA DE OJO ALARGADO PARA PERNO 16 MM | E54: UND | F54: =VLOOKUP(C54,$C$185:$E$228,3,FALSE) -> 42 | G54: 15840 | H54: 13170 | I54: 14286 | K54: =AVERAGEIF(G54:J54,">0") -> 14432 | L54: =K54*F54 -> 606144 | N54: =IF(G54,0,D112) -> 0 | O54: =IF(H54,0,D112) -> 0 | P54: =IF(I54,0,D112) -> 0
A55: 1- 04- 05- 0259 | B55: 146 | C55: 2601 | D55: VARILLA DE ANCLAJE CON OJO - DIÁMETRO 16MM LONGITUD 1,8M | E55: UND | F55: =VLOOKUP(C55,$C$185:$E$228,3,FALSE) -> 9 | G55: 0 | H55: 39879 | I55: 0 | K55: =AVERAGEIF(G55:J55,">0") -> 39879 | L55: =K55*F55 -> 358911 | N55: =IF(G55,0,D113) -> ESPÁRRAGO DE HIERRO GALVANIZADO ROSCADO EN TODA SU LONGITUD, 4 TUERCAS. DIAMETRO 16 MM LONGITUD 458 MM | O55: =IF(H55,0,D113) -> 0 | P55: =IF(I55,0,D113) -> ESPÁRRAGO DE HIERRO GALVANIZADO ROSCADO EN TODA SU LONGITUD, 4 TUERCAS. DIAMETRO 16 MM LONGITUD 458 MM
A56: 1- 04- 19- 0166 | B56: 96 | C56: 1411 | D56: VARILLA DE PUESTA A TIERRA DE 15,88*2438 MM | E56: UND | F56: =VLOOKUP(C56,$C$185:$E$228,3,FALSE) -> 4 | G56: 50924 | H56: 39879 | I56: 142857 | K56: =AVERAGEIF(G56:J56,">0") -> 77886.667 | L56: =K56*F56 -> 311546.67 | N56: =IF(G56,0,D114) -> 0 | O56: =IF(H56,0,D114) -> 0 | P56: =IF(I56,0,D114) -> 0 | V56: 0 | W56: 3400
A57: 1- 04- 19- 0321 | B57: 4 | C57: 2701 | D57: VIGUETA DE ANCLAJE FE=2500 PSI ES=1400K/CM^2 | E57: UND | F57: =VLOOKUP(C57,$C$185:$E$228,3,FALSE) -> 9 | G57: 0 | H57: 21001 | I57: 0 | K57: =AVERAGEIF(G57:J57,">0") -> 21001 | L57: =K57*F57 -> 189009 | N57: =IF(G57,0,D115) -> ARANDELA DE PRESIÓN DE Ø= 26 MM PARA PERNO Ø= 16 MM (5/8") | O57: =IF(H57,0,D115) -> 0 | P57: =IF(I57,0,D115) -> ARANDELA DE PRESIÓN DE Ø= 26 MM PARA PERNO Ø= 16 MM (5/8") | V57: 0 | W57: 81137
C58: 15 | D58: CONCRETO IMPERMEABLE 3000 PSI | E58: m3 | F58: 3.76 | J58: 645156 | K58: =AVERAGEIF(G58:J58,">0") -> 645156 | L58: =K58*F58 -> 2425786.6
L59: =SUM(L3:L58) -> 2.7641267e+08 | V59: 113243.7 | W59: 45438
V60: 77352.94 | W60: 43788
V61: 0 | W61: 5313
N62: =IF(G62,0,D119) -> AISLADOR TIPO DISCO DE HORQUILLA. DIAMETRO 254 MM 34.5 KV ANSI 52-4 | O62: =IF(H62,0,D119) -> AISLADOR TIPO DISCO DE HORQUILLA. DIAMETRO 254 MM 34.5 KV ANSI 52-4 | P62: =IF(I62,0,D119) -> AISLADOR TIPO DISCO DE HORQUILLA. DIAMETRO 254 MM 34.5 KV ANSI 52-4 | V62: 802.52 | W62: 726
N63: =IF(G63,0,D120) -> GRAPA TERMINAL O DE RETENCIÓN EN ACERO GALVANIZADO. CONDUCTORES AWG-MCM 6 - 2/0. 6000 KGF. | O63: =IF(H63,0,D120) -> GRAPA TERMINAL O DE RETENCIÓN EN ACERO GALVANIZADO. CONDUCTORES AWG-MCM 6 - 2/0. 6000 KGF. | P63: =IF(I63,0,D120) -> GRAPA TERMINAL O DE RETENCIÓN EN ACERO GALVANIZADO. CONDUCTORES AWG-MCM 6 - 2/0. 6000 KGF. | V63: 168.07 | W63: 121
N64: =IF(G64,0,D121) -> CONECTOR DE RANURAS PARALELAS DE UN PERNO. DIMENSIONES 35*45*45 MM | O64: =IF(H64,0,D121) -> CONECTOR DE RANURAS PARALELAS DE UN PERNO. DIMENSIONES 35*45*45 MM | P64: =IF(I64,0,D121) -> CONECTOR DE RANURAS PARALELAS DE UN PERNO. DIMENSIONES 35*45*45 MM | V64: 310.92 | W64: 260
N65: =IF(G65,0,D122) -> PERNO DE MÁQUINA DE HIERRO GALVANIZADO CON CABEZA Y TUERCA CUADRADA. DIAMETRO 13 MM. LARGO 51 MM. | O65: =IF(H65,0,D122) -> PERNO DE MÁQUINA DE HIERRO GALVANIZADO CON CABEZA Y TUERCA CUADRADA. DIAMETRO 13 MM. LARGO 51 MM. | P65: =IF(I65,0,D122) -> PERNO DE MÁQUINA DE HIERRO GALVANIZADO CON CABEZA Y TUERCA CUADRADA. DIAMETRO 13 MM. LARGO 51 MM. | V65: 96470.59 | W65: 68750
N66: =IF(G66,0,D123) -> PERNO DE MÁQUINA DE HIERRO GALVANIZADO CON CABEZA Y TUERCA CUADRADA. DIAMETRO 16 MM. LARGO 254 MM. | O66: =IF(H66,0,D123) -> PERNO DE MÁQUINA DE HIERRO GALVANIZADO CON CABEZA Y TUERCA CUADRADA. DIAMETRO 16 MM. LARGO 254 MM. | P66: =IF(I66,0,D123) -> PERNO DE MÁQUINA DE HIERRO GALVANIZADO CON CABEZA Y TUERCA CUADRADA. DIAMETRO 16 MM. LARGO 254 MM. | V66: 5567.23 | W66: 5000
N67: =IF(G67,0,D124) -> ESPÁRRAGO DE HIERRO GALVANIZADO ROSCADO EN TODA SU LONGITUD, 4 TUERCAS. DIAMETRO 16 MM LONGITUD 356 MM | O67: =IF(H67,0,D124) -> ESPÁRRAGO DE HIERRO GALVANIZADO ROSCADO EN TODA SU LONGITUD, 4 TUERCAS. DIAMETRO 16 MM LONGITUD 356 MM | P67: =IF(I67,0,D124) -> ESPÁRRAGO DE HIERRO GALVANIZADO ROSCADO EN TODA SU LONGITUD, 4 TUERCAS. DIAMETRO 16 MM LONGITUD 356 MM | V67: 14226.89 | W67: 13324
N68: =IF(G68,#REF!,0) -> 0 | O68: =IF(H68,0,#REF!) -> #REF! | P68: =IF(I68,0,#REF!) -> #REF! | V68: 2432.77 | W68: 2572
V69: 35077.31 | W69: 33947
C70: Datos base | V70: 28388.24 | W70: 27473
C71: =P103N2!A4 -> 268 | D71: =P103N2!B4 -> CRUCETA METÁLICA DE ÁNGULO GALVANIZADO DE 2 M DE LONGITUD. CALIBRE (64*64*5) MM | E71: =P103N2!D4 -> 2
C72: =P103N2!A5 -> 332 | D72: =P103N2!B5 -> DIAGONAL RECTA EN ÁNGULO PARA CRUCETA METÁLICA DE (38*38*5)MM - LONGITUD 1100MM | E72: =P103N2!D5 -> 2
C73: =P103N2!A6 -> 511 | D73: =P103N2!B6 -> ESPIGO DE ACERO GALVANIZADO ALTURA 150 MM DIAMETRO 19 MM PARA CRUCETA METÁLICA | E73: =P103N2!D6 -> 6
C74: =P103N2!A7 -> 611 | D74: =P103N2!B7 -> AISLADOR TIPO ESPIGO ROSCA 25,4MM 15kV ANSI 55-5 | E74: =P103N2!D7 -> 6
C75: =P103N2!A8 -> 1214 | D75: =P103N2!B8 -> COLLARÍN DE UNA SALIDA EN PLATINA DE HIERRO GALVANIZADO. DIAMETRO DEL POSTE 20 - 25 CM | E75: =P103N2!D8 -> 2
C76: =P103N2!A9 -> 2014 | D76: =P103N2!B9 -> PERNO DE MÁQUINA DE HIERRO GALVANIZADO CON CABEZA Y TUERCA CUADRADA. DIAMETRO 13 MM. LARGO 51 MM. | E76: =P103N2!D9 -> 2
C77: =P103N2!A10 -> 2034 | D77: =P103N2!B10 -> PERNO DE MÁQUINA DE HIERRO GALVANIZADO CON CABEZA Y TUERCA CUADRADA. DIAMETRO 16 MM. LARGO 254 MM. | E77: =P103N2!D10 -> 2
C78: =P103N2!A11 -> 2412 | D78: =P103N2!B11 -> ARANDELA CUADRADA PLANA DE 51*17 MM Ø= 16 MM (2"X2"X5/8") | E78: =P103N2!D11 -> 2
C79: =P103N2!A12 -> 2433 | D79: =P103N2!B12 -> ARANDELA DE PRESIÓN DE Ø= 26 MM PARA PERNO Ø= 13 MM (1/2") | E79: =P103N2!D12 -> 2
C80: =P103N2!A13 -> 2434 | D80: =P103N2!B13 -> ARANDELA DE PRESIÓN DE Ø= 26 MM PARA PERNO Ø= 16 MM (5/8") | E80: =P103N2!D13 -> 2
C81: =P103N3!A4 -> 268 | D81: =P103N3!B4 -> CRUCETA METÁLICA DE ÁNGULO GALVANIZADO DE 2 M DE LONGITUD. CALIBRE (64*64*5) MM | E81: =P103N3!D4 -> 3
C82: =P103N3!A5 -> 332 | D82: =P103N3!B5 -> DIAGONAL RECTA EN ÁNGULO PARA CRUCETA METÁLICA DE (38*38*5)MM - LONGITUD 1100MM | E82: =P103N3!D5 -> 3
C83: =P103N3!A6 -> 512 | D83: =P103N3!B6 -> ESPIGO DE ACERO GALVANIZADO ALTURA 330 MM DIÁMETRO 35 MM PARA CRUCETA METÁLICA | E83: =P103N3!D6 -> 9
C84: =P103N3!A7 -> 613 | D84: =P103N3!B7 -> AISLADOR TIPO ESPIGO ROSCA 35MM 15kV ANSI 56-3 | E84: =P103N3!D7 -> 9
C85: =P103N3!A8 -> 1214 | D85: =P103N3!B8 -> COLLARÍN DE UNA SALIDA EN PLATINA DE HIERRO GALVANIZADO. DIAMETRO DEL POSTE 20 - 25 CM | E85: =P103N3!D8 -> 3
C86: =P103N3!A9 -> 2014 | D86: =P103N3!B9 -> PERNO DE MÁQUINA DE HIERRO GALVANIZADO CON CABEZA Y TUERCA CUADRADA. DIAMETRO 13 MM. LARGO 51 MM. | E86: =P103N3!D9 -> 3
C87: =P103N3!A10 -> 2034 | D87: =P103N3!B10 -> PERNO DE MÁQUINA DE HIERRO GALVANIZADO CON CABEZA Y TUERCA CUADRADA. DIAMETRO 16 MM. LARGO 254 MM. | E87: =P103N3!D10 -> 3
C88: =P103N3!A11 -> 2412 | D88: =P103N3!B11 -> ARANDELA CUADRADA PLANA DE 51*17 MM Ø= 16 MM (2"X2"X5/8") | E88: =P103N3!D11 -> 3
C89: =P103N3!A12 -> 2433 | D89: =P103N3!B12 -> ARANDELA DE PRESIÓN DE Ø= 26 MM PARA PERNO Ø= 13 MM (1/2") | E89: =P103N3!D12 -> 3
C90: =P103N3!A13 -> 2434 | D90: =P103N3!B13 -> ARANDELA DE PRESIÓN DE Ø= 26 MM PARA PERNO Ø= 16 MM (5/8") | E90: =P103N3!D13 -> 3
C91: ='560N2'!A4 -> 268 | D91: ='560N2'!B4 -> CRUCETA METÁLICA DE ÁNGULO GALVANIZADO DE 2 M DE LONGITUD. CALIBRE (64*64*5) MM | E91: ='560N2'!D4 -> 4
C92: ='560N2'!A5 -> 333 | D92: ='560N2'!B5 -> DIAGONAL RECTA EN ÁNGULO PARA CRUCETA METÁLICA DE (38*38*5)MM - LONGITUD 680MM | E92: ='560N2'!D5 -> 8
C93: ='560N2'!A6 -> 511 | D93: ='560N2'!B6 -> ESPIGO DE ACERO GALVANIZADO ALTURA 150 MM DIAMETRO 19 MM PARA CRUCETA METÁLICA | E93: ='560N2'!D6 -> 2
C94: ='560N2'!A7 -> 601 | D94: ='560N2'!B7 -> AISLADOR TIPO DISCO DE HORQUILLA. DIAMETRO 152 MM 13,2 KV ANSI 52-1 | E94: ='560N2'!D7 -> 24
C95: ='560N2'!A8 -> 611 | D95: ='560N2'!B8 -> AISLADOR TIPO ESPIGO ROSCA 25,4MM 15kV ANSI 55-5 | E95: ='560N2'!D8 -> 2
C96: ='560N2'!A9 -> 711 | D96: ='560N2'!B9 -> GRAPA TERMINAL O DE RETENCIÓN EN ACERO GALVANIZADO. CONDUCTORES AWG-MCM 6 - 2/0. 6000 KGF. | E96: ='560N2'!D9 -> 12
C97: ='560N2'!A10 -> 1021 | D97: ='560N2'!B10 -> CONECTOR DE RANURAS PARALELAS DE UN PERNO. DIMENSIONES 35*45*45 MM | E97: ='560N2'!D10 -> 12
C98: ='560N2'!A11 -> 2014 | D98: ='560N2'!B11 -> PERNO DE MÁQUINA DE HIERRO GALVANIZADO CON CABEZA Y TUERCA CUADRADA. DIAMETRO 13 MM. LARGO 51 MM. | E98: ='560N2'!D11 -> 8
C99: ='560N2'!A12 -> 2102 | D99: ='560N2'!B12 -> ESPÁRRAGO DE HIERRO GALVANIZADO ROSCADO EN TODA SU LONGITUD, 4 TUERCAS. DIAMETRO 16 MM LONGITUD 305 MM | E99: ='560N2'!D12 -> 6
C100: ='560N2'!A13 -> 2433 | D100: ='560N2'!B13 -> ARANDELA DE PRESIÓN DE Ø= 26 MM PARA PERNO Ø= 13 MM (1/2") | E100: ='560N2'!D13 -> 8
...

Sheet BD materiales
A1: Código | B1: Material
A2: 243 | B2: CRUCETA METÁLICA DE ÁNGULO GALVANIZADO DE 4 M DE LONGITUD. CALIBRE (76*76*6) MM
A3: 268 | B3: CRUCETA METÁLICA DE ÁNGULO GALVANIZADO DE 2 M DE LONGITUD. CALIBRE (64*64*5) MM
A4: 271 | B4: CRUCETA METÁLICA DE ÁNGULO GALVANIZADO DE 1,5 M DE LONGITUD. CALIBRE (63*63*5) MM
A5: 332 | B5: DIAGONAL RECTA EN ÁNGULO PARA CRUCETA METÁLICA DE (38*38*5)MM - LONGITUD 1100MM
A6: 333 | B6: DIAGONAL RECTA EN ÁNGULO PARA CRUCETA METÁLICA DE (38*38*5)MM - LONGITUD 680MM
A7: 351 | B7: DIAGONAL DE ARRIOSTRAMIENTO EN X DE 3M DE LONGITUD. CALIBRE (64*64*5) MM.
A8: 511 | B8: ESPIGO DE ACERO GALVANIZADO ALTURA 150 MM DIAMETRO 19 MM PARA CRUCETA METÁLICA
A9: 512 | B9: ESPIGO DE ACERO GALVANIZADO ALTURA 330 MM DIÁMETRO 35 MM PARA CRUCETA METÁLICA
A10: 601 | B10: AISLADOR TIPO DISCO DE HORQUILLA. DIAMETRO 152 MM 13,2 KV ANSI 52-1
A11: 603 | B11: AISLADOR TIPO DISCO DE HORQUILLA. DIAMETRO 254 MM 34.5 KV ANSI 52-4
A12: 611 | B12: AISLADOR TIPO ESPIGO ROSCA 25,4MM 15kV ANSI 55-5
A13: 613 | B13: AISLADOR TIPO ESPIGO ROSCA 35MM 15kV ANSI 56-3
... A94: 1222 | B94: COLLARÍN DE DOS SALIDAS EN PLATINA DE HIERRO GALVANIZADO. DIAMETRO DEL POSTE 15 - 20 CM

Sheet P103N2
A1: P-103 Circuito sencillo, aislamiento en espigo (PIN) disposición semibandera SIN HILO GUARDA | C1: Cantidades | E1: Cantidad de estructuras
C2: Unitaria | D2: Total
A3: Código | B3: Montaje de la Estructura | E3: =Info_P!B19 -> 2
A4: 268 | B4: =VLOOKUP(A4,'BD materiales'!$A$2:$B$93,2,FALSE) -> CRUCETA METÁLICA DE ÁNGULO GALVANIZADO DE 2 M DE LONGITUD. CALIBRE (64*64*5) MM | C4: 1 | D4: =C4*$E$3 -> 2
A5: 332 | B5: =VLOOKUP(A5,'BD materiales'!$A$2:$B$93,2,FALSE) -> DIAGONAL RECTA EN ÁNGULO PARA CRUCETA METÁLICA DE (38*38*5)MM - LONGITUD 1100MM | C5: 1 | D5: =C5*$E$3 -> 2
A6: 511 | B6: =VLOOKUP(A6,'BD materiales'!$A$2:$B$93,2,FALSE) -> ESPIGO DE ACERO GALVANIZADO ALTURA 150 MM DIAMETRO 19 MM PARA CRUCETA METÁLICA | C6: 3 | D6: =C6*$E$3 -> 6
A7: 611 | B7: =VLOOKUP(A7,'BD materiales'!$A$2:$B$93,2,FALSE) -> AISLADOR TIPO ESPIGO ROSCA 25,4MM 15kV ANSI 55-5 | C7: 3 | D7: =C7*$E$3 -> 6
A8: 1214 | B8: =VLOOKUP(A8,'BD materiales'!$A$2:$B$93,2,FALSE) -> COLLARÍN DE UNA SALIDA EN PLATINA DE HIERRO GALVANIZADO. DIAMETRO DEL POSTE 20 - 25 CM | C8: 1 | D8: =C8*$E$3 -> 2
A9: 2014 | B9: =VLOOKUP(A9,'BD materiales'!$A$2:$B$93,2,FALSE) -> PERNO DE MÁQUINA DE HIERRO GALVANIZADO CON CABEZA Y TUERCA CUADRADA. DIAMETRO 13 MM. LARGO 51 MM. | C9: 1 | D9: =C9*$E$3 -> 2
A10: 2034 | B10: =VLOOKUP(A10,'BD materiales'!$A$2:$B$93,2,FALSE) -> PERNO DE MÁQUINA DE HIERRO GALVANIZADO CON CABEZA Y TUERCA CUADRADA. DIAMETRO 16 MM. LARGO 254 MM. | C10: 1 | D10: =C10*$E$3 -> 2
A11: 2412 | B11: =VLOOKUP(A11,'BD materiales'!$A$2:$B$93,2,FALSE) -> ARANDELA CUADRADA PLANA DE 51*17 MM Ø= 16 MM (2"X2"X5/8") | C11: 1 | D11: =C11*$E$3 -> 2
A12: 2433 | B12: =VLOOKUP(A12,'BD materiales'!$A$2:$B$93,2,FALSE) -> ARANDELA DE PRESIÓN DE Ø= 26 MM PARA PERNO Ø= 13 MM (1/2") | C12: 1 | D12: =C12*$E$3 -> 2
A13: 2434 | B13: =VLOOKUP(A13,'BD materiales'!$A$2:$B$93,2,FALSE) -> ARANDELA DE PRESIÓN DE Ø= 26 MM PARA PERNO Ø= 16 MM (5/8") | C13: 1 | D13: =C13*$E$3 -> 2
A15: NOTA | B15: EL LISTADO NO CUENTA CON LA ESTRUCTURA DE HILO GUARDA

Sheet P103N3
A1: P-103 Circuito sencillo, aislamiento en espigo (PIN) disposición semibandera | C1: Cantidades | E1: Cantidad de estructuras
C2: Unitaria | D2: Total
A3: Código | B3: Montaje de la Estructura | E3: =Info_P!B21 -> 3
A4: 268 | B4: =VLOOKUP(A4,'BD materiales'!$A$2:$B$93,2,FALSE) -> CRUCETA METÁLICA DE ÁNGULO GALVANIZADO DE 2 M DE LONGITUD. CALIBRE (64*64*5) MM | C4: =SUMIF($A$20:$C$34,A4,$C$20:$C$34) -> 1 | D4: =C4*$E$3 -> 3
A5: 332 | B5: =VLOOKUP(A5,'BD materiales'!$A$2:$B$93,2,FALSE) -> DIAGONAL RECTA EN ÁNGULO PARA CRUCETA METÁLICA DE (38*38*5)MM - LONGITUD 1100MM | C5: =SUMIF($A$20:$C$34,A5,$C$20:$C$34) -> 1 | D5: =C5*$E$3 -> 3
A6: 512 | B6: =VLOOKUP(A6,'BD materiales'!$A$2:$B$93,2,FALSE) -> ESPIGO DE ACERO GALVANIZADO ALTURA 330 MM DIÁMETRO 35 MM PARA CRUCETA METÁLICA | C6: =SUMIF($A$20:$C$34,A6,$C$20:$C$34) -> 3 | D6: =C6*$E$3 -> 9
A7: 613 | B7: =VLOOKUP(A7,'BD materiales'!$A$2:$B$93,2,FALSE) -> AISLADOR TIPO ESPIGO ROSCA 35MM 15kV ANSI 56-3 | C7: =SUMIF($A$20:$C$34,A7,$C$20:$C$34) -> 3 | D7: =C7*$E$3 -> 9
A8: 1214 | B8: =VLOOKUP(A8,'BD materiales'!$A$2:$B$93,2,FALSE) -> COLLARÍN DE UNA SALIDA EN PLATINA DE HIERRO GALVANIZADO. DIAMETRO DEL POSTE 20 - 25 CM | C8: =SUMIF($A$20:$C$34,A8,$C$20:$C$34) -> 1 | D8: =C8*$E$3 -> 3
A9: 2014 | B9: =VLOOKUP(A9,'BD materiales'!$A$2:$B$93,2,FALSE) -> PERNO DE MÁQUINA DE HIERRO GALVANIZADO CON CABEZA Y TUERCA CUADRADA. DIAMETRO 13 MM. LARGO 51 MM. | C9: =SUMIF($A$20:$C$34,A9,$C$20:$C$34) -> 1 | D9: =C9*$E$3 -> 3
A10: 2034 | B10: =VLOOKUP(A10,'BD materiales'!$A$2:$B$93,2,FALSE) -> PERNO DE MÁQUINA DE HIERRO GALVANIZADO CON CABEZA Y TUERCA CUADRADA. DIAMETRO 16 MM. LARGO 254 MM. | C10: =SUMIF($A$20:$C$34,A10,$C$20:$C$34) -> 1 | D10: =C10*$E$3 -> 3
A11: 2412 | B11: =VLOOKUP(A11,'BD materiales'!$A$2:$B$93,2,FALSE) -> ARANDELA CUADRADA PLANA DE 51*17 MM Ø= 16 MM (2"X2"X5/8") | C11: =SUMIF($A$20:$C$34,A11,$C$20:$C$34) -> 1 | D11: =C11*$E$3 -> 3
A12: 2433 | B12: =VLOOKUP(A12,'BD materiales'!$A$2:$B$93,2,FALSE) -> ARANDELA DE PRESIÓN DE Ø= 26 MM PARA PERNO Ø= 13 MM (1/2") | C12: =SUMIF($A$20:$C$34,A12,$C$20:$C$34) -> 1 | D12: =C12*$E$3 -> 3
A13: 2434 | B13: =VLOOKUP(A13,'BD materiales'!$A$2:$B$93,2,FALSE) -> ARANDELA DE PRESIÓN DE Ø= 26 MM PARA PERNO Ø= 16 MM (5/8") | C13: =SUMIF($A$20:$C$34,A13,$C$20:$C$34) -> 1 | D13: =C13*$E$3 -> 3
A20: 268 | B20: =VLOOKUP(A20,[1]L.mat!$A$2:$B$83,2,FALSE) -> CRUCETA METÁLICA DE ÁNGULO GALVANIZADO DE 2 M DE LONGITUD. CALIBRE (64*64*5) MM | C20: 1
A21: 332 | B21: =VLOOKUP(A21,[1]L.mat!$A$2:$B$83,2,FALSE) -> DIAGONAL RECTA EN ÁNGULO PARA CRUCETA METÁLICA DE (38*38*5)MM - LONGITUD 1100MM | C21: 1
A22: 512 | B22: =VLOOKUP(A22,[1]L.mat!$A$2:$B$83,2,FALSE) -> ESPIGO DE ACERO GALVANIZADO ALTURA 330 MM DIÁMETRO 35 MM PARA CRUCETA METÁLICA | C22: 3
A23: 613 | B23: =VLOOKUP(A23,[1]L.mat!$A$2:$B$83,2,FALSE) -> AISLADOR TIPO ESPIGO ROSCA 35MM 15kV ANSI 56-3 | C23: 3
A24: 1214 | B24: =VLOOKUP(A24,[1]L.mat!$A$2:$B$83,2,FALSE) -> COLLARÍN DE UNA SALIDA EN PLATINA DE HIERRO GALVANIZADO. DIAMETRO DEL POSTE 20 - 25 CM | C24: 1
A25: 2014 | B25: =VLOOKUP(A25,[1]L.mat!$A$2:$B$83,2,FALSE) -> PERNO DE MÁQUINA DE HIERRO GALVANIZADO CON CABEZA Y TUERCA CUADRADA. DIAMETRO 13 MM. LARGO 51 MM. | C25: 1
A26: 2034 | B26: =VLOOKUP(A26,[1]L.mat!$A$2:$B$83,2,FALSE) -> PERNO DE MÁQUINA DE HIERRO GALVANIZADO CON CABEZA Y TUERCA CUADRADA. DIAMETRO 16 MM. LARGO 254 MM. | C26: 1
A27: 2412 | B27: =VLOOKUP(A27,[1]L.mat!$A$2:$B$83,2,FALSE) -> ARANDELA CUADRADA PLANA DE 51*17 MM Ø= 16 MM (2"X2"X5/8") | C27: 1
A28: 2433 | B28: =VLOOKUP(A28,[1]L.mat!$A$2:$B$83,2,FALSE) -> ARANDELA DE PRESIÓN DE Ø= 26 MM PARA PERNO Ø= 13 MM (1/2") | C28: 1
A29: 2434 | B29: =VLOOKUP(A29,[1]L.mat!$A$2:$B$83,2,FALSE) -> ARANDELA DE PRESIÓN DE Ø= 26 MM PARA PERNO Ø= 16 MM (5/8") | C29: 1

Sheet 560N2
A1: EH-NC-560 Circuito trifásico estructura de retención, disposición horizontal | C1: Cantidades | E1: Cantidad de estructuras
C2: Unitaria | D2: Total | E2: =Info_P!B18 -> 2
A3: Código | B3: Montaje de la Estructura
A4: 268 | B4: =VLOOKUP(A4,'BD materiales'!$A$2:$B$93,2,FALSE) -> CRUCETA METÁLICA DE ÁNGULO GALVANIZADO DE 2 M DE LONGITUD. CALIBRE (64*64*5) MM | C4: 2 | D4: =C4*$E$2 -> 4
A5: 333 | B5: =VLOOKUP(A5,'BD materiales'!$A$2:$B$93,2,FALSE) -> DIAGONAL RECTA EN ÁNGULO PARA CRUCETA METÁLICA DE (38*38*5)MM - LONGITUD 680MM | C5: 4 | D5: =C5*$E$2 -> 8
A6: 511 | B6: =VLOOKUP(A6,'BD materiales'!$A$2:$B$93,2,FALSE) -> ESPIGO DE ACERO GALVANIZADO ALTURA 150 MM DIAMETRO 19 MM PARA CRUCETA METÁLICA | C6: 1 | D6: =C6*$E$2 -> 2
A7: 601 | B7: =VLOOKUP(A7,'BD materiales'!$A$2:$B$93,2,FALSE) -> AISLADOR TIPO DISCO DE HORQUILLA. DIAMETRO 152 MM 13,2 KV ANSI 52-1 | C7: 12 | D7: =C7*$E$2 -> 24
A8: 611 | B8: =VLOOKUP(A8,'BD materiales'!$A$2:$B$93,2,FALSE) -> AISLADOR TIPO ESPIGO ROSCA 25,4MM 15kV ANSI 55-5 | C8: 1 | D8: =C8*$E$2 -> 2
A9: 711 | B9: =VLOOKUP(A9,'BD materiales'!$A$2:$B$93,2,FALSE) -> GRAPA TERMINAL O DE RETENCIÓN EN ACERO GALVANIZADO. CONDUCTORES AWG-MCM 6 - 2/0. 6000 KGF. | C9: 6 | D9: =C9*$E$2 -> 12
A10: 1021 | B10: =VLOOKUP(A10,'BD materiales'!$A$2:$B$93,2,FALSE) -> CONECTOR DE RANURAS PARALELAS DE UN PERNO. DIMENSIONES 35*45*45 MM | C10: 6 | D10: =C10*$E$2 -> 12
A11: 2014 | B11: =VLOOKUP(A11,'BD materiales'!$A$2:$B$93,2,FALSE) -> PERNO DE MÁQUINA DE HIERRO GALVANIZADO CON CABEZA Y TUERCA CUADRADA. DIAMETRO 13 MM. LARGO 51 MM. | C11: 4 | D11: =C11*$E$2 -> 8
A12: 2102 | B12: =VLOOKUP(A12,'BD materiales'!$A$2:$B$93,2,FALSE) -> ESPÁRRAGO DE HIERRO GALVANIZADO ROSCADO EN TODA SU LONGITUD, 4 TUERCAS. DIAMETRO 16 MM LONGITUD 305 MM | C12: 3 | D12: =C12*$E$2 -> 6
A13: 2433 | B13: =VLOOKUP(A13,'BD materiales'!$A$2:$B$93,2,FALSE) -> ARANDELA DE PRESIÓN DE Ø= 26 MM PARA PERNO Ø= 13 MM (1/2") | C13: 4 | D13: =C13*$E$2 -> 8
A14: 2434 | B14: =VLOOKUP(A14,'BD materiales'!$A$2:$B$93,2,FALSE) -> ARANDELA DE PRESIÓN DE Ø= 26 MM PARA PERNO Ø= 16 MM (5/8") | C14: 14 | D14: =C14*$E$2 -> 28
A15: 2512 | B15: =VLOOKUP(A15,'BD materiales'!$A$2:$B$93,2,FALSE) -> TUERCA DE OJO ALARGADO PARA PERNO 16 MM | C15: 6 | D15: =C15*$E$2 -> 12
A17: NOTA | B17: MISMA ESTRUCTURA 560 CON DIFERENTES AISLADORES

Sheet 580N2
A1: EH-NC-580 Circuito trifásico sencillo estructura de derivación, disposición horizontal | C1: Cantidades | E1: Cantidad de estructuras
C2: Unitaria | D2: Total | E2: =[1]Info_P!B20 -> 1
A3: Código | B3: Montaje de la Estructura
A4: 268 | B4: =VLOOKUP(A4,[1]L.mat!$A$2:$B$85,2,FALSE) -> CRUCETA METÁLICA DE ÁNGULO GALVANIZADO DE 2 M DE LONGITUD. CALIBRE (64*64*5) MM | C4: 4 | D4: =C4*$E$2 -> 4
A5: 333 | B5: =VLOOKUP(A5,[1]L.mat!$A$2:$B$85,2,FALSE) -> DIAGONAL RECTA EN ÁNGULO PARA CRUCETA METÁLICA DE (38*38*5)MM - LONGITUD 680MM | C5: 8 | D5: =C5*$E$2 -> 8
A6: 511 | B6: =VLOOKUP(A6,[1]L.mat!$A$2:$B$85,2,FALSE) -> ESPIGO DE ACERO GALVANIZADO ALTURA 150 MM DIAMETRO 19 MM PARA CRUCETA METÁLICA | C6: 2 | D6: =C6*$E$2 -> 2
A7: 601 | B7: =VLOOKUP(A7,[1]L.mat!$A$2:$B$85,2,FALSE) -> AISLADOR TIPO DISCO DE HORQUILLA. DIAMETRO 152 MM 13,2 KV ANSI 52-1 | C7: 12 | D7: =C7*$E$2 -> 12
A8: 611 | B8: =VLOOKUP(A8,[1]L.mat!$A$2:$B$85,2,FALSE) -> AISLADOR TIPO ESPIGO ROSCA 25,4MM 15kV ANSI 55-5 | C8: 2 | D8: =C8*$E$2 -> 2
A9: 711 | B9: =VLOOKUP(A9,[1]L.mat!$A$2:$B$85,2,FALSE) -> GRAPA TERMINAL O DE RETENCIÓN EN ACERO GALVANIZADO. CONDUCTORES AWG-MCM 6 - 2/0. 6000 KGF. | C9: 6 | D9: =C9*$E$2 -> 6
A10: 1021 | B10: =VLOOKUP(A10,[1]L.mat!$A$2:$B$85,2,FALSE) -> CONECTOR DE RANURAS PARALELAS DE UN PERNO. DIMENSIONES 35*45*45 MM | C10: 6 | D10: =C10*$E$2 -> 6
A11: 1222 | B11: COLLARÍN DE DOS SALIDAS EN PLATINA DE HIERRO GALVANIZADO. DIAMETRO DEL POSTE 15 - 20 CM | C11: 1 | D11: =C11*$E$2 -> 1
A12: 2014 | B12: =VLOOKUP(A12,[1]L.mat!$A$2:$B$85,2,FALSE) -> PERNO DE MÁQUINA DE HIERRO GALVANIZADO CON CABEZA Y TUERCA CUADRADA. DIAMETRO 13 MM. LARGO 51 MM. | C12: 8 | D12: =C12*$E$2 -> 8
A13: 2034 | B13: =VLOOKUP(A13,[1]L.mat!$A$2:$B$85,2,FALSE) -> PERNO DE MÁQUINA DE HIERRO GALVANIZADO CON CABEZA Y TUERCA CUADRADA. DIAMETRO 16 MM. LARGO 254 MM. | C13: 1 | D13: =C13*$E$2 -> 1
A14: 2102 | B14: =VLOOKUP(A14,[1]L.mat!$A$2:$B$85,2,FALSE) -> ESPÁRRAGO DE HIERRO GALVANIZADO ROSCADO EN TODA SU LONGITUD, 4 TUERCAS. DIAMETRO 16 MM LONGITUD 305 MM | C14: 6 | D14: =C14*$E$2 -> 6
A15: 2433 | B15: =VLOOKUP(A15,[1]L.mat!$A$2:$B$85,2,FALSE) -> ARANDELA DE PRESIÓN DE Ø= 26 MM PARA PERNO Ø= 13 MM (1/2") | C15: 8 | D15: =C15*$E$2 -> 8
A16: 2434 | B16: =VLOOKUP(A16,[1]L.mat!$A$2:$B$85,2,FALSE) -> ARANDELA DE PRESIÓN DE Ø= 26 MM PARA PERNO Ø= 16 MM (5/8") | C16: 26 | D16: =C16*$E$2 -> 26
A17: 2512 | B17: =VLOOKUP(A17,[1]L.mat!$A$2:$B$85,2,FALSE) -> TUERCA DE OJO ALARGADO PARA PERNO 16 MM | C17: 6 | D17: =C17*$E$2 -> 6

Sheet 562N3
A1: 562 N3 Circuito trifásico estructura de retención, disposición en semibandera | C1: Cantidades | E1: Cantidad de estructuras
C2: Unitaria | D2: Total | E2: =Info_P!B22 -> 1
A3: Código | B3: Montaje de la Estructura
A4: 268 | B4: =VLOOKUP(A4,'BD materiales'!$A$2:$B$93,2,FALSE) -> CRUCETA METÁLICA DE ÁNGULO GALVANIZADO DE 2 M DE LONGITUD. CALIBRE (64*64*5) MM | C4: =SUMIF($A$22:$C$40,A4,$C$22:$C$40) -> 2 | D4: =C22*$E$2 -> 2
A5: 332 | B5: =VLOOKUP(A5,'BD materiales'!$A$2:$B$93,2,FALSE) -> DIAGONAL RECTA EN ÁNGULO PARA CRUCETA METÁLICA DE (38*38*5)MM - LONGITUD 1100MM | C5: =SUMIF($A$22:$C$40,A5,$C$22:$C$40) -> 2 | D5: =C23*$E$2 -> 2
A6: 512 | B6: =VLOOKUP(A6,'BD materiales'!$A$2:$B$93,2,FALSE) -> ESPIGO DE ACERO GALVANIZADO ALTURA 330 MM DIÁMETRO 35 MM PARA CRUCETA METÁLICA | C6: =SUMIF($A$22:$C$40,A6,$C$22:$C$40) -> 1 | D6: =C24*$E$2 -> 1
A7: 603 | B7: =VLOOKUP(A7,'BD materiales'!$A$2:$B$93,2,FALSE) -> AISLADOR TIPO DISCO DE HORQUILLA. DIAMETRO 254 MM 34.5 KV ANSI 52-4 | C7: =SUMIF($A$22:$C$40,A7,$C$22:$C$40) -> 18 | D7: =C25*$E$2 -> 18
A8: 613 | B8: =VLOOKUP(A8,'BD materiales'!$A$2:$B$93,2,FALSE) -> AISLADOR TIPO ESPIGO ROSCA 35MM 15kV ANSI 56-3 | C8: =SUMIF($A$22:$C$40,A8,$C$22:$C$40) -> 1 | D8: =C26*$E$2 -> 1
A9: 711 | B9: =VLOOKUP(A9,'BD materiales'!$A$2:$B$93,2,FALSE) -> GRAPA TERMINAL O DE RETENCIÓN EN ACERO GALVANIZADO. CONDUCTORES AWG-MCM 6 - 2/0. 6000 KGF. | C9: =SUMIF($A$22:$C$40,A9,$C$22:$C$40) -> 6 | D9: =C27*$E$2 -> 6
A10: 1021 | B10: =VLOOKUP(A10,'BD materiales'!$A$2:$B$93,2,FALSE) -> CONECTOR DE RANURAS PARALELAS DE UN PERNO. DIMENSIONES 35*45*45 MM | C10: =SUMIF($A$22:$C$40,A10,$C$22:$C$40) -> 6 | D10: =C28*$E$2 -> 6
A11: 1601 | B11: =VLOOKUP(A11,'BD materiales'!$A$2:$B$93,2,FALSE) -> ESLABÓN EN U CON PASADOR. DIMENSIONES 51 MM 8000 KGF | C11: =SUMIF($A$22:$C$40,A11,$C$22:$C$40) -> 6 | D11: =C29*$E$2 -> 6
A12: 2014 | B12: =VLOOKUP(A12,'BD materiales'!$A$2:$B$93,2,FALSE) -> PERNO DE MÁQUINA DE HIERRO GALVANIZADO CON CABEZA Y TUERCA CUADRADA. DIAMETRO 13 MM. LARGO 51 MM. | C12: =SUMIF($A$22:$C$40,A12,$C$22:$C$40) -> 2 | D12: =C30*$E$2 -> 2
A13: 2034 | B13: =VLOOKUP(A13,'BD materiales'!$A$2:$B$93,2,FALSE) -> PERNO DE MÁQUINA DE HIERRO GALVANIZADO CON CABEZA Y TUERCA CUADRADA. DIAMETRO 16 MM. LARGO 254 MM. | C13: =SUMIF($A$22:$C$40,A13,$C$22:$C$40) -> 2 | D13: =C31*$E$2 -> 2
A14: 2105 | B14: =VLOOKUP(A14,'BD materiales'!$A$2:$B$93,2,FALSE) -> ESPÁRRAGO DE HIERRO GALVANIZADO ROSCADO EN TODA SU LONGITUD, 4 TUERCAS. DIAMETRO 16 MM LONGITUD 458 MM | C14: =SUMIF($A$22:$C$40,A14,$C$22:$C$40) -> 3 | D14: =C32*$E$2 -> 3
A15: 2433 | B15: =VLOOKUP(A15,'BD materiales'!$A$2:$B$93,2,FALSE) -> ARANDELA DE PRESIÓN DE Ø= 26 MM PARA PERNO Ø= 13 MM (1/2") | C15: =SUMIF($A$22:$C$40,A15,$C$22:$C$40) -> 2 | D15: =C33*$E$2 -> 2
... A17: 2512 | B17: =VLOOKUP(A17,'BD materiales'!$A$2:$B$93,2,FALSE) -> TUERCA DE OJO ALARGADO PARA PERNO 16 MM | C17: =SUMIF($A$22:$C$40,A17,$C$22:$C$40) -> 6 | D17: =C35*$E$2 -> 6
A19: NOTA | B19: PROPUESTO COMO REEMPLAZO DE 560N3
A22: 268 | B22: =VLOOKUP(A22,[1]L.mat!$A$2:$B$81,2,FALSE) -> CRUCETA METÁLICA DE ÁNGULO GALVANIZADO DE 2 M DE LONGITUD. CALIBRE (64*64*5) MM | C22: 2
A23: 332 | B23: =VLOOKUP(A23,[1]L.mat!$A$2:$B$81,2,FALSE) -> DIAGONAL RECTA EN ÁNGULO PARA CRUCETA METÁLICA DE (38*38*5)MM - LONGITUD 1100MM | C23: 2
A24: 512 | B24: =VLOOKUP(A24,[1]L.mat!$A$2:$B$81,2,FALSE) -> ESPIGO DE ACERO GALVANIZADO ALTURA 330 MM DIÁMETRO 35 MM PARA CRUCETA METÁLICA | C24: 1
A25: 603 | B25: =VLOOKUP(A25,[1]L.mat!$A$2:$B$81,2,FALSE) -> AISLADOR TIPO DISCO DE HORQUILLA. DIAMETRO 254 MM 34.5 KV ANSI 52-4 | C25: 18
A26: 613 | B26: AISLADOR TIPO ESPIGO ROSCA 35MM 15kV ANSI 56-3 | C26: 1
A27: 711 | B27: =VLOOKUP(A27,[1]L.mat!$A$2:$B$81,2,FALSE) -> GRAPA TERMINAL O DE RETENCIÓN EN ACERO GALVANIZADO. CONDUCTORES AWG-MCM 6 - 2/0. 6000 KGF. | C27: 6
A28: 1021 | B28: =VLOOKUP(A28,[1]L.mat!$A$2:$B$81,2,FALSE) -> CONECTOR DE RANURAS PARALELAS DE UN PERNO. DIMENSIONES 35*45*45 MM | C28: 6
A29: 1601 | B29: ESLABÓN EN U CON PASADOR. DIMENSIONES 51 MM 8000 KGF | C29: 6
A30: 2014 | B30: =VLOOKUP(A30,[1]L.mat!$A$2:$B$81,2,FALSE) -> PERNO DE MÁQUINA DE HIERRO GALVANIZADO CON CABEZA Y TUERCA CUADRADA. DIAMETRO 13 MM. LARGO 51 MM. | C30: 2
A31: 2034 | B31: =VLOOKUP(A31,[1]L.mat!$A$2:$B$81,2,FALSE) -> PERNO DE MÁQUINA DE HIERRO GALVANIZADO CON CABEZA Y TUERCA CUADRADA. DIAMETRO 16 MM. LARGO 254 MM. | C31: 2
A32: 2105 | B32: =VLOOKUP(A32,[1]L.mat!$A$2:$B$81,2,FALSE) -> ESPÁRRAGO DE HIERRO GALVANIZADO ROSCADO EN TODA SU LONGITUD, 4 TUERCAS. DIAMETRO 16 MM LONGITUD 458 MM | C32: 3
A33: 2433 | B33: =VLOOKUP(A33,[1]L.mat!$A$2:$B$81,2,FALSE) -> ARANDELA DE PRESIÓN DE Ø= 26 MM PARA PERNO Ø= 13 MM (1/2") | C33: 2
A34: 2434 | B34: =VLOOKUP(A34,[1]L.mat!$A$2:$B$81,2,FALSE) -> ARANDELA DE PRESIÓN DE Ø= 26 MM PARA PERNO Ø= 16 MM (5/8") | C34: 14
A35: 2512 | B35: =VLOOKUP(A35,[1]L.mat!$A$2:$B$81,2,FALSE) -> TUERCA DE OJO ALARGADO PARA PERNO 16 MM | C35: 6

Sheet 555N3
A1: 555 N3 Circuito trifásico estructura terminal, disposición horizontal semibandera | C1: Cantidades | E1: Cantidad de estructuras
C2: Unitaria | D2: Total | E2: =Info_P!B23 -> 6
A3: Código | B3: Montaje de la Estructura
A4: 268 | B4: =VLOOKUP(A4,'BD materiales'!$A$2:$B$93,2,FALSE) -> CRUCETA METÁLICA DE ÁNGULO GALVANIZADO DE 2 M DE LONGITUD. CALIBRE (64*64*5) MM | C4: 2 | D4: =C4*$E$2 -> 12
A5: 332 | B5: =VLOOKUP(A5,'BD materiales'!$A$2:$B$93,2,FALSE) -> DIAGONAL RECTA EN ÁNGULO PARA CRUCETA METÁLICA DE (38*38*5)MM - LONGITUD 1100MM | C5: 2 | D5: =C5*$E$2 -> 12
A6: 603 | B6: =VLOOKUP(A6,'BD materiales'!$A$2:$B$93,2,FALSE) -> AISLADOR TIPO DISCO DE HORQUILLA. DIAMETRO 254 MM 34.5 KV ANSI 52-4 | C6: 9 | D6: =C6*$E$2 -> 54
A7: 711 | B7: =VLOOKUP(A7,'BD materiales'!$A$2:$B$93,2,FALSE) -> GRAPA TERMINAL O DE RETENCIÓN EN ACERO GALVANIZADO. CONDUCTORES AWG-MCM 6 - 2/0. 6000 KGF. | C7: 3 | D7: =C7*$E$2 -> 18
A8: 1021 | B8: =VLOOKUP(A8,'BD materiales'!$A$2:$B$93,2,FALSE) -> CONECTOR DE RANURAS PARALELAS DE UN PERNO. DIMENSIONES 35*45*45 MM | C8: 3 | D8: =C8*$E$2 -> 18
A9: 2014 | B9: =VLOOKUP(A9,'BD materiales'!$A$2:$B$93,2,FALSE) -> PERNO DE MÁQUINA DE HIERRO GALVANIZADO CON CABEZA Y TUERCA CUADRADA. DIAMETRO 13 MM. LARGO 51 MM. | C9: 2 | D9: =C9*$E$2 -> 12
A10: 2034 | B10: =VLOOKUP(A10,'BD materiales'!$A$2:$B$93,2,FALSE) -> PERNO DE MÁQUINA DE HIERRO GALVANIZADO CON CABEZA Y TUERCA CUADRADA. DIAMETRO 16 MM. LARGO 254 MM. | C10: 2 | D10: =C10*$E$2 -> 12
A11: 2103 | B11: =VLOOKUP(A11,'BD materiales'!$A$2:$B$93,2,FALSE) -> ESPÁRRAGO DE HIERRO GALVANIZADO ROSCADO EN TODA SU LONGITUD, 4 TUERCAS. DIAMETRO 16 MM LONGITUD 356 MM | C11: 3 | D11: =C11*$E$2 -> 18
A12: 2433 | B12: =VLOOKUP(A12,'BD materiales'!$A$2:$B$93,2,FALSE) -> ARANDELA DE PRESIÓN DE Ø= 26 MM PARA PERNO Ø= 13 MM (1/2") | C12: 2 | D12: =C12*$E$2 -> 12
A13: 2434 | B13: =VLOOKUP(A13,'BD materiales'!$A$2:$B$93,2,FALSE) -> ARANDELA DE PRESIÓN DE Ø= 26 MM PARA PERNO Ø= 16 MM (5/8") | C13: 14 | D13: =C13*$E$2 -> 84
A14: 2512 | B14: =VLOOKUP(A14,'BD materiales'!$A$2:$B$93,2,FALSE) -> TUERCA DE OJO ALARGADO PARA PERNO 16 MM | C14: 3 | D14: =C14*$E$2 -> 18

Sheet 619N1
A1: NC-619 - Estructura de retención apoyo con percha de tres puestos. | C1: Cantidades | E1: Cantidad de estructuras
C2: Unitaria | D2: Total | E2: =Info_P!B17 -> 1
A3: Código | B3: Montaje de la Estructura
A4: 621 | B4: =VLOOKUP(A4,'BD materiales'!$A$2:$B$93,2,FALSE) -> AISLADOR TIPO CARRETE. ALTURA 76,2 MM ANSI 53-3 | C4: 3 | D4: =C4*$E$2 -> 3
A5: 2034 | B5: =VLOOKUP(A5,'BD materiales'!$A$2:$B$93,2,FALSE) -> PERNO DE MÁQUINA DE HIERRO GALVANIZADO CON CABEZA Y TUERCA CUADRADA. DIAMETRO 16 MM. LARGO 254 MM. | C5: 2 | D5: =C5*$E$2 -> 2
A6: 2412 | B6: =VLOOKUP(A6,'BD materiales'!$A$2:$B$93,2,FALSE) -> ARANDELA CUADRADA PLANA DE 51*17 MM Ø= 16 MM (2"X2"X5/8") | C6: 2 | D6: =C6*$E$2 -> 2
A7: 2434 | B7: =VLOOKUP(A7,'BD materiales'!$A$2:$B$93,2,FALSE) -> ARANDELA DE PRESIÓN DE Ø= 26 MM PARA PERNO Ø= 16 MM (5/8") | C7: 2 | D7: =C7*$E$2 -> 2
A8: 1803 | B8: =VLOOKUP(A8,'BD materiales'!$A$2:$B$93,2,FALSE) -> PERCHA DE HIERRO FORJADAS Y GALVANIZADAS EN CALIENTE, TRES PUESTOS | C8: 1 | D8: =C8*$E$2 -> 1

Sheet HG-P
A1: ESTRUCTURA DE HILO GUARDA INDEPENDIENTE PARA ESTRUCTURA TIPO PASO | C1: Cantidades | E1: Cantidad de estructuras
C2: Unitaria | D2: Total | E2: =Info_P!B27 -> 4
A3: Código | B3: Montaje de la Estructura
A4: 1661 | B4: =VLOOKUP(A4,'BD materiales'!$A$2:$B$93,2,FALSE) -> PERNO EN U PARA ESTRUCTURA EN SUSPENSIÓN 5.400KGF. 51*32*38 mm 12000 LBF | C4: 1 | D4: =C4*$E$2 -> 4
A5: 1903 | B5: =VLOOKUP(A5,'BD materiales'!$A$2:$B$93,2,FALSE) -> BAYONETA SENCILLA, ESTRUCTURA EN ALINEAMIETO, 2 PERFORACIONES 11/16" DE 1,5 M | C5: 1 | D5: =C5*$E$2 -> 4
A6: 2034 | B6: =VLOOKUP(A6,'BD materiales'!$A$2:$B$93,2,FALSE) -> PERNO DE MÁQUINA DE HIERRO GALVANIZADO CON CABEZA Y TUERCA CUADRADA. DIAMETRO 16 MM. LARGO 254 MM. | C6: 2 | D6: =C6*$E$2 -> 8
A7: 2412 | B7: =VLOOKUP(A7,'BD materiales'!$A$2:$B$93,2,FALSE) -> ARANDELA CUADRADA PLANA DE 51*17 MM Ø= 16 MM (2"X2"X5/8") | C7: 2 | D7: =C7*$E$2 -> 8
A8: 2434 | B8: =VLOOKUP(A8,'BD materiales'!$A$2:$B$93,2,FALSE) -> ARANDELA DE PRESIÓN DE Ø= 26 MM PARA PERNO Ø= 16 MM (5/8") | C8: 2 | D8: =C8*$E$2 -> 8

Sheet HG-R
A1: ESTRUCTURA DE HILO GUARDA INDEPENDIENTE PARA ESTRUCTURA TIPO RETENCIÓN | C1: Cantidades | E1: Cantidad de estructuras
C2: Unitaria | D2: Total | E2: =Info_P!B28 -> 2
A3: Código | B3: Montaje de la Estructura
A4: 701 | B4: =VLOOKUP(A4,'BD materiales'!$A$2:$B$93,2,FALSE) -> GRAPA TERMINAL O DE RETENCIÓN EN ALEACIÓN DE ALUMINIO DE 2 PERSNOS. CONDUCTORES AWG-MCM 5 - 2/0. 3000 KGF. | C4: 2 | D4: =C4*$E$2 -> 4
A5: 1214 | B5: =VLOOKUP(A5,'BD materiales'!$A$2:$B$93,2,FALSE) -> COLLARÍN DE UNA SALIDA EN PLATINA DE HIERRO GALVANIZADO. DIAMETRO DEL POSTE 20 - 25 CM | C5: 1 | D5: =C5*$E$2 -> 2
A6: 1601 | B6: =VLOOKUP(A6,'BD materiales'!$A$2:$B$93,2,FALSE) -> ESLABÓN EN U CON PASADOR. DIMENSIONES 51 MM 8000 KGF | C6: 2 | D6: =C6*$E$2 -> 4
A7: 2201 | B7: =VLOOKUP(A7,'BD materiales'!$A$2:$B$93,2,FALSE) -> PERNO DE OJO – DOS TUERCAS – DIÁMETRO 16 MM – LONGITUD 102 MM | C7: 1 | D7: =C7*$E$2 -> 2
A8: 2204 | B8: =VLOOKUP(A8,'BD materiales'!$A$2:$B$93,2,FALSE) -> PERNO DE OJO – DOS TUERCAS – DIÁMETRO 16 MM – LONGITUD 254 MM | C8: 1 | D8: =C8*$E$2 -> 2
A9: 2412 | B9: =VLOOKUP(A9,'BD materiales'!$A$2:$B$93,2,FALSE) -> ARANDELA CUADRADA PLANA DE 51*17 MM Ø= 16 MM (2"X2"X5/8") | C9: 2 | D9: =C9*$E$2 -> 4

Sheet R.D
A1: TEMPLETE DIRECTO A VARILLA DE ANCLAJE 34,5kV | C1: Cantidades | E1: Cantidad de estructuras
C2: Unitaria | D2: Total | E2: =Info_P!B25 -> 4
A3: Código | B3: Montaje de la Estructura
A4: 634 | B4: =VLOOKUP(A4,'BD materiales'!$A$2:$B$93,2,FALSE) -> AISLADOR TIPO TENSOR ANSI 54-4 DE 6 3/4" PARA 34.5 KV | C4: 1 | D4: =C4*$E$2 -> 4
A5: 771 | B5: =VLOOKUP(A5,'BD materiales'!$A$2:$B$93,2,FALSE) -> GRAPA PRENSADORA. DIÁMETRO DEL CONDUCTOR 6,35MM - 9,18MM DIMENSIONES 150*15MM | C5: 4 | D5: =C5*$E$2 -> 16
A6: 1101 | B6: =VLOOKUP(A6,'BD materiales'!$A$2:$B$93,2,FALSE) -> GUARDACABODE ACERO GALVANIZADO PARA CABLE DE 15,87MM | C6: 1 | D6: =C6*$E$2 -> 4
A7: 1202 | B7: =VLOOKUP(A7,'BD materiales'!$A$2:$B$93,2,FALSE) -> COLLARÍN SIN SALIDA EN PLATINA DE HIERRO GALVANIZADO. DIAMETRO DEL POSTE 15 - 20 CM | C7: 1 | D7: =C7*$E$2 -> 4
A8: 2601 | B8: =VLOOKUP(A8,'BD materiales'!$A$2:$B$93,2,FALSE) -> VARILLA DE ANCLAJE CON OJO - DIÁMETRO 16MM LONGITUD 1,8M | C8: 1 | D8: =C8*$E$2 -> 4
A9: 2701 | B9: =VLOOKUP(A9,'BD materiales'!$A$2:$B$93,2,FALSE) -> VIGUETA DE ANCLAJE FE=2500 PSI ES=1400K/CM^2 | C9: 1 | D9: =C9*$E$2 -> 4
A10: 2815 | B10: =VLOOKUP(A10,'BD materiales'!$A$2:$B$93,2,FALSE) -> CABLE DE ACERO GALVANIZADO TIPO SUPERRRESISTENTE PARA TEMPLETE DE 9,5 MM CON CARGA DE ROTURA 6980 KGF | C10: 20 | D10: =C10*$E$2 -> 80

Sheet R.CG
A1: TEMPLETE CUERDA DE GUITARRA 34,5kV | C1: Cantidades | E1: Cantidad de estructuras
C2: Unitaria | D2: Total | E2: =Info_P!B24 -> 5
A3: Código | B3: Montaje de la Estructura
A4: 634 | B4: =VLOOKUP(A4,'BD materiales'!$A$2:$B$93,2,FALSE) -> AISLADOR TIPO TENSOR ANSI 54-4 DE 6 3/4" PARA 34.5 KV | C4: 1 | D4: =C4*$E$2 -> 5
A5: 771 | B5: =VLOOKUP(A5,'BD materiales'!$A$2:$B$93,2,FALSE) -> GRAPA PRENSADORA. DIÁMETRO DEL CONDUCTOR 6,35MM - 9,18MM DIMENSIONES 150*15MM | C5: 4 | D5: =C5*$E$2 -> 20
A6: 1101 | B6: =VLOOKUP(A6,'BD materiales'!$A$2:$B$93,2,FALSE) -> GUARDACABODE ACERO GALVANIZADO PARA CABLE DE 15,87MM | C6: 1 | D6: =C6*$E$2 -> 5
A7: 1202 | B7: =VLOOKUP(A7,'BD materiales'!$A$2:$B$93,2,FALSE) -> COLLARÍN SIN SALIDA EN PLATINA DE HIERRO GALVANIZADO. DIAMETRO DEL POSTE 15 - 20 CM | C7: 1 | D7: =C7*$E$2 -> 5
A8: 2601 | B8: =VLOOKUP(A8,'BD materiales'!$A$2:$B$93,2,FALSE) -> VARILLA DE ANCLAJE CON OJO - DIÁMETRO 16MM LONGITUD 1,8M | C8: 1 | D8: =C8*$E$2 -> 5
A9: 2701 | B9: =VLOOKUP(A9,'BD materiales'!$A$2:$B$93,2,FALSE) -> VIGUETA DE ANCLAJE FE=2500 PSI ES=1400K/CM^2 | C9: 1 | D9: =C9*$E$2 -> 5
A10: 2815 | B10: =VLOOKUP(A10,'BD materiales'!$A$2:$B$93,2,FALSE) -> CABLE DE ACERO GALVANIZADO TIPO SUPERRRESISTENTE PARA TEMPLETE DE 9,5 MM CON CARGA DE ROTURA 6980 KGF | C10: 20 | D10: =C10*$E$2 -> 100
A11: 3301 | B11: =VLOOKUP(A11,'BD materiales'!$A$2:$B$93,2,FALSE) -> ACCESORIOS PARA TEMPLETE CUERDA GUITARRA | C11: 1 | D11: =C11*$E$2 -> 5

Sheet SPT_18
A1: SPT REDES TRIFÁSICAS DE 34,5kV CON CABLE GUARDA POSTE SENCILLO | C1: Cantidades | E1: Cantidad de estructuras
C2: Unitaria | D2: Total | E2: =Info_P!B26 -> 4
A3: Código | B3: Montaje de la Estructura
A4: 803 | B4: =VLOOKUP(A4,'BD materiales'!$A$2:$B$93,2,FALSE) -> CABLE DE COBRE DESNUDO CALIBRE 4 AWG | C4: 1 | D4: =C4*$E$2 -> 4
A5: 1411 | B5: =VLOOKUP(A5,'BD materiales'!$A$2:$B$93,2,FALSE) -> VARILLA DE PUESTA A TIERRA DE 15,88*2438 MM | C5: 1 | D5: =C5*$E$2 -> 4
A6: 41062 | B6: =VLOOKUP(A6,[1]L.mat!$A$2:$B$93,2,FALSE) -> CONECTOR TIPO TORNILLO PARA PUESTA A TIERRA | C6: 1 | D6: =C6*$E$2 -> 4
A7: 1 | B7: CONECTOR DE COMPRESIÓN TIPO C EN COBRE | C7: 2 | D7: =C7*$E$2 -> 8
A8: 2 | B8: CONECTOR DE COMPRESIÓN TIPO PALA 4 AWG DE 1 HUECO | C8: 2 | D8: =C8*$E$2 -> 8
A9: 3 | B9: CONECTOS COMPRESIÓN TIPO H | C9: 1 | D9: =C9*$E$2 -> 4
A10: 4 | B10: TORNILLO EN ACERO GALVANIZADO DE CABEZA Y TUERCA HEXAGONAL 3/8" X 1" CON ARNDELA REDONDA DE 3/8" | C10: 2 | D10: =C10*$E$2 -> 8

Sheet Info_P
A1: Información de levantamiento y proyección de postes
A2: Número | B2: Placa | C2: Tipo | D2: ESTRUCTURAS PROYECTADAS | I2: Ret. directa | J2: Ret. C.G. | K2: SPT | L2: Poste nuevo | M2: HG | N2: OBS
D3: N1 | E3: N2 | G3: N3
A4: E-100 | B4: M017130 | C4: Paso | G4: 555 | I4: 6 | J4: 0 | K4: 0 | M4: 0 | N4: Desvestir 550 N3 y vestir 103 N3
A5: E-99 | B5: M017029 | C5: Ret | I5: 0 | J5: 0 | K5: 0 | M5: 0 | N5: Vestido
A6: E-98 | B6: M071918 | C6: Ret | I6: 0 | J6: 0 | K6: 0 | M6: 0 | N6: No se conecta a 34,5 kV
A7: E-97 | B7: M017028 | C7: Ret | D7: 619 | E7: 560N2 | G7: 562 | I7: 6 | J7: 3 | K7: 1 | L7: x | M7: P | N7: Cambiar poste
A8: E-96 | B8: M017027 | C8: Paso | G8: 103N3 | I8: 0 | J8: 0 | K8: 0 | M8: P | N8: Vestir 130N3
A9: E-95D | B9: M017026 | C9: Ret | E9: 580 | G9: 555 | H9: 555 | I9: 0 | J9: 2 | K9: 0 | L9: x | M9: R | N9: Nuevo de retención
A10: E-95C | C10: Paso | E10: 103N2 | G10: 103N3 | I10: 2 | J10: 0 | K10: 1 | L10: x | M10: P | N10: Nuevo de paso
A11: E-95B | B11: M017100 | C11: Paso | E11: 103N2 | G11: 103N3 | I11: 2 | J11: 0 | K11: 1 | L11: x | M11: P | N11: Nuevo de paso
A12: E-95A | B12: M017101 | C12: Ret | E12: 560N2 | G12: 555 | H12: 555 | I12: 1 | J12: 2 | K12: 0 | L12: x | M12: R | N12: Nuevo de retención
A13: E-95 | B13: M108463 | C13: Paso | G13: 555 | I13: 2 | J13: 0 | K13: 1 | M13: 0 | N13: Desvestir 131N3 y vestir 130N3
A15: Estructuras a instalar
A16: Tipo | B16: Cantidad
A17: 619 | B17: =COUNTIF($D$4:$H$13,A17) -> 1
A18: 560N2 | B18: =COUNTIF($D$4:$H$13,A18) -> 2
A19: 103N2 | B19: =COUNTIF($D$4:$H$13,A19) -> 2
A20: 580 | B20: =COUNTIF($D$4:$H$13,A20) -> 1
A21: 103N3 | B21: =COUNTIF($D$4:$H$13,A21) -> 3
A22: 562 | B22: =COUNTIF($D$4:$H$13,A22) -> 1
A23: 555 | B23: =COUNTIF($D$4:$H$13,A23) -> 6
A24: RET CG | B24: 5
A25: RET DIR | B25: 4
A26: SPT | B26: =SUM(K4:K13) -> 4
A27: HG-P | B27: =COUNTIF($M$4:$M$13,"P") -> 4
A28: HG-R | B28: =COUNTIF($M$4:$M$13,"R") -> 2

Sheet APU_P
A1: No. | B1: Descripcion | C1: E-100 | D1: E-99 | E1: E-98 | F1: E-97 | G1: E-96 | H1: E-95D | I1: E-95C | J1: E-95B | K1: E-95A | L1: E-95 | M1: GRAL | N1: Cantidad
B2: Mano de obra | C2: M017130 | D2: M017029 | E2: M071918 | F2: M017028 | G2: M017027 | H2: M017026 | I2: N | J2: M017100 | K2: M017101 | L2: M108463
A3: 1.1 | B3: =Presupuesto!#REF! -> #REF! | C3: 0 | D3: 0 | E3: 0 | F3: 0 | G3: 0 | H3: 0 | I3: 0 | J3: 0 | K3: 0 | L3: 0 | M3: 0 | N3: =SUM(C3:M3) -> 0
A4: 1.2 | B4: =Presupuesto!B6 -> APERTURA DE EXCAVACION POSTE DE 14 MTS M.T. RURAL | C4: 0 | D4: 0 | E4: 0 | F4: 0 | G4: 0 | H4: 0 | I4: 1 | J4: 1 | K4: 0 | L4: 0 | M4: 0 | N4: =SUM(C4:M4) -> 2
A5: 1.3 | B5: =Presupuesto!B7 -> APERTURA DE EXCAVACION PARA VIGUETA EN RETENIDA RURAL | C5: 0 | D5: 0 | E5: 0 | F5: 3 | G5: 0 | H5: 2 | I5: 2 | J5: 2 | K5: 3 | L5: 0 | M5: 0 | N5: =SUM(C5:M5) -> 12
A6: 1.6 | B6: =Presupuesto!B8 -> HINCADA, PLOMADA Y ORIENTACIÓN DE POSTE DE 14, 16 Y 18 MTS CON GRUA | C6: 0 | D6: 0 | E6: 0 | F6: 1 | G6: 0 | H6: 1 | I6: 1 | J6: 1 | K6: 1 | L6: 0 | M6: 0 | N6: =SUM(C6:M6) -> 5
A7: 1.7 | B7: =Presupuesto!B9 -> INSTALACION LINE A TIERRA MEDIA TENSION | C7: 0 | D7: 0 | E7: 0 | F7: 1 | G7: 0 | H7: 1 | I7: 1 | J7: 1 | K7: 0 | L7: 0 | M7: 0 | N7: =SUM(C7:M7) -> 4
A8: 1.8 | B8: =Presupuesto!B10 -> INSTALACIÓN DE TEMPLETE CUERDA GUITARRA CON TODOS SUS ACCESORIOS M.T. RURAL | C8: 0 | D8: 0 | E8: 0 | F8: 1 | G8: 0 | H8: 2 | I8: 0 | J8: 0 | K8: 2 | L8: 0 | M8: 0 | N8: =SUM(C8:M8) -> 5
A9: 1.9 | B9: =Presupuesto!B11 -> RIEGA, TENDIDO Y TENSIONADO DE UN CABLE DE GUARDA | C9: 0 | D9: 0 | E9: 0 | F9: 0 | G9: 0 | H9: 0 | I9: 0 | J9: 0 | K9: 0 | L9: 0 | M9: 0.716 | N9: =SUM(C9:M9) -> 0.716
A10: 1.10 | B10: =Presupuesto!#REF! -> #REF! | C10: 0 | D10: 0 | E10: 0 | F10: 0 | G10: 0 | H10: 0 | I10: 0 | J10: 0 | K10: 0 | L10: 0 | M10: 0 | N10: =SUM(C10:M10) -> 0
A11: 1.11 | B11: =Presupuesto!B12 -> TENDIDO Y TENSIONADO DE CABLE ECOLOGICO PARA RED MT TRIFASICA 36 KV DISPOSICION HORIZONTAL | C11: 0 | D11: 0 | E11: 0 | F11: 0 | G11: 0 | H11: 0 | I11: 0 | J11: 0 | K11: 0 | L11: 0 | M11: 2.149 | N11: =SUM(C11:M11) -> 2.149
A12: 1.12 | B12: =Presupuesto!B13 -> TRANSPORTE DE POSTE 14 MTS M.T. RURAL DE BODEGA A SITIO CERCANO | C12: 0 | D12: 0 | E12: 0 | F12: 1 | G12: 0 | H12: 1 | I12: 1 | J12: 1 | K12: 1 | L12: 0 | M12: 0 | N12: =SUM(C12:M12) -> 5
A13: 1.13 | B13: =Presupuesto!#REF! -> #REF! | C13: 0 | D13: 0 | E13: 0 | F13: 0 | G13: 0 | H13: 0 | I13: 0 | J13: 0 | K13: 0 | L13: 0 | M13: 0 | N13: =SUM(C13:M13) -> 0
A14: 1.14 | B14: =Presupuesto!#REF! -> #REF! | C14: 0 | D14: 0 | E14: 0 | F14: 0 | G14: 0 | H14: 0 | I14: 0 | J14: 0 | K14: 0 | L14: 0 | M14: 1 | N14: 0
A15: 1.15 | B15: =Presupuesto!B14 -> VESTIDA DE ESTRUCTURA TRIFASICA DE PASO UN POSTE 13,8kV | C15: 0 | D15: 0 | E15: 0 | F15: 0 | G15: 0 | H15: 0 | I15: 1 | J15: 1 | K15: 1 | L15: 0 | M15: 0 | N15: =SUM(C15:M15) -> 3
A16: 1.16 | B16: =Presupuesto!B15 -> VESTIDA DE ESTRUCTURA TRIFASICA DE RETENCION UN POSTE 13,8 Kv | C16: 0 | D16: 0 | E16: 0 | F16: 1 | G16: 0 | H16: 1 | I16: 0 | J16: 0 | K16: 0 | L16: 0 | M16: 0 | N16: =SUM(C16:M16) -> 2
A17: 1.17 | B17: =Presupuesto!B16 -> VESTIDA DE ESTRUCTURA TRIFASICA DE UN POSTE TIPO PASO 34.5 KV | C17: 0 | D17: 0 | E17: 0 | F17: 0 | G17: 1 | H17: 0 | I17: 1 | J17: 1 | K17: 0 | L17: 0 | M17: 0 | N17: =SUM(C17:M17) -> 3
A18: 1.18 | B18: =Presupuesto!B17 -> VESTIDA DE ESTRUCTURA TRIFASICA DE UN POSTE TIPO RETENCIÓN - 34.5 KV | C18: 1 | D18: 0 | E18: 0 | F18: 1 | G18: 0 | H18: 1 | I18: 0 | J18: 0 | K18: 1 | L18: 1 | M18: 0 | N18: =SUM(C18:M18) -> 5
A19: 1.19 | B19: =Presupuesto!B18 -> VESTIDA ESTRUCTURA CABLE DE GUARDA - RETENCION | C19: 0 | D19: 0 | E19: 0 | F19: 1 | G19: 0 | H19: 1 | I19: 0 | J19: 0 | K19: 1 | L19: 0 | M19: 0 | N19: =SUM(C19:M19) -> 3
A20: 1.20 | B20: =Presupuesto!B19 -> VESTIDA ESTRUCTURA CABLE DE GUARDA DE PASO | C20: 0 | D20: 0 | E20: 0 | F20: 0 | G20: 1 | H20: 0 | I20: 1 | J20: 1 | K20: 0 | L20: 0 | M20: 0 | N20: =SUM(C20:M20) -> 3
A21: 1.21 | B21: =Presupuesto!B20 -> DESVESTIDA ESTRUCTURA DE RETENCION MT RURAL | C21: 0 | D21: 0 | E21: 0 | F21: 1 | G21: 0 | H21: 1 | I21: 0 | J21: 0 | K21: 1 | L21: 0 | M21: 0 | N21: =SUM(C21:M21) -> 3
A22: 1.22 | B22: =Presupuesto!B21 -> DESVESTIDA ESTRUCTURA DE SUSPENSION MT RURAL | C22: 0 | D22: 0 | E22: 0 | F22: 0 | G22: 0 | H22: 0 | I22: 0 | J22: 1 | K22: 0 | L22: 0 | M22: 0 | N22: =SUM(C22:M22) -> 1
A23: 1.23 | B23: =Presupuesto!B22 -> DESHINCADA DE POSTES 10, 12 Y 14 mts MT | C23: 0 | D23: 0 | E23: 0 | F23: 1 | G23: 0 | H23: 1 | I23: 0 | J23: 1 | K23: 1 | L23: 0 | M23: 0 | N23: =SUM(C23:M23) -> 4
A24: 1.24 | B24: =Presupuesto!B23 -> INSTALACIÓN DE TEMPLETE SENCILLO CON TODOS SUS ACCESORIOS M.T. RURAL | C24: 0 | D24: 0 | E24: 0 | F24: 2 | G24: 0 | H24: 0 | I24: 2 | J24: 2 | K24: 1 | L24: 0 | M24: 0 | N24: =SUM(C24:M24) -> 7
A25: 1.25 | B25: =Presupuesto!#REF! -> #REF! | C25: 0 | D25: 0 | E25: 0 | F25: 1 | G25: 0 | H25: 1 | I25: 0 | J25: 1 | K25: 1 | L25: 0 | M25: 0 | N25: =SUM(C25:M25) -> 4
A26: 1.26 | B26: =Presupuesto!B24 -> TRANSPORTE DE POSTE RURAL DE SITIO CERCANO A BODEGA EH | C26: 0 | D26: 0 | E26: 0 | F26: 1 | G26: 0 | H26: 1 | I26: 0 | J26: 1 | K26: 1 | L26: 0 | M26: 0 | N26: =SUM(C26:M26) -> 4
A27: 1.27 | B27: =Presupuesto!B25 -> DESMONTE DE TRANSFORMADOR MONOFASICO | C27: 0 | D27: 0 | E27: 0 | F27: 0 | G27: 0 | H27: 1 | I27: 0 | J27: 0 | K27: 0 | L27: 0 | M27: 0 | N27: =SUM(C27:M27) -> 1
A28: 1.28 | B28: =Presupuesto!B26 -> MONTAJE DE TRANSFORMADOR MONOFASICO CON TODAS SUS PROTECCIONES RURAL | C28: 0 | D28: 0 | E28: 0 | F28: 0 | G28: 0 | H28: 1 | I28: 0 | J28: 0 | K28: 0 | L28: 0 | M28: 0 | N28: =SUM(C28:M28) -> 1
A29: 1.29 | B29: =Presupuesto!B27 -> DESVESTIDA DE ESTRUCTURA BT EXISTENTE | C29: 0 | D29: 0 | E29: 0 | F29: 1 | G29: 0 | H29: 1 | I29: 0 | J29: 0 | K29: 0 | L29: 0 | M29: 0 | N29: =SUM(C29:M29) -> 2
A30: 1.30 | B30: =Presupuesto!B28 -> VESTIDA DE ESTRUCTURA BT | C30: 0 | D30: 0 | E30: 0 | F30: 1 | G30: 0 | H30: 1 | I30: 0 | J30: 0 | K30: 0 | L30: 0 | M30: 0 | N30: =SUM(C30:M30) -> 2
A31: 1.31 | B31: =Presupuesto!B29 -> DESMONTE, RECOGIDA Y ENROLLADO CABLE MT URBANO TRIFASICO | C31: 0 | D31: 0 | E31: 0 | F31: 0 | G31: 0 | H31: 0 | I31: 0 | J31: 0 | K31: 0 | L31: 0 | M31: 1.47 | N31: =SUM(C31:M31) -> 1.47
A32: 1.32 | B32: =Presupuesto!B30 -> TENDIDO Y TENSIONADO DE CABLE ECOLOGICO PARA RED MT TRIFASICA 15 KV DISPOSICION HORIZONTAL | C32: 0 | D32: 0 | E32: 0 | F32: 0 | G32: 0 | H32: 0 | I32: 0 | J32: 0 | K32: 0 | L32: 0 | M32: 1.47 | N32: =SUM(C32:M32) -> 1.47
A33: 1.33 | B33: =Presupuesto!B31 -> INSTALACIÓN DE DEFENSA METALICA - ABATIMIENTO N2 | C33: 0 | D33: 0 | E33: 0 | F33: 0 | G33: 0 | H33: 0 | I33: 0 | J33: 0 | K33: 0 | L33: 0 | M33: 307 | N33: =SUM(C33:M33) -> 307
A34: 2.1 | B34: =Presupuesto!B32 -> INSTALACIÓN DE PLACAS DE IDENTIFICACIÓN DE PELIGRO RED ENERGIZADA (INCLUYE PLACA EN ACRILICO Y CONECTORES A RED) | C34: 0 | D34: 0 | E34: 0 | F34: 1 | G34: 0 | H34: 1 | I34: 1 | J34: 1 | K34: 1 | L34: 0 | M34: 0 | N34: =SUM(C34:M34) -> 5
A35: 2.2 | B35: =Presupuesto!B33 -> INSTALACIÓN DE PLACAS DE IDENTIFICACIÓN DE POSTE, (INCLUYE PLACA DE ALUMINIO, CINTA BAND IT Y HEBILLA) | C35: 0 | D35: 0 | E35: 0 | F35: 1 | G35: 0 | H35: 1 | I35: 1 | J35: 1 | K35: 1 | L35: 0 | M35: 0 | N35: =SUM(C35:M35) -> 5
A36: 2.3 | B36: =Presupuesto!B34 -> LEVANTAMIENTO DE PLANO AS-BUILT DE OBRA CONSTRUIDA, GEOREFERENCIADA, MEDIA TENSIÓN Y BAJA TENSIÓN, INCLUYE REGISTRO FOTOGRÁFICO, COPIA FÍSICA Y ARCHIVOS EN CD | C36: 0 | D36: 0 | E36: 0 | F36: 0 | G36: 0 | H36: 0 | I36: 0 | J36: 0 | K36: 0 | L36: 0 | M36: 1 | N36: =SUM(C36:M36) -> 1
A37: 2.4 | B37: =Presupuesto!B35 -> PREPARACION DISEÑO, MEMORIA DE CALCULO Y DEMAS DOCUMENTOS PARA CERTIFICACION RETIE (ART 10.1 DE RETIE-2013) | C37: 0 | D37: 0 | E37: 0 | F37: 0 | G37: 0 | H37: 0 | I37: 0 | J37: 0 | K37: 0 | L37: 0 | M37: 1 | N37: =SUM(C37:M37) -> 1
... A41: 3.2 | B41: =Presupuesto!B39 -> ELABORACIÓN DE DOSSIER Y MANUALES DE OPERACIÓN Y MANTENIMIENTO | C41: 0 | D41: 0 | E41: 0 | F41: 0 | G41: 0 | H41: 0 | I41: 0 | J41: 0 | K41: 0 | L41: 0 | M41: 1 | N41: =SUM(C41:M41) -> 1
A42: 4.1 | B42: SUMINISTRO DE MATERIALES PARA LA ESTRUCTURA P103 N2 | C42: 0 | D42: 0 | E42: 0 | F42: 0 | G42: 0 | H42: 0 | I42: 1 | J42: 1 | K42: 0 | L42: 0 | M42: 0 | N42: =SUM(C42:M42) -> 2
A43: 4.2 | B43: SUMINISTRO DE MATERIALES PARA LA ESTRUCTURA P103 N3 | C43: 0 | D43: 0 | E43: 0 | F43: 0 | G43: 1 | H43: 0 | I43: 1 | J43: 1 | K43: 0 | L43: 0 | M43: 0 | N43: =SUM(C43:M43) -> 3
A44: 4.3 | B44: SUMINISTRO DE MATERIALES PARA LA ESTRUCTURA 560 N2 | C44: 0 | D44: 0 | E44: 0 | F44: 1 | G44: 0 | H44: 0 | I44: 0 | J44: 0 | K44: 1 | L44: 0 | M44: 0 | N44: =SUM(C44:M44) -> 2
A45: 4.4 | B45: SUMINISTRO DE MATERIALES PARA LA ESTRUCTURA 562 N2 | C45: 0 | D45: 0 | E45: 0 | F45: 1 | G45: 0 | H45: 0 | I45: 0 | J45: 0 | K45: 0 | L45: 0 | M45: 0 | N45: =SUM(C45:M45) -> 1
A46: 4.5 | B46: SUMINISTRO DE MATERIALES PARA LA ESTRUCTURA 580 N2 | C46: 0 | D46: 0 | E46: 0 | F46: 0 | G46: 0 | H46: 1 | I46: 0 | J46: 0 | K46: 0 | L46: 0 | M46: 0 | N46: =SUM(C46:M46) -> 1
A47: 4.6 | B47: SUMINISTRO DE MATERIALES PARA LA ESTRUCTURA DE HILO DE GUARDA INDEPENDIENTE PARA ESTRUCTURA TIPO PASO HG-P | C47: 0 | D47: 0 | E47: 0 | F47: 1 | G47: 1 | H47: 0 | I47: 1 | J47: 1 | K47: 0 | L47: 0 | M47: 0 | N47: =SUM(C47:M47) -> 4
A48: 4.7 | B48: SUMINISTRO DE MATERIALES PARA LA ESTRUCTURA DE HILO DE GUARDA INDEPENDIENTE PARA ESTRUCTURA TIPO RETENCIÓN HG-R | C48: 0 | D48: 0 | E48: 0 | F48: 0 | G48: 0 | H48: 1 | I48: 0 | J48: 0 | K48: 1 | L48: 0 | M48: 0 | N48: =SUM(C48:M48) -> 2
A49: 4.8 | B49: SUMINISTRO DE MATERIALES PARA LA ESTRUCTURA 555 N3 | C49: 1 | D49: 0 | E49: 0 | F49: 0 | G49: 0 | H49: 2 | I49: 0 | J49: 0 | K49: 2 | L49: 1 | M49: 0 | N49: =SUM(C49:M49) -> 6
A50: 4.9 | B50: SUMINISTRO DE MATERIALES PARA LA ESTRUCTURA 619 N1 | C50: 0 | D50: 0 | E50: 0 | F50: 1 | G50: 0 | H50: 0 | I50: 0 | J50: 0 | K50: 0 | L50: 0 | M50: 0 | N50: =SUM(C50:M50) -> 1
A51: 4.10 | B51: SUMINISTRO DE TEMPLETE CUAERDA DE GUITARRA 34.5 KV | C51: 0 | D51: 0 | E51: 0 | F51: 1 | G51: 0 | H51: 2 | I51: 0 | J51: 0 | K51: 2 | L51: 0 | M51: 0 | N51: =SUM(C51:M51) -> 5
A52: 4.11 | B52: SUMINISTRO DE TEMPLETE DIRECTO A VARILLA DE ANCLAJE 34.5 KV | C52: 0 | D52: 0 | E52: 0 | F52: 2 | G52: 0 | H52: 0 | I52: 2 | J52: 2 | K52: 1 | L52: 0 | M52: 0 | N52: =SUM(C52:M52) -> 7
A53: 4.12 | B53: SUMINISTRO DE SISTEMA DE PUESTA A TIERRA REDES TRIFASICAS CON CABLE DE GUARDA POSTE SENCILLO | C53: 0 | D53: 0 | E53: 0 | F53: 1 | G53: 0 | H53: 1 | I53: 1 | J53: 1 | K53: 0 | L53: 0 | M53: 0 | N53: =SUM(C53:M53) -> 4
A54: 4.13 | B54: SUMINISTRO DE SISTEMA DE BARRERAS METÁLICAS CON ABATIMIENTO N2 | C54: 0 | D54: 0 | E54: 0 | F54: 0 | G54: 0 | H54: 0 | I54: 0 | J54: 0 | K54: 0 | L54: 0 | M54: 1 | N54: =SUM(C54:M54) -> 1
A55: 4.14 | B55: SUMINISTRO DE CABLE ECOLÓGICO TRICAPA XLPE-TK DE 4/0 | C55: 0 | D55: 0 | E55: 0 | F55: 0 | G55: 0 | H55: 0 | I55: 0 | J55: 0 | K55: 0 | L55: 0 | M55: 1 | N55: 2149
A56: 4.15 | B56: SUMINISTRO DE CABLE DE ACERO GALVANIZADO EXTRARRESISTENTE DE 1/4 GX-3000 KG PARA HILO GUARDA | C56: 0 | D56: 0 | E56: 0 | F56: 0 | G56: 0 | H56: 0 | I56: 0 | J56: 0 | K56: 0 | L56: 0 | M56: 1 | N56: 716.4
A57: 4.16 | B57: SUMINISTRO DE POSTE DE CONCRETO DE 14 M X 750 KGF VIBRADO Y REFORZADO | C57: 0 | D57: 0 | E57: 0 | F57: 0 | G57: 0 | H57: 0 | I57: 1 | J57: 1 | K57: 0 | L57: 0 | M57: 0 | N57: =SUM(C57:M57) -> 2
A58: 4.17 | B58: SUMINISTRO DE POSTE DE CONCRETO DE 14 M X 1050 KGF VIBRADO Y REFORZADO | C58: 0 | D58: 0 | E58: 0 | F58: 1 | G58: 0 | H58: 0 | I58: 0 | J58: 0 | K58: 0 | L58: 0 | M58: 0 | N58: =SUM(C58:M58) -> 1
A59: 4.18 | B59: SUMINISTRO DE POSTE DE CONCRETO DE 16 M X 1350 KGF VIBRADO Y REFORZADO | C59: 0 | D59: 0 | E59: 0 | F59: 0 | G59: 0 | H59: 1 | I59: 0 | J59: 0 | K59: 1 | L59: 0 | M59: 0 | N59: =SUM(C59:M59) -> 2
A60: 4.19 | B60: ='4.19'!B6:G6 -> SUMINISTRO DE CABLE ECOLÓGICO TRICAPA XLPE-TK 2/0 | C60: 0 | D60: 0 | E60: 0 | F60: 0 | G60: 0 | H60: 0 | I60: 0 | J60: 0 | K60: 0 | L60: 0 | M60: 1 | N60: 1470

Sheet Listado actividades
A1: Poste E100
A2: Código | B2: Actividad | C2: Cantidad
A3: 1.18 | B3: =VLOOKUP(A3,APU_P!$A$3:$M$59,2,FALSE) -> VESTIDA DE ESTRUCTURA TRIFASICA DE UN POSTE TIPO RETENCIÓN - 34.5 KV | C3: =VLOOKUP(A3,APU_P!$A$3:$M$56,3,FALSE) -> 1 | D3: =VLOOKUP(A3,Presupuesto!$A$5:$J$58,10,FALSE) -> 339503.99 | E3: Se instalará una estructura terminal 555 N3 con el fin de acoplar la linea 34,5kV proyectada con la existente
A4: 1.19 | B4: =VLOOKUP(A4,APU_P!$A$3:$M$59,2,FALSE) -> VESTIDA ESTRUCTURA CABLE DE GUARDA - RETENCION | C4: =VLOOKUP(A4,APU_P!$A$3:$M$56,3,FALSE) -> 0 | D4: =VLOOKUP(A4,Presupuesto!$A$5:$J$58,10,FALSE) -> 105413.07
A5: 4.8 | B5: =VLOOKUP(A5,APU_P!$A$3:$M$59,2,FALSE) -> SUMINISTRO DE MATERIALES PARA LA ESTRUCTURA 555 N3 | C5: 1 | D5: =VLOOKUP(A5,Presupuesto!$A$5:$J$58,10,FALSE) -> 1269542.3
A6: TOTAL | D6: =SUM(D3:D5) -> 1714459.3
A7: Poste E99
A8: Código | B8: Actividad
A14: Poste E97
A15: Código | B15: Actividad | C15: Cantidad
A16: 1.3 | B16: =VLOOKUP(A16,APU_P!$A$3:$B$59,2,FALSE) -> APERTURA DE EXCAVACION PARA VIGUETA EN RETENIDA RURAL | C16: =VLOOKUP(A16,APU_P!$A$3:$M$56,6,FALSE) -> 3 | D16: =VLOOKUP(A16,Presupuesto!$A$5:$J$58,10,FALSE) -> 92232.969 | E16: Se reemplazará el poste de concreto de 14m 1050 kg, se debe desvestir las estructuras instaladas, y retirar el poste. Posteriormente se hincará y vestira con las estructuras 619, 560 y 562 de retención para N1, N2 y N3 respectivamente. Además se harán excavaciones de viguetas para instalación de templetes, junto con la instalación del sistema de puesta a tierra. Al poste se instalará placas de peligro de red energizada y de identificación.
A17: 1.6 | B17: =VLOOKUP(A17,APU_P!$A$3:$B$59,2,FALSE) -> HINCADA, PLOMADA Y ORIENTACIÓN DE POSTE DE 14, 16 Y 18 MTS CON GRUA | C17: =VLOOKUP(A17,APU_P!$A$3:$M$56,6,FALSE) -> 1 | D17: =VLOOKUP(A17,Presupuesto!$A$5:$J$58,10,FALSE) -> 418245.81
A18: 1.7 | B18: =VLOOKUP(A18,APU_P!$A$3:$B$59,2,FALSE) -> INSTALACION LINE A TIERRA MEDIA TENSION | C18: =VLOOKUP(A18,APU_P!$A$3:$M$56,6,FALSE) -> 1 | D18: =VLOOKUP(A18,Presupuesto!$A$5:$J$58,10,FALSE) -> 143889.32
A19: 1.8 | B19: =VLOOKUP(A19,APU_P!$A$3:$B$59,2,FALSE) -> INSTALACIÓN DE TEMPLETE CUERDA GUITARRA CON TODOS SUS ACCESORIOS M.T. RURAL | C19: =VLOOKUP(A19,APU_P!$A$3:$M$56,6,FALSE) -> 1 | D19: =VLOOKUP(A19,Presupuesto!$A$5:$J$58,10,FALSE) -> 100479.29
A20: 1.12 | B20: =VLOOKUP(A20,APU_P!$A$3:$B$59,2,FALSE) -> TRANSPORTE DE POSTE 14 MTS M.T. RURAL DE BODEGA A SITIO CERCANO | C20: =VLOOKUP(A20,APU_P!$A$3:$M$56,6,FALSE) -> 1 | D20: =VLOOKUP(A20,Presupuesto!$A$5:$J$58,10,FALSE) -> 372676.45
A21: 1.16 | B21: =VLOOKUP(A21,APU_P!$A$3:$B$59,2,FALSE) -> VESTIDA DE ESTRUCTURA TRIFASICA DE RETENCION UN POSTE 13,8 Kv | C21: =VLOOKUP(A21,APU_P!$A$3:$M$56,6,FALSE) -> 1 | D21: =VLOOKUP(A21,Presupuesto!$A$5:$J$58,10,FALSE) -> 136496.99
A22: 1.18 | B22: =VLOOKUP(A22,APU_P!$A$3:$B$59,2,FALSE) -> VESTIDA DE ESTRUCTURA TRIFASICA DE UN POSTE TIPO RETENCIÓN - 34.5 KV | C22: =VLOOKUP(A22,APU_P!$A$3:$M$56,6,FALSE) -> 1 | D22: =VLOOKUP(A22,Presupuesto!$A$5:$J$58,10,FALSE) -> 339503.99
A23: 1.19 | B23: =VLOOKUP(A23,APU_P!$A$3:$B$59,2,FALSE) -> VESTIDA ESTRUCTURA CABLE DE GUARDA - RETENCION | C23: =VLOOKUP(A23,APU_P!$A$3:$M$56,6,FALSE) -> 1 | D23: =VLOOKUP(A23,Presupuesto!$A$5:$J$58,10,FALSE) -> 105413.07
A24: 1.21 | B24: =VLOOKUP(A24,APU_P!$A$3:$B$59,2,FALSE) -> DESVESTIDA ESTRUCTURA DE RETENCION MT RURAL | C24: =VLOOKUP(A24,APU_P!$A$3:$M$56,6,FALSE) -> 1 | D24: =VLOOKUP(A24,Presupuesto!$A$5:$J$58,10,FALSE) -> 143889.32
A25: 1.23 | B25: =VLOOKUP(A25,APU_P!$A$3:$B$59,2,FALSE) -> DESHINCADA DE POSTES 10, 12 Y 14 mts MT | C25: =VLOOKUP(A25,APU_P!$A$3:$M$56,6,FALSE) -> 1 | D25: =VLOOKUP(A25,Presupuesto!$A$5:$J$58,10,FALSE) -> 527904.55
A26: 1.24 | B26: =VLOOKUP(A26,APU_P!$A$3:$B$59,2,FALSE) -> INSTALACIÓN DE TEMPLETE SENCILLO CON TODOS SUS ACCESORIOS M.T. RURAL | C26: =VLOOKUP(A26,APU_P!$A$3:$M$56,6,FALSE) -> 2 | D26: =VLOOKUP(A26,Presupuesto!$A$5:$J$58,10,FALSE) -> 86009.275
A27: 1.25 | B27: =VLOOKUP(A27,APU_P!$A$3:$B$59,2,FALSE) -> #REF! | C27: =VLOOKUP(A27,APU_P!$A$3:$M$56,6,FALSE) -> 1 | D27: =VLOOKUP(A27,Presupuesto!$A$5:$J$58,10,FALSE) -> #N/A
A28: 1.26 | B28: =VLOOKUP(A28,APU_P!$A$3:$B$59,2,FALSE) -> TRANSPORTE DE POSTE RURAL DE SITIO CERCANO A BODEGA EH | C28: =VLOOKUP(A28,APU_P!$A$3:$M$56,6,FALSE) -> 1 | D28: =VLOOKUP(A28,Presupuesto!$A$5:$J$58,10,FALSE) -> 208958.59
... A35: 4.6 | B35: =VLOOKUP(A35,APU_P!$A$3:$B$59,2,FALSE) -> SUMINISTRO DE MATERIALES PARA LA ESTRUCTURA DE HILO DE GUARDA INDEPENDIENTE PARA ESTRUCTURA TIPO PASO HG-P | C35: =VLOOKUP(A35,APU_P!$A$3:$M$56,6,FALSE) -> 1 | D35: =VLOOKUP(A35,Presupuesto!$A$5:$J$58,10,FALSE) -> 149297.16
A36: 4.9 | B36: =VLOOKUP(A36,APU_P!$A$3:$B$59,2,FALSE) -> SUMINISTRO DE MATERIALES PARA LA ESTRUCTURA 619 N1 | C36: =VLOOKUP(A36,APU_P!$A$3:$M$59,6,FALSE) -> 1 | D36: =VLOOKUP(A36,Presupuesto!$A$5:$J$58,10,FALSE) -> 99742.293
A37: 4.10 | B37: =VLOOKUP(A37,APU_P!$A$3:$B$59,2,FALSE) -> SUMINISTRO DE TEMPLETE CUAERDA DE GUITARRA 34.5 KV | C37: =VLOOKUP(A37,APU_P!$A$3:$M$59,6,FALSE) -> 1 | D37: =VLOOKUP(A37,Presupuesto!$A$5:$J$58,10,FALSE) -> 458854.66
A38: 4.11 | B38: =VLOOKUP(A38,APU_P!$A$3:$B$59,2,FALSE) -> SUMINISTRO DE TEMPLETE DIRECTO A VARILLA DE ANCLAJE 34.5 KV | C38: =VLOOKUP(A38,APU_P!$A$3:$M$59,6,FALSE) -> 2 | D38: =VLOOKUP(A38,Presupuesto!$A$5:$J$58,10,FALSE) -> 376404.16
A39: 4.12 | B39: =VLOOKUP(A39,APU_P!$A$3:$B$59,2,FALSE) -> SUMINISTRO DE SISTEMA DE PUESTA A TIERRA REDES TRIFASICAS CON CABLE DE GUARDA POSTE SENCILLO | C39: =VLOOKUP(A39,APU_P!$A$3:$M$59,6,FALSE) -> 1 | D39: =VLOOKUP(A39,Presupuesto!$A$5:$J$58,10,FALSE) -> 159930.21
A40: 4.17 | B40: =VLOOKUP(A40,APU_P!$A$3:$B$59,2,FALSE) -> SUMINISTRO DE POSTE DE CONCRETO DE 14 M X 1050 KGF VIBRADO Y REFORZADO | C40: =VLOOKUP(A40,APU_P!$A$3:$M$59,6,FALSE) -> 1 | D40: =VLOOKUP(A40,Presupuesto!$A$5:$J$58,10,FALSE) -> 3151689
A41: TOTAL | D41: =SUM(D16:D40) -> #N/A
A42: Poste E96
A43: Código | B43: Actividad | C43: Cantidad
A44: 1.17 | B44: =VLOOKUP(A44,APU_P!$A$3:$M$56,2,FALSE) -> VESTIDA DE ESTRUCTURA TRIFASICA DE UN POSTE TIPO PASO 34.5 KV | C44: =VLOOKUP(A44,APU_P!$A$3:$M$56,7,FALSE) -> 1 | D44: =VLOOKUP(A44,Presupuesto!$A$5:$J$58,10,FALSE) -> 254628 | E44: Se instalará una estructura trifásica tipo paso 103N3 y una estructura de hilo guarda tipo paso.
A45: 1.20 | B45: =VLOOKUP(A45,APU_P!$A$3:$M$56,2,FALSE) -> VESTIDA ESTRUCTURA CABLE DE GUARDA DE PASO | C45: =VLOOKUP(A45,APU_P!$A$3:$M$56,7,FALSE) -> 1 | D45: =VLOOKUP(A45,Presupuesto!$A$5:$J$58,10,FALSE) -> 92236.437
A46: 4.2 | B46: =VLOOKUP(A46,APU_P!$A$3:$M$56,2,FALSE) -> SUMINISTRO DE MATERIALES PARA LA ESTRUCTURA P103 N3 | C46: =VLOOKUP(A46,APU_P!$A$3:$M$56,7,FALSE) -> 1 | D46: =VLOOKUP(A46,Presupuesto!$A$5:$J$58,10,FALSE) -> 467060.34
A47: 4.6 | B47: =VLOOKUP(A47,APU_P!$A$3:$M$56,2,FALSE) -> SUMINISTRO DE MATERIALES PARA LA ESTRUCTURA DE HILO DE GUARDA INDEPENDIENTE PARA ESTRUCTURA TIPO PASO HG-P | C47: =VLOOKUP(A47,APU_P!$A$3:$M$56,7,FALSE) -> 1 | D47: =VLOOKUP(A47,Presupuesto!$A$5:$J$58,10,FALSE) -> 149297.16
A48: TOTAL | D48: =SUM(D44:D47) -> 963221.93
A49: Poste E95D
A50: Código | B50: Actividad | C50: Cantidad
A51: 1.3 | B51: =VLOOKUP(A51,APU_P!$A$3:$M$59,2,FALSE) -> APERTURA DE EXCAVACION PARA VIGUETA EN RETENIDA RURAL | C51: =VLOOKUP(A51,APU_P!$A$3:$M$59,8,FALSE) -> 2 | D51: =VLOOKUP(A51,Presupuesto!$A$5:$J$58,10,FALSE) -> 92232.969 | E51: Se reemplazará el poste de concreto de 14m por uno de 16m 1350 kg, se debe desvestir las estructuras instaladas, desmontar un transformador monofásico y retirar el poste. Posteriormente se hincará y vestirá el nuevo poste con las estructuras trifásicas 580 N2 y dos 555 N3. Se realizará el montaje del transformador monofásico. Además se harán excavaciones de viguetas para instalación de templetes, junto con la instalación del sistema de puesta a tierra. Al poste se le instalarán placas de peligro de red energizada y de identificación.
A52: 1.6 | B52: =VLOOKUP(A52,APU_P!$A$3:$M$59,2,FALSE) -> HINCADA, PLOMADA Y ORIENTACIÓN DE POSTE DE 14, 16 Y 18 MTS CON GRUA | C52: =VLOOKUP(A52,APU_P!$A$3:$M$59,8,FALSE) -> 1 | D52: =VLOOKUP(A52,Presupuesto!$A$5:$J$58,10,FALSE) -> 418245.81
A53: 1.7 | B53: =VLOOKUP(A53,APU_P!$A$3:$M$59,2,FALSE) -> INSTALACION LINE A TIERRA MEDIA TENSION | C53: =VLOOKUP(A53,APU_P!$A$3:$M$59,8,FALSE) -> 1 | D53: =VLOOKUP(A53,Presupuesto!$A$5:$J$58,10,FALSE) -> 143889.32
A54: 1.8 | B54: =VLOOKUP(A54,APU_P!$A$3:$M$59,2,FALSE) -> INSTALACIÓN DE TEMPLETE CUERDA GUITARRA CON TODOS SUS ACCESORIOS M.T. RURAL | C54: =VLOOKUP(A54,APU_P!$A$3:$M$59,8,FALSE) -> 2 | D54: =VLOOKUP(A54,Presupuesto!$A$5:$J$58,10,FALSE) -> 100479.29
A55: 1.12 | B55: =VLOOKUP(A55,APU_P!$A$3:$M$59,2,FALSE) -> TRANSPORTE DE POSTE 14 MTS M.T. RURAL DE BODEGA A SITIO CERCANO | C55: =VLOOKUP(A55,APU_P!$A$3:$M$59,8,FALSE) -> 1 | D55: =VLOOKUP(A55,Presupuesto!$A$5:$J$58,10,FALSE) -> 372676.45
A56: 1.16 | B56: =VLOOKUP(A56,APU_P!$A$3:$M$59,2,FALSE) -> VESTIDA DE ESTRUCTURA TRIFASICA DE RETENCION UN POSTE 13,8 Kv | C56: =VLOOKUP(A56,APU_P!$A$3:$M$59,8,FALSE) -> 1 | D56: =VLOOKUP(A56,Presupuesto!$A$5:$J$58,10,FALSE) -> 136496.99
A57: 1.18 | B57: =VLOOKUP(A57,APU_P!$A$3:$M$59,2,FALSE) -> VESTIDA DE ESTRUCTURA TRIFASICA DE UN POSTE TIPO RETENCIÓN - 34.5 KV | C57: =VLOOKUP(A57,APU_P!$A$3:$M$59,8,FALSE) -> 1 | D57: =VLOOKUP(A57,Presupuesto!$A$5:$J$58,10,FALSE) -> 339503.99
A58: 1.19 | B58: =VLOOKUP(A58,APU_P!$A$3:$M$59,2,FALSE) -> VESTIDA ESTRUCTURA CABLE DE GUARDA - RETENCION | C58: =VLOOKUP(A58,APU_P!$A$3:$M$59,8,FALSE) -> 1 | D58: =VLOOKUP(A58,Presupuesto!$A$5:$J$58,10,FALSE) -> 105413.07
A59: 1.21 | B59: =VLOOKUP(A59,APU_P!$A$3:$M$59,2,FALSE) -> DESVESTIDA ESTRUCTURA DE RETENCION MT RURAL | C59: =VLOOKUP(A59,APU_P!$A$3:$M$59,8,FALSE) -> 1 | D59: =VLOOKUP(A59,Presupuesto!$A$5:$J$58,10,FALSE) -> 143889.32
A60: 1.23 | B60: =VLOOKUP(A60,APU_P!$A$3:$M$59,2,FALSE) -> DESHINCADA DE POSTES 10, 12 Y 14 mts MT | C60: =VLOOKUP(A60,APU_P!$A$3:$M$59,8,FALSE) -> 1 | D60: =VLOOKUP(A60,Presupuesto!$A$5:$J$58,10,FALSE) -> 527904.55
A61: 1.25 | B61: =VLOOKUP(A61,APU_P!$A$3:$M$59,2,FALSE) -> #REF! | C61: =VLOOKUP(A61,APU_P!$A$3:$M$59,8,FALSE) -> 1 | D61: =VLOOKUP(A61,Presupuesto!$A$5:$J$58,10,FALSE) -> #N/A
A62: 1.26 | B62: =VLOOKUP(A62,APU_P!$A$3:$M$59,2,FALSE) -> TRANSPORTE DE POSTE RURAL DE SITIO CERCANO A BODEGA EH | C62: =VLOOKUP(A62,APU_P!$A$3:$M$59,8,FALSE) -> 1 | D62: =VLOOKUP(A62,Presupuesto!$A$5:$J$58,10,FALSE) -> 208958.59
A63: 1.27 | B63: =VLOOKUP(A63,APU_P!$A$3:$M$59,2,FALSE) -> DESMONTE DE TRANSFORMADOR MONOFASICO | C63: =VLOOKUP(A63,APU_P!$A$3:$M$59,8,FALSE) -> 1 | D63: =VLOOKUP(A63,Presupuesto!$A$5:$J$58,10,FALSE) -> 406908.96
... A74: 4.18 | B74: =VLOOKUP(A74,APU_P!$A$3:$M$59,2,FALSE) -> SUMINISTRO DE POSTE DE CONCRETO DE 16 M X 1350 KGF VIBRADO Y REFORZADO | C74: =VLOOKUP(A74,APU_P!$A$3:$M$59,8,FALSE) -> 1 | D74: =VLOOKUP(A74,Presupuesto!$A$5:$J$58,10,FALSE) -> 4801050.4
A75: TOTAL | D75: =SUM(D51:D74) -> #N/A
A76: Poste E95C
A77: Código | B77: Actividad | C77: Cantidad
A78: 1.2 | B78: =VLOOKUP(A78,APU_P!$A$3:$M$59,2,FALSE) -> APERTURA DE EXCAVACION POSTE DE 14 MTS M.T. RURAL | C78: =VLOOKUP(A78,APU_P!$A$3:$M$59,9,FALSE) -> 1 | D78: =VLOOKUP(A78,Presupuesto!$A$5:$J$58,10,FALSE) -> 208106.49 | E78: Se realizará la excavación e hincada de un poste de 14m 750kg. Se instalarán estructuras trifásicas de tipo paso P102N2 y P103N3. Además se harán excavaciones de viguetas para instalación de templetes, junto con la instalación del sistema de puesta a tierra. Al poste se le instalarán placas de peligro de red energizada y de identificación.
A79: 1.3 | B79: =VLOOKUP(A79,APU_P!$A$3:$M$59,2,FALSE) -> APERTURA DE EXCAVACION PARA VIGUETA EN RETENIDA RURAL | C79: =VLOOKUP(A79,APU_P!$A$3:$M$59,9,FALSE) -> 2 | D79: =VLOOKUP(A79,Presupuesto!$A$5:$J$58,10,FALSE) -> 92232.969
A80: 1.6 | B80: =VLOOKUP(A80,APU_P!$A$3:$M$59,2,FALSE) -> HINCADA, PLOMADA Y ORIENTACIÓN DE POSTE DE 14, 16 Y 18 MTS CON GRUA | C80: =VLOOKUP(A80,APU_P!$A$3:$M$59,9,FALSE) -> 1 | D80: =VLOOKUP(A80,Presupuesto!$A$5:$J$58,10,FALSE) -> 418245.81
A81: 1.7 | B81: =VLOOKUP(A81,APU_P!$A$3:$M$59,2,FALSE) -> INSTALACION LINE A TIERRA MEDIA TENSION | C81: =VLOOKUP(A81,APU_P!$A$3:$M$59,9,FALSE) -> 1 | D81: =VLOOKUP(A81,Presupuesto!$A$5:$J$58,10,FALSE) -> 143889.32
A82: 1.12 | B82: =VLOOKUP(A82,APU_P!$A$3:$M$59,2,FALSE) -> TRANSPORTE DE POSTE 14 MTS M.T. RURAL DE BODEGA A SITIO CERCANO | C82: =VLOOKUP(A82,APU_P!$A$3:$M$59,9,FALSE) -> 1 | D82: =VLOOKUP(A82,Presupuesto!$A$5:$J$58,10,FALSE) -> 372676.45
A83: 1.15 | B83: =VLOOKUP(A83,APU_P!$A$3:$M$59,2,FALSE) -> VESTIDA DE ESTRUCTURA TRIFASICA DE PASO UN POSTE 13,8kV | C83: =VLOOKUP(A83,APU_P!$A$3:$M$59,9,FALSE) -> 1 | D83: =VLOOKUP(A83,Presupuesto!$A$5:$J$58,10,FALSE) -> 102381.27
A84: 1.17 | B84: =VLOOKUP(A84,APU_P!$A$3:$M$59,2,FALSE) -> VESTIDA DE ESTRUCTURA TRIFASICA DE UN POSTE TIPO PASO 34.5 KV | C84: =VLOOKUP(A84,APU_P!$A$3:$M$59,9,FALSE) -> 1 | D84: =VLOOKUP(A84,Presupuesto!$A$5:$J$58,10,FALSE) -> 254628
A85: 1.20 | B85: =VLOOKUP(A85,APU_P!$A$3:$M$59,2,FALSE) -> VESTIDA ESTRUCTURA CABLE DE GUARDA DE PASO | C85: =VLOOKUP(A85,APU_P!$A$3:$M$59,9,FALSE) -> 1 | D85: =VLOOKUP(A85,Presupuesto!$A$5:$J$58,10,FALSE) -> 92236.437
A86: 1.24 | B86: =VLOOKUP(A86,APU_P!$A$3:$M$59,2,FALSE) -> INSTALACIÓN DE TEMPLETE SENCILLO CON TODOS SUS ACCESORIOS M.T. RURAL | C86: =VLOOKUP(A86,APU_P!$A$3:$M$59,9,FALSE) -> 2 | D86: =VLOOKUP(A86,Presupuesto!$A$5:$J$58,10,FALSE) -> 86009.275
A87: 2.1 | B87: =VLOOKUP(A87,APU_P!$A$3:$M$59,2,FALSE) -> INSTALACIÓN DE PLACAS DE IDENTIFICACIÓN DE PELIGRO RED ENERGIZADA (INCLUYE PLACA EN ACRILICO Y CONECTORES A RED) | C87: =VLOOKUP(A87,APU_P!$A$3:$M$59,9,FALSE) -> 1 | D87: =VLOOKUP(A87,Presupuesto!$A$5:$J$58,10,FALSE) -> 44367.324
A88: 2.2 | B88: =VLOOKUP(A88,APU_P!$A$3:$M$59,2,FALSE) -> INSTALACIÓN DE PLACAS DE IDENTIFICACIÓN DE POSTE, (INCLUYE PLACA DE ALUMINIO, CINTA BAND IT Y HEBILLA) | C88: =VLOOKUP(A88,APU_P!$A$3:$M$59,9,FALSE) -> 1 | D88: =VLOOKUP(A88,Presupuesto!$A$5:$J$58,10,FALSE) -> 37835.817
A89: 4.1 | B89: =VLOOKUP(A89,APU_P!$A$3:$M$59,2,FALSE) -> SUMINISTRO DE MATERIALES PARA LA ESTRUCTURA P103 N2 | C89: =VLOOKUP(A89,APU_P!$A$3:$M$59,9,FALSE) -> 1 | D89: =VLOOKUP(A89,Presupuesto!$A$5:$J$58,10,FALSE) -> 429643.28
A90: 4.2 | B90: =VLOOKUP(A90,APU_P!$A$3:$M$59,2,FALSE) -> SUMINISTRO DE MATERIALES PARA LA ESTRUCTURA P103 N3 | C90: =VLOOKUP(A90,APU_P!$A$3:$M$59,9,FALSE) -> 1 | D90: =VLOOKUP(A90,Presupuesto!$A$5:$J$58,10,FALSE) -> 467060.34
... A94: 4.16 | B94: =VLOOKUP(A94,APU_P!$A$3:$M$59,2,FALSE) -> SUMINISTRO DE POSTE DE CONCRETO DE 14 M X 750 KGF VIBRADO Y REFORZADO | C94: =VLOOKUP(A94,APU_P!$A$3:$M$59,9,FALSE) -> 1 | D94: =VLOOKUP(A94,Presupuesto!$A$5:$J$58,10,FALSE) -> 2178445
A95: TOTAL | D95: =SUM(D78:D94) -> 5613389.3
A96: Poste E95B
A97: Código | B97: Actividad | C97: Cantidad | E97: Se realizará la desvestida y deshincada de poste de 14m. Se realizará la excavación e hincada de un poste de 14m 750kg en las coordenadas especificadas en el plano. Se instalarán estructuras trifásicas de tipo paso P102N2 y P103N3. Además se harán excavaciones de viguetas para instalación de templetes, junto con la instalación del sistema de puesta a tierra. Al poste se le instalarán placas de peligro de red energizada y de identificación.
A98: 1.2 | B98: =VLOOKUP(A98,APU_P!$A$3:$M$59,2,FALSE) -> APERTURA DE EXCAVACION POSTE DE 14 MTS M.T. RURAL | C98: =VLOOKUP(A98,APU_P!$A$3:$M$59,10,FALSE) -> 1 | D98: =VLOOKUP(A98,Presupuesto!$A$5:$J$58,10,FALSE) -> 208106.49
A99: 1.3 | B99: =VLOOKUP(A99,APU_P!$A$3:$M$59,2,FALSE) -> APERTURA DE EXCAVACION PARA VIGUETA EN RETENIDA RURAL | C99: =VLOOKUP(A99,APU_P!$A$3:$M$59,10,FALSE) -> 2 | D99: =VLOOKUP(A99,Presupuesto!$A$5:$J$58,10,FALSE) -> 92232.969
A100: 1.6 | B100: =VLOOKUP(A100,APU_P!$A$3:$M$59,2,FALSE) -> HINCADA, PLOMADA Y ORIENTACIÓN DE POSTE DE 14, 16 Y 18 MTS CON GRUA | C100: =VLOOKUP(A100,APU_P!$A$3:$M$59,10,FALSE) -> 1 | D100: =VLOOKUP(A100,Presupuesto!$A$5:$J$58,10,FALSE) -> 418245.81
A101: 1.7 | B101: =VLOOKUP(A101,APU_P!$A$3:$M$59,2,FALSE) -> INSTALACION LINE A TIERRA MEDIA TENSION | C101: =VLOOKUP(A101,APU_P!$A$3:$M$59,10,FALSE) -> 1 | D101: =VLOOKUP(A101,Presupuesto!$A$5:$J$58,10,FALSE) -> 143889.32
A102: 1.12 | B102: =VLOOKUP(A102,APU_P!$A$3:$M$59,2,FALSE) -> TRANSPORTE DE POSTE 14 MTS M.T. RURAL DE BODEGA A SITIO CERCANO | C102: =VLOOKUP(A102,APU_P!$A$3:$M$59,10,FALSE) -> 1 | D102: =VLOOKUP(A102,Presupuesto!$A$5:$J$58,10,FALSE) -> 372676.45
A103: 1.15 | B103: =VLOOKUP(A103,APU_P!$A$3:$M$59,2,FALSE) -> VESTIDA DE ESTRUCTURA TRIFASICA DE PASO UN POSTE 13,8kV | C103: =VLOOKUP(A103,APU_P!$A$3:$M$59,10,FALSE) -> 1 | D103: =VLOOKUP(A103,Presupuesto!$A$5:$J$58,10,FALSE) -> 102381.27
A104: 1.17 | B104: =VLOOKUP(A104,APU_P!$A$3:$M$59,2,FALSE) -> VESTIDA DE ESTRUCTURA TRIFASICA DE UN POSTE TIPO PASO 34.5 KV | C104: =VLOOKUP(A104,APU_P!$A$3:$M$59,10,FALSE) -> 1 | D104: =VLOOKUP(A104,Presupuesto!$A$5:$J$58,10,FALSE) -> 254628
A105: 1.20 | B105: =VLOOKUP(A105,APU_P!$A$3:$M$59,2,FALSE) -> VESTIDA ESTRUCTURA CABLE DE GUARDA DE PASO | C105: =VLOOKUP(A105,APU_P!$A$3:$M$59,10,FALSE) -> 1 | D105: =VLOOKUP(A105,Presupuesto!$A$5:$J$58,10,FALSE) -> 92236.437
A106: 1.22 | B106: =VLOOKUP(A106,APU_P!$A$3:$M$59,2,FALSE) -> DESVESTIDA ESTRUCTURA DE SUSPENSION MT RURAL | C106: =VLOOKUP(A106,APU_P!$A$3:$M$59,10,FALSE) -> 1 | D106: =VLOOKUP(A106,Presupuesto!$A$5:$J$58,10,FALSE) -> 100479.29
A107: 1.23 | B107: =VLOOKUP(A107,APU_P!$A$3:$M$59,2,FALSE) -> DESHINCADA DE POSTES 10, 12 Y 14 mts MT | C107: =VLOOKUP(A107,APU_P!$A$3:$M$59,10,FALSE) -> 1 | D107: =VLOOKUP(A107,Presupuesto!$A$5:$J$58,10,FALSE) -> 527904.55
A108: 1.24 | B108: =VLOOKUP(A108,APU_P!$A$3:$M$59,2,FALSE) -> INSTALACIÓN DE TEMPLETE SENCILLO CON TODOS SUS ACCESORIOS M.T. RURAL | C108: =VLOOKUP(A108,APU_P!$A$3:$M$59,10,FALSE) -> 2 | D108: =VLOOKUP(A108,Presupuesto!$A$5:$J$58,10,FALSE) -> 86009.275
A109: 1.25 | B109: =VLOOKUP(A109,APU_P!$A$3:$M$59,2,FALSE) -> #REF! | C109: =VLOOKUP(A109,APU_P!$A$3:$M$59,10,FALSE) -> 1 | D109: =VLOOKUP(A109,Presupuesto!$A$5:$J$58,10,FALSE) -> #N/A
... A118: 4.16 | B118: =VLOOKUP(A118,APU_P!$A$3:$M$59,2,FALSE) -> SUMINISTRO DE POSTE DE CONCRETO DE 14 M X 750 KGF VIBRADO Y REFORZADO | C118: =VLOOKUP(A118,APU_P!$A$3:$M$59,10,FALSE) -> 1 | D118: =VLOOKUP(A118,Presupuesto!$A$5:$J$58,10,FALSE) -> 2178445
A119: TOTAL | D119: =SUM(D98:D118) -> #N/A
A120: Poste E95A
A121: Código | B121: Actividad | C121: Cantidad
A122: 1.3 | B122: =VLOOKUP(A122,APU_P!$A$3:$M$59,2,FALSE) -> APERTURA DE EXCAVACION PARA VIGUETA EN RETENIDA RURAL | C122: =VLOOKUP(A122,APU_P!$A$3:$M$59,11,FALSE) -> 3 | D122: =VLOOKUP(A122,Presupuesto!$A$5:$J$58,10,FALSE) -> 92232.969 | E122: Se reemplazará el poste de concreto de 14m por uno de 16m 1350 kg, se debe desvestir las estructuras instaladas y retirar el poste. Posteriormente se hincará y vestirá el nuevo poste con las estructuras trifásicas 560 N2 (tipo paso) y dos 555 N3. Además se harán excavaciones de viguetas para instalación de templetes. Al poste se le instalarán placas de peligro de red energizada y de identificación.
A123: 1.6 | B123: =VLOOKUP(A123,APU_P!$A$3:$M$59,2,FALSE) -> HINCADA, PLOMADA Y ORIENTACIÓN DE POSTE DE 14, 16 Y 18 MTS CON GRUA | C123: =VLOOKUP(A123,APU_P!$A$3:$M$59,11,FALSE) -> 1 | D123: =VLOOKUP(A123,Presupuesto!$A$5:$J$58,10,FALSE) -> 418245.81
A124: 1.8 | B124: =VLOOKUP(A124,APU_P!$A$3:$M$59,2,FALSE) -> INSTALACIÓN DE TEMPLETE CUERDA GUITARRA CON TODOS SUS ACCESORIOS M.T. RURAL | C124: =VLOOKUP(A124,APU_P!$A$3:$M$59,11,FALSE) -> 2 | D124: =VLOOKUP(A124,Presupuesto!$A$5:$J$58,10,FALSE) -> 100479.29
A125: 1.12 | B125: =VLOOKUP(A125,APU_P!$A$3:$M$59,2,FALSE) -> TRANSPORTE DE POSTE 14 MTS M.T. RURAL DE BODEGA A SITIO CERCANO | C125: =VLOOKUP(A125,APU_P!$A$3:$M$59,11,FALSE) -> 1 | D125: =VLOOKUP(A125,Presupuesto!$A$5:$J$58,10,FALSE) -> 372676.45
A126: 1.15 | B126: =VLOOKUP(A126,APU_P!$A$3:$M$59,2,FALSE) -> VESTIDA DE ESTRUCTURA TRIFASICA DE PASO UN POSTE 13,8kV | C126: =VLOOKUP(A126,APU_P!$A$3:$M$59,11,FALSE) -> 1 | D126: =VLOOKUP(A126,Presupuesto!$A$5:$J$58,10,FALSE) -> 102381.27
A127: 1.18 | B127: =VLOOKUP(A127,APU_P!$A$3:$M$59,2,FALSE) -> VESTIDA DE ESTRUCTURA TRIFASICA DE UN POSTE TIPO RETENCIÓN - 34.5 KV | C127: =VLOOKUP(A127,APU_P!$A$3:$M$59,11,FALSE) -> 1 | D127: =VLOOKUP(A127,Presupuesto!$A$5:$J$58,10,FALSE) -> 339503.99
A128: 1.19 | B128: =VLOOKUP(A128,APU_P!$A$3:$M$59,2,FALSE) -> VESTIDA ESTRUCTURA CABLE DE GUARDA - RETENCION | C128: =VLOOKUP(A128,APU_P!$A$3:$M$59,11,FALSE) -> 1 | D128: =VLOOKUP(A128,Presupuesto!$A$5:$J$58,10,FALSE) -> 105413.07
A129: 1.21 | B129: =VLOOKUP(A129,APU_P!$A$3:$M$59,2,FALSE) -> DESVESTIDA ESTRUCTURA DE RETENCION MT RURAL | C129: =VLOOKUP(A129,APU_P!$A$3:$M$59,11,FALSE) -> 1 | D129: =VLOOKUP(A129,Presupuesto!$A$5:$J$58,10,FALSE) -> 143889.32
A130: 1.23 | B130: =VLOOKUP(A130,APU_P!$A$3:$M$59,2,FALSE) -> DESHINCADA DE POSTES 10, 12 Y 14 mts MT | C130: =VLOOKUP(A130,APU_P!$A$3:$M$59,11,FALSE) -> 1 | D130: =VLOOKUP(A130,Presupuesto!$A$5:$J$58,10,FALSE) -> 527904.55
A131: 1.24 | B131: =VLOOKUP(A131,APU_P!$A$3:$M$59,2,FALSE) -> INSTALACIÓN DE TEMPLETE SENCILLO CON TODOS SUS ACCESORIOS M.T. RURAL | C131: =VLOOKUP(A131,APU_P!$A$3:$M$59,11,FALSE) -> 1 | D131: =VLOOKUP(A131,Presupuesto!$A$5:$J$58,10,FALSE) -> 86009.275
A132: 1.25 | B132: =VLOOKUP(A132,APU_P!$A$3:$M$59,2,FALSE) -> #REF! | C132: =VLOOKUP(A132,APU_P!$A$3:$M$59,11,FALSE) -> 1 | D132: =VLOOKUP(A132,Presupuesto!$A$5:$J$58,10,FALSE) -> #N/A
...

Sheet 1.1
A1: ACARREO, HINCADA, PLOMADA Y ORIENTACIÓN DE POSTE PRFV EMBONADO DE 12 Y 14 M
A2: ANALISIS DE PRECIOS UNITARIOS ( A.P.U )
A4: Item: | B4: 1.1 | E4: Vr Unitario Item: | F4: =H67 -> 175274.36 | G4: Fecha: | H4: 22/05//2025
A6: Actividad: | B6: =A1 -> ACARREO, HINCADA, PLOMADA Y ORIENTACIÓN DE POSTE PRFV EMBONADO DE 12 Y 14 M | H6: UN
A9: A. MATERIAL
A10: Referencia | B10: Descripción | E10: Unidad | F10: Vr. Unitario | G10: Cantidad | H10: Vr. Total
H11: =F11*G11 -> 0
H12: =F12*G12 -> 0
H13: =F13*G13 -> 0
H14: =F14*G14 -> 0
H15: =F15*G15 -> 0
H16: =F16*G16 -> 0
A17: Subtotal A | H17: =SUM(H11:H16) -> 0
A19: B. MANO DE OBRA
A20: Referencia | B20: Descripción | D20: Cantidad | E20: Unidad | F20: Jornal -día ($) | G20: Rend./día | H20: Vr. Unitario ($) | L20: SMMLV 23 | M20: SMMLV25
B21: Ing. Coordinador | D21: 0 | E21: Un. | F21: =K21*$L$22 -> 491355.26 | G21: 10 | H21: =(D21*F21)/G21 -> 0 | K21: 400401.9 | L21: 1160000 | M21: 1423500
B22: Ing. Especialista | D22: 0 | E22: Un. | F22: =K22*$L$22 -> 491355.26 | G22: 10 | H22: =(D22*F22)/G22 -> 0 | K22: 400401.9 | L22: =M21/L21 -> 1.2271552
B23: Ing. Diseñador | D23: 0 | E23: Un. | F23: =K23*$L$22 -> 316219.24 | G23: 5 | H23: =(D23*F23)/G23 -> 0 | K23: 257684.8
B24: Ing. Residente | D24: 1 | E24: Un. | F24: =K24*$L$22 -> 301624.56 | G24: 10 | H24: =(D24*F24)/G24 -> 30162.456 | K24: 245791.7
B25: Topografo | D25: 0 | E25: Un. | F25: =K25*$L$22 -> 257840.52 | G25: 10 | H25: =(D25*F25)/G25 -> 0 | K25: 210112.4
B26: Liniero | D26: 2 | E26: Un. | F26: =K26*$L$22 -> 199461.84 | G26: 10 | H26: =(D26*F26)/G26 -> 39892.369 | K26: 162540.03
B27: Auxiliar de línea | D27: 2 | E27: Un. | F27: =K27*$L$22 -> 81158.644 | G27: 10 | H27: =(D27*F27)/G27 -> 16231.729 | K27: 66135.6
B28: Técnico | D28: 0 | E28: Un. | F28: =K28*$L$22 -> 184867.16 | G28: 10 | H28: =(D28*F28)/G28 -> 0 | K28: 150646.93
B29: Auxiliar técnico | D29: 0 | E29: Un. | F29: =K29*$L$22 -> 117645.32 | G29: 13 | H29: =(D29*F29)/G29 -> 0 | K29: 95868.333
B30: Oficial civil | D30: 0 | E30: Un. | F30: =K30*$L$22 -> 184867.16 | G30: 13 | H30: =(D30*F30)/G30 -> 0 | K30: 150646.93
B31: Auxiliar civil | D31: 0 | E31: Un. | F31: =K31*$L$22 -> 103050.68 | G31: 10 | H31: =(D31*F31)/G31 -> 0 | K31: 83975.267
B32: Supervisor HSEQ | D32: 1 | E32: Un. | F32: =K32*$L$22 -> 177569.84 | G32: 13 | H32: =(D32*F32)/G32 -> 13659.219 | K32: 144700.4
B33: Dibujante | D33: 0 | E33: Un. | F33: =K33*$L$22 -> 117646.14 | G33: 10 | H33: =(D33*F33)/G33 -> 0 | K33: 95869
A34: Subtotal B | H34: =SUM(H21:H33) -> 99945.772
A36: C. SERVICIO, EQUIPO, HERRAMIENTAS Y HSE
A37: Referencia | B37: Descripción | D37: Cantidad | E37: Unidad | F37: Rend. | G37: Vr. Unitario ($) | H37: Vr. Total Unit ($)
A38: 1 | B38: Herr. Común | D38: 1 | E38: Un. | F38: 10 | G38: 69701.165 | H38: =(D38*G38)/F38 -> 6970.1165
A39: 2 | B39: Serv. Técnicos | D39: 0 | E39: Un. | F39: 1 | G39: 2500000 | H39: =(D39*G39)/F39 -> 0
A40: 3 | B40: Equipo de trabajo redes MT | D40: 0 | E40: Un. | F40: 10 | G40: 55509.259 | H40: =(D40*G40)/F40 -> 0
A41: 4 | B41: Equipo prueba y diagnostico | D41: 0 | E41: Un. | F41: 13 | G41: 1000000 | H41: =(D41*G41)/F41 -> 0
A42: 5 | B42: Montacarga | D42: 0 | E42: Un. | F42: 10 | G42: 120000 | H42: =(D42*G42)/F42 -> 0
A43: 6 | B43: Andamios | D43: 0 | E43: Secc. | F43: 10 | G43: 28500 | H43: =(D43*G43)/F43 -> 0
A44: 7 | B44: Planta eléctrica 4kVA | D44: 0 | E44: Hra | F44: 1 | G44: 464100 | H44: =(D44*G44)/F44 -> 0
A45: 8 | B45: Cabrestante 70 Ton | D45: 0 | E45: Día | F45: 1 | G45: 952380.95 | H45: =(D45*G45)/F45 -> 0
A46: 9 | B46: GrúaTelescópica | D46: 0 | E46: Día | F46: 1 | G46: 2700000 | H46: =(D46*G46)/F46 -> 0
A47: 10 | B47: Grua PH | D47: 0 | E47: Día | F47: 2 | G47: 3800000 | H47: =(D47*G47)/F47 -> 0
A48: 11 | B48: Carro canasta | D48: 0 | E48: Día | F48: 10 | G48: 3200000 | H48: =(D48*G48)/F48 -> 0
A49: 12 | B49: Camion | D49: 0 | E49: Día | F49: 2 | G49: 2600000 | H49: =(D49*G49)/F49 -> 0
A50: 13 | B50: Camabaja | D50: 0 | E50: Un. | F50: 1 | G50: 4500000 | H50: =(D50*G50)/F50 -> 0
A51: Subtotal C | H51: =SUM(H38:H50) -> 6970.1165
A53: D. TRANSPORTE
A54: Referencia | B54: Descripción | D54: Unidad | E54: Cantidad | F54: Valor Unitario | G54: Rendimiento | H54: Vr. Unitario ($)
A55: 1 | B55: Transporte terrestre | D55: Un. | E55: 0 | F55: 210000 | G55: 13 | H55: =(E55*F55)/G55 -> 0
A56: 2 | B56: Transporte mercancia (terrestre y/o aéreo) | D56: Vje | E56: 1 | F56: 410150.86 | G56: 6 | H56: =(E56*F56)/G56 -> 68358.476
A57: 3 | B57: Transporte Aéreo | D57: Vje | E57: 0 | F57: 500000 | G57: 10 | H57: =(E57*F57)/G57 -> 0
A58: Subtotal D | H58: =SUM(H55:H57) -> 68358.476
A60: E. VIATICOS
A61: Referencia | B61: Descripción | D61: Cantidad | E61: Unidad | F61: Rendimiento | G61: Valor Unitario | H61: Vr. Unitario ($)
A62: 1 | B62: Hospedaje | D62: 0 | E62: Día | F62: 10 | G62: 70000 | H62: =(D62*G62)/F62 -> 0
A63: 2 | B63: Alimentación | D63: 0 | E63: Día | F63: 13 | G63: 45000 | H63: =(D63*G63)/F63 -> 0
A64: 3 | B64: Serv. De manutención | D64: 0 | E64: Día | F64: 13 | G64: 20000 | H64: =(D64*G64)/F64 -> 0
A65: Subtotal E | H65: =SUM(H62:H64) -> 0
A67: COSTOS DIRECTOS ( C.D ) | H67: =H65+H58+H51+H34+H17 -> 175274.36
A69: COSTOS INDIRECTOS Y UTILIDAD | C69: 0.05 | H69: =H67*(C69) -> 8763.7182
A70: IVA | C70: 0.19 | H70: =C70*(H67+1) -> 33302.319
A72: COSTOS INDIRECTOS ( C.I ) | H72: =SUM(H69:H70) -> 42066.037

Sheet 1.2
A1: APERTURA DE EXCAVACION POSTE DE 14 MTS M.T. RURAL
A2: ANALISIS DE PRECIOS UNITARIOS ( A.P.U )
A4: Item: | B4: 1.2 | E4: Vr Unitario Item: | F4: =H67 -> 208106.49 | G4: Fecha: | H4: 22/05//2025
A6: Actividad: | B6: =A1 -> APERTURA DE EXCAVACION POSTE DE 14 MTS M.T. RURAL | H6: UN
A9: A. MATERIAL
A10: Referencia | B10: Descripción | E10: Unidad | F10: Vr. Unitario | G10: Cantidad | H10: Vr. Total
H11: =F11*G11 -> 0
H12: =F12*G12 -> 0
H13: =F13*G13 -> 0
H14: =F14*G14 -> 0
H15: =F15*G15 -> 0
H16: =F16*G16 -> 0
A17: Subtotal A | H17: =SUM(H11:H16) -> 0
A19: B. MANO DE OBRA
A20: Referencia | B20: Descripción | D20: Cantidad | E20: Unidad | F20: Jornal -día ($) | G20: Rend./día | H20: Vr. Unitario ($)
B21: Ing. Coordinador | D21: 0 | E21: Un. | F21: ='1.1'!F21 -> 491355.26 | G21: 3 | H21: =(D21*F21)/G21 -> 0
B22: Ing. Especialista | D22: 0 | E22: Un. | F22: ='1.1'!F22 -> 491355.26 | G22: 3 | H22: =(D22*F22)/G22 -> 0
B23: Ing. Diseñador | D23: 0 | E23: Un. | F23: ='1.1'!F23 -> 316219.24 | G23: 5 | H23: =(D23*F23)/G23 -> 0
B24: Ing. Residente | D24: 1 | E24: Un. | F24: ='1.1'!F24 -> 301624.56 | G24: 3 | H24: =(D24*F24)/G24 -> 100541.52
B25: Topografo | D25: 0 | E25: Un. | F25: ='1.1'!F25 -> 257840.52 | G25: 3 | H25: =(D25*F25)/G25 -> 0
B26: Liniero | D26: 0 | E26: Un. | F26: ='1.1'!F26 -> 199461.84 | G26: 3 | H26: =(D26*F26)/G26 -> 0
B27: Auxiliar de línea | D27: 0 | E27: Un. | F27: ='1.1'!F27 -> 81158.644 | G27: 3 | H27: =(D27*F27)/G27 -> 0
B28: Técnico | D28: 1 | E28: Un. | F28: ='1.1'!F28 -> 184867.16 | G28: 3 | H28: =(D28*F28)/G28 -> 61622.388
B29: Auxiliar técnico | D29: 1 | E29: Un. | F29: ='1.1'!F29 -> 117645.32 | G29: 13 | H29: =(D29*F29)/G29 -> 9049.6401
B30: Oficial civil | D30: 0 | E30: Un. | F30: ='1.1'!F30 -> 184867.16 | G30: 13 | H30: =(D30*F30)/G30 -> 0
B31: Auxiliar civil | D31: 0 | E31: Un. | F31: ='1.1'!F31 -> 103050.68 | G31: 3 | H31: =(D31*F31)/G31 -> 0
B32: Supervisor HSEQ | D32: 1 | E32: Un. | F32: ='1.1'!F32 -> 177569.84 | G32: 13 | H32: =(D32*F32)/G32 -> 13659.219
B33: Dibujante | D33: 0 | E33: Un. | F33: ='1.1'!F33 -> 117646.14 | G33: 3 | H33: =(D33*F33)/G33 -> 0
A34: Subtotal B | H34: =SUM(H21:H33) -> 184872.77
A36: C. SERVICIO, EQUIPO, HERRAMIENTAS Y HSE
A37: Referencia | B37: Descripción | D37: Cantidad | E37: Unidad | F37: Rend. | G37: Vr. Unitario ($) | H37: Vr. Total Unit ($)
A38: 1 | B38: Herr. Común | D38: 1 | E38: Un. | F38: 3 | G38: 69701.165 | H38: =(D38*G38)/F38 -> 23233.722
A39: 2 | B39: Serv. Técnicos | D39: 0 | E39: Un. | F39: 1 | G39: 2500000 | H39: =(D39*G39)/F39 -> 0
A40: 3 | B40: Equipo de trabajo redes MT | D40: 0 | E40: Un. | F40: 3 | G40: 55509.259 | H40: =(D40*G40)/F40 -> 0
A41: 4 | B41: Equipo prueba y diagnostico | D41: 0 | E41: Un. | F41: 13 | G41: 1000000 | H41: =(D41*G41)/F41 -> 0
A42: 5 | B42: Montacarga | D42: 0 | E42: Un. | F42: 3 | G42: 120000 | H42: =(D42*G42)/F42 -> 0
A43: 6 | B43: Andamios | D43: 0 | E43: Secc. | F43: 3 | G43: 28500 | H43: =(D43*G43)/F43 -> 0
A44: 7 | B44: Planta eléctrica 4kVA | D44: 0 | E44: Hra | F44: 1 | G44: 464100 | H44: =(D44*G44)/F44 -> 0
A45: 8 | B45: Cabrestante 70 Ton | D45: 0 | E45: Día | F45: 1 | G45: 952380.95 | H45: =(D45*G45)/F45 -> 0
A46: 9 | B46: GrúaTelescópica | D46: 0 | E46: Día | F46: 1 | G46: 2700000 | H46: =(D46*G46)/F46 -> 0
A47: 10 | B47: Grua PH | D47: 0 | E47: Día | F47: 2 | G47: 3800000 | H47: =(D47*G47)/F47 -> 0
A48: 11 | B48: Carro canasta | D48: 0 | E48: Día | F48: 3 | G48: 3200000 | H48: =(D48*G48)/F48 -> 0
A49: 12 | B49: Camion | D49: 0 | E49: Día | F49: 2 | G49: 2600000 | H49: =(D49*G49)/F49 -> 0
A50: 13 | B50: Camabaja | D50: 0 | E50: Un. | F50: 1 | G50: 4500000 | H50: =(D50*G50)/F50 -> 0
A51: Subtotal C | H51: =SUM(H38:H50) -> 23233.722
A53: D. TRANSPORTE
A54: Referencia | B54: Descripción | D54: Unidad | E54: Cantidad | F54: Valor Unitario | G54: Rendimiento | H54: Vr. Unitario ($)
A55: 1 | B55: Transporte terrestre | D55: Un. | E55: 0 | F55: 210000 | G55: 4 | H55: =(E55*F55)/G55 -> 0
A56: 2 | B56: Transporte mercancia (terrestre y/o aéreo) | D56: Vje | E56: 0 | F56: 410150.86 | G56: 6 | H56: =(E56*F56)/G56 -> 0
A57: 3 | B57: Transporte Aéreo | D57: Vje | E57: 0 | F57: 500000 | G57: 3 | H57: =(E57*F57)/G57 -> 0
A58: Subtotal D | H58: =SUM(H55:H57) -> 0
A60: E. VIATICOS
A61: Referencia | B61: Descripción | D61: Cantidad | E61: Unidad | F61: Rendimiento | G61: Valor Unitario | H61: Vr. Unitario ($)
A62: 1 | B62: Hospedaje | D62: 0 | E62: Día | F62: 3 | G62: 70000 | H62: =(D62*G62)/F62 -> 0
A63: 2 | B63: Alimentación | D63: 0 | E63: Día | F63: 13 | G63: 45000 | H63: =(D63*G63)/F63 -> 0
A64: 3 | B64: Serv. De manutención | D64: 0 | E64: Día | F64: 13 | G64: 20000 | H64: =(D64*G64)/F64 -> 0
A65: Subtotal E | H65: =SUM(H62:H64) -> 0
A67: COSTOS DIRECTOS ( C.D ) | H67: =SUM(H65,H58,H51,H34,H17) -> 208106.49
A69: COSTOS INDIRECTOS Y UTILIDAD | C69: 0.05 | H69: 0
A70: IVA | C70: 0 | H70: 0
A72: COSTOS INDIRECTOS ( C.I ) | H72: 0

Sheet 1.3
A1: APERTURA DE EXCAVACION PARA VIGUETA EN RETENIDA RURAL
A2: ANALISIS DE PRECIOS UNITARIOS ( A.P.U )
A4: Item: | B4: 1.3 | E4: Vr Unitario Item: | F4: =H67 -> 92232.969 | G4: Fecha: | H4: 22/05//2025
A6: Actividad: | B6: =A1 -> APERTURA DE EXCAVACION PARA VIGUETA EN RETENIDA RURAL | H6: UN
A9: A. MATERIAL
A10: Referencia | B10: Descripción | E10: Unidad | F10: Vr. Unitario | G10: Cantidad | H10: Vr. Total
H11: =F11*G11 -> 0
H12: =F12*G12 -> 0
H13: =F13*G13 -> 0
H14: =F14*G14 -> 0
H15: =F15*G15 -> 0
H16: =F16*G16 -> 0
A17: Subtotal A | H17: =H11+H12+H13+H14+H15+H16 -> 0
A19: B. MANO DE OBRA
A20: Referencia | B20: Descripción | D20: Cantidad | E20: Unidad | F20: Jornal -día ($) | G20: Rend./día | H20: Vr. Unitario ($)
B21: Ing. Coordinador | D21: 0 | E21: Un. | F21: ='1.1'!F21 -> 491355.26 | G21: 8 | H21: =(D21*F21)/G21 -> 0
B22: Ing. Especialista | D22: 0 | E22: Un. | F22: ='1.1'!F22 -> 491355.26 | G22: 8 | H22: =(D22*F22)/G22 -> 0
B23: Ing. Diseñador | D23: 0 | E23: Un. | F23: ='1.1'!F23 -> 316219.24 | G23: 5 | H23: =(D23*F23)/G23 -> 0
B24: Ing. Residente | D24: 1 | E24: Un. | F24: ='1.1'!F24 -> 301624.56 | G24: 8 | H24: =(D24*F24)/G24 -> 37703.069
B25: Topografo | D25: 0 | E25: Un. | F25: ='1.1'!F25 -> 257840.52 | G25: 8 | H25: =(D25*F25)/G25 -> 0
B26: Liniero | D26: 0 | E26: Un. | F26: ='1.1'!F26 -> 199461.84 | G26: 8 | H26: =(D26*F26)/G26 -> 0
B27: Auxiliar de línea | D27: 0 | E27: Un. | F27: ='1.1'!F27 -> 81158.644 | G27: 8 | H27: =(D27*F27)/G27 -> 0
B28: Técnico | D28: 1 | E28: Un. | F28: ='1.1'!F28 -> 184867.16 | G28: 8 | H28: =(D28*F28)/G28 -> 23108.395
B29: Auxiliar técnico | D29: 1 | E29: Un. | F29: ='1.1'!F29 -> 117645.32 | G29: 13 | H29: =(D29*F29)/G29 -> 9049.6401
B30: Oficial civil | D30: 0 | E30: Un. | F30: ='1.1'!F30 -> 184867.16 | G30: 13 | H30: =(D30*F30)/G30 -> 0
B31: Auxiliar civil | D31: 0 | E31: Un. | F31: ='1.1'!F31 -> 103050.68 | G31: 8 | H31: =(D31*F31)/G31 -> 0
B32: Supervisor HSEQ | D32: 1 | E32: Un. | F32: ='1.1'!F32 -> 177569.84 | G32: 13 | H32: =(D32*F32)/G32 -> 13659.219
B33: Dibujante | D33: 0 | E33: Un. | F33: ='1.1'!F33 -> 117646.14 | G33: 8 | H33: =(D33*F33)/G33 -> 0
A34: Subtotal B | H34: =H21+H22+H23+H24+H25+H26+H27+H28+H29+H30+H31+H32+H33 -> 83520.324
A36: C. SERVICIO, EQUIPO, HERRAMIENTAS Y HSE
A37: Referencia | B37: Descripción | D37: Cantidad | E37: Unidad | F37: Rend. | G37: Vr. Unitario ($) | H37: Vr. Total Unit ($)
A38: 1 | B38: Herr. Común | D38: 1 | E38: Un. | F38: 8 | G38: 69701.165 | H38: =(D38*G38)/F38 -> 8712.6456
A39: 2 | B39: Serv. Técnicos | D39: 0 | E39: Un. | F39: 1 | G39: 2500000 | H39: =(D39*G39)/F39 -> 0
A40: 3 | B40: Equipo de trabajo redes MT | D40: 0 | E40: Un. | F40: 8 | G40: 55509.259 | H40: =(D40*G40)/F40 -> 0
A41: 4 | B41: Equipo prueba y diagnostico | D41: 0 | E41: Un. | F41: 13 | G41: 1000000 | H41: =(D41*G41)/F41 -> 0
A42: 5 | B42: Montacarga | D42: 0 | E42: Un. | F42: 8 | G42: 120000 | H42: =(D42*G42)/F42 -> 0
A43: 6 | B43: Andamios | D43: 0 | E43: Secc. | F43: 8 | G43: 28500 | H43: =(D43*G43)/F43 -> 0
A44: 7 | B44: Planta eléctrica 4kVA | D44: 0 | E44: Hra | F44: 1 | G44: 464100 | H44: =(D44*G44)/F44 -> 0
A45: 8 | B45: Cabrestante 70 Ton | D45: 0 | E45: Día | F45: 1 | G45: 952380.95 | H45: =(D45*G45)/F45 -> 0
A46: 9 | B46: GrúaTelescópica | D46: 0 | E46: Día | F46: 1 | G46: 2700000 | H46: =(D46*G46)/F46 -> 0
A47: 10 | B47: Grua PH | D47: 0 | E47: Día | F47: 2 | G47: 3800000 | H47: =(D47*G47)/F47 -> 0
A48: 11 | B48: Carro canasta | D48: 0 | E48: Día | F48: 8 | G48: 3200000 | H48: =(D48*G48)/F48 -> 0
A49: 12 | B49: Camion | D49: 0 | E49: Día | F49: 2 | G49: 2600000 | H49: =(D49*G49)/F49 -> 0
A50: 13 | B50: Camabaja | D50: 0 | E50: Un. | F50: 1 | G50: 4500000 | H50: =(D50*G50)/F50 -> 0
A51: Subtotal C | H51: =H38+H39+H40+H42+H41+H43+H44+H45+H47+H46+H48+H49+H50 -> 8712.6456
A53: D. TRANSPORTE
A54: Referencia | B54: Descripción | D54: Unidad | E54: Cantidad | F54: Valor Unitario | G54: Rendimiento | H54: Vr. Unitario ($)
A55: 1 | B55: Transporte terrestre | D55: Un. | E55: 0 | F55: 210000 | G55: 13 | H55: =(E55*F55)/G55 -> 0
A56: 2 | B56: Transporte mercancia (terrestre y/o aéreo) | D56: Vje | E56: 0 | F56: 410150.86 | G56: 6
A57: 3 | B57: Transporte Aéreo | D57: Vje | E57: 0 | F57: 500000 | G57: 8 | H57: =(E57*F57)/G57 -> 0
A58: Subtotal D | H58: =H55+H56+H57 -> 0
A60: E. VIATICOS
A61: Referencia | B61: Descripción | D61: Cantidad | E61: Unidad | F61: Rendimiento | G61: Valor Unitario | H61: Vr. Unitario ($)
A62: 1 | B62: Hospedaje | D62: 0 | E62: Día | F62: 8 | G62: 70000 | H62: =(D62*G62)/F62 -> 0
A63: 2 | B63: Alimentación | D63: 0 | E63: Día | F63: 13 | G63: 45000 | H63: =(D63*G63)/F63 -> 0
A64: 3 | B64: Serv. De manutención | D64: 0 | E64: Día | F64: 13 | G64: 20000 | H64: =(D64*G64)/F64 -> 0
A65: Subtotal E | H65: =H62+H63+H64 -> 0
A67: COSTOS DIRECTOS ( C.D ) | H67: =H65+H58+H51+H17+H34 -> 92232.969
A69: COSTOS INDIRECTOS Y UTILIDAD | C69: 0 | H69: 0
A70: IVA | C70: 0 | H70: 0
A72: COSTOS INDIRECTOS ( C.I ) | H72: 0

Sheet 1.6
A1: HINCADA, PLOMADA Y ORIENTACIÓN DE POSTE DE 14, 16 Y 18 MTS CON GRUA
A2: ANALISIS DE PRECIOS UNITARIOS ( A.P.U )
A4: Item: | B4: 1.6 | E4: Vr Unitario Item: | F4: =H67 -> 418245.81 | G4: Fecha: | H4: 22/05//2025
A6: Actividad: | B6: =A1 -> HINCADA, PLOMADA Y ORIENTACIÓN DE POSTE DE 14, 16 Y 18 MTS CON GRUA | H6: UN
A9: A. MATERIAL
A10: Referencia | B10: Descripción | E10: Unidad | F10: Vr. Unitario | G10: Cantidad | H10: Vr. Total
H11: =F11*G11 -> 0
H12: =F12*G12 -> 0
H13: =F13*G13 -> 0
H14: =F14*G14 -> 0
H15: =F15*G15 -> 0
H16: =F16*G16 -> 0
A17: Subtotal A | H17: =SUM(H11:H16) -> 0
A19: B. MANO DE OBRA
A20: Referencia | B20: Descripción | D20: Cantidad | E20: Unidad | F20: Jornal -día ($) | G20: Rend./día | H20: Vr. Unitario ($)
B21: Ing. Coordinador | D21: 0 | E21: Un. | F21: ='1.1'!F21 -> 491355.26 | G21: 9 | H21: =(D21*F21)/G21 -> 0
B22: Ing. Especialista | D22: 0 | E22: Un. | F22: ='1.1'!F22 -> 491355.26 | G22: 9 | H22: =(D22*F22)/G22 -> 0
B23: Ing. Diseñador | D23: 0 | E23: Un. | F23: ='1.1'!F23 -> 316219.24 | G23: 5 | H23: =(D23*F23)/G23 -> 0
B24: Ing. Residente | D24: 1 | E24: Un. | F24: ='1.1'!F24 -> 301624.56 | G24: 9 | H24: =(D24*F24)/G24 -> 33513.84
B25: Topografo | D25: 0 | E25: Un. | F25: ='1.1'!F25 -> 257840.52 | G25: 9 | H25: =(D25*F25)/G25 -> 0
B26: Liniero | D26: 2 | E26: Un. | F26: ='1.1'!F26 -> 199461.84 | G26: 9 | H26: =(D26*F26)/G26 -> 44324.854
B27: Auxiliar de línea | D27: 2 | E27: Un. | F27: ='1.1'!F27 -> 81158.644 | G27: 9 | H27: =(D27*F27)/G27 -> 18035.254
B28: Técnico | D28: 0 | E28: Un. | F28: ='1.1'!F28 -> 184867.16 | G28: 9 | H28: =(D28*F28)/G28 -> 0
B29: Auxiliar técnico | D29: 0 | E29: Un. | F29: ='1.1'!F29 -> 117645.32 | G29: 13 | H29: =(D29*F29)/G29 -> 0
B30: Oficial civil | D30: 0 | E30: Un. | F30: ='1.1'!F30 -> 184867.16 | G30: 13 | H30: =(D30*F30)/G30 -> 0
B31: Auxiliar civil | D31: 0 | E31: Un. | F31: ='1.1'!F31 -> 103050.68 | G31: 9 | H31: =(D31*F31)/G31 -> 0
B32: Supervisor HSEQ | D32: 1 | E32: Un. | F32: ='1.1'!F32 -> 177569.84 | G32: 13 | H32: =(D32*F32)/G32 -> 13659.219
B33: Dibujante | D33: 0 | E33: Un. | F33: ='1.1'!F33 -> 117646.14 | G33: 9 | H33: =(D33*F33)/G33 -> 0
A34: Subtotal B | H34: =SUM(H21:H33) -> 109533.17
A36: C. SERVICIO, EQUIPO, HERRAMIENTAS Y HSE
A37: Referencia | B37: Descripción | D37: Cantidad | E37: Unidad | F37: Rend. | G37: Vr. Unitario ($) | H37: Vr. Total Unit ($)
A38: 1 | B38: Herr. Común | D38: 1 | E38: Un. | F38: 8 | G38: 69701.165 | H38: =(D38*G38)/F38 -> 8712.6456
A39: 2 | B39: Serv. Técnicos | D39: 0 | E39: Un. | F39: 1 | G39: 2500000 | H39: =(D39*G39)/F39 -> 0
A40: 3 | B40: Equipo de trabajo redes MT | D40: 0 | E40: Un. | F40: 9 | G40: 55509.259 | H40: =(D40*G40)/F40 -> 0
A41: 4 | B41: Equipo prueba y diagnostico | D41: 0 | E41: Un. | F41: 13 | G41: 1000000 | H41: =(D41*G41)/F41 -> 0
A42: 5 | B42: Montacarga | D42: 0 | E42: Un. | F42: 8 | G42: 120000 | H42: =(D42*G42)/F42 -> 0
A43: 6 | B43: Andamios | D43: 0 | E43: Secc. | F43: 8 | G43: 28500 | H43: =(D43*G43)/F43 -> 0
A44: 7 | B44: Planta eléctrica 4kVA | D44: 0 | E44: Hra | F44: 1 | G44: 464100 | H44: =(D44*G44)/F44 -> 0
A45: 8 | B45: Cabrestante 70 Ton | D45: 0 | E45: Día | F45: 1 | G45: 952380.95 | H45: =(D45*G45)/F45 -> 0
A46: 9 | B46: GrúaTelescópica | D46: 1 | E46: Día | F46: 9 | G46: 2700000 | H46: =(D46*G46)/F46 -> 300000
A47: 10 | B47: Grua PH | D47: 0 | E47: Día | F47: 2 | G47: 3800000 | H47: =(D47*G47)/F47 -> 0
A48: 11 | B48: Carro canasta | D48: 0 | E48: Día | F48: 8 | G48: 3200000 | H48: =(D48*G48)/F48 -> 0
A49: 12 | B49: Camion | D49: 0 | E49: Día | F49: 2 | G49: 2600000 | H49: =(D49*G49)/F49 -> 0
A50: 13 | B50: Camabaja | D50: 0 | E50: Un. | F50: 1 | G50: 4500000 | H50: =(D50*G50)/F50 -> 0
A51: Subtotal C | H51: =SUM(H38:H50) -> 308712.65
A53: D. TRANSPORTE
A54: Referencia | B54: Descripción | D54: Unidad | E54: Cantidad | F54: Valor Unitario | G54: Rendimiento | H54: Vr. Unitario ($)
A55: 1 | B55: Transporte terrestre | D55: Un. | E55: 0 | F55: 210000 | G55: 13 | H55: =(E55*F55)/G55 -> 0
A56: 2 | B56: Transporte mercancia (terrestre y/o aéreo) | D56: Vje | E56: 0 | F56: 410150.86 | G56: 6 | H56: =(E56*F56)/G56 -> 0
A57: 3 | B57: Transporte Aéreo | D57: Vje | E57: 0 | F57: 500000 | G57: 9 | H57: =(E57*F57)/G57 -> 0
A58: Subtotal D | H58: =SUM(H55:H57) -> 0
A60: E. VIATICOS
A61: Referencia | B61: Descripción | D61: Cantidad | E61: Unidad | F61: Rendimiento | G61: Valor Unitario | H61: Vr. Unitario ($)
A62: 1 | B62: Hospedaje | D62: 0 | E62: Día | F62: 9 | G62: 70000 | H62: =(D62*G62)/F62 -> 0
A63: 2 | B63: Alimentación | D63: 0 | E63: Día | F63: 13 | G63: 45000 | H63: =(D63*G63)/F63 -> 0
A64: 3 | B64: Serv. De manutención | D64: 0 | E64: Día | F64: 13 | G64: 20000 | H64: =(D64*G64)/F64 -> 0
A65: Subtotal E | H65: =SUM(H62:H64) -> 0
A67: COSTOS DIRECTOS ( C.D ) | H67: =SUM(H65,H58,H51,H34,H17) -> 418245.81
A69: COSTOS INDIRECTOS Y UTILIDAD | C69: 0 | H69: 0
A70: IVA | C70: 0 | H70: 0
A72: COSTOS INDIRECTOS ( C.I ) | H72: 0

Sheet 1.7
A1: INSTALACION LINE A TIERRA MEDIA TENSION
A2: ANALISIS DE PRECIOS UNITARIOS ( A.P.U )
A4: Item: | B4: 1.7 | E4: Vr Unitario Item: | F4: =H67 -> 143889.32 | G4: Fecha: | H4: 22/05//2025
A6: Actividad: | B6: =A1 -> INSTALACION LINE A TIERRA MEDIA TENSION | H6: UN
A9: A. MATERIAL
A10: Referencia | B10: Descripción | E10: Unidad | F10: Vr. Unitario | G10: Cantidad | H10: Vr. Total
H11: =F11*G11 -> 0
H12: =F12*G12 -> 0
H13: =F13*G13 -> 0
H14: =F14*G14 -> 0
H15: =F15*G15 -> 0
H16: =F16*G16 -> 0
A17: Subtotal A | H17: =SUM(H11:H16) -> 0
A19: B. MANO DE OBRA
A20: Referencia | B20: Descripción | D20: Cantidad | E20: Unidad | F20: Jornal -día ($) | G20: Rend./día | H20: Vr. Unitario ($)
B21: Ing. Coordinador | D21: 0 | E21: Un. | F21: ='1.1'!F21 -> 491355.26 | G21: 10 | H21: =(D21*F21)/G21 -> 0
B22: Ing. Especialista | D22: 0 | E22: Un. | F22: ='1.1'!F22 -> 491355.26 | G22: 10 | H22: =(D22*F22)/G22 -> 0
B23: Ing. Diseñador | D23: 0 | E23: Un. | F23: ='1.1'!F23 -> 316219.24 | G23: 5 | H23: =(D23*F23)/G23 -> 0
B24: Ing. Residente | D24: 1 | E24: Un. | F24: ='1.1'!F24 -> 301624.56 | G24: 10 | H24: =(D24*F24)/G24 -> 30162.456
B25: Topografo | D25: 0 | E25: Un. | F25: ='1.1'!F25 -> 257840.52 | G25: 10 | H25: =(D25*F25)/G25 -> 0
B26: Liniero | D26: 2 | E26: Un. | F26: ='1.1'!F26 -> 199461.84 | G26: 10 | H26: =(D26*F26)/G26 -> 39892.369
B27: Auxiliar de línea | D27: 2 | E27: Un. | F27: ='1.1'!F27 -> 81158.644 | G27: 10 | H27: =(D27*F27)/G27 -> 16231.729
B28: Técnico | D28: 2 | E28: Un. | F28: ='1.1'!F28 -> 184867.16 | G28: 10 | H28: =(D28*F28)/G28 -> 36973.433
B29: Auxiliar técnico | D29: 0 | E29: Un. | F29: ='1.1'!F29 -> 117645.32 | G29: 13 | H29: =(D29*F29)/G29 -> 0
B30: Oficial civil | D30: 0 | E30: Un. | F30: ='1.1'!F30 -> 184867.16 | G30: 13 | H30: =(D30*F30)/G30 -> 0
B31: Auxiliar civil | D31: 0 | E31: Un. | F31: ='1.1'!F31 -> 103050.68 | G31: 10 | H31: =(D31*F31)/G31 -> 0
B32: Supervisor HSEQ | D32: 1 | E32: Un. | F32: ='1.1'!F32 -> 177569.84 | G32: 13 | H32: =(D32*F32)/G32 -> 13659.219
B33: Dibujante | D33: 0 | E33: Un. | F33: ='1.1'!F33 -> 117646.14 | G33: 10 | H33: =(D33*F33)/G33 -> 0
A34: Subtotal B | H34: =SUM(H21:H33) -> 136919.2
A36: C. SERVICIO, EQUIPO, HERRAMIENTAS Y HSE
A37: Referencia | B37: Descripción | D37: Cantidad | E37: Unidad | F37: Rend. | G37: Vr. Unitario ($) | H37: Vr. Total Unit ($)
A38: 1 | B38: Herr. Común | D38: 1 | E38: Un. | F38: 10 | G38: 69701.165 | H38: =(D38*G38)/F38 -> 6970.1165
A39: 2 | B39: Serv. Técnicos | D39: 0 | E39: Un. | F39: 1 | G39: 2500000 | H39: =(D39*G39)/F39 -> 0
A40: 3 | B40: Equipo de trabajo redes MT | D40: 0 | E40: Un. | F40: 10 | G40: 55509.259 | H40: =(D40*G40)/F40 -> 0
A41: 4 | B41: Equipo prueba y diagnostico | D41: 0 | E41: Un. | F41: 13 | G41: 1000000 | H41: =(D41*G41)/F41 -> 0
A42: 5 | B42: Montacarga | D42: 0 | E42: Un. | F42: 10 | G42: 120000 | H42: =(D42*G42)/F42 -> 0
A43: 6 | B43: Andamios | D43: 0 | E43: Secc. | F43: 10 | G43: 28500 | H43: =(D43*G43)/F43 -> 0
A44: 7 | B44: Planta eléctrica 4kVA | D44: 0 | E44: Hra | F44: 1 | G44: 464100 | H44: =(D44*G44)/F44 -> 0
A45: 8 | B45: Cabrestante 70 Ton | D45: 0 | E45: Día | F45: 1 | G45: 952380.95 | H45: =(D45*G45)/F45 -> 0
A46: 9 | B46: GrúaTelescópica | D46: 0 | E46: Día | F46: 1 | G46: 2700000 | H46: =(D46*G46)/F46 -> 0
A47: 10 | B47: Grua PH | D47: 0 | E47: Día | F47: 2 | G47: 3800000 | H47: =(D47*G47)/F47 -> 0
A48: 11 | B48: Carro canasta | D48: 0 | E48: Día | F48: 10 | G48: 3200000 | H48: =(D48*G48)/F48 -> 0
A49: 12 | B49: Camion | D49: 0 | E49: Día | F49: 2 | G49: 2600000 | H49: =(D49*G49)/F49 -> 0
A50: 13 | B50: Camabaja | D50: 0 | E50: Un. | F50: 1 | G50: 4500000 | H50: =(D50*G50)/F50 -> 0
A51: Subtotal C | H51: =SUM(H38:H50) -> 6970.1165
A53: D. TRANSPORTE
A54: Referencia | B54: Descripción | D54: Unidad | E54: Cantidad | F54: Valor Unitario | G54: Rendimiento | H54: Vr. Unitario ($)
A55: 1 | B55: Transporte terrestre | D55: Un. | E55: 0 | F55: 210000 | G55: 1 | H55: =(E55*F55)/G55 -> 0
A56: 2 | B56: Transporte mercancia (terrestre y/o aéreo) | D56: Vje | E56: 0 | F56: 410150.86 | G56: 1 | H56: =(E56*F56)/G56 -> 0
A57: 3 | B57: Transporte Aéreo | D57: Vje | E57: 0 | F57: 500000 | G57: 10 | H57: =(E57*F57)/G57 -> 0
A58: Subtotal D | H58: =SUM(H55:H57) -> 0
A60: E. VIATICOS
A61: Referencia | B61: Descripción | D61: Cantidad | E61: Unidad | F61: Rendimiento | G61: Valor Unitario | H61: Vr. Unitario ($)
A62: 1 | B62: Hospedaje | D62: 0 | E62: Día | F62: 10 | G62: 70000 | H62: =(D62*G62)/F62 -> 0
A63: 2 | B63: Alimentación | D63: 0 | E63: Día | F63: 13 | G63: 45000 | H63: =(D63*G63)/F63 -> 0
A64: 3 | B64: Serv. De manutención | D64: 0 | E64: Día | F64: 13 | G64: 20000 | H64: =(D64*G64)/F64 -> 0
A65: Subtotal E | H65: =SUM(H62:H64) -> 0
A67: COSTOS DIRECTOS ( C.D ) | H67: =SUM(H65,H58,H51,H34,H17) -> 143889.32
A69: COSTOS INDIRECTOS Y UTILIDAD | C69: 0 | H69: 0
A70: IVA | C70: 0 | H70: 0
A72: COSTOS INDIRECTOS ( C.I ) | H72: 0

Sheet 1.8
A1: INSTALACIÓN DE TEMPLETE CUERDA GUITARRA CON TODOS SUS ACCESORIOS M.T. RURAL
A2: ANALISIS DE PRECIOS UNITARIOS ( A.P.U )
A4: Item: | B4: 1.8 | E4: Vr Unitario Item: | F4: =H67 -> 100479.29 | G4: Fecha: | H4: 22/05//2025
A6: Actividad: | B6: =A1 -> INSTALACIÓN DE TEMPLETE CUERDA GUITARRA CON TODOS SUS ACCESORIOS M.T. RURAL | H6: UN
A9: A. MATERIAL
A10: Referencia | B10: Descripción | E10: Unidad | F10: Vr. Unitario | G10: Cantidad | H10: Vr. Total
H11: =F11*G11 -> 0
H12: =F12*G12 -> 0
H13: =F13*G13 -> 0
H14: =F14*G14 -> 0
H15: =F15*G15 -> 0
H16: =F16*G16 -> 0
A17: Subtotal A | H17: =SUM(H11:H16) -> 0
A19: B. MANO DE OBRA
A20: Referencia | B20: Descripción | D20: Cantidad | E20: Unidad | F20: Jornal -día ($) | G20: Rend./día | H20: Vr. Unitario ($)
B21: Ing. Coordinador | D21: 0 | E21: Un. | F21: ='1.1'!F21 -> 491355.26 | G21: 15 | H21: =(D21*F21)/G21 -> 0
B22: Ing. Especialista | D22: 0 | E22: Un. | F22: ='1.1'!F22 -> 491355.26 | G22: 15 | H22: =(D22*F22)/G22 -> 0
B23: Ing. Diseñador | D23: 0 | E23: Un. | F23: ='1.1'!F23 -> 316219.24 | G23: 5 | H23: =(D23*F23)/G23 -> 0
B24: Ing. Residente | D24: 1 | E24: Un. | F24: ='1.1'!F24 -> 301624.56 | G24: 15 | H24: =(D24*F24)/G24 -> 20108.304
B25: Topografo | D25: 0 | E25: Un. | F25: ='1.1'!F25 -> 257840.52 | G25: 15 | H25: =(D25*F25)/G25 -> 0
B26: Liniero | D26: 2 | E26: Un. | F26: ='1.1'!F26 -> 199461.84 | G26: 15 | H26: =(D26*F26)/G26 -> 26594.912
B27: Auxiliar de línea | D27: 2 | E27: Un. | F27: ='1.1'!F27 -> 81158.644 | G27: 15 | H27: =(D27*F27)/G27 -> 10821.152
B28: Técnico | D28: 2 | E28: Un. | F28: ='1.1'!F28 -> 184867.16 | G28: 15 | H28: =(D28*F28)/G28 -> 24648.955
B29: Auxiliar técnico | D29: 0 | E29: Un. | F29: ='1.1'!F29 -> 117645.32 | G29: 13 | H29: =(D29*F29)/G29 -> 0
B30: Oficial civil | D30: 0 | E30: Un. | F30: ='1.1'!F30 -> 184867.16 | G30: 13 | H30: =(D30*F30)/G30 -> 0
B31: Auxiliar civil | D31: 0 | E31: Un. | F31: ='1.1'!F31 -> 103050.68 | G31: 15 | H31: =(D31*F31)/G31 -> 0
B32: Supervisor HSEQ | D32: 1 | E32: Un. | F32: ='1.1'!F32 -> 177569.84 | G32: 13 | H32: =(D32*F32)/G32 -> 13659.219
B33: Dibujante | D33: 0 | E33: Un. | F33: ='1.1'!F33 -> 117646.14 | G33: 15 | H33: =(D33*F33)/G33 -> 0
A34: Subtotal B | H34: =SUM(H21:H33) -> 95832.542
A36: C. SERVICIO, EQUIPO, HERRAMIENTAS Y HSE
A37: Referencia | B37: Descripción | D37: Cantidad | E37: Unidad | F37: Rend. | G37: Vr. Unitario ($) | H37: Vr. Total Unit ($)
A38: 1 | B38: Herr. Común | D38: 1 | E38: Un. | F38: 15 | G38: 69701.165 | H38: =(D38*G38)/F38 -> 4646.7443
A39: 2 | B39: Serv. Técnicos | D39: 0 | E39: Un. | F39: 1 | G39: 2500000 | H39: =(D39*G39)/F39 -> 0
